Workbook

Sheet Lisez-moi
A1: Bilan stock-to-use du café et prix KC1 / DF1 — campagnes 2010/11 à 2026/27
A3: Ce que demande l'analyse
A4: Calculer le stock-to-use (STU) du café, le comparer au prix, et comprendre comment le prix réagit selon son niveau, pour prévoir le prix à partir de la production.
A5: Définitions
A6: STU = stocks de fin ÷ (consommation domestique + exportations), données USDA. Monde = somme des 93 pays du fichier USDA.
A7: STU certifié = stocks certifiés ICE en fin de campagne (fin septembre ; fin août 2026 pour 2025/26) ÷ (consommation domestique + exportations). New York pour l'arabica, Londres pour le robusta, les deux pour le total.
A8: Prix : moyenne de la campagne octobre-septembre de ICE New York (KC) et ICE Londres (DF), moyennes mensuelles publiées par l'ICO (2e-3e positions, proxy de KC1 / DF1). 2025/26 = octobre 2025 → août 2026 (11 mois).
A9: Arabica et robusta : ce que l'USDA publie et comment le STU est calculé
A10: Pour chaque pays, l'USDA publie la production arabica et la production robusta, mais un seul chiffre de stocks de fin, de consommation et d'exportations, toutes espèces confondues (vérifié sur les 19 attributs du fichier : exportations, importations et consommation ne sont ventilées que par forme — vert, torréfié, soluble). Il n'existe donc pas de « stocks de fin arabica » USDA, même pays par pays.
A11: Calcul : pour chacun des 42 pays d'origine (producteurs exportateurs nets), stocks et utilisation sont multipliés par la part de l'espèce dans sa production de l'année, puis additionnés. Pour les pays à une seule espèce (Colombie, Éthiopie, Honduras : 100 % arabica), c'est le chiffre USDA exact ; le Vietnam est à ≈ 96-97 % robusta. La répartition porte sur les pays mixtes : Brésil (60 à 81 % d'arabica selon l'année), Inde, Ouganda, Indonésie, Mexique, etc.
A12: Ces STU arabica / robusta sont ceux des PAYS D'ORIGINE : les stocks des pays consommateurs (UE, États-Unis, Japon : 51 à 77 % des stocks mondiaux, dont les stocks certifiés) ne sont pas répartis par espèce et ne figurent que dans le STU mondial.
A13: Contrôles : les colonnes J-K des onglets 2 et 3 recalculent le STU sans aucune répartition. Espèce majoritaire : même courbe (corrélation 0,99 arabica, 0,94 robusta). Pays purs ≥ 90 % : même forme en robusta (0,88), courbe différente en arabica (0,31) car le Brésil en est exclu.
... A25: 16 campagnes (15 avec stocks certifiés), très autocorrélées (≈ 4 à 7 observations indépendantes) : des ordres de grandeur, pas des lois. Le lien STU mondial / prix repose surtout sur 2023/24-2025/26. Campagnes USDA locales (Brésil juillet-juin) contre prix octobre-septembre. Prix non corrigés de l'inflation ni du real brésilien. Les stocks USDA sont en partie estimés, pour tous les pays (États-Unis figés à 5,7 M sacs depuis 2022/23).

Sheet 1_Monde
A1: 1 — Monde : production, stock-to-use et stock-to-use des stocks certifiés, avec KC1 et DF1
A2: STU = stocks de fin ÷ (consommation domestique + exportations), somme des 93 pays USDA. STU certifié = (stocks certifiés New York + Londres, fin de campagne) ÷ (consommation + exportations).
A3: Prix : moyenne octobre-septembre, KC1 et DF1 en US c/lb pour partager l'axe (DF1 en US$/t dans la colonne M).
A4: Campagne | B4: Production monde (1000 sacs) | C4: Production (M sacs) | D4: Stocks de fin monde | E4: Consommation domestique monde | F4: Exportations monde | G4: STU = stocks ÷ (conso + export) | H4: Certifiés NY (M sacs) | I4: Certifiés Londres (M sacs) | J4: STU certifié = (NY + Londres) ÷ (conso + export) | K4: KC1 (US c/lb) | L4: DF1 (US c/lb) | M4: DF1 (US$/t) | N4: Info : STU = stocks ÷ conso (déf. USDA/ICO)
A5: 2010/11 | B5: ='Donnees_USDA'!C102 -> 141409 | C5: =B5/1000 -> 141.409 | D5: ='Donnees_USDA'!C408 -> 28640 | E5: ='Donnees_USDA'!C510 -> 135508 | F5: ='Donnees_USDA'!C612 -> 116972 | G5: =D5/(E5+F5) -> 0.11343473 | K5: ='Prix_ICE'!I5 -> 249.66 | L5: ='Prix_ICE'!J5 -> 100.65583 | M5: ='Prix_ICE'!K5 -> 2219.0813 | N5: =D5/E5 -> 0.21135284
A6: 2011/12 | B6: ='Donnees_USDA'!D102 -> 144837 | C6: =B6/1000 -> 144.837 | D6: ='Donnees_USDA'!D408 -> 25748 | E6: ='Donnees_USDA'!D510 -> 142831 | F6: ='Donnees_USDA'!D612 -> 118031 | G6: =D6/(E6+F6) -> 0.098703529 | H6: ='Stocks_certifies'!H6 -> 2.43 | I6: ='Stocks_certifies'!I6 -> 2.17 | J6: =(H6+I6)*1000/(E6+F6) -> 0.017633845 | K6: ='Prix_ICE'!I6 -> 197.84167 | L6: ='Prix_ICE'!J6 -> 91.384167 | M6: ='Prix_ICE'!K6 -> 2014.676 | N6: =D6/E6 -> 0.18026899
A7: 2012/13 | B7: ='Donnees_USDA'!E102 -> 158018 | C7: =B7/1000 -> 158.018 | D7: ='Donnees_USDA'!E408 -> 35365 | E7: ='Donnees_USDA'!E510 -> 143400 | F7: ='Donnees_USDA'!E612 -> 123239 | G7: =D7/(E7+F7) -> 0.13263251 | H7: ='Stocks_certifies'!H7 -> 3.13 | I7: ='Stocks_certifies'!I7 -> 1.01 | J7: =(H7+I7)*1000/(E7+F7) -> 0.015526611 | K7: ='Prix_ICE'!I7 -> 140.69833 | L7: ='Prix_ICE'!J7 -> 88.480833 | M7: ='Prix_ICE'!K7 -> 1950.6685 | N7: =D7/E7 -> 0.24661785
A8: 2013/14 | B8: ='Donnees_USDA'!F102 -> 160054 | C8: =B8/1000 -> 160.054 | D8: ='Donnees_USDA'!F408 -> 41184 | E8: ='Donnees_USDA'!F510 -> 143877 | F8: ='Donnees_USDA'!F612 -> 129260 | G8: =D8/(E8+F8) -> 0.15078148 | H8: ='Stocks_certifies'!H8 -> 2.68 | I8: ='Stocks_certifies'!I8 -> 1.88 | J8: =(H8+I8)*1000/(E8+F8) -> 0.016694919 | K8: ='Prix_ICE'!I8 -> 161.4675 | L8: ='Prix_ICE'!J8 -> 85.874167 | M8: ='Prix_ICE'!K8 -> 1893.2013 | N8: =D8/E8 -> 0.2862445
A9: 2014/15 | B9: ='Donnees_USDA'!G102 -> 153796 | C9: =B9/1000 -> 153.796 | D9: ='Donnees_USDA'!G408 -> 43132 | E9: ='Donnees_USDA'!G510 -> 147163 | F9: ='Donnees_USDA'!G612 -> 124027 | G9: =D9/(E9+F9) -> 0.15904716 | H9: ='Stocks_certifies'!H9 -> 2.28 | I9: ='Stocks_certifies'!I9 -> 3.43 | J9: =(H9+I9)*1000/(E9+F9) -> 0.021055349 | K9: ='Prix_ICE'!I9 -> 154.02083 | L9: ='Prix_ICE'!J9 -> 83.910833 | M9: ='Prix_ICE'!K9 -> 1849.9172 | N9: =D9/E9 -> 0.29308998
A10: 2015/16 | B10: ='Donnees_USDA'!H102 -> 152429 | C10: =B10/1000 -> 152.429 | D10: ='Donnees_USDA'!H408 -> 34951 | E10: ='Donnees_USDA'!H510 -> 153186 | F10: ='Donnees_USDA'!H612 -> 133845 | G10: =D10/(E10+F10) -> 0.12176734 | H10: ='Stocks_certifies'!H10 -> 1.42 | I10: ='Stocks_certifies'!I10 -> 2.32 | J10: =(H10+I10)*1000/(E10+F10) -> 0.013029951 | K10: ='Prix_ICE'!I10 -> 131.8325 | L10: ='Prix_ICE'!J10 -> 74.068333 | M10: ='Prix_ICE'!K10 -> 1632.9272 | N10: =D10/E10 -> 0.22816054
A11: 2016/17 | B11: ='Donnees_USDA'!I102 -> 161079 | C11: =B11/1000 -> 161.079 | D11: ='Donnees_USDA'!I408 -> 36453 | E11: ='Donnees_USDA'!I510 -> 155104 | F11: ='Donnees_USDA'!I612 -> 133606 | G11: =D11/(E11+F11) -> 0.12626165 | H11: ='Stocks_certifies'!H11 -> 2.03 | I11: ='Stocks_certifies'!I11 -> 2.52 | J11: =(H11+I11)*1000/(E11+F11) -> 0.015759759 | K11: ='Prix_ICE'!I11 -> 143.77167 | L11: ='Prix_ICE'!J11 -> 95.123333 | M11: ='Prix_ICE'!K11 -> 2097.1105 | N11: =D11/E11 -> 0.23502295
A12: 2017/18 | B12: ='Donnees_USDA'!J102 -> 159814 | C12: =B12/1000 -> 159.814 | D12: ='Donnees_USDA'!J408 -> 31951 | E12: ='Donnees_USDA'!J510 -> 160627 | F12: ='Donnees_USDA'!J612 -> 134174 | G12: =D12/(E12+F12) -> 0.10838159 | H12: ='Stocks_certifies'!H12 -> 2.7 | I12: ='Stocks_certifies'!I12 -> 1.51 | J12: =(H12+I12)*1000/(E12+F12) -> 0.01428082 | K12: ='Prix_ICE'!I12 -> 120.60083 | L12: ='Prix_ICE'!J12 -> 78.285 | M12: ='Prix_ICE'!K12 -> 1725.8888 | N12: =D12/E12 -> 0.19891425
A13: 2018/19 | B13: ='Donnees_USDA'!K102 -> 175856 | C13: =B13/1000 -> 175.856 | D13: ='Donnees_USDA'!K408 -> 36946 | E13: ='Donnees_USDA'!K510 -> 166003 | F13: ='Donnees_USDA'!K612 -> 143364 | G13: =D13/(E13+F13) -> 0.1194245 | H13: ='Stocks_certifies'!H13 -> 2.6 | I13: ='Stocks_certifies'!I13 -> 2.62 | J13: =(H13+I13)*1000/(E13+F13) -> 0.016873164 | K13: ='Prix_ICE'!I13 -> 104.98083 | L13: ='Prix_ICE'!J13 -> 67.5325 | M13: ='Prix_ICE'!K13 -> 1488.8368 | N13: =D13/E13 -> 0.22256224
A14: 2019/20 | B14: ='Donnees_USDA'!L102 -> 169030 | C14: =B14/1000 -> 169.03 | D14: ='Donnees_USDA'!L408 -> 35808 | E14: ='Donnees_USDA'!L510 -> 162355 | F14: ='Donnees_USDA'!L612 -> 139001 | G14: =D14/(E14+F14) -> 0.11882292 | H14: ='Stocks_certifies'!H14 -> 1.26 | I14: ='Stocks_certifies'!I14 -> 1.85 | J14: =(H14+I14)*1000/(E14+F14) -> 0.01032002 | K14: ='Prix_ICE'!I14 -> 113.23667 | L14: ='Prix_ICE'!J14 -> 59.220833 | M14: ='Prix_ICE'!K14 -> 1305.5959 | N14: =D14/E14 -> 0.22055372
A15: 2020/21 | B15: ='Donnees_USDA'!M102 -> 176594 | C15: =B15/1000 -> 176.594 | D15: ='Donnees_USDA'!M408 -> 37494 | E15: ='Donnees_USDA'!M510 -> 162093 | F15: ='Donnees_USDA'!M612 -> 144941 | G15: =D15/(E15+F15) -> 0.12211677 | H15: ='Stocks_certifies'!H15 -> 2.27 | I15: ='Stocks_certifies'!I15 -> 2.1 | J15: =(H15+I15)*1000/(E15+F15) -> 0.014232951 | K15: ='Prix_ICE'!I15 -> 143.75333 | L15: ='Prix_ICE'!J15 -> 69.895833 | M15: ='Prix_ICE'!K15 -> 1540.9394 | N15: =D15/E15 -> 0.23131165
A16: 2021/22 | B16: ='Donnees_USDA'!N102 -> 165044 | C16: =B16/1000 -> 165.044 | D16: ='Donnees_USDA'!N408 -> 31940 | E16: ='Donnees_USDA'!N510 -> 167876 | F16: ='Donnees_USDA'!N612 -> 143583 | G16: =D16/(E16+F16) -> 0.10254961 | H16: ='Stocks_certifies'!H16 -> 0.45 | I16: ='Stocks_certifies'!I16 -> 1.59 | J16: =(H16+I16)*1000/(E16+F16) -> 0.0065498188 | K16: ='Prix_ICE'!I16 -> 224.0875 | L16: ='Prix_ICE'!J16 -> 97.529167 | M16: ='Prix_ICE'!K16 -> 2150.1501 | N16: =D16/E16 -> 0.19025948
A17: 2022/23 | B17: ='Donnees_USDA'!O102 -> 164529 | C17: =B17/1000 -> 164.529 | D17: ='Donnees_USDA'!O408 -> 26934 | E17: ='Donnees_USDA'!O510 -> 168754 | F17: ='Donnees_USDA'!O612 -> 134699 | G17: =D17/(E17+F17) -> 0.088758391 | H17: ='Stocks_certifies'!H17 -> 0.49 | I17: ='Stocks_certifies'!I17 -> 0.73 | J17: =(H17+I17)*1000/(E17+F17) -> 0.004020392 | K17: ='Prix_ICE'!I17 -> 171.19 | L17: ='Prix_ICE'!J17 -> 100.565 | M17: ='Prix_ICE'!K17 -> 2217.0787 | N17: =D17/E17 -> 0.15960511
A18: 2023/24 | B18: ='Donnees_USDA'!P102 -> 169335 | C18: =B18/1000 -> 169.335 | D18: ='Donnees_USDA'!P408 -> 23121 | E18: ='Donnees_USDA'!P510 -> 163944 | F18: ='Donnees_USDA'!P612 -> 143474 | G18: =D18/(E18+F18) -> 0.0752103 | H18: ='Stocks_certifies'!H18 -> 0.87 | I18: ='Stocks_certifies'!I18 -> 0.74 | J18: =(H18+I18)*1000/(E18+F18) -> 0.0052371689 | K18: ='Prix_ICE'!I18 -> 204.00167 | L18: ='Prix_ICE'!J18 -> 158.95 | M18: ='Prix_ICE'!K18 -> 3504.2477 | N18: =D18/E18 -> 0.14102986
A19: 2024/25 | B19: ='Donnees_USDA'!Q102 -> 176816 | C19: =B19/1000 -> 176.816 | D19: ='Donnees_USDA'!Q408 -> 22010 | E19: ='Donnees_USDA'!Q510 -> 171761 | F19: ='Donnees_USDA'!Q612 -> 147746 | G19: =D19/(E19+F19) -> 0.06888738 | H19: ='Stocks_certifies'!H19 -> 0.62 | I19: ='Stocks_certifies'!I19 -> 1.08 | J19: =(H19+I19)*1000/(E19+F19) -> 0.0053206972 | K19: ='Prix_ICE'!I19 -> 333.06 | L19: ='Prix_ICE'!J19 -> 213.2675 | M19: ='Prix_ICE'!K19 -> 4701.7435 | N19: =D19/E19 -> 0.12814318
A20: 2025/26 | B20: ='Donnees_USDA'!R102 -> 178830 | C20: =B20/1000 -> 178.83 | D20: ='Donnees_USDA'!R408 -> 24370 | E20: ='Donnees_USDA'!R510 -> 173459 | F20: ='Donnees_USDA'!R612 -> 145942 | G20: =D20/(E20+F20) -> 0.076299072 | H20: ='Stocks_certifies'!H20 -> 0.24 | I20: ='Stocks_certifies'!I20 -> 0.83 | J20: =(H20+I20)*1000/(E20+F20) -> 0.0033500208 | K20: ='Prix_ICE'!I20 -> 312.21 | L20: ='Prix_ICE'!J20 -> 171.84182 | M20: ='Prix_ICE'!K20 -> 3788.4636 | N20: =D20/E20 -> 0.1404943
A21: 2026/27 (prév.) | B21: ='Donnees_USDA'!S102 -> 189667 | C21: =B21/1000 -> 189.667 | D21: ='Donnees_USDA'!S408 -> 26283 | E21: ='Donnees_USDA'!S510 -> 179736 | F21: ='Donnees_USDA'!S612 -> 158874 | G21: =D21/(E21+F21) -> 0.077620271 | N21: =D21/E21 -> 0.14623114
A23: Lecture : la production mondiale monte de 141 à 190 M sacs sans lien avec le niveau des prix. Le STU mondial suit le prix à l'envers (corrélation -0,63 avec le KC, -0,72 avec le DF, sur le logarithme des prix, 16 campagnes). Ce lien repose surtout sur 2023/24-2025/26 (STU < 8 %) : sans ces trois campagnes, -0,26 et -0,21. Définition USDA/ICO (stocks ÷ conso) en colonne N : même forme, niveau plus haut.

Sheet 2_Arabica
A1: 2 — Arabica : production, stock-to-use (stocks de fin) et stock-to-use des stocks certifiés New York, avec KC1
A2: STU des PAYS D'ORIGINE. L'USDA ne publie les stocks, la consommation et les exportations que tous cafés confondus, pays par pays. Méthode : pour chaque pays d'origine (42 exportateurs nets), stocks et utilisation sont multipliés par la part de l'espèce dans sa production de l'année, puis additionnés. Les stocks des pays consommateurs (UE, États-Unis, Japon : 51 à 77 % des stocks mondiaux, dont les stocks certifiés) ne sont pas répartis par espèce : ils ne sont que dans le STU mondial (onglet 1).
A3: Colonnes J-K : tests sans répartition. Espèce majoritaire (100 %) : même courbe que la méthode (corrélation 0,99). Pays « purs » ≥ 90 % : 0,31 — courbe différente, car le Brésil (60 à 81 % d'arabica) en est exclu.
A4: Campagne | B4: Production arabica monde (1000 sacs) | C4: Production arabica (M sacs) | D4: Stocks de fin arabica (pays d'origine) | E4: Conso + export arabica (pays d'origine) | F4: STU arabica = stocks ÷ (conso + export) | G4: Certifiés New York (M sacs, fin de campagne) | H4: STU certifié = certifiés ÷ (conso + export) | I4: KC1 (US c/lb) | J4: Test : STU espèce majoritaire (100 %) | K4: Test : STU pays purs (≥ 90 %)
A5: 2010/11 | B5: ='Donnees_USDA'!C204 -> 87943 | C5: =B5/1000 -> 87.943 | D5: =SUMPRODUCT('Donnees_USDA'!C312:C353,'Donnees_USDA'!C720:C761) -> 4474.3687 | E5: =SUMPRODUCT('Donnees_USDA'!C414:C455,'Donnees_USDA'!C720:C761)+SUMPRODUCT('Donnees_USDA'!C516:C557,'Donnees_USDA'!C720:C761) -> 90468.29 | F5: =D5/E5 -> 0.049457868 | I5: ='Prix_ICE'!I5 -> 249.66 | J5: =SUMPRODUCT('Donnees_USDA'!C312:C353,'Donnees_USDA'!C924:C965)/(SUMPRODUCT('Donnees_USDA'!C414:C455,'Donnees_USDA'!C924:C965)+SUMPRODUCT('Donnees_USDA'!C516:C557,'Donnees_USDA'!C924:C965)) -> 0.045543955 | K5: =SUMPRODUCT('Donnees_USDA'!C312:C353,'Donnees_USDA'!C1128:C1169)/(SUMPRODUCT('Donnees_USDA'!C414:C455,'Donnees_USDA'!C1128:C1169)+SUMPRODUCT('Donnees_USDA'!C516:C557,'Donnees_USDA'!C1128:C1169)) -> 0.033546553
A6: 2011/12 | B6: ='Donnees_USDA'!D204 -> 84542 | C6: =B6/1000 -> 84.542 | D6: =SUMPRODUCT('Donnees_USDA'!D312:D353,'Donnees_USDA'!D720:D761) -> 4373.0747 | E6: =SUMPRODUCT('Donnees_USDA'!D414:D455,'Donnees_USDA'!D720:D761)+SUMPRODUCT('Donnees_USDA'!D516:D557,'Donnees_USDA'!D720:D761) -> 86770.502 | F6: =D6/E6 -> 0.050398172 | G6: ='Stocks_certifies'!H6 -> 2.43 | H6: =G6*1000/E6 -> 0.028004909 | I6: ='Prix_ICE'!I6 -> 197.84167 | J6: =SUMPRODUCT('Donnees_USDA'!D312:D353,'Donnees_USDA'!D924:D965)/(SUMPRODUCT('Donnees_USDA'!D414:D455,'Donnees_USDA'!D924:D965)+SUMPRODUCT('Donnees_USDA'!D516:D557,'Donnees_USDA'!D924:D965)) -> 0.045761927 | K6: =SUMPRODUCT('Donnees_USDA'!D312:D353,'Donnees_USDA'!D1128:D1169)/(SUMPRODUCT('Donnees_USDA'!D414:D455,'Donnees_USDA'!D1128:D1169)+SUMPRODUCT('Donnees_USDA'!D516:D557,'Donnees_USDA'!D1128:D1169)) -> 0.043491809
A7: 2012/13 | B7: ='Donnees_USDA'!E204 -> 92872 | C7: =B7/1000 -> 92.872 | D7: =SUMPRODUCT('Donnees_USDA'!E312:E353,'Donnees_USDA'!E720:E761) -> 9514.9917 | E7: =SUMPRODUCT('Donnees_USDA'!E414:E455,'Donnees_USDA'!E720:E761)+SUMPRODUCT('Donnees_USDA'!E516:E557,'Donnees_USDA'!E720:E761) -> 89074.254 | F7: =D7/E7 -> 0.1068209 | G7: ='Stocks_certifies'!H7 -> 3.13 | H7: =G7*1000/E7 -> 0.035139222 | I7: ='Prix_ICE'!I7 -> 140.69833 | J7: =SUMPRODUCT('Donnees_USDA'!E312:E353,'Donnees_USDA'!E924:E965)/(SUMPRODUCT('Donnees_USDA'!E414:E455,'Donnees_USDA'!E924:E965)+SUMPRODUCT('Donnees_USDA'!E516:E557,'Donnees_USDA'!E924:E965)) -> 0.11615704 | K7: =SUMPRODUCT('Donnees_USDA'!E312:E353,'Donnees_USDA'!E1128:E1169)/(SUMPRODUCT('Donnees_USDA'!E414:E455,'Donnees_USDA'!E1128:E1169)+SUMPRODUCT('Donnees_USDA'!E516:E557,'Donnees_USDA'!E1128:E1169)) -> 0.039625263
A8: 2013/14 | B8: ='Donnees_USDA'!F204 -> 92465 | C8: =B8/1000 -> 92.465 | D8: =SUMPRODUCT('Donnees_USDA'!F312:F353,'Donnees_USDA'!F720:F761) -> 12077.864 | E8: =SUMPRODUCT('Donnees_USDA'!F414:F455,'Donnees_USDA'!F720:F761)+SUMPRODUCT('Donnees_USDA'!F516:F557,'Donnees_USDA'!F720:F761) -> 91093.228 | F8: =D8/E8 -> 0.13258795 | G8: ='Stocks_certifies'!H8 -> 2.68 | H8: =G8*1000/E8 -> 0.029420409 | I8: ='Prix_ICE'!I8 -> 161.4675 | J8: =SUMPRODUCT('Donnees_USDA'!F312:F353,'Donnees_USDA'!F924:F965)/(SUMPRODUCT('Donnees_USDA'!F414:F455,'Donnees_USDA'!F924:F965)+SUMPRODUCT('Donnees_USDA'!F516:F557,'Donnees_USDA'!F924:F965)) -> 0.14601268 | K8: =SUMPRODUCT('Donnees_USDA'!F312:F353,'Donnees_USDA'!F1128:F1169)/(SUMPRODUCT('Donnees_USDA'!F414:F455,'Donnees_USDA'!F1128:F1169)+SUMPRODUCT('Donnees_USDA'!F516:F557,'Donnees_USDA'!F1128:F1169)) -> 0.048254457
A9: 2014/15 | B9: ='Donnees_USDA'!G204 -> 86688 | C9: =B9/1000 -> 86.688 | D9: =SUMPRODUCT('Donnees_USDA'!G312:G353,'Donnees_USDA'!G720:G761) -> 9532.9157 | E9: =SUMPRODUCT('Donnees_USDA'!G414:G455,'Donnees_USDA'!G720:G761)+SUMPRODUCT('Donnees_USDA'!G516:G557,'Donnees_USDA'!G720:G761) -> 89143.069 | F9: =D9/E9 -> 0.10693951 | G9: ='Stocks_certifies'!H9 -> 2.28 | H9: =G9*1000/E9 -> 0.025576862 | I9: ='Prix_ICE'!I9 -> 154.02083 | J9: =SUMPRODUCT('Donnees_USDA'!G312:G353,'Donnees_USDA'!G924:G965)/(SUMPRODUCT('Donnees_USDA'!G414:G455,'Donnees_USDA'!G924:G965)+SUMPRODUCT('Donnees_USDA'!G516:G557,'Donnees_USDA'!G924:G965)) -> 0.11069829 | K9: =SUMPRODUCT('Donnees_USDA'!G312:G353,'Donnees_USDA'!G1128:G1169)/(SUMPRODUCT('Donnees_USDA'!G414:G455,'Donnees_USDA'!G1128:G1169)+SUMPRODUCT('Donnees_USDA'!G516:G557,'Donnees_USDA'!G1128:G1169)) -> 0.038300757
A10: 2015/16 | B10: ='Donnees_USDA'!H204 -> 86135 | C10: =B10/1000 -> 86.135 | D10: =SUMPRODUCT('Donnees_USDA'!H312:H353,'Donnees_USDA'!H720:H761) -> 5330.1739 | E10: =SUMPRODUCT('Donnees_USDA'!H414:H455,'Donnees_USDA'!H720:H761)+SUMPRODUCT('Donnees_USDA'!H516:H557,'Donnees_USDA'!H720:H761) -> 92159.87 | F10: =D10/E10 -> 0.057836169 | G10: ='Stocks_certifies'!H10 -> 1.42 | H10: =G10*1000/E10 -> 0.015408008 | I10: ='Prix_ICE'!I10 -> 131.8325 | J10: =SUMPRODUCT('Donnees_USDA'!H312:H353,'Donnees_USDA'!H924:H965)/(SUMPRODUCT('Donnees_USDA'!H414:H455,'Donnees_USDA'!H924:H965)+SUMPRODUCT('Donnees_USDA'!H516:H557,'Donnees_USDA'!H924:H965)) -> 0.048712343 | K10: =SUMPRODUCT('Donnees_USDA'!H312:H353,'Donnees_USDA'!H1128:H1169)/(SUMPRODUCT('Donnees_USDA'!H414:H455,'Donnees_USDA'!H1128:H1169)+SUMPRODUCT('Donnees_USDA'!H516:H557,'Donnees_USDA'!H1128:H1169)) -> 0.052816347
A11: 2016/17 | B11: ='Donnees_USDA'!I204 -> 101136 | C11: =B11/1000 -> 101.136 | D11: =SUMPRODUCT('Donnees_USDA'!I312:I353,'Donnees_USDA'!I720:I761) -> 6145.9664 | E11: =SUMPRODUCT('Donnees_USDA'!I414:I455,'Donnees_USDA'!I720:I761)+SUMPRODUCT('Donnees_USDA'!I516:I557,'Donnees_USDA'!I720:I761) -> 101254.66 | F11: =D11/E11 -> 0.060698111 | G11: ='Stocks_certifies'!H11 -> 2.03 | H11: =G11*1000/E11 -> 0.020048461 | I11: ='Prix_ICE'!I11 -> 143.77167 | J11: =SUMPRODUCT('Donnees_USDA'!I312:I353,'Donnees_USDA'!I924:I965)/(SUMPRODUCT('Donnees_USDA'!I414:I455,'Donnees_USDA'!I924:I965)+SUMPRODUCT('Donnees_USDA'!I516:I557,'Donnees_USDA'!I924:I965)) -> 0.057640498 | K11: =SUMPRODUCT('Donnees_USDA'!I312:I353,'Donnees_USDA'!I1128:I1169)/(SUMPRODUCT('Donnees_USDA'!I414:I455,'Donnees_USDA'!I1128:I1169)+SUMPRODUCT('Donnees_USDA'!I516:I557,'Donnees_USDA'!I1128:I1169)) -> 0.041114111
A12: 2017/18 | B12: ='Donnees_USDA'!J204 -> 95224 | C12: =B12/1000 -> 95.224 | D12: =SUMPRODUCT('Donnees_USDA'!J312:J353,'Donnees_USDA'!J720:J761) -> 5673.6869 | E12: =SUMPRODUCT('Donnees_USDA'!J414:J455,'Donnees_USDA'!J720:J761)+SUMPRODUCT('Donnees_USDA'!J516:J557,'Donnees_USDA'!J720:J761) -> 96715.596 | F12: =D12/E12 -> 0.058663619 | G12: ='Stocks_certifies'!H12 -> 2.7 | H12: =G12*1000/E12 -> 0.027916904 | I12: ='Prix_ICE'!I12 -> 120.60083 | J12: =SUMPRODUCT('Donnees_USDA'!J312:J353,'Donnees_USDA'!J924:J965)/(SUMPRODUCT('Donnees_USDA'!J414:J455,'Donnees_USDA'!J924:J965)+SUMPRODUCT('Donnees_USDA'!J516:J557,'Donnees_USDA'!J924:J965)) -> 0.056923195 | K12: =SUMPRODUCT('Donnees_USDA'!J312:J353,'Donnees_USDA'!J1128:J1169)/(SUMPRODUCT('Donnees_USDA'!J414:J455,'Donnees_USDA'!J1128:J1169)+SUMPRODUCT('Donnees_USDA'!J516:J557,'Donnees_USDA'!J1128:J1169)) -> 0.050295858
A13: 2018/19 | B13: ='Donnees_USDA'!K204 -> 104926 | C13: =B13/1000 -> 104.926 | D13: =SUMPRODUCT('Donnees_USDA'!K312:K353,'Donnees_USDA'!K720:K761) -> 6096.1861 | E13: =SUMPRODUCT('Donnees_USDA'!K414:K455,'Donnees_USDA'!K720:K761)+SUMPRODUCT('Donnees_USDA'!K516:K557,'Donnees_USDA'!K720:K761) -> 106143.21 | F13: =D13/E13 -> 0.057433592 | G13: ='Stocks_certifies'!H13 -> 2.6 | H13: =G13*1000/E13 -> 0.024495207 | I13: ='Prix_ICE'!I13 -> 104.98083 | J13: =SUMPRODUCT('Donnees_USDA'!K312:K353,'Donnees_USDA'!K924:K965)/(SUMPRODUCT('Donnees_USDA'!K414:K455,'Donnees_USDA'!K924:K965)+SUMPRODUCT('Donnees_USDA'!K516:K557,'Donnees_USDA'!K924:K965)) -> 0.058197052 | K13: =SUMPRODUCT('Donnees_USDA'!K312:K353,'Donnees_USDA'!K1128:K1169)/(SUMPRODUCT('Donnees_USDA'!K414:K455,'Donnees_USDA'!K1128:K1169)+SUMPRODUCT('Donnees_USDA'!K516:K557,'Donnees_USDA'!K1128:K1169)) -> 0.030557694
A14: 2019/20 | B14: ='Donnees_USDA'!L204 -> 94921 | C14: =B14/1000 -> 94.921 | D14: =SUMPRODUCT('Donnees_USDA'!L312:L353,'Donnees_USDA'!L720:L761) -> 4625.7279 | E14: =SUMPRODUCT('Donnees_USDA'!L414:L455,'Donnees_USDA'!L720:L761)+SUMPRODUCT('Donnees_USDA'!L516:L557,'Donnees_USDA'!L720:L761) -> 97936.031 | F14: =D14/E14 -> 0.047232135 | G14: ='Stocks_certifies'!H14 -> 1.26 | H14: =G14*1000/E14 -> 0.012865541 | I14: ='Prix_ICE'!I14 -> 113.23667 | J14: =SUMPRODUCT('Donnees_USDA'!L312:L353,'Donnees_USDA'!L924:L965)/(SUMPRODUCT('Donnees_USDA'!L414:L455,'Donnees_USDA'!L924:L965)+SUMPRODUCT('Donnees_USDA'!L516:L557,'Donnees_USDA'!L924:L965)) -> 0.042434468 | K14: =SUMPRODUCT('Donnees_USDA'!L312:L353,'Donnees_USDA'!L1128:L1169)/(SUMPRODUCT('Donnees_USDA'!L414:L455,'Donnees_USDA'!L1128:L1169)+SUMPRODUCT('Donnees_USDA'!L516:L557,'Donnees_USDA'!L1128:L1169)) -> 0.046951745
A15: 2020/21 | B15: ='Donnees_USDA'!M204 -> 102155 | C15: =B15/1000 -> 102.155 | D15: =SUMPRODUCT('Donnees_USDA'!M312:M353,'Donnees_USDA'!M720:M761) -> 6273.5205 | E15: =SUMPRODUCT('Donnees_USDA'!M414:M455,'Donnees_USDA'!M720:M761)+SUMPRODUCT('Donnees_USDA'!M516:M557,'Donnees_USDA'!M720:M761) -> 103161.87 | F15: =D15/E15 -> 0.060812395 | G15: ='Stocks_certifies'!H15 -> 2.27 | H15: =G15*1000/E15 -> 0.022004254 | I15: ='Prix_ICE'!I15 -> 143.75333 | J15: =SUMPRODUCT('Donnees_USDA'!M312:M353,'Donnees_USDA'!M924:M965)/(SUMPRODUCT('Donnees_USDA'!M414:M455,'Donnees_USDA'!M924:M965)+SUMPRODUCT('Donnees_USDA'!M516:M557,'Donnees_USDA'!M924:M965)) -> 0.058215662 | K15: =SUMPRODUCT('Donnees_USDA'!M312:M353,'Donnees_USDA'!M1128:M1169)/(SUMPRODUCT('Donnees_USDA'!M414:M455,'Donnees_USDA'!M1128:M1169)+SUMPRODUCT('Donnees_USDA'!M516:M557,'Donnees_USDA'!M1128:M1169)) -> 0.053951213
A16: 2021/22 | B16: ='Donnees_USDA'!N204 -> 87089 | C16: =B16/1000 -> 87.089 | D16: =SUMPRODUCT('Donnees_USDA'!N312:N353,'Donnees_USDA'!N720:N761) -> 2451.9278 | E16: =SUMPRODUCT('Donnees_USDA'!N414:N455,'Donnees_USDA'!N720:N761)+SUMPRODUCT('Donnees_USDA'!N516:N557,'Donnees_USDA'!N720:N761) -> 93909.889 | F16: =D16/E16 -> 0.026109367 | G16: ='Stocks_certifies'!H16 -> 0.45 | H16: =G16*1000/E16 -> 0.0047918276 | I16: ='Prix_ICE'!I16 -> 224.0875 | J16: =SUMPRODUCT('Donnees_USDA'!N312:N353,'Donnees_USDA'!N924:N965)/(SUMPRODUCT('Donnees_USDA'!N414:N455,'Donnees_USDA'!N924:N965)+SUMPRODUCT('Donnees_USDA'!N516:N557,'Donnees_USDA'!N924:N965)) -> 0.020110274 | K16: =SUMPRODUCT('Donnees_USDA'!N312:N353,'Donnees_USDA'!N1128:N1169)/(SUMPRODUCT('Donnees_USDA'!N414:N455,'Donnees_USDA'!N1128:N1169)+SUMPRODUCT('Donnees_USDA'!N516:N557,'Donnees_USDA'!N1128:N1169)) -> 0.036178619
A17: 2022/23 | B17: ='Donnees_USDA'!O204 -> 87908 | C17: =B17/1000 -> 87.908 | D17: =SUMPRODUCT('Donnees_USDA'!O312:O353,'Donnees_USDA'!O720:O761) -> 4817.1311 | E17: =SUMPRODUCT('Donnees_USDA'!O414:O455,'Donnees_USDA'!O720:O761)+SUMPRODUCT('Donnees_USDA'!O516:O557,'Donnees_USDA'!O720:O761) -> 88807.386 | F17: =D17/E17 -> 0.05424246 | G17: ='Stocks_certifies'!H17 -> 0.49 | H17: =G17*1000/E17 -> 0.0055175591 | I17: ='Prix_ICE'!I17 -> 171.19 | J17: =SUMPRODUCT('Donnees_USDA'!O312:O353,'Donnees_USDA'!O924:O965)/(SUMPRODUCT('Donnees_USDA'!O414:O455,'Donnees_USDA'!O924:O965)+SUMPRODUCT('Donnees_USDA'!O516:O557,'Donnees_USDA'!O924:O965)) -> 0.058545245 | K17: =SUMPRODUCT('Donnees_USDA'!O312:O353,'Donnees_USDA'!O1128:O1169)/(SUMPRODUCT('Donnees_USDA'!O414:O455,'Donnees_USDA'!O1128:O1169)+SUMPRODUCT('Donnees_USDA'!O516:O557,'Donnees_USDA'!O1128:O1169)) -> 0.036544686
A18: 2023/24 | B18: ='Donnees_USDA'!P204 -> 97160 | C18: =B18/1000 -> 97.16 | D18: =SUMPRODUCT('Donnees_USDA'!P312:P353,'Donnees_USDA'!P720:P761) -> 3083.2351 | E18: =SUMPRODUCT('Donnees_USDA'!P414:P455,'Donnees_USDA'!P720:P761)+SUMPRODUCT('Donnees_USDA'!P516:P557,'Donnees_USDA'!P720:P761) -> 101400.76 | F18: =D18/E18 -> 0.030406431 | G18: ='Stocks_certifies'!H18 -> 0.87 | H18: =G18*1000/E18 -> 0.0085798177 | I18: ='Prix_ICE'!I18 -> 204.00167 | J18: =SUMPRODUCT('Donnees_USDA'!P312:P353,'Donnees_USDA'!P924:P965)/(SUMPRODUCT('Donnees_USDA'!P414:P455,'Donnees_USDA'!P924:P965)+SUMPRODUCT('Donnees_USDA'!P516:P557,'Donnees_USDA'!P924:P965)) -> 0.029703717 | K18: =SUMPRODUCT('Donnees_USDA'!P312:P353,'Donnees_USDA'!P1128:P1169)/(SUMPRODUCT('Donnees_USDA'!P414:P455,'Donnees_USDA'!P1128:P1169)+SUMPRODUCT('Donnees_USDA'!P516:P557,'Donnees_USDA'!P1128:P1169)) -> 0.032614717
A19: 2024/25 | B19: ='Donnees_USDA'!Q204 -> 102276 | C19: =B19/1000 -> 102.276 | D19: =SUMPRODUCT('Donnees_USDA'!Q312:Q353,'Donnees_USDA'!Q720:Q761) -> 2712.5481 | E19: =SUMPRODUCT('Donnees_USDA'!Q414:Q455,'Donnees_USDA'!Q720:Q761)+SUMPRODUCT('Donnees_USDA'!Q516:Q557,'Donnees_USDA'!Q720:Q761) -> 105510.21 | F19: =D19/E19 -> 0.025708868 | G19: ='Stocks_certifies'!H19 -> 0.62 | H19: =G19*1000/E19 -> 0.0058762083 | I19: ='Prix_ICE'!I19 -> 333.06 | J19: =SUMPRODUCT('Donnees_USDA'!Q312:Q353,'Donnees_USDA'!Q924:Q965)/(SUMPRODUCT('Donnees_USDA'!Q414:Q455,'Donnees_USDA'!Q924:Q965)+SUMPRODUCT('Donnees_USDA'!Q516:Q557,'Donnees_USDA'!Q924:Q965)) -> 0.022630314 | K19: =SUMPRODUCT('Donnees_USDA'!Q312:Q353,'Donnees_USDA'!Q1128:Q1169)/(SUMPRODUCT('Donnees_USDA'!Q414:Q455,'Donnees_USDA'!Q1128:Q1169)+SUMPRODUCT('Donnees_USDA'!Q516:Q557,'Donnees_USDA'!Q1128:Q1169)) -> 0.03248559
A20: 2025/26 | B20: ='Donnees_USDA'!R204 -> 94440 | C20: =B20/1000 -> 94.44 | D20: =SUMPRODUCT('Donnees_USDA'!R312:R353,'Donnees_USDA'!R720:R761) -> 4672.9401 | E20: =SUMPRODUCT('Donnees_USDA'!R414:R455,'Donnees_USDA'!R720:R761)+SUMPRODUCT('Donnees_USDA'!R516:R557,'Donnees_USDA'!R720:R761) -> 96609.532 | F20: =D20/E20 -> 0.048369348 | G20: ='Stocks_certifies'!H20 -> 0.24 | H20: =G20*1000/E20 -> 0.0024842269 | I20: ='Prix_ICE'!I20 -> 312.21 | J20: =SUMPRODUCT('Donnees_USDA'!R312:R353,'Donnees_USDA'!R924:R965)/(SUMPRODUCT('Donnees_USDA'!R414:R455,'Donnees_USDA'!R924:R965)+SUMPRODUCT('Donnees_USDA'!R516:R557,'Donnees_USDA'!R924:R965)) -> 0.051171404 | K20: =SUMPRODUCT('Donnees_USDA'!R312:R353,'Donnees_USDA'!R1128:R1169)/(SUMPRODUCT('Donnees_USDA'!R414:R455,'Donnees_USDA'!R1128:R1169)+SUMPRODUCT('Donnees_USDA'!R516:R557,'Donnees_USDA'!R1128:R1169)) -> 0.041244649
A21: 2026/27 (prév.) | B21: ='Donnees_USDA'!S204 -> 105867 | C21: =B21/1000 -> 105.867 | D21: =SUMPRODUCT('Donnees_USDA'!S312:S353,'Donnees_USDA'!S720:S761) -> 5169.044 | E21: =SUMPRODUCT('Donnees_USDA'!S414:S455,'Donnees_USDA'!S720:S761)+SUMPRODUCT('Donnees_USDA'!S516:S557,'Donnees_USDA'!S720:S761) -> 109453.09 | F21: =D21/E21 -> 0.047226115 | J21: =SUMPRODUCT('Donnees_USDA'!S312:S353,'Donnees_USDA'!S924:S965)/(SUMPRODUCT('Donnees_USDA'!S414:S455,'Donnees_USDA'!S924:S965)+SUMPRODUCT('Donnees_USDA'!S516:S557,'Donnees_USDA'!S924:S965)) -> 0.050486097 | K21: =SUMPRODUCT('Donnees_USDA'!S312:S353,'Donnees_USDA'!S1128:S1169)/(SUMPRODUCT('Donnees_USDA'!S414:S455,'Donnees_USDA'!S1128:S1169)+SUMPRODUCT('Donnees_USDA'!S516:S557,'Donnees_USDA'!S1128:S1169)) -> 0.039105249
A23: Corrélations avec le logarithme du KC (16 campagnes ; 15 pour les certifiés) : production -0,14, STU stocks de fin -0,39, STU certifié -0,61. Le lien certifiés / KC vient surtout de la tendance commune (sans tendance -0,34), un peu du point 2025/26 (sans lui -0,51, toujours le plus fort). Le KC réagit à la récolte arabica de la campagne suivante (-0,49), pas à celle en cours (-0,08).

Sheet 3_Robusta
A1: 3 — Robusta : production, stock-to-use (stocks de fin) et stock-to-use des stocks certifiés Londres, avec DF1
A2: STU des PAYS D'ORIGINE. L'USDA ne publie les stocks, la consommation et les exportations que tous cafés confondus, pays par pays. Méthode : pour chaque pays d'origine (42 exportateurs nets), stocks et utilisation sont multipliés par la part de l'espèce dans sa production de l'année, puis additionnés. Les stocks des pays consommateurs (UE, États-Unis, Japon : 51 à 77 % des stocks mondiaux, dont les stocks certifiés) ne sont pas répartis par espèce : ils ne sont que dans le STU mondial (onglet 1).
A3: Colonnes J-K : tests sans répartition. Espèce majoritaire (100 %) : même courbe que la méthode (corrélation 0,94). Pays « purs » ≥ 90 % : 0,88 — même forme.
A4: Campagne | B4: Production robusta monde (1000 sacs) | C4: Production robusta (M sacs) | D4: Stocks de fin robusta (pays d'origine) | E4: Conso + export robusta (pays d'origine) | F4: STU robusta = stocks ÷ (conso + export) | G4: Certifiés Londres (M sacs, fin de campagne) | H4: STU certifié = certifiés ÷ (conso + export) | I4: DF1 (US$/t) | J4: Test : STU espèce majoritaire (100 %) | K4: Test : STU pays purs (≥ 90 %)
A5: 2010/11 | B5: ='Donnees_USDA'!C306 -> 53466 | C5: =B5/1000 -> 53.466 | D5: =SUMPRODUCT('Donnees_USDA'!C312:C353,'Donnees_USDA'!C822:C863) -> 3853.6313 | E5: =SUMPRODUCT('Donnees_USDA'!C414:C455,'Donnees_USDA'!C822:C863)+SUMPRODUCT('Donnees_USDA'!C516:C557,'Donnees_USDA'!C822:C863) -> 58714.71 | F5: =D5/E5 -> 0.065633149 | I5: ='Prix_ICE'!K5 -> 2219.0813 | J5: =SUMPRODUCT('Donnees_USDA'!C312:C353,'Donnees_USDA'!C1026:C1067)/(SUMPRODUCT('Donnees_USDA'!C414:C455,'Donnees_USDA'!C1026:C1067)+SUMPRODUCT('Donnees_USDA'!C516:C557,'Donnees_USDA'!C1026:C1067)) -> 0.076186861 | K5: =SUMPRODUCT('Donnees_USDA'!C312:C353,'Donnees_USDA'!C1230:C1271)/(SUMPRODUCT('Donnees_USDA'!C414:C455,'Donnees_USDA'!C1230:C1271)+SUMPRODUCT('Donnees_USDA'!C516:C557,'Donnees_USDA'!C1230:C1271)) -> 0.047679386
A6: 2011/12 | B6: ='Donnees_USDA'!D306 -> 60295 | C6: =B6/1000 -> 60.295 | D6: =SUMPRODUCT('Donnees_USDA'!D312:D353,'Donnees_USDA'!D822:D863) -> 3466.9253 | E6: =SUMPRODUCT('Donnees_USDA'!D414:D455,'Donnees_USDA'!D822:D863)+SUMPRODUCT('Donnees_USDA'!D516:D557,'Donnees_USDA'!D822:D863) -> 64830.498 | F6: =D6/E6 -> 0.053476765 | G6: ='Stocks_certifies'!I6 -> 2.17 | H6: =G6*1000/E6 -> 0.033471901 | I6: ='Prix_ICE'!K6 -> 2014.676 | J6: =SUMPRODUCT('Donnees_USDA'!D312:D353,'Donnees_USDA'!D1026:D1067)/(SUMPRODUCT('Donnees_USDA'!D414:D455,'Donnees_USDA'!D1026:D1067)+SUMPRODUCT('Donnees_USDA'!D516:D557,'Donnees_USDA'!D1026:D1067)) -> 0.062336994 | K6: =SUMPRODUCT('Donnees_USDA'!D312:D353,'Donnees_USDA'!D1230:D1271)/(SUMPRODUCT('Donnees_USDA'!D414:D455,'Donnees_USDA'!D1230:D1271)+SUMPRODUCT('Donnees_USDA'!D516:D557,'Donnees_USDA'!D1230:D1271)) -> 0.03642298
A7: 2012/13 | B7: ='Donnees_USDA'!E306 -> 65146 | C7: =B7/1000 -> 65.146 | D7: =SUMPRODUCT('Donnees_USDA'!E312:E353,'Donnees_USDA'!E822:E863) -> 6411.0083 | E7: =SUMPRODUCT('Donnees_USDA'!E414:E455,'Donnees_USDA'!E822:E863)+SUMPRODUCT('Donnees_USDA'!E516:E557,'Donnees_USDA'!E822:E863) -> 67498.746 | F7: =D7/E7 -> 0.094979666 | G7: ='Stocks_certifies'!I7 -> 1.01 | H7: =G7*1000/E7 -> 0.014963241 | I7: ='Prix_ICE'!K7 -> 1950.6685 | J7: =SUMPRODUCT('Donnees_USDA'!E312:E353,'Donnees_USDA'!E1026:E1067)/(SUMPRODUCT('Donnees_USDA'!E414:E455,'Donnees_USDA'!E1026:E1067)+SUMPRODUCT('Donnees_USDA'!E516:E557,'Donnees_USDA'!E1026:E1067)) -> 0.077460209 | K7: =SUMPRODUCT('Donnees_USDA'!E312:E353,'Donnees_USDA'!E1230:E1271)/(SUMPRODUCT('Donnees_USDA'!E414:E455,'Donnees_USDA'!E1230:E1271)+SUMPRODUCT('Donnees_USDA'!E516:E557,'Donnees_USDA'!E1230:E1271)) -> 0.058680329
A8: 2013/14 | B8: ='Donnees_USDA'!F306 -> 67589 | C8: =B8/1000 -> 67.589 | D8: =SUMPRODUCT('Donnees_USDA'!F312:F353,'Donnees_USDA'!F822:F863) -> 7326.1359 | E8: =SUMPRODUCT('Donnees_USDA'!F414:F455,'Donnees_USDA'!F822:F863)+SUMPRODUCT('Donnees_USDA'!F516:F557,'Donnees_USDA'!F822:F863) -> 71812.772 | F8: =D8/E8 -> 0.10201717 | G8: ='Stocks_certifies'!I8 -> 1.88 | H8: =G8*1000/E8 -> 0.026179187 | I8: ='Prix_ICE'!K8 -> 1893.2013 | J8: =SUMPRODUCT('Donnees_USDA'!F312:F353,'Donnees_USDA'!F1026:F1067)/(SUMPRODUCT('Donnees_USDA'!F414:F455,'Donnees_USDA'!F1026:F1067)+SUMPRODUCT('Donnees_USDA'!F516:F557,'Donnees_USDA'!F1026:F1067)) -> 0.075683656 | K8: =SUMPRODUCT('Donnees_USDA'!F312:F353,'Donnees_USDA'!F1230:F1271)/(SUMPRODUCT('Donnees_USDA'!F414:F455,'Donnees_USDA'!F1230:F1271)+SUMPRODUCT('Donnees_USDA'!F516:F557,'Donnees_USDA'!F1230:F1271)) -> 0.057172369
A9: 2014/15 | B9: ='Donnees_USDA'!G306 -> 67108 | C9: =B9/1000 -> 67.108 | D9: =SUMPRODUCT('Donnees_USDA'!G312:G353,'Donnees_USDA'!G822:G863) -> 11561.084 | E9: =SUMPRODUCT('Donnees_USDA'!G414:G455,'Donnees_USDA'!G822:G863)+SUMPRODUCT('Donnees_USDA'!G516:G557,'Donnees_USDA'!G822:G863) -> 68976.931 | F9: =D9/E9 -> 0.16760798 | G9: ='Stocks_certifies'!I9 -> 3.43 | H9: =G9*1000/E9 -> 0.04972677 | I9: ='Prix_ICE'!K9 -> 1849.9172 | J9: =SUMPRODUCT('Donnees_USDA'!G312:G353,'Donnees_USDA'!G1026:G1067)/(SUMPRODUCT('Donnees_USDA'!G414:G455,'Donnees_USDA'!G1026:G1067)+SUMPRODUCT('Donnees_USDA'!G516:G557,'Donnees_USDA'!G1026:G1067)) -> 0.17499373 | K9: =SUMPRODUCT('Donnees_USDA'!G312:G353,'Donnees_USDA'!G1230:G1271)/(SUMPRODUCT('Donnees_USDA'!G414:G455,'Donnees_USDA'!G1230:G1271)+SUMPRODUCT('Donnees_USDA'!G516:G557,'Donnees_USDA'!G1230:G1271)) -> 0.19317702
A10: 2015/16 | B10: ='Donnees_USDA'!H306 -> 66294 | C10: =B10/1000 -> 66.294 | D10: =SUMPRODUCT('Donnees_USDA'!H312:H353,'Donnees_USDA'!H822:H863) -> 7121.8261 | E10: =SUMPRODUCT('Donnees_USDA'!H414:H455,'Donnees_USDA'!H822:H863)+SUMPRODUCT('Donnees_USDA'!H516:H557,'Donnees_USDA'!H822:H863) -> 75076.13 | F10: =D10/E10 -> 0.094861392 | G10: ='Stocks_certifies'!I10 -> 2.32 | H10: =G10*1000/E10 -> 0.030901966 | I10: ='Prix_ICE'!K10 -> 1632.9272 | J10: =SUMPRODUCT('Donnees_USDA'!H312:H353,'Donnees_USDA'!H1026:H1067)/(SUMPRODUCT('Donnees_USDA'!H414:H455,'Donnees_USDA'!H1026:H1067)+SUMPRODUCT('Donnees_USDA'!H516:H557,'Donnees_USDA'!H1026:H1067)) -> 0.11471891 | K10: =SUMPRODUCT('Donnees_USDA'!H312:H353,'Donnees_USDA'!H1230:H1271)/(SUMPRODUCT('Donnees_USDA'!H414:H455,'Donnees_USDA'!H1230:H1271)+SUMPRODUCT('Donnees_USDA'!H516:H557,'Donnees_USDA'!H1230:H1271)) -> 0.10572775
A11: 2016/17 | B11: ='Donnees_USDA'!I306 -> 59943 | C11: =B11/1000 -> 59.943 | D11: =SUMPRODUCT('Donnees_USDA'!I312:I353,'Donnees_USDA'!I822:I863) -> 5186.0336 | E11: =SUMPRODUCT('Donnees_USDA'!I414:I455,'Donnees_USDA'!I822:I863)+SUMPRODUCT('Donnees_USDA'!I516:I557,'Donnees_USDA'!I822:I863) -> 66386.343 | F11: =D11/E11 -> 0.078118984 | G11: ='Stocks_certifies'!I11 -> 2.52 | H11: =G11*1000/E11 -> 0.037959615 | I11: ='Prix_ICE'!K11 -> 2097.1105 | J11: =SUMPRODUCT('Donnees_USDA'!I312:I353,'Donnees_USDA'!I1026:I1067)/(SUMPRODUCT('Donnees_USDA'!I414:I455,'Donnees_USDA'!I1026:I1067)+SUMPRODUCT('Donnees_USDA'!I516:I557,'Donnees_USDA'!I1026:I1067)) -> 0.084787665 | K11: =SUMPRODUCT('Donnees_USDA'!I312:I353,'Donnees_USDA'!I1230:I1271)/(SUMPRODUCT('Donnees_USDA'!I414:I455,'Donnees_USDA'!I1230:I1271)+SUMPRODUCT('Donnees_USDA'!I516:I557,'Donnees_USDA'!I1230:I1271)) -> 0.074517992
A12: 2017/18 | B12: ='Donnees_USDA'!J306 -> 64590 | C12: =B12/1000 -> 64.59 | D12: =SUMPRODUCT('Donnees_USDA'!J312:J353,'Donnees_USDA'!J822:J863) -> 3035.3131 | E12: =SUMPRODUCT('Donnees_USDA'!J414:J455,'Donnees_USDA'!J822:J863)+SUMPRODUCT('Donnees_USDA'!J516:J557,'Donnees_USDA'!J822:J863) -> 72802.404 | F12: =D12/E12 -> 0.041692485 | G12: ='Stocks_certifies'!I12 -> 1.51 | H12: =G12*1000/E12 -> 0.020741073 | I12: ='Prix_ICE'!K12 -> 1725.8888 | J12: =SUMPRODUCT('Donnees_USDA'!J312:J353,'Donnees_USDA'!J1026:J1067)/(SUMPRODUCT('Donnees_USDA'!J414:J455,'Donnees_USDA'!J1026:J1067)+SUMPRODUCT('Donnees_USDA'!J516:J557,'Donnees_USDA'!J1026:J1067)) -> 0.042498696 | K12: =SUMPRODUCT('Donnees_USDA'!J312:J353,'Donnees_USDA'!J1230:J1271)/(SUMPRODUCT('Donnees_USDA'!J414:J455,'Donnees_USDA'!J1230:J1271)+SUMPRODUCT('Donnees_USDA'!J516:J557,'Donnees_USDA'!J1230:J1271)) -> 0.017069206
A13: 2018/19 | B13: ='Donnees_USDA'!K306 -> 70930 | C13: =B13/1000 -> 70.93 | D13: =SUMPRODUCT('Donnees_USDA'!K312:K353,'Donnees_USDA'!K822:K863) -> 5115.8139 | E13: =SUMPRODUCT('Donnees_USDA'!K414:K455,'Donnees_USDA'!K822:K863)+SUMPRODUCT('Donnees_USDA'!K516:K557,'Donnees_USDA'!K822:K863) -> 75251.786 | F13: =D13/E13 -> 0.067982625 | G13: ='Stocks_certifies'!I13 -> 2.62 | H13: =G13*1000/E13 -> 0.034816449 | I13: ='Prix_ICE'!K13 -> 1488.8368 | J13: =SUMPRODUCT('Donnees_USDA'!K312:K353,'Donnees_USDA'!K1026:K1067)/(SUMPRODUCT('Donnees_USDA'!K414:K455,'Donnees_USDA'!K1026:K1067)+SUMPRODUCT('Donnees_USDA'!K516:K557,'Donnees_USDA'!K1026:K1067)) -> 0.068678726 | K13: =SUMPRODUCT('Donnees_USDA'!K312:K353,'Donnees_USDA'!K1230:K1271)/(SUMPRODUCT('Donnees_USDA'!K414:K455,'Donnees_USDA'!K1230:K1271)+SUMPRODUCT('Donnees_USDA'!K516:K557,'Donnees_USDA'!K1230:K1271)) -> 0.014505271
A14: 2019/20 | B14: ='Donnees_USDA'!L306 -> 74109 | C14: =B14/1000 -> 74.109 | D14: =SUMPRODUCT('Donnees_USDA'!L312:L353,'Donnees_USDA'!L822:L863) -> 5997.2721 | E14: =SUMPRODUCT('Donnees_USDA'!L414:L455,'Donnees_USDA'!L822:L863)+SUMPRODUCT('Donnees_USDA'!L516:L557,'Donnees_USDA'!L822:L863) -> 79117.969 | F14: =D14/E14 -> 0.075801644 | G14: ='Stocks_certifies'!I14 -> 1.85 | H14: =G14*1000/E14 -> 0.023382805 | I14: ='Prix_ICE'!K14 -> 1305.5959 | J14: =SUMPRODUCT('Donnees_USDA'!L312:L353,'Donnees_USDA'!L1026:L1067)/(SUMPRODUCT('Donnees_USDA'!L414:L455,'Donnees_USDA'!L1026:L1067)+SUMPRODUCT('Donnees_USDA'!L516:L557,'Donnees_USDA'!L1026:L1067)) -> 0.091597502 | K14: =SUMPRODUCT('Donnees_USDA'!L312:L353,'Donnees_USDA'!L1230:L1271)/(SUMPRODUCT('Donnees_USDA'!L414:L455,'Donnees_USDA'!L1230:L1271)+SUMPRODUCT('Donnees_USDA'!L516:L557,'Donnees_USDA'!L1230:L1271)) -> 0.055091431
A15: 2020/21 | B15: ='Donnees_USDA'!M306 -> 74439 | C15: =B15/1000 -> 74.439 | D15: =SUMPRODUCT('Donnees_USDA'!M312:M353,'Donnees_USDA'!M822:M863) -> 7449.4795 | E15: =SUMPRODUCT('Donnees_USDA'!M414:M455,'Donnees_USDA'!M822:M863)+SUMPRODUCT('Donnees_USDA'!M516:M557,'Donnees_USDA'!M822:M863) -> 78096.128 | F15: =D15/E15 -> 0.09538859 | G15: ='Stocks_certifies'!I15 -> 2.1 | H15: =G15*1000/E15 -> 0.026889937 | I15: ='Prix_ICE'!K15 -> 1540.9394 | J15: =SUMPRODUCT('Donnees_USDA'!M312:M353,'Donnees_USDA'!M1026:M1067)/(SUMPRODUCT('Donnees_USDA'!M414:M455,'Donnees_USDA'!M1026:M1067)+SUMPRODUCT('Donnees_USDA'!M516:M557,'Donnees_USDA'!M1026:M1067)) -> 0.10901256 | K15: =SUMPRODUCT('Donnees_USDA'!M312:M353,'Donnees_USDA'!M1230:M1271)/(SUMPRODUCT('Donnees_USDA'!M414:M455,'Donnees_USDA'!M1230:M1271)+SUMPRODUCT('Donnees_USDA'!M516:M557,'Donnees_USDA'!M1230:M1271)) -> 0.10422896
A16: 2021/22 | B16: ='Donnees_USDA'!N306 -> 77955 | C16: =B16/1000 -> 77.955 | D16: =SUMPRODUCT('Donnees_USDA'!N312:N353,'Donnees_USDA'!N822:N863) -> 5254.0722 | E16: =SUMPRODUCT('Donnees_USDA'!N414:N455,'Donnees_USDA'!N822:N863)+SUMPRODUCT('Donnees_USDA'!N516:N557,'Donnees_USDA'!N822:N863) -> 86121.111 | F16: =D16/E16 -> 0.061007948 | G16: ='Stocks_certifies'!I16 -> 1.59 | H16: =G16*1000/E16 -> 0.018462372 | I16: ='Prix_ICE'!K16 -> 2150.1501 | J16: =SUMPRODUCT('Donnees_USDA'!N312:N353,'Donnees_USDA'!N1026:N1067)/(SUMPRODUCT('Donnees_USDA'!N414:N455,'Donnees_USDA'!N1026:N1067)+SUMPRODUCT('Donnees_USDA'!N516:N557,'Donnees_USDA'!N1026:N1067)) -> 0.080724608 | K16: =SUMPRODUCT('Donnees_USDA'!N312:N353,'Donnees_USDA'!N1230:N1271)/(SUMPRODUCT('Donnees_USDA'!N414:N455,'Donnees_USDA'!N1230:N1271)+SUMPRODUCT('Donnees_USDA'!N516:N557,'Donnees_USDA'!N1230:N1271)) -> 0.089770407
A17: 2022/23 | B17: ='Donnees_USDA'!O306 -> 76621 | C17: =B17/1000 -> 76.621 | D17: =SUMPRODUCT('Donnees_USDA'!O312:O353,'Donnees_USDA'!O822:O863) -> 3783.8689 | E17: =SUMPRODUCT('Donnees_USDA'!O414:O455,'Donnees_USDA'!O822:O863)+SUMPRODUCT('Donnees_USDA'!O516:O557,'Donnees_USDA'!O822:O863) -> 83350.614 | F17: =D17/E17 -> 0.045397013 | G17: ='Stocks_certifies'!I17 -> 0.73 | H17: =G17*1000/E17 -> 0.0087581838 | I17: ='Prix_ICE'!K17 -> 2217.0787 | J17: =SUMPRODUCT('Donnees_USDA'!O312:O353,'Donnees_USDA'!O1026:O1067)/(SUMPRODUCT('Donnees_USDA'!O414:O455,'Donnees_USDA'!O1026:O1067)+SUMPRODUCT('Donnees_USDA'!O516:O557,'Donnees_USDA'!O1026:O1067)) -> 0.036237681 | K17: =SUMPRODUCT('Donnees_USDA'!O312:O353,'Donnees_USDA'!O1230:O1271)/(SUMPRODUCT('Donnees_USDA'!O414:O455,'Donnees_USDA'!O1230:O1271)+SUMPRODUCT('Donnees_USDA'!O516:O557,'Donnees_USDA'!O1230:O1271)) -> 0.021848958
A18: 2023/24 | B18: ='Donnees_USDA'!P306 -> 72175 | C18: =B18/1000 -> 72.175 | D18: =SUMPRODUCT('Donnees_USDA'!P312:P353,'Donnees_USDA'!P822:P863) -> 2427.7649 | E18: =SUMPRODUCT('Donnees_USDA'!P414:P455,'Donnees_USDA'!P822:P863)+SUMPRODUCT('Donnees_USDA'!P516:P557,'Donnees_USDA'!P822:P863) -> 79542.244 | F18: =D18/E18 -> 0.030521705 | G18: ='Stocks_certifies'!I18 -> 0.74 | H18: =G18*1000/E18 -> 0.0093032326 | I18: ='Prix_ICE'!K18 -> 3504.2477 | J18: =SUMPRODUCT('Donnees_USDA'!P312:P353,'Donnees_USDA'!P1026:P1067)/(SUMPRODUCT('Donnees_USDA'!P414:P455,'Donnees_USDA'!P1026:P1067)+SUMPRODUCT('Donnees_USDA'!P516:P557,'Donnees_USDA'!P1026:P1067)) -> 0.031918004 | K18: =SUMPRODUCT('Donnees_USDA'!P312:P353,'Donnees_USDA'!P1230:P1271)/(SUMPRODUCT('Donnees_USDA'!P414:P455,'Donnees_USDA'!P1230:P1271)+SUMPRODUCT('Donnees_USDA'!P516:P557,'Donnees_USDA'!P1230:P1271)) -> 0.025105902
A19: 2024/25 | B19: ='Donnees_USDA'!Q306 -> 74540 | C19: =B19/1000 -> 74.54 | D19: =SUMPRODUCT('Donnees_USDA'!Q312:Q353,'Donnees_USDA'!Q822:Q863) -> 2459.4519 | E19: =SUMPRODUCT('Donnees_USDA'!Q414:Q455,'Donnees_USDA'!Q822:Q863)+SUMPRODUCT('Donnees_USDA'!Q516:Q557,'Donnees_USDA'!Q822:Q863) -> 80313.786 | F19: =D19/E19 -> 0.030623035 | G19: ='Stocks_certifies'!I19 -> 1.08 | H19: =G19*1000/E19 -> 0.013447256 | I19: ='Prix_ICE'!K19 -> 4701.7435 | J19: =SUMPRODUCT('Donnees_USDA'!Q312:Q353,'Donnees_USDA'!Q1026:Q1067)/(SUMPRODUCT('Donnees_USDA'!Q414:Q455,'Donnees_USDA'!Q1026:Q1067)+SUMPRODUCT('Donnees_USDA'!Q516:Q557,'Donnees_USDA'!Q1026:Q1067)) -> 0.037862793 | K19: =SUMPRODUCT('Donnees_USDA'!Q312:Q353,'Donnees_USDA'!Q1230:Q1271)/(SUMPRODUCT('Donnees_USDA'!Q414:Q455,'Donnees_USDA'!Q1230:Q1271)+SUMPRODUCT('Donnees_USDA'!Q516:Q557,'Donnees_USDA'!Q1230:Q1271)) -> 0.030121982
A20: 2025/26 | B20: ='Donnees_USDA'!R306 -> 84390 | C20: =B20/1000 -> 84.39 | D20: =SUMPRODUCT('Donnees_USDA'!R312:R353,'Donnees_USDA'!R822:R863) -> 3597.0599 | E20: =SUMPRODUCT('Donnees_USDA'!R414:R455,'Donnees_USDA'!R822:R863)+SUMPRODUCT('Donnees_USDA'!R516:R557,'Donnees_USDA'!R822:R863) -> 89103.468 | F20: =D20/E20 -> 0.040369471 | G20: ='Stocks_certifies'!I20 -> 0.83 | H20: =G20*1000/E20 -> 0.0093150134 | I20: ='Prix_ICE'!K20 -> 3788.4636 | J20: =SUMPRODUCT('Donnees_USDA'!R312:R353,'Donnees_USDA'!R1026:R1067)/(SUMPRODUCT('Donnees_USDA'!R414:R455,'Donnees_USDA'!R1026:R1067)+SUMPRODUCT('Donnees_USDA'!R516:R557,'Donnees_USDA'!R1026:R1067)) -> 0.033456395 | K20: =SUMPRODUCT('Donnees_USDA'!R312:R353,'Donnees_USDA'!R1230:R1271)/(SUMPRODUCT('Donnees_USDA'!R414:R455,'Donnees_USDA'!R1230:R1271)+SUMPRODUCT('Donnees_USDA'!R516:R557,'Donnees_USDA'!R1230:R1271)) -> 0.017164923
A21: 2026/27 (prév.) | B21: ='Donnees_USDA'!S306 -> 83800 | C21: =B21/1000 -> 83.8 | D21: =SUMPRODUCT('Donnees_USDA'!S312:S353,'Donnees_USDA'!S822:S863) -> 3113.956 | E21: =SUMPRODUCT('Donnees_USDA'!S414:S455,'Donnees_USDA'!S822:S863)+SUMPRODUCT('Donnees_USDA'!S516:S557,'Donnees_USDA'!S822:S863) -> 90236.914 | F21: =D21/E21 -> 0.034508671 | J21: =SUMPRODUCT('Donnees_USDA'!S312:S353,'Donnees_USDA'!S1026:S1067)/(SUMPRODUCT('Donnees_USDA'!S414:S455,'Donnees_USDA'!S1026:S1067)+SUMPRODUCT('Donnees_USDA'!S516:S557,'Donnees_USDA'!S1026:S1067)) -> 0.024861446 | K21: =SUMPRODUCT('Donnees_USDA'!S312:S353,'Donnees_USDA'!S1230:S1271)/(SUMPRODUCT('Donnees_USDA'!S414:S455,'Donnees_USDA'!S1230:S1271)+SUMPRODUCT('Donnees_USDA'!S516:S557,'Donnees_USDA'!S1230:S1271)) -> 0.011879023
A23: Corrélations avec le logarithme du DF (16 campagnes ; 15 pour les certifiés) : production (niveau) 0,31, STU stocks de fin -0,54, STU certifié -0,56. En variations d'une campagne à l'autre, une récolte robusta plus faible fait monter le DF la même campagne (-0,62) (significatif).

Sheet 4_STU_pays
A1: 4 — Stock-to-use de chaque pays d'origine = stocks de fin ÷ (consommation domestique + exportations), USDA
A2: Couleurs par ligne : rouge = bas pour ce pays, vert = haut. Colonnes de droite : ce qui fait l'importance d'un pays pour le prix (taille, chocs, coussin).
A4: Pays | B4: Part arabica 26/27 | C4: 2010/11 | D4: 2011/12 | E4: 2012/13 | F4: 2013/14 | G4: 2014/15 | H4: 2015/16 | I4: 2016/17 | J4: 2017/18 | K4: 2018/19 | L4: 2019/20 | M4: 2020/21 | N4: 2021/22 | O4: 2022/23 | P4: 2023/24 | Q4: 2024/25 | R4: 2025/26 | S4: 2026/27 | T4: STU moyen 2010-26 | U4: Part de la production mondiale 26/27 | V4: Part des exportations mondiales 26/27 | W4: Part des stocks des pays d'origine 26/27 | X4: Stock en semaines d'exportation 26/27 | Y4: Poids dans les chocs de production (2011-26) | Z4: Poids dans les variations de stocks (2011-26) | AA4: r STU / KC | AB4: r STU / DF
A5: Brésil | B5: ='Donnees_USDA'!S720 -> 0.66063978 | C5: =IF(('Donnees_USDA'!C414+'Donnees_USDA'!C516)>0,'Donnees_USDA'!C312/('Donnees_USDA'!C414+'Donnees_USDA'!C516),"") -> 0.053389675 | D5: =IF(('Donnees_USDA'!D414+'Donnees_USDA'!D516)>0,'Donnees_USDA'!D312/('Donnees_USDA'!D414+'Donnees_USDA'!D516),"") -> 0.044878479 | E5: =IF(('Donnees_USDA'!E414+'Donnees_USDA'!E516)>0,'Donnees_USDA'!E312/('Donnees_USDA'!E414+'Donnees_USDA'!E516),"") -> 0.17860942 | F5: =IF(('Donnees_USDA'!F414+'Donnees_USDA'!F516)>0,'Donnees_USDA'!F312/('Donnees_USDA'!F414+'Donnees_USDA'!F516),"") -> 0.21977335 | G5: =IF(('Donnees_USDA'!G414+'Donnees_USDA'!G516)>0,'Donnees_USDA'!G312/('Donnees_USDA'!G414+'Donnees_USDA'!G516),"") -> 0.16326566 | H5: =IF(('Donnees_USDA'!H414+'Donnees_USDA'!H516)>0,'Donnees_USDA'!H312/('Donnees_USDA'!H414+'Donnees_USDA'!H516),"") -> 0.042058229 | I5: =IF(('Donnees_USDA'!I414+'Donnees_USDA'!I516)>0,'Donnees_USDA'!I312/('Donnees_USDA'!I414+'Donnees_USDA'!I516),"") -> 0.069974043 | J5: =IF(('Donnees_USDA'!J414+'Donnees_USDA'!J516)>0,'Donnees_USDA'!J312/('Donnees_USDA'!J414+'Donnees_USDA'!J516),"") -> 0.058913644 | ... S5: =IF(('Donnees_USDA'!S414+'Donnees_USDA'!S516)>0,'Donnees_USDA'!S312/('Donnees_USDA'!S414+'Donnees_USDA'!S516),"") -> 0.061922754 | T5: =AVERAGE(C5:S5) -> 0.074706885 | U5: ='Donnees_USDA'!S6/'Donnees_USDA'!S102 -> 0.37908545 | V5: ='Donnees_USDA'!S516/'Donnees_USDA'!S612 -> 0.30886111 | W5: ='Donnees_USDA'!S312/'Donnees_USDA'!S405 -> 0.53422673 | X5: =IF('Donnees_USDA'!S516>0,'Donnees_USDA'!S312/'Donnees_USDA'!S516*52,"") -> 4.6892195 | Y5: 0.82547521 | Z5: 0.75503449 | AA5: -0.2965362 | AB5: -0.25921205
A6: Vietnam | B6: ='Donnees_USDA'!S721 -> 0.033846154 | C6: =IF(('Donnees_USDA'!C415+'Donnees_USDA'!C517)>0,'Donnees_USDA'!C313/('Donnees_USDA'!C415+'Donnees_USDA'!C517),"") -> 0.040046053 | D6: =IF(('Donnees_USDA'!D415+'Donnees_USDA'!D517)>0,'Donnees_USDA'!D313/('Donnees_USDA'!D415+'Donnees_USDA'!D517),"") -> 0.041666667 | E6: =IF(('Donnees_USDA'!E415+'Donnees_USDA'!E517)>0,'Donnees_USDA'!E313/('Donnees_USDA'!E415+'Donnees_USDA'!E517),"") -> 0.073522744 | F6: =IF(('Donnees_USDA'!F415+'Donnees_USDA'!F517)>0,'Donnees_USDA'!F313/('Donnees_USDA'!F415+'Donnees_USDA'!F517),"") -> 0.07030399 | G6: =IF(('Donnees_USDA'!G415+'Donnees_USDA'!G517)>0,'Donnees_USDA'!G313/('Donnees_USDA'!G415+'Donnees_USDA'!G517),"") -> 0.26639758 | H6: =IF(('Donnees_USDA'!H415+'Donnees_USDA'!H517)>0,'Donnees_USDA'!H313/('Donnees_USDA'!H415+'Donnees_USDA'!H517),"") -> 0.13254457 | I6: =IF(('Donnees_USDA'!I415+'Donnees_USDA'!I517)>0,'Donnees_USDA'!I313/('Donnees_USDA'!I415+'Donnees_USDA'!I517),"") -> 0.091752225 | J6: =IF(('Donnees_USDA'!J415+'Donnees_USDA'!J517)>0,'Donnees_USDA'!J313/('Donnees_USDA'!J415+'Donnees_USDA'!J517),"") -> 0.0077469729 | ... S6: =IF(('Donnees_USDA'!S415+'Donnees_USDA'!S517)>0,'Donnees_USDA'!S313/('Donnees_USDA'!S415+'Donnees_USDA'!S517),"") -> 0.014403535 | T6: =AVERAGE(C6:S6) -> 0.069581623 | U6: ='Donnees_USDA'!S7/'Donnees_USDA'!S102 -> 0.17135295 | V6: ='Donnees_USDA'!S517/'Donnees_USDA'!S612 -> 0.18221987 | W6: ='Donnees_USDA'!S313/'Donnees_USDA'!S405 -> 0.059036581 | X6: =IF('Donnees_USDA'!S517>0,'Donnees_USDA'!S313/'Donnees_USDA'!S517*52,"") -> 0.87834197 | Y6: -0.029891137 | Z6: 0.17882889 | AA6: -0.20225458 | AB6: -0.31546639
A7: Colombie | B7: ='Donnees_USDA'!S722 -> 1 | C7: =IF(('Donnees_USDA'!C416+'Donnees_USDA'!C518)>0,'Donnees_USDA'!C314/('Donnees_USDA'!C416+'Donnees_USDA'!C518),"") -> 0.010415571 | D7: =IF(('Donnees_USDA'!D416+'Donnees_USDA'!D518)>0,'Donnees_USDA'!D314/('Donnees_USDA'!D416+'Donnees_USDA'!D518),"") -> 0.028886311 | E7: =IF(('Donnees_USDA'!E416+'Donnees_USDA'!E518)>0,'Donnees_USDA'!E314/('Donnees_USDA'!E416+'Donnees_USDA'!E518),"") -> 0.07667827 | F7: =IF(('Donnees_USDA'!F416+'Donnees_USDA'!F518)>0,'Donnees_USDA'!F314/('Donnees_USDA'!F416+'Donnees_USDA'!F518),"") -> 0.077876823 | G7: =IF(('Donnees_USDA'!G416+'Donnees_USDA'!G518)>0,'Donnees_USDA'!G314/('Donnees_USDA'!G416+'Donnees_USDA'!G518),"") -> 0.048552822 | H7: =IF(('Donnees_USDA'!H416+'Donnees_USDA'!H518)>0,'Donnees_USDA'!H314/('Donnees_USDA'!H416+'Donnees_USDA'!H518),"") -> 0.081926838 | I7: =IF(('Donnees_USDA'!I416+'Donnees_USDA'!I518)>0,'Donnees_USDA'!I314/('Donnees_USDA'!I416+'Donnees_USDA'!I518),"") -> 0.058270306 | J7: =IF(('Donnees_USDA'!J416+'Donnees_USDA'!J518)>0,'Donnees_USDA'!J314/('Donnees_USDA'!J416+'Donnees_USDA'!J518),"") -> 0.077286957 | ... S7: =IF(('Donnees_USDA'!S416+'Donnees_USDA'!S518)>0,'Donnees_USDA'!S314/('Donnees_USDA'!S416+'Donnees_USDA'!S518),"") -> 0.042948718 | T7: =AVERAGE(C7:S7) -> 0.056811993 | U7: ='Donnees_USDA'!S8/'Donnees_USDA'!S102 -> 0.070650139 | V7: ='Donnees_USDA'!S518/'Donnees_USDA'!S612 -> 0.084343568 | W7: ='Donnees_USDA'!S314/'Donnees_USDA'!S405 -> 0.080888567 | X7: =IF('Donnees_USDA'!S518>0,'Donnees_USDA'!S314/'Donnees_USDA'!S518*52,"") -> 2.6 | Y7: 0.066947222 | Z7: 0.012797501 | AA7: -0.3290299 | AB7: -0.15949983
A8: Éthiopie | B8: ='Donnees_USDA'!S723 -> 1 | C8: =IF(('Donnees_USDA'!C417+'Donnees_USDA'!C519)>0,'Donnees_USDA'!C315/('Donnees_USDA'!C417+'Donnees_USDA'!C519),"") -> 0.016406891 | D8: =IF(('Donnees_USDA'!D417+'Donnees_USDA'!D519)>0,'Donnees_USDA'!D315/('Donnees_USDA'!D417+'Donnees_USDA'!D519),"") -> 0.037156704 | E8: =IF(('Donnees_USDA'!E417+'Donnees_USDA'!E519)>0,'Donnees_USDA'!E315/('Donnees_USDA'!E417+'Donnees_USDA'!E519),"") -> 0.015082956 | F8: =IF(('Donnees_USDA'!F417+'Donnees_USDA'!F519)>0,'Donnees_USDA'!F315/('Donnees_USDA'!F417+'Donnees_USDA'!F519),"") -> 0.006245121 | G8: =IF(('Donnees_USDA'!G417+'Donnees_USDA'!G519)>0,'Donnees_USDA'!G315/('Donnees_USDA'!G417+'Donnees_USDA'!G519),"") -> 0.0046260601 | H8: =IF(('Donnees_USDA'!H417+'Donnees_USDA'!H519)>0,'Donnees_USDA'!H315/('Donnees_USDA'!H417+'Donnees_USDA'!H519),"") -> 0.0038372985 | I8: =IF(('Donnees_USDA'!I417+'Donnees_USDA'!I519)>0,'Donnees_USDA'!I315/('Donnees_USDA'!I417+'Donnees_USDA'!I519),"") -> 0.0021573422 | J8: =IF(('Donnees_USDA'!J417+'Donnees_USDA'!J519)>0,'Donnees_USDA'!J315/('Donnees_USDA'!J417+'Donnees_USDA'!J519),"") -> 0.0038335936 | ... S8: =IF(('Donnees_USDA'!S417+'Donnees_USDA'!S519)>0,'Donnees_USDA'!S315/('Donnees_USDA'!S417+'Donnees_USDA'!S519),"") -> 0.011953833 | T8: =AVERAGE(C8:S8) -> 0.011449793 | U8: ='Donnees_USDA'!S9/'Donnees_USDA'!S102 -> 0.063796021 | V8: ='Donnees_USDA'!S519/'Donnees_USDA'!S612 -> 0.044878331 | W8: ='Donnees_USDA'!S315/'Donnees_USDA'!S405 -> 0.017505735 | X8: =IF('Donnees_USDA'!S519>0,'Donnees_USDA'!S315/'Donnees_USDA'!S519*52,"") -> 1.0575035 | Y8: 0.021747079 | Z8: -0.0050503297 | AA8: 0.13490134 | AB8: -0.14407753
A9: Indonésie | B9: ='Donnees_USDA'!S724 -> 0.12126538 | C9: =IF(('Donnees_USDA'!C418+'Donnees_USDA'!C520)>0,'Donnees_USDA'!C316/('Donnees_USDA'!C418+'Donnees_USDA'!C520),"") -> 0.0072934974 | D9: =IF(('Donnees_USDA'!D418+'Donnees_USDA'!D520)>0,'Donnees_USDA'!D316/('Donnees_USDA'!D418+'Donnees_USDA'!D520),"") -> 0.0094929881 | E9: =IF(('Donnees_USDA'!E418+'Donnees_USDA'!E520)>0,'Donnees_USDA'!E316/('Donnees_USDA'!E418+'Donnees_USDA'!E520),"") -> 0.0074581431 | F9: =IF(('Donnees_USDA'!F418+'Donnees_USDA'!F520)>0,'Donnees_USDA'!F316/('Donnees_USDA'!F418+'Donnees_USDA'!F520),"") -> 0.0037151703 | G9: =IF(('Donnees_USDA'!G418+'Donnees_USDA'!G520)>0,'Donnees_USDA'!G316/('Donnees_USDA'!G418+'Donnees_USDA'!G520),"") -> 0.0045611015 | H9: =IF(('Donnees_USDA'!H418+'Donnees_USDA'!H520)>0,'Donnees_USDA'!H316/('Donnees_USDA'!H418+'Donnees_USDA'!H520),"") -> 0.0035192411 | I9: =IF(('Donnees_USDA'!I418+'Donnees_USDA'!I520)>0,'Donnees_USDA'!I316/('Donnees_USDA'!I418+'Donnees_USDA'!I520),"") -> 0.0010547596 | J9: =IF(('Donnees_USDA'!J418+'Donnees_USDA'!J520)>0,'Donnees_USDA'!J316/('Donnees_USDA'!J418+'Donnees_USDA'!J520),"") -> 0.051253241 | ... S9: =IF(('Donnees_USDA'!S418+'Donnees_USDA'!S520)>0,'Donnees_USDA'!S316/('Donnees_USDA'!S418+'Donnees_USDA'!S520),"") -> 0.052096273 | T9: =AVERAGE(C9:S9) -> 0.057528885 | U9: ='Donnees_USDA'!S10/'Donnees_USDA'!S102 -> 0.059999895 | V9: ='Donnees_USDA'!S520/'Donnees_USDA'!S612 -> 0.050669084 | W9: ='Donnees_USDA'!S316/'Donnees_USDA'!S405 -> 0.081009296 | X9: =IF('Donnees_USDA'!S520>0,'Donnees_USDA'!S316/'Donnees_USDA'!S520*52,"") -> 4.3344099 | Y9: 0.044651825 | Z9: 0.020282059 | AA9: -0.36876234 | AB9: -0.3488393
A10: Ouganda | B10: ='Donnees_USDA'!S725 -> 0.15851955 | C10: =IF(('Donnees_USDA'!C419+'Donnees_USDA'!C521)>0,'Donnees_USDA'!C317/('Donnees_USDA'!C419+'Donnees_USDA'!C521),"") -> 0.18575758 | D10: =IF(('Donnees_USDA'!D419+'Donnees_USDA'!D521)>0,'Donnees_USDA'!D317/('Donnees_USDA'!D419+'Donnees_USDA'!D521),"") -> 0.17079365 | E10: =IF(('Donnees_USDA'!E419+'Donnees_USDA'!E521)>0,'Donnees_USDA'!E317/('Donnees_USDA'!E419+'Donnees_USDA'!E521),"") -> 0.09615894 | F10: =IF(('Donnees_USDA'!F419+'Donnees_USDA'!F521)>0,'Donnees_USDA'!F317/('Donnees_USDA'!F419+'Donnees_USDA'!F521),"") -> 0.10287958 | G10: =IF(('Donnees_USDA'!G419+'Donnees_USDA'!G521)>0,'Donnees_USDA'!G317/('Donnees_USDA'!G419+'Donnees_USDA'!G521),"") -> 0.087430168 | H10: =IF(('Donnees_USDA'!H419+'Donnees_USDA'!H521)>0,'Donnees_USDA'!H317/('Donnees_USDA'!H419+'Donnees_USDA'!H521),"") -> 0.088169014 | I10: =IF(('Donnees_USDA'!I419+'Donnees_USDA'!I521)>0,'Donnees_USDA'!I317/('Donnees_USDA'!I419+'Donnees_USDA'!I521),"") -> 0.069690722 | J10: =IF(('Donnees_USDA'!J419+'Donnees_USDA'!J521)>0,'Donnees_USDA'!J317/('Donnees_USDA'!J419+'Donnees_USDA'!J521),"") -> 0.085274725 | ... S10: =IF(('Donnees_USDA'!S419+'Donnees_USDA'!S521)>0,'Donnees_USDA'!S317/('Donnees_USDA'!S419+'Donnees_USDA'!S521),"") -> 0.045917655 | T10: =AVERAGE(C10:S10) -> 0.082360113 | U10: ='Donnees_USDA'!S11/'Donnees_USDA'!S102 -> 0.037750373 | V10: ='Donnees_USDA'!S521/'Donnees_USDA'!S612 -> 0.042990042 | W10: ='Donnees_USDA'!S317/'Donnees_USDA'!S405 -> 0.039719908 | X10: =IF('Donnees_USDA'!S521>0,'Donnees_USDA'!S317/'Donnees_USDA'!S521*52,"") -> 2.5048316 | Y10: 0.025994173 | Z10: -0.0051267594 | AA10: 0.020536828 | AB10: -0.29420162
A11: Inde | B11: ='Donnees_USDA'!S726 -> 0.25407166 | C11: =IF(('Donnees_USDA'!C420+'Donnees_USDA'!C522)>0,'Donnees_USDA'!C318/('Donnees_USDA'!C420+'Donnees_USDA'!C522),"") -> 0.2582271 | D11: =IF(('Donnees_USDA'!D420+'Donnees_USDA'!D522)>0,'Donnees_USDA'!D318/('Donnees_USDA'!D420+'Donnees_USDA'!D522),"") -> 0.23048036 | E11: =IF(('Donnees_USDA'!E420+'Donnees_USDA'!E522)>0,'Donnees_USDA'!E318/('Donnees_USDA'!E420+'Donnees_USDA'!E522),"") -> 0.33266197 | F11: =IF(('Donnees_USDA'!F420+'Donnees_USDA'!F522)>0,'Donnees_USDA'!F318/('Donnees_USDA'!F420+'Donnees_USDA'!F522),"") -> 0.32767265 | G11: =IF(('Donnees_USDA'!G420+'Donnees_USDA'!G522)>0,'Donnees_USDA'!G318/('Donnees_USDA'!G420+'Donnees_USDA'!G522),"") -> 0.42497946 | H11: =IF(('Donnees_USDA'!H420+'Donnees_USDA'!H522)>0,'Donnees_USDA'!H318/('Donnees_USDA'!H420+'Donnees_USDA'!H522),"") -> 0.38095924 | I11: =IF(('Donnees_USDA'!I420+'Donnees_USDA'!I522)>0,'Donnees_USDA'!I318/('Donnees_USDA'!I420+'Donnees_USDA'!I522),"") -> 0.25455287 | J11: =IF(('Donnees_USDA'!J420+'Donnees_USDA'!J522)>0,'Donnees_USDA'!J318/('Donnees_USDA'!J420+'Donnees_USDA'!J522),"") -> 0.16949613 | ... S11: =IF(('Donnees_USDA'!S420+'Donnees_USDA'!S522)>0,'Donnees_USDA'!S318/('Donnees_USDA'!S420+'Donnees_USDA'!S522),"") -> 0.027695858 | T11: =AVERAGE(C11:S11) -> 0.17918315 | U11: ='Donnees_USDA'!S12/'Donnees_USDA'!S102 -> 0.032372527 | V11: ='Donnees_USDA'!S522/'Donnees_USDA'!S612 -> 0.039144228 | W11: ='Donnees_USDA'!S318/'Donnees_USDA'!S405 -> 0.026077508 | X11: =IF('Donnees_USDA'!S522>0,'Donnees_USDA'!S318/'Donnees_USDA'!S522*52,"") -> 1.8060781 | Y11: -0.0078451565 | Z11: 0.051984832 | AA11: -0.40735047 | AB11: -0.47312094
A12: Honduras | B12: ='Donnees_USDA'!S727 -> 1 | C12: =IF(('Donnees_USDA'!C421+'Donnees_USDA'!C523)>0,'Donnees_USDA'!C319/('Donnees_USDA'!C421+'Donnees_USDA'!C523),"") -> 0.0071667463 | D12: =IF(('Donnees_USDA'!D421+'Donnees_USDA'!D523)>0,'Donnees_USDA'!D319/('Donnees_USDA'!D421+'Donnees_USDA'!D523),"") -> 0.01620162 | E12: =IF(('Donnees_USDA'!E421+'Donnees_USDA'!E523)>0,'Donnees_USDA'!E319/('Donnees_USDA'!E421+'Donnees_USDA'!E523),"") -> 0.029850746 | F12: =IF(('Donnees_USDA'!F421+'Donnees_USDA'!F523)>0,'Donnees_USDA'!F319/('Donnees_USDA'!F421+'Donnees_USDA'!F523),"") -> 0.070505288 | G12: =IF(('Donnees_USDA'!G421+'Donnees_USDA'!G523)>0,'Donnees_USDA'!G319/('Donnees_USDA'!G421+'Donnees_USDA'!G523),"") -> 0.066929134 | H12: =IF(('Donnees_USDA'!H421+'Donnees_USDA'!H523)>0,'Donnees_USDA'!H319/('Donnees_USDA'!H421+'Donnees_USDA'!H523),"") -> 0.058933583 | I12: =IF(('Donnees_USDA'!I421+'Donnees_USDA'!I523)>0,'Donnees_USDA'!I319/('Donnees_USDA'!I421+'Donnees_USDA'!I523),"") -> 0.039735099 | J12: =IF(('Donnees_USDA'!J421+'Donnees_USDA'!J523)>0,'Donnees_USDA'!J319/('Donnees_USDA'!J421+'Donnees_USDA'!J523),"") -> 0.042763158 | ... S12: =IF(('Donnees_USDA'!S421+'Donnees_USDA'!S523)>0,'Donnees_USDA'!S319/('Donnees_USDA'!S421+'Donnees_USDA'!S523),"") -> 0.11946604 | T12: =AVERAGE(C12:S12) -> 0.042052885 | U12: ='Donnees_USDA'!S13/'Donnees_USDA'!S102 -> 0.031792563 | V12: ='Donnees_USDA'!S523/'Donnees_USDA'!S612 -> 0.034637511 | W12: ='Donnees_USDA'!S319/'Donnees_USDA'!S405 -> 0.085355548 | X12: =IF('Donnees_USDA'!S523>0,'Donnees_USDA'!S319/'Donnees_USDA'!S523*52,"") -> 6.6807196 | Y12: 0.046165884 | Z12: 0.013481169 | AA12: 0.013933495 | AB12: 0.10949043
A13: Pérou | B13: ='Donnees_USDA'!S728 -> 1 | C13: =IF(('Donnees_USDA'!C422+'Donnees_USDA'!C524)>0,'Donnees_USDA'!C320/('Donnees_USDA'!C422+'Donnees_USDA'!C524),"") -> 0.030617284 | D13: =IF(('Donnees_USDA'!D422+'Donnees_USDA'!D524)>0,'Donnees_USDA'!D320/('Donnees_USDA'!D422+'Donnees_USDA'!D524),"") -> 0.0026365348 | E13: =IF(('Donnees_USDA'!E422+'Donnees_USDA'!E524)>0,'Donnees_USDA'!E320/('Donnees_USDA'!E422+'Donnees_USDA'!E524),"") -> 0.01030445 | F13: =IF(('Donnees_USDA'!F422+'Donnees_USDA'!F524)>0,'Donnees_USDA'!F320/('Donnees_USDA'!F422+'Donnees_USDA'!F524),"") -> 0.0056206089 | G13: =IF(('Donnees_USDA'!G422+'Donnees_USDA'!G524)>0,'Donnees_USDA'!G320/('Donnees_USDA'!G422+'Donnees_USDA'!G524),"") -> 0.001369863 | H13: =IF(('Donnees_USDA'!H422+'Donnees_USDA'!H524)>0,'Donnees_USDA'!H320/('Donnees_USDA'!H422+'Donnees_USDA'!H524),"") -> 0.012716763 | I13: =IF(('Donnees_USDA'!I422+'Donnees_USDA'!I524)>0,'Donnees_USDA'!I320/('Donnees_USDA'!I422+'Donnees_USDA'!I524),"") -> 0.01788269 | J13: =IF(('Donnees_USDA'!J422+'Donnees_USDA'!J524)>0,'Donnees_USDA'!J320/('Donnees_USDA'!J422+'Donnees_USDA'!J524),"") -> 0.019473081 | ... S13: =IF(('Donnees_USDA'!S422+'Donnees_USDA'!S524)>0,'Donnees_USDA'!S320/('Donnees_USDA'!S422+'Donnees_USDA'!S524),"") -> 0.0053508952 | T13: =AVERAGE(C13:S13) -> 0.013512529 | U13: ='Donnees_USDA'!S14/'Donnees_USDA'!S102 -> 0.025202065 | V13: ='Donnees_USDA'!S524/'Donnees_USDA'!S612 -> 0.028664224 | W13: ='Donnees_USDA'!S320/'Donnees_USDA'!S405 -> 0.0031389593 | X13: =IF('Donnees_USDA'!S524>0,'Donnees_USDA'!S320/'Donnees_USDA'!S524*52,"") -> 0.29688186 | Y13: -0.001661915 | Z13: -0.0019015823 | AA13: -0.17054256 | AB13: -0.35663042
A14: Mexique | B14: ='Donnees_USDA'!S729 -> 0.86457074 | C14: =IF(('Donnees_USDA'!C423+'Donnees_USDA'!C525)>0,'Donnees_USDA'!C321/('Donnees_USDA'!C423+'Donnees_USDA'!C525),"") -> 0.017181467 | D14: =IF(('Donnees_USDA'!D423+'Donnees_USDA'!D525)>0,'Donnees_USDA'!D321/('Donnees_USDA'!D423+'Donnees_USDA'!D525),"") -> 0.010969568 | E14: =IF(('Donnees_USDA'!E423+'Donnees_USDA'!E525)>0,'Donnees_USDA'!E321/('Donnees_USDA'!E423+'Donnees_USDA'!E525),"") -> 0.010542689 | F14: =IF(('Donnees_USDA'!F423+'Donnees_USDA'!F525)>0,'Donnees_USDA'!F321/('Donnees_USDA'!F423+'Donnees_USDA'!F525),"") -> 0.030975073 | G14: =IF(('Donnees_USDA'!G423+'Donnees_USDA'!G525)>0,'Donnees_USDA'!G321/('Donnees_USDA'!G423+'Donnees_USDA'!G525),"") -> 0.025515411 | H14: =IF(('Donnees_USDA'!H423+'Donnees_USDA'!H525)>0,'Donnees_USDA'!H321/('Donnees_USDA'!H423+'Donnees_USDA'!H525),"") -> 0.045016077 | I14: =IF(('Donnees_USDA'!I423+'Donnees_USDA'!I525)>0,'Donnees_USDA'!I321/('Donnees_USDA'!I423+'Donnees_USDA'!I525),"") -> 0.031084925 | J14: =IF(('Donnees_USDA'!J423+'Donnees_USDA'!J525)>0,'Donnees_USDA'!J321/('Donnees_USDA'!J423+'Donnees_USDA'!J525),"") -> 0.03318223 | ... S14: =IF(('Donnees_USDA'!S423+'Donnees_USDA'!S525)>0,'Donnees_USDA'!S321/('Donnees_USDA'!S423+'Donnees_USDA'!S525),"") -> 0.0007518797 | T14: =AVERAGE(C14:S14) -> 0.015924279 | U14: ='Donnees_USDA'!S15/'Donnees_USDA'!S102 -> 0.021801368 | V14: ='Donnees_USDA'!S525/'Donnees_USDA'!S612 -> 0.02146355 | W14: ='Donnees_USDA'!S321/'Donnees_USDA'!S405 -> 0.00060364602 | X14: =IF('Donnees_USDA'!S525>0,'Donnees_USDA'!S321/'Donnees_USDA'!S525*52,"") -> 0.076246334 | Y14: 0.010126047 | Z14: -0.0061789204 | AA14: -0.42450316 | AB14: -0.44744765
A15: Guatemala | B15: ='Donnees_USDA'!S730 -> 0.9601227 | C15: =IF(('Donnees_USDA'!C424+'Donnees_USDA'!C526)>0,'Donnees_USDA'!C322/('Donnees_USDA'!C424+'Donnees_USDA'!C526),"") -> 0.057108434 | D15: =IF(('Donnees_USDA'!D424+'Donnees_USDA'!D526)>0,'Donnees_USDA'!D322/('Donnees_USDA'!D424+'Donnees_USDA'!D526),"") -> 0.087162162 | E15: =IF(('Donnees_USDA'!E424+'Donnees_USDA'!E526)>0,'Donnees_USDA'!E322/('Donnees_USDA'!E424+'Donnees_USDA'!E526),"") -> 0.048512586 | F15: =IF(('Donnees_USDA'!F424+'Donnees_USDA'!F526)>0,'Donnees_USDA'!F322/('Donnees_USDA'!F424+'Donnees_USDA'!F526),"") -> 0.057687148 | G15: =IF(('Donnees_USDA'!G424+'Donnees_USDA'!G526)>0,'Donnees_USDA'!G322/('Donnees_USDA'!G424+'Donnees_USDA'!G526),"") -> 0.0042016807 | H15: =IF(('Donnees_USDA'!H424+'Donnees_USDA'!H526)>0,'Donnees_USDA'!H322/('Donnees_USDA'!H424+'Donnees_USDA'!H526),"") -> 0.0074841681 | I15: =IF(('Donnees_USDA'!I424+'Donnees_USDA'!I526)>0,'Donnees_USDA'!I322/('Donnees_USDA'!I424+'Donnees_USDA'!I526),"") -> 0.0095112285 | J15: =IF(('Donnees_USDA'!J424+'Donnees_USDA'!J526)>0,'Donnees_USDA'!J322/('Donnees_USDA'!J424+'Donnees_USDA'!J526),"") -> 0.026835443 | ... S15: =IF(('Donnees_USDA'!S424+'Donnees_USDA'!S526)>0,'Donnees_USDA'!S322/('Donnees_USDA'!S424+'Donnees_USDA'!S526),"") -> 0.003902439 | T15: =AVERAGE(C15:S15) -> 0.022663813 | U15: ='Donnees_USDA'!S16/'Donnees_USDA'!S102 -> 0.017188019 | V15: ='Donnees_USDA'!S526/'Donnees_USDA'!S612 -> 0.020141748 | W15: ='Donnees_USDA'!S322/'Donnees_USDA'!S405 -> 0.0019316673 | X15: =IF('Donnees_USDA'!S526>0,'Donnees_USDA'!S322/'Donnees_USDA'!S526*52,"") -> 0.26 | Y15: 0.010815037 | Z15: -0.0076613065 | AA15: -0.059966146 | AB15: -0.29429062
A16: Nicaragua | B16: ='Donnees_USDA'!S731 -> 0.94262295 | C16: =IF(('Donnees_USDA'!C425+'Donnees_USDA'!C527)>0,'Donnees_USDA'!C323/('Donnees_USDA'!C425+'Donnees_USDA'!C527),"") -> 0.012188366 | D16: =IF(('Donnees_USDA'!D425+'Donnees_USDA'!D527)>0,'Donnees_USDA'!D323/('Donnees_USDA'!D425+'Donnees_USDA'!D527),"") -> 0.13228346 | E16: =IF(('Donnees_USDA'!E425+'Donnees_USDA'!E527)>0,'Donnees_USDA'!E323/('Donnees_USDA'!E425+'Donnees_USDA'!E527),"") -> 0.0077625571 | F16: =IF(('Donnees_USDA'!F425+'Donnees_USDA'!F527)>0,'Donnees_USDA'!F323/('Donnees_USDA'!F425+'Donnees_USDA'!F527),"") -> 0.010891089 | G16: =IF(('Donnees_USDA'!G425+'Donnees_USDA'!G527)>0,'Donnees_USDA'!G323/('Donnees_USDA'!G425+'Donnees_USDA'!G527),"") -> 0.049156627 | H16: =IF(('Donnees_USDA'!H425+'Donnees_USDA'!H527)>0,'Donnees_USDA'!H323/('Donnees_USDA'!H425+'Donnees_USDA'!H527),"") -> 0.016666667 | I16: =IF(('Donnees_USDA'!I425+'Donnees_USDA'!I527)>0,'Donnees_USDA'!I323/('Donnees_USDA'!I425+'Donnees_USDA'!I527),"") -> 0.027376426 | J16: =IF(('Donnees_USDA'!J425+'Donnees_USDA'!J527)>0,'Donnees_USDA'!J323/('Donnees_USDA'!J425+'Donnees_USDA'!J527),"") -> 0.052886406 | ... S16: =IF(('Donnees_USDA'!S425+'Donnees_USDA'!S527)>0,'Donnees_USDA'!S323/('Donnees_USDA'!S425+'Donnees_USDA'!S527),"") -> 0.03526971 | T16: =AVERAGE(C16:S16) -> 0.032378321 | U16: ='Donnees_USDA'!S17/'Donnees_USDA'!S102 -> 0.012864652 | V16: ='Donnees_USDA'!S527/'Donnees_USDA'!S612 -> 0.014162166 | W16: ='Donnees_USDA'!S323/'Donnees_USDA'!S405 -> 0.010261982 | X16: =IF('Donnees_USDA'!S527>0,'Donnees_USDA'!S323/'Donnees_USDA'!S527*52,"") -> 1.9644444 | Y16: 0.0024191414 | Z16: -0.0074874231 | AA16: 0.00582078 | AB16: 0.053546885
A17: Tanzanie | B17: ='Donnees_USDA'!S732 -> 0.53125 | C17: =IF(('Donnees_USDA'!C426+'Donnees_USDA'!C528)>0,'Donnees_USDA'!C324/('Donnees_USDA'!C426+'Donnees_USDA'!C528),"") -> 0.048076923 | D17: =IF(('Donnees_USDA'!D426+'Donnees_USDA'!D528)>0,'Donnees_USDA'!D324/('Donnees_USDA'!D426+'Donnees_USDA'!D528),"") -> 0.078947368 | E17: =IF(('Donnees_USDA'!E426+'Donnees_USDA'!E528)>0,'Donnees_USDA'!E324/('Donnees_USDA'!E426+'Donnees_USDA'!E528),"") -> 0.2628866 | F17: =IF(('Donnees_USDA'!F426+'Donnees_USDA'!F528)>0,'Donnees_USDA'!F324/('Donnees_USDA'!F426+'Donnees_USDA'!F528),"") -> 0.23681125 | G17: =IF(('Donnees_USDA'!G426+'Donnees_USDA'!G528)>0,'Donnees_USDA'!G324/('Donnees_USDA'!G426+'Donnees_USDA'!G528),"") -> 0.31262136 | H17: =IF(('Donnees_USDA'!H426+'Donnees_USDA'!H528)>0,'Donnees_USDA'!H324/('Donnees_USDA'!H426+'Donnees_USDA'!H528),"") -> 0.21331058 | I17: =IF(('Donnees_USDA'!I426+'Donnees_USDA'!I528)>0,'Donnees_USDA'!I324/('Donnees_USDA'!I426+'Donnees_USDA'!I528),"") -> 0.2037037 | J17: =IF(('Donnees_USDA'!J426+'Donnees_USDA'!J528)>0,'Donnees_USDA'!J324/('Donnees_USDA'!J426+'Donnees_USDA'!J528),"") -> 0.26851852 | ... S17: =IF(('Donnees_USDA'!S426+'Donnees_USDA'!S528)>0,'Donnees_USDA'!S324/('Donnees_USDA'!S426+'Donnees_USDA'!S528),"") -> 0.10466667 | T17: =AVERAGE(C17:S17) -> 0.13306054 | U17: ='Donnees_USDA'!S18/'Donnees_USDA'!S102 -> 0.0084358375 | V17: ='Donnees_USDA'!S528/'Donnees_USDA'!S612 -> 0.0088749575 | W17: ='Donnees_USDA'!S324/'Donnees_USDA'!S405 -> 0.018954485 | X17: =IF('Donnees_USDA'!S528>0,'Donnees_USDA'!S324/'Donnees_USDA'!S528*52,"") -> 5.7900709 | Y17: 0.0037887332 | Z17: 0.010381759 | AA17: -0.64070327 | AB17: -0.52819816
A18: Malaisie | B18: ='Donnees_USDA'!S733 -> 0 | C18: =IF(('Donnees_USDA'!C427+'Donnees_USDA'!C529)>0,'Donnees_USDA'!C325/('Donnees_USDA'!C427+'Donnees_USDA'!C529),"") -> 0 | D18: =IF(('Donnees_USDA'!D427+'Donnees_USDA'!D529)>0,'Donnees_USDA'!D325/('Donnees_USDA'!D427+'Donnees_USDA'!D529),"") -> 0 | E18: =IF(('Donnees_USDA'!E427+'Donnees_USDA'!E529)>0,'Donnees_USDA'!E325/('Donnees_USDA'!E427+'Donnees_USDA'!E529),"") -> 0 | F18: =IF(('Donnees_USDA'!F427+'Donnees_USDA'!F529)>0,'Donnees_USDA'!F325/('Donnees_USDA'!F427+'Donnees_USDA'!F529),"") -> 0 | G18: =IF(('Donnees_USDA'!G427+'Donnees_USDA'!G529)>0,'Donnees_USDA'!G325/('Donnees_USDA'!G427+'Donnees_USDA'!G529),"") -> 0 | H18: =IF(('Donnees_USDA'!H427+'Donnees_USDA'!H529)>0,'Donnees_USDA'!H325/('Donnees_USDA'!H427+'Donnees_USDA'!H529),"") -> 0 | I18: =IF(('Donnees_USDA'!I427+'Donnees_USDA'!I529)>0,'Donnees_USDA'!I325/('Donnees_USDA'!I427+'Donnees_USDA'!I529),"") -> 0 | J18: =IF(('Donnees_USDA'!J427+'Donnees_USDA'!J529)>0,'Donnees_USDA'!J325/('Donnees_USDA'!J427+'Donnees_USDA'!J529),"") -> 0 | ... S18: =IF(('Donnees_USDA'!S427+'Donnees_USDA'!S529)>0,'Donnees_USDA'!S325/('Donnees_USDA'!S427+'Donnees_USDA'!S529),"") -> 0 | T18: =AVERAGE(C18:S18) -> 0 | U18: ='Donnees_USDA'!S19/'Donnees_USDA'!S102 -> 0.0079085977 | V18: ='Donnees_USDA'!S529/'Donnees_USDA'!S612 -> 0.01573574 | W18: ='Donnees_USDA'!S325/'Donnees_USDA'!S405 -> 0 | X18: =IF('Donnees_USDA'!S529>0,'Donnees_USDA'!S325/'Donnees_USDA'!S529*52,"") -> 0 | Y18: -0.0065256484 | Z18: 0
A19: Côte d'Ivoire | B19: ='Donnees_USDA'!S734 -> 0 | C19: =IF(('Donnees_USDA'!C428+'Donnees_USDA'!C530)>0,'Donnees_USDA'!C326/('Donnees_USDA'!C428+'Donnees_USDA'!C530),"") -> 0.31750973 | D19: =IF(('Donnees_USDA'!D428+'Donnees_USDA'!D530)>0,'Donnees_USDA'!D326/('Donnees_USDA'!D428+'Donnees_USDA'!D530),"") -> 0.045833333 | E19: =IF(('Donnees_USDA'!E428+'Donnees_USDA'!E530)>0,'Donnees_USDA'!E326/('Donnees_USDA'!E428+'Donnees_USDA'!E530),"") -> 0.027964206 | F19: =IF(('Donnees_USDA'!F428+'Donnees_USDA'!F530)>0,'Donnees_USDA'!F326/('Donnees_USDA'!F428+'Donnees_USDA'!F530),"") -> 0.032934132 | G19: =IF(('Donnees_USDA'!G428+'Donnees_USDA'!G530)>0,'Donnees_USDA'!G326/('Donnees_USDA'!G428+'Donnees_USDA'!G530),"") -> 0.021052632 | H19: =IF(('Donnees_USDA'!H428+'Donnees_USDA'!H530)>0,'Donnees_USDA'!H326/('Donnees_USDA'!H428+'Donnees_USDA'!H530),"") -> 0.0092879257 | I19: =IF(('Donnees_USDA'!I428+'Donnees_USDA'!I530)>0,'Donnees_USDA'!I326/('Donnees_USDA'!I428+'Donnees_USDA'!I530),"") -> 0.013761468 | J19: =IF(('Donnees_USDA'!J428+'Donnees_USDA'!J530)>0,'Donnees_USDA'!J326/('Donnees_USDA'!J428+'Donnees_USDA'!J530),"") -> 0.012 | ... S19: =IF(('Donnees_USDA'!S428+'Donnees_USDA'!S530)>0,'Donnees_USDA'!S326/('Donnees_USDA'!S428+'Donnees_USDA'!S530),"") -> 0 | T19: =AVERAGE(C19:S19) -> 0.028696672 | U19: ='Donnees_USDA'!S20/'Donnees_USDA'!S102 -> 0.006854118 | V19: ='Donnees_USDA'!S530/'Donnees_USDA'!S612 -> 0.0078678701 | W19: ='Donnees_USDA'!S326/'Donnees_USDA'!S405 -> 0 | X19: =IF('Donnees_USDA'!S530>0,'Donnees_USDA'!S326/'Donnees_USDA'!S530*52,"") -> 0 | Y19: 0.0023911633 | Z19: -0.00016385612 | AA19: 0.25777002 | AB19: -0.0083277348
A20: Costa Rica | B20: ='Donnees_USDA'!S735 -> 1 | C20: =IF(('Donnees_USDA'!C429+'Donnees_USDA'!C531)>0,'Donnees_USDA'!C327/('Donnees_USDA'!C429+'Donnees_USDA'!C531),"") -> 0.11785504 | D20: =IF(('Donnees_USDA'!D429+'Donnees_USDA'!D531)>0,'Donnees_USDA'!D327/('Donnees_USDA'!D429+'Donnees_USDA'!D531),"") -> 0.13157895 | E20: =IF(('Donnees_USDA'!E429+'Donnees_USDA'!E531)>0,'Donnees_USDA'!E327/('Donnees_USDA'!E429+'Donnees_USDA'!E531),"") -> 0.10674157 | F20: =IF(('Donnees_USDA'!F429+'Donnees_USDA'!F531)>0,'Donnees_USDA'!F327/('Donnees_USDA'!F429+'Donnees_USDA'!F531),"") -> 0.075581395 | G20: =IF(('Donnees_USDA'!G429+'Donnees_USDA'!G531)>0,'Donnees_USDA'!G327/('Donnees_USDA'!G429+'Donnees_USDA'!G531),"") -> 0.072289157 | H20: =IF(('Donnees_USDA'!H429+'Donnees_USDA'!H531)>0,'Donnees_USDA'!H327/('Donnees_USDA'!H429+'Donnees_USDA'!H531),"") -> 0.19688474 | I20: =IF(('Donnees_USDA'!I429+'Donnees_USDA'!I531)>0,'Donnees_USDA'!I327/('Donnees_USDA'!I429+'Donnees_USDA'!I531),"") -> 0.14966887 | J20: =IF(('Donnees_USDA'!J429+'Donnees_USDA'!J531)>0,'Donnees_USDA'!J327/('Donnees_USDA'!J429+'Donnees_USDA'!J531),"") -> 0.16131065 | ... S20: =IF(('Donnees_USDA'!S429+'Donnees_USDA'!S531)>0,'Donnees_USDA'!S327/('Donnees_USDA'!S429+'Donnees_USDA'!S531),"") -> 0.049275362 | T20: =AVERAGE(C20:S20) -> 0.13086753 | U20: ='Donnees_USDA'!S21/'Donnees_USDA'!S102 -> 0.0063268782 | V20: ='Donnees_USDA'!S531/'Donnees_USDA'!S612 -> 0.0066719539 | W20: ='Donnees_USDA'!S327/'Donnees_USDA'!S405 -> 0.0082095859 | X20: =IF('Donnees_USDA'!S531>0,'Donnees_USDA'!S327/'Donnees_USDA'!S531*52,"") -> 3.3358491 | Y20: -0.0050045999 | Z20: -0.01069469 | AA20: -0.36274727 | AB20: -0.36789557
A21: Kenya | B21: ='Donnees_USDA'!S736 -> 1 | C21: =IF(('Donnees_USDA'!C430+'Donnees_USDA'!C532)>0,'Donnees_USDA'!C328/('Donnees_USDA'!C430+'Donnees_USDA'!C532),"") -> 0.60285714 | D21: =IF(('Donnees_USDA'!D430+'Donnees_USDA'!D532)>0,'Donnees_USDA'!D328/('Donnees_USDA'!D430+'Donnees_USDA'!D532),"") -> 0.39186047 | E21: =IF(('Donnees_USDA'!E430+'Donnees_USDA'!E532)>0,'Donnees_USDA'!E328/('Donnees_USDA'!E430+'Donnees_USDA'!E532),"") -> 0.17981439 | F21: =IF(('Donnees_USDA'!F430+'Donnees_USDA'!F532)>0,'Donnees_USDA'!F328/('Donnees_USDA'!F430+'Donnees_USDA'!F532),"") -> 0.24096386 | G21: =IF(('Donnees_USDA'!G430+'Donnees_USDA'!G532)>0,'Donnees_USDA'!G328/('Donnees_USDA'!G430+'Donnees_USDA'!G532),"") -> 0.2956636 | H21: =IF(('Donnees_USDA'!H430+'Donnees_USDA'!H532)>0,'Donnees_USDA'!H328/('Donnees_USDA'!H430+'Donnees_USDA'!H532),"") -> 0.24619289 | I21: =IF(('Donnees_USDA'!I430+'Donnees_USDA'!I532)>0,'Donnees_USDA'!I328/('Donnees_USDA'!I430+'Donnees_USDA'!I532),"") -> 0.30086313 | J21: =IF(('Donnees_USDA'!J430+'Donnees_USDA'!J532)>0,'Donnees_USDA'!J328/('Donnees_USDA'!J430+'Donnees_USDA'!J532),"") -> 0.31664411 | ... S21: =IF(('Donnees_USDA'!S430+'Donnees_USDA'!S532)>0,'Donnees_USDA'!S328/('Donnees_USDA'!S430+'Donnees_USDA'!S532),"") -> 0.11976048 | T21: =AVERAGE(C21:S21) -> 0.23738961 | U21: ='Donnees_USDA'!S22/'Donnees_USDA'!S102 -> 0.0050087785 | V21: ='Donnees_USDA'!S532/'Donnees_USDA'!S612 -> 0.0059166383 | W21: ='Donnees_USDA'!S328/'Donnees_USDA'!S405 -> 0.014487505 | X21: =IF('Donnees_USDA'!S532>0,'Donnees_USDA'!S328/'Donnees_USDA'!S532*52,"") -> 6.6382979 | Y21: 0.0032265687 | Z21: -0.0064574982 | AA21: -0.13882347 | AB21: -0.45907058
A22: Thaïlande | B22: ='Donnees_USDA'!S737 -> 0 | C22: =IF(('Donnees_USDA'!C431+'Donnees_USDA'!C533)>0,'Donnees_USDA'!C329/('Donnees_USDA'!C431+'Donnees_USDA'!C533),"") -> 0 | D22: =IF(('Donnees_USDA'!D431+'Donnees_USDA'!D533)>0,'Donnees_USDA'!D329/('Donnees_USDA'!D431+'Donnees_USDA'!D533),"") -> 0 | E22: =IF(('Donnees_USDA'!E431+'Donnees_USDA'!E533)>0,'Donnees_USDA'!E329/('Donnees_USDA'!E431+'Donnees_USDA'!E533),"") -> 0 | F22: =IF(('Donnees_USDA'!F431+'Donnees_USDA'!F533)>0,'Donnees_USDA'!F329/('Donnees_USDA'!F431+'Donnees_USDA'!F533),"") -> 0 | G22: =IF(('Donnees_USDA'!G431+'Donnees_USDA'!G533)>0,'Donnees_USDA'!G329/('Donnees_USDA'!G431+'Donnees_USDA'!G533),"") -> 0 | H22: =IF(('Donnees_USDA'!H431+'Donnees_USDA'!H533)>0,'Donnees_USDA'!H329/('Donnees_USDA'!H431+'Donnees_USDA'!H533),"") -> 0 | I22: =IF(('Donnees_USDA'!I431+'Donnees_USDA'!I533)>0,'Donnees_USDA'!I329/('Donnees_USDA'!I431+'Donnees_USDA'!I533),"") -> 0 | J22: =IF(('Donnees_USDA'!J431+'Donnees_USDA'!J533)>0,'Donnees_USDA'!J329/('Donnees_USDA'!J431+'Donnees_USDA'!J533),"") -> 0 | ... S22: =IF(('Donnees_USDA'!S431+'Donnees_USDA'!S533)>0,'Donnees_USDA'!S329/('Donnees_USDA'!S431+'Donnees_USDA'!S533),"") -> 0 | T22: =AVERAGE(C22:S22) -> 0 | U22: ='Donnees_USDA'!S23/'Donnees_USDA'!S102 -> 0.0047451586 | V22: ='Donnees_USDA'!S533/'Donnees_USDA'!S612 -> 0.0037765777 | W22: ='Donnees_USDA'!S329/'Donnees_USDA'!S405 -> 0 | X22: =IF('Donnees_USDA'!S533>0,'Donnees_USDA'!S329/'Donnees_USDA'!S533*52,"") -> 0 | Y22: 0.00065655296 | Z22: 0
A23: Papouasie-N.-G. | B23: ='Donnees_USDA'!S738 -> 0.9375 | C23: =IF(('Donnees_USDA'!C432+'Donnees_USDA'!C534)>0,'Donnees_USDA'!C330/('Donnees_USDA'!C432+'Donnees_USDA'!C534),"") -> 0.023863636 | D23: =IF(('Donnees_USDA'!D432+'Donnees_USDA'!D534)>0,'Donnees_USDA'!D330/('Donnees_USDA'!D432+'Donnees_USDA'!D534),"") -> 0.022302158 | E23: =IF(('Donnees_USDA'!E432+'Donnees_USDA'!E534)>0,'Donnees_USDA'!E330/('Donnees_USDA'!E432+'Donnees_USDA'!E534),"") -> 0.043902439 | F23: =IF(('Donnees_USDA'!F432+'Donnees_USDA'!F534)>0,'Donnees_USDA'!F330/('Donnees_USDA'!F432+'Donnees_USDA'!F534),"") -> 0.042105263 | G23: =IF(('Donnees_USDA'!G432+'Donnees_USDA'!G534)>0,'Donnees_USDA'!G330/('Donnees_USDA'!G432+'Donnees_USDA'!G534),"") -> 0.044444444 | H23: =IF(('Donnees_USDA'!H432+'Donnees_USDA'!H534)>0,'Donnees_USDA'!H330/('Donnees_USDA'!H432+'Donnees_USDA'!H534),"") -> 0.048 | I23: =IF(('Donnees_USDA'!I432+'Donnees_USDA'!I534)>0,'Donnees_USDA'!I330/('Donnees_USDA'!I432+'Donnees_USDA'!I534),"") -> 0.032286996 | J23: =IF(('Donnees_USDA'!J432+'Donnees_USDA'!J534)>0,'Donnees_USDA'!J330/('Donnees_USDA'!J432+'Donnees_USDA'!J534),"") -> 0.044444444 | ... S23: =IF(('Donnees_USDA'!S432+'Donnees_USDA'!S534)>0,'Donnees_USDA'!S330/('Donnees_USDA'!S432+'Donnees_USDA'!S534),"") -> 0.04375 | T23: =AVERAGE(C23:S23) -> 0.040218079 | U23: ='Donnees_USDA'!S24/'Donnees_USDA'!S102 -> 0.0042179188 | V23: ='Donnees_USDA'!S534/'Donnees_USDA'!S612 -> 0.0047207221 | W23: ='Donnees_USDA'!S330/'Donnees_USDA'!S405 -> 0.0042255222 | X23: =IF('Donnees_USDA'!S534>0,'Donnees_USDA'!S330/'Donnees_USDA'!S534*52,"") -> 2.4266667 | Y23: -0.0010490866 | Z23: 0.00015337571 | AA23: -0.193657 | AB23: -0.090697561
A24: Salvador | B24: ='Donnees_USDA'!S739 -> 1 | C24: =IF(('Donnees_USDA'!C433+'Donnees_USDA'!C535)>0,'Donnees_USDA'!C331/('Donnees_USDA'!C433+'Donnees_USDA'!C535),"") -> 0.0061934254 | D24: =IF(('Donnees_USDA'!D433+'Donnees_USDA'!D535)>0,'Donnees_USDA'!D331/('Donnees_USDA'!D433+'Donnees_USDA'!D535),"") -> 0.013081395 | E24: =IF(('Donnees_USDA'!E433+'Donnees_USDA'!E535)>0,'Donnees_USDA'!E331/('Donnees_USDA'!E433+'Donnees_USDA'!E535),"") -> 0.012676056 | F24: =IF(('Donnees_USDA'!F433+'Donnees_USDA'!F535)>0,'Donnees_USDA'!F331/('Donnees_USDA'!F433+'Donnees_USDA'!F535),"") -> 0.017218543 | G24: =IF(('Donnees_USDA'!G433+'Donnees_USDA'!G535)>0,'Donnees_USDA'!G331/('Donnees_USDA'!G433+'Donnees_USDA'!G535),"") -> 0.020571429 | H24: =IF(('Donnees_USDA'!H433+'Donnees_USDA'!H535)>0,'Donnees_USDA'!H331/('Donnees_USDA'!H433+'Donnees_USDA'!H535),"") -> 0.016993464 | I24: =IF(('Donnees_USDA'!I433+'Donnees_USDA'!I535)>0,'Donnees_USDA'!I331/('Donnees_USDA'!I433+'Donnees_USDA'!I535),"") -> 0.03566879 | J24: =IF(('Donnees_USDA'!J433+'Donnees_USDA'!J535)>0,'Donnees_USDA'!J331/('Donnees_USDA'!J433+'Donnees_USDA'!J535),"") -> 0.032 | ... S24: =IF(('Donnees_USDA'!S433+'Donnees_USDA'!S535)>0,'Donnees_USDA'!S331/('Donnees_USDA'!S433+'Donnees_USDA'!S535),"") -> 0.089569161 | T24: =AVERAGE(C24:S24) -> 0.0509524 | U24: ='Donnees_USDA'!S25/'Donnees_USDA'!S102 -> 0.00285764 | V24: ='Donnees_USDA'!S535/'Donnees_USDA'!S612 -> 0.0034178028 | W24: ='Donnees_USDA'!S331/'Donnees_USDA'!S405 -> 0.0095376071 | X24: =IF('Donnees_USDA'!S535>0,'Donnees_USDA'!S331/'Donnees_USDA'!S535*52,"") -> 7.5653775 | Y24: 0.00062604278 | Z24: -0.00087708893 | AA24: 0.64856161 | AB24: 0.86573007
A25: Laos | B25: ='Donnees_USDA'!S740 -> 0 | C25: =IF(('Donnees_USDA'!C434+'Donnees_USDA'!C536)>0,'Donnees_USDA'!C332/('Donnees_USDA'!C434+'Donnees_USDA'!C536),"") -> 0 | D25: =IF(('Donnees_USDA'!D434+'Donnees_USDA'!D536)>0,'Donnees_USDA'!D332/('Donnees_USDA'!D434+'Donnees_USDA'!D536),"") -> 0 | E25: =IF(('Donnees_USDA'!E434+'Donnees_USDA'!E536)>0,'Donnees_USDA'!E332/('Donnees_USDA'!E434+'Donnees_USDA'!E536),"") -> 0 | F25: =IF(('Donnees_USDA'!F434+'Donnees_USDA'!F536)>0,'Donnees_USDA'!F332/('Donnees_USDA'!F434+'Donnees_USDA'!F536),"") -> 0 | G25: =IF(('Donnees_USDA'!G434+'Donnees_USDA'!G536)>0,'Donnees_USDA'!G332/('Donnees_USDA'!G434+'Donnees_USDA'!G536),"") -> 0 | H25: =IF(('Donnees_USDA'!H434+'Donnees_USDA'!H536)>0,'Donnees_USDA'!H332/('Donnees_USDA'!H434+'Donnees_USDA'!H536),"") -> 0 | I25: =IF(('Donnees_USDA'!I434+'Donnees_USDA'!I536)>0,'Donnees_USDA'!I332/('Donnees_USDA'!I434+'Donnees_USDA'!I536),"") -> 0 | J25: =IF(('Donnees_USDA'!J434+'Donnees_USDA'!J536)>0,'Donnees_USDA'!J332/('Donnees_USDA'!J434+'Donnees_USDA'!J536),"") -> 0 | ... S25: =IF(('Donnees_USDA'!S434+'Donnees_USDA'!S536)>0,'Donnees_USDA'!S332/('Donnees_USDA'!S434+'Donnees_USDA'!S536),"") -> 0 | T25: =AVERAGE(C25:S25) -> 0 | U25: ='Donnees_USDA'!S26/'Donnees_USDA'!S102 -> 0.0026361992 | V25: ='Donnees_USDA'!S536/'Donnees_USDA'!S612 -> 0.0025177184 | W25: ='Donnees_USDA'!S332/'Donnees_USDA'!S405 -> 0 | X25: =IF('Donnees_USDA'!S536>0,'Donnees_USDA'!S332/'Donnees_USDA'!S536*52,"") -> 0 | Y25: -0.00019339058 | Z25: 0
A26: Équateur | B26: ='Donnees_USDA'!S741 -> 0.28571429 | C26: =IF(('Donnees_USDA'!C435+'Donnees_USDA'!C537)>0,'Donnees_USDA'!C333/('Donnees_USDA'!C435+'Donnees_USDA'!C537),"") -> 0.098281787 | D26: =IF(('Donnees_USDA'!D435+'Donnees_USDA'!D537)>0,'Donnees_USDA'!D333/('Donnees_USDA'!D435+'Donnees_USDA'!D537),"") -> 0.11682504 | E26: =IF(('Donnees_USDA'!E435+'Donnees_USDA'!E537)>0,'Donnees_USDA'!E333/('Donnees_USDA'!E435+'Donnees_USDA'!E537),"") -> 0.17310924 | F26: =IF(('Donnees_USDA'!F435+'Donnees_USDA'!F537)>0,'Donnees_USDA'!F333/('Donnees_USDA'!F435+'Donnees_USDA'!F537),"") -> 0.32958199 | G26: =IF(('Donnees_USDA'!G435+'Donnees_USDA'!G537)>0,'Donnees_USDA'!G333/('Donnees_USDA'!G435+'Donnees_USDA'!G537),"") -> 0.34632035 | H26: =IF(('Donnees_USDA'!H435+'Donnees_USDA'!H537)>0,'Donnees_USDA'!H333/('Donnees_USDA'!H435+'Donnees_USDA'!H537),"") -> 0.18918919 | I26: =IF(('Donnees_USDA'!I435+'Donnees_USDA'!I537)>0,'Donnees_USDA'!I333/('Donnees_USDA'!I435+'Donnees_USDA'!I537),"") -> 0.29962073 | J26: =IF(('Donnees_USDA'!J435+'Donnees_USDA'!J537)>0,'Donnees_USDA'!J333/('Donnees_USDA'!J435+'Donnees_USDA'!J537),"") -> 0.22732124 | ... S26: =IF(('Donnees_USDA'!S435+'Donnees_USDA'!S537)>0,'Donnees_USDA'!S333/('Donnees_USDA'!S435+'Donnees_USDA'!S537),"") -> 0.037267081 | T26: =AVERAGE(C26:S26) -> 0.19247848 | U26: ='Donnees_USDA'!S27/'Donnees_USDA'!S102 -> 0.0018453395 | V26: ='Donnees_USDA'!S537/'Donnees_USDA'!S612 -> 0.0027065473 | W26: ='Donnees_USDA'!S333/'Donnees_USDA'!S405 -> 0.0036218761 | X26: =IF('Donnees_USDA'!S537>0,'Donnees_USDA'!S333/'Donnees_USDA'!S537*52,"") -> 3.627907 | Y26: -0.0025354815 | Z26: 0.010608951 | AA26: -0.67295776 | AB26: -0.63969877
A27: Rwanda | B27: ='Donnees_USDA'!S742 -> 1 | C27: =IF(('Donnees_USDA'!C436+'Donnees_USDA'!C538)>0,'Donnees_USDA'!C334/('Donnees_USDA'!C436+'Donnees_USDA'!C538),"") -> 0 | D27: =IF(('Donnees_USDA'!D436+'Donnees_USDA'!D538)>0,'Donnees_USDA'!D334/('Donnees_USDA'!D436+'Donnees_USDA'!D538),"") -> 0 | E27: =IF(('Donnees_USDA'!E436+'Donnees_USDA'!E538)>0,'Donnees_USDA'!E334/('Donnees_USDA'!E436+'Donnees_USDA'!E538),"") -> 0 | F27: =IF(('Donnees_USDA'!F436+'Donnees_USDA'!F538)>0,'Donnees_USDA'!F334/('Donnees_USDA'!F436+'Donnees_USDA'!F538),"") -> 0 | G27: =IF(('Donnees_USDA'!G436+'Donnees_USDA'!G538)>0,'Donnees_USDA'!G334/('Donnees_USDA'!G436+'Donnees_USDA'!G538),"") -> 0 | H27: =IF(('Donnees_USDA'!H436+'Donnees_USDA'!H538)>0,'Donnees_USDA'!H334/('Donnees_USDA'!H436+'Donnees_USDA'!H538),"") -> 0 | I27: =IF(('Donnees_USDA'!I436+'Donnees_USDA'!I538)>0,'Donnees_USDA'!I334/('Donnees_USDA'!I436+'Donnees_USDA'!I538),"") -> 0 | J27: =IF(('Donnees_USDA'!J436+'Donnees_USDA'!J538)>0,'Donnees_USDA'!J334/('Donnees_USDA'!J436+'Donnees_USDA'!J538),"") -> 0 | ... S27: =IF(('Donnees_USDA'!S436+'Donnees_USDA'!S538)>0,'Donnees_USDA'!S334/('Donnees_USDA'!S436+'Donnees_USDA'!S538),"") -> 0 | T27: =AVERAGE(C27:S27) -> 0 | U27: ='Donnees_USDA'!S28/'Donnees_USDA'!S102 -> 0.0018453395 | V27: ='Donnees_USDA'!S538/'Donnees_USDA'!S612 -> 0.0022030036 | W27: ='Donnees_USDA'!S334/'Donnees_USDA'!S405 -> 0 | X27: =IF('Donnees_USDA'!S538>0,'Donnees_USDA'!S334/'Donnees_USDA'!S538*52,"") -> 0 | Y27: -0.001337826 | Z27: 0
A28: Madagascar | B28: ='Donnees_USDA'!S743 -> 0.083333333 | C28: =IF(('Donnees_USDA'!C437+'Donnees_USDA'!C539)>0,'Donnees_USDA'!C335/('Donnees_USDA'!C437+'Donnees_USDA'!C539),"") -> 0.021428571 | D28: =IF(('Donnees_USDA'!D437+'Donnees_USDA'!D539)>0,'Donnees_USDA'!D335/('Donnees_USDA'!D437+'Donnees_USDA'!D539),"") -> 0.012612613 | E28: =IF(('Donnees_USDA'!E437+'Donnees_USDA'!E539)>0,'Donnees_USDA'!E335/('Donnees_USDA'!E437+'Donnees_USDA'!E539),"") -> 0.013333333 | F28: =IF(('Donnees_USDA'!F437+'Donnees_USDA'!F539)>0,'Donnees_USDA'!F335/('Donnees_USDA'!F437+'Donnees_USDA'!F539),"") -> 0 | G28: =IF(('Donnees_USDA'!G437+'Donnees_USDA'!G539)>0,'Donnees_USDA'!G335/('Donnees_USDA'!G437+'Donnees_USDA'!G539),"") -> 0 | H28: =IF(('Donnees_USDA'!H437+'Donnees_USDA'!H539)>0,'Donnees_USDA'!H335/('Donnees_USDA'!H437+'Donnees_USDA'!H539),"") -> 0 | I28: =IF(('Donnees_USDA'!I437+'Donnees_USDA'!I539)>0,'Donnees_USDA'!I335/('Donnees_USDA'!I437+'Donnees_USDA'!I539),"") -> 0 | J28: =IF(('Donnees_USDA'!J437+'Donnees_USDA'!J539)>0,'Donnees_USDA'!J335/('Donnees_USDA'!J437+'Donnees_USDA'!J539),"") -> 0 | ... S28: =IF(('Donnees_USDA'!S437+'Donnees_USDA'!S539)>0,'Donnees_USDA'!S335/('Donnees_USDA'!S437+'Donnees_USDA'!S539),"") -> 0 | T28: =AVERAGE(C28:S28) -> 0.0027867363 | U28: ='Donnees_USDA'!S29/'Donnees_USDA'!S102 -> 0.0015817195 | V28: ='Donnees_USDA'!S539/'Donnees_USDA'!S612 -> 0.00062942961 | W28: ='Donnees_USDA'!S335/'Donnees_USDA'!S405 -> 0 | X28: =IF('Donnees_USDA'!S539>0,'Donnees_USDA'!S335/'Donnees_USDA'!S539*52,"") -> 0 | Y28: 0.0021658546 | Z28: -9.301205e-05 | AA28: 0.21235161 | AB28: -0.01935467
A29: Cameroun | B29: ='Donnees_USDA'!S744 -> 0.11627907 | C29: =IF(('Donnees_USDA'!C438+'Donnees_USDA'!C540)>0,'Donnees_USDA'!C336/('Donnees_USDA'!C438+'Donnees_USDA'!C540),"") -> 0.046896552 | D29: =IF(('Donnees_USDA'!D438+'Donnees_USDA'!D540)>0,'Donnees_USDA'!D336/('Donnees_USDA'!D438+'Donnees_USDA'!D540),"") -> 0.032214765 | E29: =IF(('Donnees_USDA'!E438+'Donnees_USDA'!E540)>0,'Donnees_USDA'!E336/('Donnees_USDA'!E438+'Donnees_USDA'!E540),"") -> 0.044859813 | F29: =IF(('Donnees_USDA'!F438+'Donnees_USDA'!F540)>0,'Donnees_USDA'!F336/('Donnees_USDA'!F438+'Donnees_USDA'!F540),"") -> 0.058962264 | G29: =IF(('Donnees_USDA'!G438+'Donnees_USDA'!G540)>0,'Donnees_USDA'!G336/('Donnees_USDA'!G438+'Donnees_USDA'!G540),"") -> 0.052631579 | H29: =IF(('Donnees_USDA'!H438+'Donnees_USDA'!H540)>0,'Donnees_USDA'!H336/('Donnees_USDA'!H438+'Donnees_USDA'!H540),"") -> 0.056451613 | I29: =IF(('Donnees_USDA'!I438+'Donnees_USDA'!I540)>0,'Donnees_USDA'!I336/('Donnees_USDA'!I438+'Donnees_USDA'!I540),"") -> 0.080808081 | J29: =IF(('Donnees_USDA'!J438+'Donnees_USDA'!J540)>0,'Donnees_USDA'!J336/('Donnees_USDA'!J438+'Donnees_USDA'!J540),"") -> 0.094117647 | ... S29: =IF(('Donnees_USDA'!S438+'Donnees_USDA'!S540)>0,'Donnees_USDA'!S336/('Donnees_USDA'!S438+'Donnees_USDA'!S540),"") -> 0.046511628 | T29: =AVERAGE(C29:S29) -> 0.059096868 | U29: ='Donnees_USDA'!S30/'Donnees_USDA'!S102 -> 0.0011335657 | V29: ='Donnees_USDA'!S540/'Donnees_USDA'!S612 -> 0.00094414442 | W29: ='Donnees_USDA'!S336/'Donnees_USDA'!S405 -> 0.001207292 | X29: =IF('Donnees_USDA'!S540>0,'Donnees_USDA'!S336/'Donnees_USDA'!S540*52,"") -> 3.4666667 | Y29: -0.0030046813 | Z29: -0.00032346644 | AA29: -0.39780997 | AB29: -0.32525616
A30: RD Congo | B30: ='Donnees_USDA'!S745 -> 0.3125 | C30: =IF(('Donnees_USDA'!C439+'Donnees_USDA'!C541)>0,'Donnees_USDA'!C337/('Donnees_USDA'!C439+'Donnees_USDA'!C541),"") -> 0.087272727 | D30: =IF(('Donnees_USDA'!D439+'Donnees_USDA'!D541)>0,'Donnees_USDA'!D337/('Donnees_USDA'!D439+'Donnees_USDA'!D541),"") -> 0.037174721 | E30: =IF(('Donnees_USDA'!E439+'Donnees_USDA'!E541)>0,'Donnees_USDA'!E337/('Donnees_USDA'!E439+'Donnees_USDA'!E541),"") -> 0.043478261 | F30: =IF(('Donnees_USDA'!F439+'Donnees_USDA'!F541)>0,'Donnees_USDA'!F337/('Donnees_USDA'!F439+'Donnees_USDA'!F541),"") -> 0.041666667 | G30: =IF(('Donnees_USDA'!G439+'Donnees_USDA'!G541)>0,'Donnees_USDA'!G337/('Donnees_USDA'!G439+'Donnees_USDA'!G541),"") -> 0.045454545 | H30: =IF(('Donnees_USDA'!H439+'Donnees_USDA'!H541)>0,'Donnees_USDA'!H337/('Donnees_USDA'!H439+'Donnees_USDA'!H541),"") -> 0.022222222 | I30: =IF(('Donnees_USDA'!I439+'Donnees_USDA'!I541)>0,'Donnees_USDA'!I337/('Donnees_USDA'!I439+'Donnees_USDA'!I541),"") -> 0.02173913 | J30: =IF(('Donnees_USDA'!J439+'Donnees_USDA'!J541)>0,'Donnees_USDA'!J337/('Donnees_USDA'!J439+'Donnees_USDA'!J541),"") -> 0 | ... S30: =IF(('Donnees_USDA'!S439+'Donnees_USDA'!S541)>0,'Donnees_USDA'!S337/('Donnees_USDA'!S439+'Donnees_USDA'!S541),"") -> 0 | T30: =AVERAGE(C30:S30) -> 0.017588722 | U30: ='Donnees_USDA'!S31/'Donnees_USDA'!S102 -> 0.00084358375 | V30: ='Donnees_USDA'!S541/'Donnees_USDA'!S612 -> 0.00037765777 | W30: ='Donnees_USDA'!S337/'Donnees_USDA'!S405 -> 0 | X30: =IF('Donnees_USDA'!S541>0,'Donnees_USDA'!S337/'Donnees_USDA'!S541*52,"") -> 0 | Y30: -0.00096360587 | Z30: 0.00026746356 | AA30: 0.095152375 | AB30: -0.13096786
A31: Burundi | B31: ='Donnees_USDA'!S746 -> 1 | C31: =IF(('Donnees_USDA'!C440+'Donnees_USDA'!C542)>0,'Donnees_USDA'!C338/('Donnees_USDA'!C440+'Donnees_USDA'!C542),"") -> 0.061728395 | D31: =IF(('Donnees_USDA'!D440+'Donnees_USDA'!D542)>0,'Donnees_USDA'!D338/('Donnees_USDA'!D440+'Donnees_USDA'!D542),"") -> 0.071428571 | E31: =IF(('Donnees_USDA'!E440+'Donnees_USDA'!E542)>0,'Donnees_USDA'!E338/('Donnees_USDA'!E440+'Donnees_USDA'!E542),"") -> 0.020408163 | F31: =IF(('Donnees_USDA'!F440+'Donnees_USDA'!F542)>0,'Donnees_USDA'!F338/('Donnees_USDA'!F440+'Donnees_USDA'!F542),"") -> 0.027027027 | G31: =IF(('Donnees_USDA'!G440+'Donnees_USDA'!G542)>0,'Donnees_USDA'!G338/('Donnees_USDA'!G440+'Donnees_USDA'!G542),"") -> 0 | H31: =IF(('Donnees_USDA'!H440+'Donnees_USDA'!H542)>0,'Donnees_USDA'!H338/('Donnees_USDA'!H440+'Donnees_USDA'!H542),"") -> 0 | I31: =IF(('Donnees_USDA'!I440+'Donnees_USDA'!I542)>0,'Donnees_USDA'!I338/('Donnees_USDA'!I440+'Donnees_USDA'!I542),"") -> 0 | J31: =IF(('Donnees_USDA'!J440+'Donnees_USDA'!J542)>0,'Donnees_USDA'!J338/('Donnees_USDA'!J440+'Donnees_USDA'!J542),"") -> 0 | ... S31: =IF(('Donnees_USDA'!S440+'Donnees_USDA'!S542)>0,'Donnees_USDA'!S338/('Donnees_USDA'!S440+'Donnees_USDA'!S542),"") -> 0 | T31: =AVERAGE(C31:S31) -> 0.010623068 | U31: ='Donnees_USDA'!S32/'Donnees_USDA'!S102 -> 0.00073813579 | V31: ='Donnees_USDA'!S542/'Donnees_USDA'!S612 -> 0.00078678701 | W31: ='Donnees_USDA'!S338/'Donnees_USDA'!S405 -> 0 | X31: =IF('Donnees_USDA'!S542>0,'Donnees_USDA'!S338/'Donnees_USDA'!S542*52,"") -> 0 | Y31: -0.00012867397 | Z31: -0.00037880241 | AA31: 0.23341581 | AB31: -0.042714093
A32: Rép. dominicaine | B32: ='Donnees_USDA'!S747 -> 1 | C32: =IF(('Donnees_USDA'!C441+'Donnees_USDA'!C543)>0,'Donnees_USDA'!C339/('Donnees_USDA'!C441+'Donnees_USDA'!C543),"") -> 0 | D32: =IF(('Donnees_USDA'!D441+'Donnees_USDA'!D543)>0,'Donnees_USDA'!D339/('Donnees_USDA'!D441+'Donnees_USDA'!D543),"") -> 0 | E32: =IF(('Donnees_USDA'!E441+'Donnees_USDA'!E543)>0,'Donnees_USDA'!E339/('Donnees_USDA'!E441+'Donnees_USDA'!E543),"") -> 0 | F32: =IF(('Donnees_USDA'!F441+'Donnees_USDA'!F543)>0,'Donnees_USDA'!F339/('Donnees_USDA'!F441+'Donnees_USDA'!F543),"") -> 0 | G32: =IF(('Donnees_USDA'!G441+'Donnees_USDA'!G543)>0,'Donnees_USDA'!G339/('Donnees_USDA'!G441+'Donnees_USDA'!G543),"") -> 0 | H32: =IF(('Donnees_USDA'!H441+'Donnees_USDA'!H543)>0,'Donnees_USDA'!H339/('Donnees_USDA'!H441+'Donnees_USDA'!H543),"") -> 0 | I32: =IF(('Donnees_USDA'!I441+'Donnees_USDA'!I543)>0,'Donnees_USDA'!I339/('Donnees_USDA'!I441+'Donnees_USDA'!I543),"") -> 0 | J32: =IF(('Donnees_USDA'!J441+'Donnees_USDA'!J543)>0,'Donnees_USDA'!J339/('Donnees_USDA'!J441+'Donnees_USDA'!J543),"") -> 0 | ... S32: =IF(('Donnees_USDA'!S441+'Donnees_USDA'!S543)>0,'Donnees_USDA'!S339/('Donnees_USDA'!S441+'Donnees_USDA'!S543),"") -> 0 | T32: =AVERAGE(C32:S32) -> 0 | U32: ='Donnees_USDA'!S33/'Donnees_USDA'!S102 -> 0.00065904981 | V32: ='Donnees_USDA'!S543/'Donnees_USDA'!S612 -> 6.2942961e-05 | W32: ='Donnees_USDA'!S339/'Donnees_USDA'!S405 -> 0 | X32: =IF('Donnees_USDA'!S543>0,'Donnees_USDA'!S339/'Donnees_USDA'!S543*52,"") -> 0 | Y32: 0.0009453661 | Z32: 0
A33: Guinée | B33: ='Donnees_USDA'!S748 -> 0 | C33: =IF(('Donnees_USDA'!C442+'Donnees_USDA'!C544)>0,'Donnees_USDA'!C340/('Donnees_USDA'!C442+'Donnees_USDA'!C544),"") -> 0.0060606061 | D33: =IF(('Donnees_USDA'!D442+'Donnees_USDA'!D544)>0,'Donnees_USDA'!D340/('Donnees_USDA'!D442+'Donnees_USDA'!D544),"") -> 0.028915663 | E33: =IF(('Donnees_USDA'!E442+'Donnees_USDA'!E544)>0,'Donnees_USDA'!E340/('Donnees_USDA'!E442+'Donnees_USDA'!E544),"") -> 0.053571429 | F33: =IF(('Donnees_USDA'!F442+'Donnees_USDA'!F544)>0,'Donnees_USDA'!F340/('Donnees_USDA'!F442+'Donnees_USDA'!F544),"") -> 0.18 | G33: =IF(('Donnees_USDA'!G442+'Donnees_USDA'!G544)>0,'Donnees_USDA'!G340/('Donnees_USDA'!G442+'Donnees_USDA'!G544),"") -> 0.06 | H33: =IF(('Donnees_USDA'!H442+'Donnees_USDA'!H544)>0,'Donnees_USDA'!H340/('Donnees_USDA'!H442+'Donnees_USDA'!H544),"") -> 0.032142857 | I33: =IF(('Donnees_USDA'!I442+'Donnees_USDA'!I544)>0,'Donnees_USDA'!I340/('Donnees_USDA'!I442+'Donnees_USDA'!I544),"") -> 0.050251256 | J33: =IF(('Donnees_USDA'!J442+'Donnees_USDA'!J544)>0,'Donnees_USDA'!J340/('Donnees_USDA'!J442+'Donnees_USDA'!J544),"") -> 0.11111111 | ... S33: =IF(('Donnees_USDA'!S442+'Donnees_USDA'!S544)>0,'Donnees_USDA'!S340/('Donnees_USDA'!S442+'Donnees_USDA'!S544),"") -> 0 | T33: =AVERAGE(C33:S33) -> 0.030708995 | U33: ='Donnees_USDA'!S34/'Donnees_USDA'!S102 -> 0.00065904981 | V33: ='Donnees_USDA'!S544/'Donnees_USDA'!S612 -> 0.00062942961 | W33: ='Donnees_USDA'!S340/'Donnees_USDA'!S405 -> 0 | X33: =IF('Donnees_USDA'!S544>0,'Donnees_USDA'!S340/'Donnees_USDA'!S544*52,"") -> 0 | Y33: -0.011340014 | Z33: -0.00045172671 | AA33: -0.2944335 | AB33: -0.24328591
A34: Cuba | B34: ='Donnees_USDA'!S749 -> 1 | C34: =IF(('Donnees_USDA'!C443+'Donnees_USDA'!C545)>0,'Donnees_USDA'!C341/('Donnees_USDA'!C443+'Donnees_USDA'!C545),"") -> 0 | D34: =IF(('Donnees_USDA'!D443+'Donnees_USDA'!D545)>0,'Donnees_USDA'!D341/('Donnees_USDA'!D443+'Donnees_USDA'!D545),"") -> 0 | E34: =IF(('Donnees_USDA'!E443+'Donnees_USDA'!E545)>0,'Donnees_USDA'!E341/('Donnees_USDA'!E443+'Donnees_USDA'!E545),"") -> 0 | F34: =IF(('Donnees_USDA'!F443+'Donnees_USDA'!F545)>0,'Donnees_USDA'!F341/('Donnees_USDA'!F443+'Donnees_USDA'!F545),"") -> 0 | G34: =IF(('Donnees_USDA'!G443+'Donnees_USDA'!G545)>0,'Donnees_USDA'!G341/('Donnees_USDA'!G443+'Donnees_USDA'!G545),"") -> 0 | H34: =IF(('Donnees_USDA'!H443+'Donnees_USDA'!H545)>0,'Donnees_USDA'!H341/('Donnees_USDA'!H443+'Donnees_USDA'!H545),"") -> 0 | I34: =IF(('Donnees_USDA'!I443+'Donnees_USDA'!I545)>0,'Donnees_USDA'!I341/('Donnees_USDA'!I443+'Donnees_USDA'!I545),"") -> 0 | J34: =IF(('Donnees_USDA'!J443+'Donnees_USDA'!J545)>0,'Donnees_USDA'!J341/('Donnees_USDA'!J443+'Donnees_USDA'!J545),"") -> 0 | ... S34: =IF(('Donnees_USDA'!S443+'Donnees_USDA'!S545)>0,'Donnees_USDA'!S341/('Donnees_USDA'!S443+'Donnees_USDA'!S545),"") -> 0 | T34: =AVERAGE(C34:S34) -> 0 | U34: ='Donnees_USDA'!S35/'Donnees_USDA'!S102 -> 0.00052723985 | V34: ='Donnees_USDA'!S545/'Donnees_USDA'!S612 -> 6.2942961e-05 | W34: ='Donnees_USDA'!S341/'Donnees_USDA'!S405 -> 0 | X34: =IF('Donnees_USDA'!S545>0,'Donnees_USDA'!S341/'Donnees_USDA'!S545*52,"") -> 0 | Y34: 0.00014623033 | Z34: 0
A35: Togo | B35: ='Donnees_USDA'!S750 -> 0 | C35: =IF(('Donnees_USDA'!C444+'Donnees_USDA'!C546)>0,'Donnees_USDA'!C342/('Donnees_USDA'!C444+'Donnees_USDA'!C546),"") -> 0 | D35: =IF(('Donnees_USDA'!D444+'Donnees_USDA'!D546)>0,'Donnees_USDA'!D342/('Donnees_USDA'!D444+'Donnees_USDA'!D546),"") -> 0 | E35: =IF(('Donnees_USDA'!E444+'Donnees_USDA'!E546)>0,'Donnees_USDA'!E342/('Donnees_USDA'!E444+'Donnees_USDA'!E546),"") -> 0 | F35: =IF(('Donnees_USDA'!F444+'Donnees_USDA'!F546)>0,'Donnees_USDA'!F342/('Donnees_USDA'!F444+'Donnees_USDA'!F546),"") -> 0 | G35: =IF(('Donnees_USDA'!G444+'Donnees_USDA'!G546)>0,'Donnees_USDA'!G342/('Donnees_USDA'!G444+'Donnees_USDA'!G546),"") -> 0 | H35: =IF(('Donnees_USDA'!H444+'Donnees_USDA'!H546)>0,'Donnees_USDA'!H342/('Donnees_USDA'!H444+'Donnees_USDA'!H546),"") -> 0 | I35: =IF(('Donnees_USDA'!I444+'Donnees_USDA'!I546)>0,'Donnees_USDA'!I342/('Donnees_USDA'!I444+'Donnees_USDA'!I546),"") -> 0 | J35: =IF(('Donnees_USDA'!J444+'Donnees_USDA'!J546)>0,'Donnees_USDA'!J342/('Donnees_USDA'!J444+'Donnees_USDA'!J546),"") -> 0 | ... S35: =IF(('Donnees_USDA'!S444+'Donnees_USDA'!S546)>0,'Donnees_USDA'!S342/('Donnees_USDA'!S444+'Donnees_USDA'!S546),"") -> 0 | T35: =AVERAGE(C35:S35) -> 0 | U35: ='Donnees_USDA'!S36/'Donnees_USDA'!S102 -> 0.00047451586 | V35: ='Donnees_USDA'!S546/'Donnees_USDA'!S612 -> 0.00056648665 | W35: ='Donnees_USDA'!S342/'Donnees_USDA'!S405 -> 0 | X35: =IF('Donnees_USDA'!S546>0,'Donnees_USDA'!S342/'Donnees_USDA'!S546*52,"") -> 0 | Y35: -0.005299096 | Z35: 0
A36: Bolivie | B36: ='Donnees_USDA'!S751 -> 1 | C36: =IF(('Donnees_USDA'!C445+'Donnees_USDA'!C547)>0,'Donnees_USDA'!C343/('Donnees_USDA'!C445+'Donnees_USDA'!C547),"") -> 0.13475177 | D36: =IF(('Donnees_USDA'!D445+'Donnees_USDA'!D547)>0,'Donnees_USDA'!D343/('Donnees_USDA'!D445+'Donnees_USDA'!D547),"") -> 0.025806452 | E36: =IF(('Donnees_USDA'!E445+'Donnees_USDA'!E547)>0,'Donnees_USDA'!E343/('Donnees_USDA'!E445+'Donnees_USDA'!E547),"") -> 0.034782609 | F36: =IF(('Donnees_USDA'!F445+'Donnees_USDA'!F547)>0,'Donnees_USDA'!F343/('Donnees_USDA'!F445+'Donnees_USDA'!F547),"") -> 0 | G36: =IF(('Donnees_USDA'!G445+'Donnees_USDA'!G547)>0,'Donnees_USDA'!G343/('Donnees_USDA'!G445+'Donnees_USDA'!G547),"") -> 0 | H36: =IF(('Donnees_USDA'!H445+'Donnees_USDA'!H547)>0,'Donnees_USDA'!H343/('Donnees_USDA'!H445+'Donnees_USDA'!H547),"") -> 0 | I36: =IF(('Donnees_USDA'!I445+'Donnees_USDA'!I547)>0,'Donnees_USDA'!I343/('Donnees_USDA'!I445+'Donnees_USDA'!I547),"") -> 0 | J36: =IF(('Donnees_USDA'!J445+'Donnees_USDA'!J547)>0,'Donnees_USDA'!J343/('Donnees_USDA'!J445+'Donnees_USDA'!J547),"") -> 0 | ... S36: =IF(('Donnees_USDA'!S445+'Donnees_USDA'!S547)>0,'Donnees_USDA'!S343/('Donnees_USDA'!S445+'Donnees_USDA'!S547),"") -> 0 | T36: =AVERAGE(C36:S36) -> 0.011490637 | U36: ='Donnees_USDA'!S37/'Donnees_USDA'!S102 -> 0.00042179188 | V36: ='Donnees_USDA'!S547/'Donnees_USDA'!S612 -> 0.00022030036 | W36: ='Donnees_USDA'!S343/'Donnees_USDA'!S405 -> 0 | X36: =IF('Donnees_USDA'!S547>0,'Donnees_USDA'!S343/'Donnees_USDA'!S547*52,"") -> 0 | Y36: -7.1614001e-05 | Z36: -2.8172872e-05 | AA36: 0.26835489 | AB36: 0.013103216
A37: Angola | B37: ='Donnees_USDA'!S752 -> 0 | C37: =IF(('Donnees_USDA'!C446+'Donnees_USDA'!C548)>0,'Donnees_USDA'!C344/('Donnees_USDA'!C446+'Donnees_USDA'!C548),"") -> 0.16129032 | D37: =IF(('Donnees_USDA'!D446+'Donnees_USDA'!D548)>0,'Donnees_USDA'!D344/('Donnees_USDA'!D446+'Donnees_USDA'!D548),"") -> 0.052631579 | E37: =IF(('Donnees_USDA'!E446+'Donnees_USDA'!E548)>0,'Donnees_USDA'!E344/('Donnees_USDA'!E446+'Donnees_USDA'!E548),"") -> 0.033333333 | F37: =IF(('Donnees_USDA'!F446+'Donnees_USDA'!F548)>0,'Donnees_USDA'!F344/('Donnees_USDA'!F446+'Donnees_USDA'!F548),"") -> 0 | G37: =IF(('Donnees_USDA'!G446+'Donnees_USDA'!G548)>0,'Donnees_USDA'!G344/('Donnees_USDA'!G446+'Donnees_USDA'!G548),"") -> 0 | H37: =IF(('Donnees_USDA'!H446+'Donnees_USDA'!H548)>0,'Donnees_USDA'!H344/('Donnees_USDA'!H446+'Donnees_USDA'!H548),"") -> 0 | I37: =IF(('Donnees_USDA'!I446+'Donnees_USDA'!I548)>0,'Donnees_USDA'!I344/('Donnees_USDA'!I446+'Donnees_USDA'!I548),"") -> 0 | J37: =IF(('Donnees_USDA'!J446+'Donnees_USDA'!J548)>0,'Donnees_USDA'!J344/('Donnees_USDA'!J446+'Donnees_USDA'!J548),"") -> 0 | ... S37: =IF(('Donnees_USDA'!S446+'Donnees_USDA'!S548)>0,'Donnees_USDA'!S344/('Donnees_USDA'!S446+'Donnees_USDA'!S548),"") -> 0 | T37: =AVERAGE(C37:S37) -> 0.014544426 | U37: ='Donnees_USDA'!S38/'Donnees_USDA'!S102 -> 0.00023725793 | V37: ='Donnees_USDA'!S548/'Donnees_USDA'!S612 -> 0.00022030036 | W37: ='Donnees_USDA'!S344/'Donnees_USDA'!S405 -> 0 | X37: =IF('Donnees_USDA'!S548>0,'Donnees_USDA'!S344/'Donnees_USDA'!S548*52,"") -> 0 | Y37: -5.312231e-05 | Z37: -4.2877867e-05 | AA37: 0.28634806 | AB37: 0.011131041
A38: Sierra Leone | B38: ='Donnees_USDA'!S753 -> 0 | C38: =IF(('Donnees_USDA'!C447+'Donnees_USDA'!C549)>0,'Donnees_USDA'!C345/('Donnees_USDA'!C447+'Donnees_USDA'!C549),"") -> 0 | D38: =IF(('Donnees_USDA'!D447+'Donnees_USDA'!D549)>0,'Donnees_USDA'!D345/('Donnees_USDA'!D447+'Donnees_USDA'!D549),"") -> 0 | E38: =IF(('Donnees_USDA'!E447+'Donnees_USDA'!E549)>0,'Donnees_USDA'!E345/('Donnees_USDA'!E447+'Donnees_USDA'!E549),"") -> 0 | F38: =IF(('Donnees_USDA'!F447+'Donnees_USDA'!F549)>0,'Donnees_USDA'!F345/('Donnees_USDA'!F447+'Donnees_USDA'!F549),"") -> 0 | G38: =IF(('Donnees_USDA'!G447+'Donnees_USDA'!G549)>0,'Donnees_USDA'!G345/('Donnees_USDA'!G447+'Donnees_USDA'!G549),"") -> 0 | H38: =IF(('Donnees_USDA'!H447+'Donnees_USDA'!H549)>0,'Donnees_USDA'!H345/('Donnees_USDA'!H447+'Donnees_USDA'!H549),"") -> 0 | I38: =IF(('Donnees_USDA'!I447+'Donnees_USDA'!I549)>0,'Donnees_USDA'!I345/('Donnees_USDA'!I447+'Donnees_USDA'!I549),"") -> 0 | J38: =IF(('Donnees_USDA'!J447+'Donnees_USDA'!J549)>0,'Donnees_USDA'!J345/('Donnees_USDA'!J447+'Donnees_USDA'!J549),"") -> 0 | ... S38: =IF(('Donnees_USDA'!S447+'Donnees_USDA'!S549)>0,'Donnees_USDA'!S345/('Donnees_USDA'!S447+'Donnees_USDA'!S549),"") -> 0 | T38: =AVERAGE(C38:S38) -> 0 | U38: ='Donnees_USDA'!S39/'Donnees_USDA'!S102 -> 0.00015817195 | V38: ='Donnees_USDA'!S549/'Donnees_USDA'!S612 -> 0.00012588592 | W38: ='Donnees_USDA'!S345/'Donnees_USDA'!S405 -> 0 | X38: =IF('Donnees_USDA'!S549>0,'Donnees_USDA'!S345/'Donnees_USDA'!S549*52,"") -> 0 | Y38: -1.6019169e-05 | Z38: 0
A39: Jamaïque | B39: ='Donnees_USDA'!S754 -> 1 | C39: =IF(('Donnees_USDA'!C448+'Donnees_USDA'!C550)>0,'Donnees_USDA'!C346/('Donnees_USDA'!C448+'Donnees_USDA'!C550),"") -> 0 | D39: =IF(('Donnees_USDA'!D448+'Donnees_USDA'!D550)>0,'Donnees_USDA'!D346/('Donnees_USDA'!D448+'Donnees_USDA'!D550),"") -> 0 | E39: =IF(('Donnees_USDA'!E448+'Donnees_USDA'!E550)>0,'Donnees_USDA'!E346/('Donnees_USDA'!E448+'Donnees_USDA'!E550),"") -> 0 | F39: =IF(('Donnees_USDA'!F448+'Donnees_USDA'!F550)>0,'Donnees_USDA'!F346/('Donnees_USDA'!F448+'Donnees_USDA'!F550),"") -> 0 | G39: =IF(('Donnees_USDA'!G448+'Donnees_USDA'!G550)>0,'Donnees_USDA'!G346/('Donnees_USDA'!G448+'Donnees_USDA'!G550),"") -> 0 | H39: =IF(('Donnees_USDA'!H448+'Donnees_USDA'!H550)>0,'Donnees_USDA'!H346/('Donnees_USDA'!H448+'Donnees_USDA'!H550),"") -> 0 | I39: =IF(('Donnees_USDA'!I448+'Donnees_USDA'!I550)>0,'Donnees_USDA'!I346/('Donnees_USDA'!I448+'Donnees_USDA'!I550),"") -> 0 | J39: =IF(('Donnees_USDA'!J448+'Donnees_USDA'!J550)>0,'Donnees_USDA'!J346/('Donnees_USDA'!J448+'Donnees_USDA'!J550),"") -> 0 | ... S39: =IF(('Donnees_USDA'!S448+'Donnees_USDA'!S550)>0,'Donnees_USDA'!S346/('Donnees_USDA'!S448+'Donnees_USDA'!S550),"") -> 0 | T39: =AVERAGE(C39:S39) -> 0 | U39: ='Donnees_USDA'!S40/'Donnees_USDA'!S102 -> 7.9085977e-05 | V39: ='Donnees_USDA'!S550/'Donnees_USDA'!S612 -> 6.2942961e-05 | W39: ='Donnees_USDA'!S346/'Donnees_USDA'!S405 -> 0 | X39: =IF('Donnees_USDA'!S550>0,'Donnees_USDA'!S346/'Donnees_USDA'!S550*52,"") -> 0 | Y39: -4.1132258e-05 | Z39: 0
A40: Centrafrique | B40: ='Donnees_USDA'!S755 -> 0 | C40: =IF(('Donnees_USDA'!C449+'Donnees_USDA'!C551)>0,'Donnees_USDA'!C347/('Donnees_USDA'!C449+'Donnees_USDA'!C551),"") -> 1.6730769 | D40: =IF(('Donnees_USDA'!D449+'Donnees_USDA'!D551)>0,'Donnees_USDA'!D347/('Donnees_USDA'!D449+'Donnees_USDA'!D551),"") -> 1.6216216 | E40: =IF(('Donnees_USDA'!E449+'Donnees_USDA'!E551)>0,'Donnees_USDA'!E347/('Donnees_USDA'!E449+'Donnees_USDA'!E551),"") -> 0.81081081 | F40: =IF(('Donnees_USDA'!F449+'Donnees_USDA'!F551)>0,'Donnees_USDA'!F347/('Donnees_USDA'!F449+'Donnees_USDA'!F551),"") -> 0.71428571 | G40: =IF(('Donnees_USDA'!G449+'Donnees_USDA'!G551)>0,'Donnees_USDA'!G347/('Donnees_USDA'!G449+'Donnees_USDA'!G551),"") -> 0 | H40: =IF(('Donnees_USDA'!H449+'Donnees_USDA'!H551)>0,'Donnees_USDA'!H347/('Donnees_USDA'!H449+'Donnees_USDA'!H551),"") -> 0 | I40: =IF(('Donnees_USDA'!I449+'Donnees_USDA'!I551)>0,'Donnees_USDA'!I347/('Donnees_USDA'!I449+'Donnees_USDA'!I551),"") -> 0 | J40: =IF(('Donnees_USDA'!J449+'Donnees_USDA'!J551)>0,'Donnees_USDA'!J347/('Donnees_USDA'!J449+'Donnees_USDA'!J551),"") -> 0 | ... S40: =IF(('Donnees_USDA'!S449+'Donnees_USDA'!S551)>0,'Donnees_USDA'!S347/('Donnees_USDA'!S449+'Donnees_USDA'!S551),"") | T40: =AVERAGE(C40:S40) -> 0.53553279 | U40: ='Donnees_USDA'!S41/'Donnees_USDA'!S102 -> 0 | V40: ='Donnees_USDA'!S551/'Donnees_USDA'!S612 -> 0 | W40: ='Donnees_USDA'!S347/'Donnees_USDA'!S405 -> 0 | X40: =IF('Donnees_USDA'!S551>0,'Donnees_USDA'!S347/'Donnees_USDA'!S551*52,"") | Y40: -5.4805229e-05 | Z40: -0.0013022204 | AA40: 0.85726768 | AB40: 0.66120091
A41: Ghana | B41: ='Donnees_USDA'!S756 -> 0 | C41: =IF(('Donnees_USDA'!C450+'Donnees_USDA'!C552)>0,'Donnees_USDA'!C348/('Donnees_USDA'!C450+'Donnees_USDA'!C552),"") -> 0.051724138 | D41: =IF(('Donnees_USDA'!D450+'Donnees_USDA'!D552)>0,'Donnees_USDA'!D348/('Donnees_USDA'!D450+'Donnees_USDA'!D552),"") -> 0.028169014 | E41: =IF(('Donnees_USDA'!E450+'Donnees_USDA'!E552)>0,'Donnees_USDA'!E348/('Donnees_USDA'!E450+'Donnees_USDA'!E552),"") -> 0.23076923 | F41: =IF(('Donnees_USDA'!F450+'Donnees_USDA'!F552)>0,'Donnees_USDA'!F348/('Donnees_USDA'!F450+'Donnees_USDA'!F552),"") -> 0.71428571 | G41: =IF(('Donnees_USDA'!G450+'Donnees_USDA'!G552)>0,'Donnees_USDA'!G348/('Donnees_USDA'!G450+'Donnees_USDA'!G552),"") -> 1.25 | H41: =IF(('Donnees_USDA'!H450+'Donnees_USDA'!H552)>0,'Donnees_USDA'!H348/('Donnees_USDA'!H450+'Donnees_USDA'!H552),"") -> 2 | I41: =IF(('Donnees_USDA'!I450+'Donnees_USDA'!I552)>0,'Donnees_USDA'!I348/('Donnees_USDA'!I450+'Donnees_USDA'!I552),"") -> 0.66666667 | J41: =IF(('Donnees_USDA'!J450+'Donnees_USDA'!J552)>0,'Donnees_USDA'!J348/('Donnees_USDA'!J450+'Donnees_USDA'!J552),"") -> 0 | ... S41: =IF(('Donnees_USDA'!S450+'Donnees_USDA'!S552)>0,'Donnees_USDA'!S348/('Donnees_USDA'!S450+'Donnees_USDA'!S552),"") | T41: =AVERAGE(C41:S41) -> 0.61770185 | U41: ='Donnees_USDA'!S42/'Donnees_USDA'!S102 -> 0 | V41: ='Donnees_USDA'!S552/'Donnees_USDA'!S612 -> 0 | W41: ='Donnees_USDA'!S348/'Donnees_USDA'!S405 -> 0 | X41: =IF('Donnees_USDA'!S552>0,'Donnees_USDA'!S348/'Donnees_USDA'!S552*52,"") | Y41: -0.00041899644 | Z41: 0.00019278202 | AA41: -0.38335976 | AB41: -0.5924625
A42: Haïti | B42: ='Donnees_USDA'!S757 -> 0 | C42: =IF(('Donnees_USDA'!C451+'Donnees_USDA'!C553)>0,'Donnees_USDA'!C349/('Donnees_USDA'!C451+'Donnees_USDA'!C553),"") -> 0.071428571 | D42: =IF(('Donnees_USDA'!D451+'Donnees_USDA'!D553)>0,'Donnees_USDA'!D349/('Donnees_USDA'!D451+'Donnees_USDA'!D553),"") -> 0.071428571 | E42: =IF(('Donnees_USDA'!E451+'Donnees_USDA'!E553)>0,'Donnees_USDA'!E349/('Donnees_USDA'!E451+'Donnees_USDA'!E553),"") -> 0.044776119 | F42: =IF(('Donnees_USDA'!F451+'Donnees_USDA'!F553)>0,'Donnees_USDA'!F349/('Donnees_USDA'!F451+'Donnees_USDA'!F553),"") -> 0.046153846 | G42: =IF(('Donnees_USDA'!G451+'Donnees_USDA'!G553)>0,'Donnees_USDA'!G349/('Donnees_USDA'!G451+'Donnees_USDA'!G553),"") -> 0.046153846 | H42: =IF(('Donnees_USDA'!H451+'Donnees_USDA'!H553)>0,'Donnees_USDA'!H349/('Donnees_USDA'!H451+'Donnees_USDA'!H553),"") -> 0 | I42: =IF(('Donnees_USDA'!I451+'Donnees_USDA'!I553)>0,'Donnees_USDA'!I349/('Donnees_USDA'!I451+'Donnees_USDA'!I553),"") | J42: =IF(('Donnees_USDA'!J451+'Donnees_USDA'!J553)>0,'Donnees_USDA'!J349/('Donnees_USDA'!J451+'Donnees_USDA'!J553),"") | ... S42: =IF(('Donnees_USDA'!S451+'Donnees_USDA'!S553)>0,'Donnees_USDA'!S349/('Donnees_USDA'!S451+'Donnees_USDA'!S553),"") | T42: =AVERAGE(C42:S42) -> 0.046656826 | U42: ='Donnees_USDA'!S43/'Donnees_USDA'!S102 -> 0 | V42: ='Donnees_USDA'!S553/'Donnees_USDA'!S612 -> 0 | W42: ='Donnees_USDA'!S349/'Donnees_USDA'!S405 -> 0 | X42: =IF('Donnees_USDA'!S553>0,'Donnees_USDA'!S349/'Donnees_USDA'!S553*52,"") | Y42: 0.0013658166 | Z42: 0.00020645895 | AA42: 0.82342303 | AB42: 0.93225233
A43: Liberia | B43: ='Donnees_USDA'!S758 -> 0 | C43: =IF(('Donnees_USDA'!C452+'Donnees_USDA'!C554)>0,'Donnees_USDA'!C350/('Donnees_USDA'!C452+'Donnees_USDA'!C554),"") -> 0 | D43: =IF(('Donnees_USDA'!D452+'Donnees_USDA'!D554)>0,'Donnees_USDA'!D350/('Donnees_USDA'!D452+'Donnees_USDA'!D554),"") -> 0 | E43: =IF(('Donnees_USDA'!E452+'Donnees_USDA'!E554)>0,'Donnees_USDA'!E350/('Donnees_USDA'!E452+'Donnees_USDA'!E554),"") -> 0 | F43: =IF(('Donnees_USDA'!F452+'Donnees_USDA'!F554)>0,'Donnees_USDA'!F350/('Donnees_USDA'!F452+'Donnees_USDA'!F554),"") -> 0 | G43: =IF(('Donnees_USDA'!G452+'Donnees_USDA'!G554)>0,'Donnees_USDA'!G350/('Donnees_USDA'!G452+'Donnees_USDA'!G554),"") -> 0 | H43: =IF(('Donnees_USDA'!H452+'Donnees_USDA'!H554)>0,'Donnees_USDA'!H350/('Donnees_USDA'!H452+'Donnees_USDA'!H554),"") | I43: =IF(('Donnees_USDA'!I452+'Donnees_USDA'!I554)>0,'Donnees_USDA'!I350/('Donnees_USDA'!I452+'Donnees_USDA'!I554),"") | J43: =IF(('Donnees_USDA'!J452+'Donnees_USDA'!J554)>0,'Donnees_USDA'!J350/('Donnees_USDA'!J452+'Donnees_USDA'!J554),"") | ... S43: =IF(('Donnees_USDA'!S452+'Donnees_USDA'!S554)>0,'Donnees_USDA'!S350/('Donnees_USDA'!S452+'Donnees_USDA'!S554),"") | T43: =AVERAGE(C43:S43) -> 0 | U43: ='Donnees_USDA'!S44/'Donnees_USDA'!S102 -> 0 | V43: ='Donnees_USDA'!S554/'Donnees_USDA'!S612 -> 0 | W43: ='Donnees_USDA'!S350/'Donnees_USDA'!S405 -> 0 | X43: =IF('Donnees_USDA'!S554>0,'Donnees_USDA'!S350/'Donnees_USDA'!S554*52,"") | Y43: -1.2445755e-06 | Z43: 0
A44: Malawi | B44: ='Donnees_USDA'!S759 -> 0 | C44: =IF(('Donnees_USDA'!C453+'Donnees_USDA'!C555)>0,'Donnees_USDA'!C351/('Donnees_USDA'!C453+'Donnees_USDA'!C555),"") -> 0 | D44: =IF(('Donnees_USDA'!D453+'Donnees_USDA'!D555)>0,'Donnees_USDA'!D351/('Donnees_USDA'!D453+'Donnees_USDA'!D555),"") -> 0 | E44: =IF(('Donnees_USDA'!E453+'Donnees_USDA'!E555)>0,'Donnees_USDA'!E351/('Donnees_USDA'!E453+'Donnees_USDA'!E555),"") -> 0 | F44: =IF(('Donnees_USDA'!F453+'Donnees_USDA'!F555)>0,'Donnees_USDA'!F351/('Donnees_USDA'!F453+'Donnees_USDA'!F555),"") -> 0 | G44: =IF(('Donnees_USDA'!G453+'Donnees_USDA'!G555)>0,'Donnees_USDA'!G351/('Donnees_USDA'!G453+'Donnees_USDA'!G555),"") -> 0 | H44: =IF(('Donnees_USDA'!H453+'Donnees_USDA'!H555)>0,'Donnees_USDA'!H351/('Donnees_USDA'!H453+'Donnees_USDA'!H555),"") -> 0 | I44: =IF(('Donnees_USDA'!I453+'Donnees_USDA'!I555)>0,'Donnees_USDA'!I351/('Donnees_USDA'!I453+'Donnees_USDA'!I555),"") -> 0 | J44: =IF(('Donnees_USDA'!J453+'Donnees_USDA'!J555)>0,'Donnees_USDA'!J351/('Donnees_USDA'!J453+'Donnees_USDA'!J555),"") -> 0 | ... S44: =IF(('Donnees_USDA'!S453+'Donnees_USDA'!S555)>0,'Donnees_USDA'!S351/('Donnees_USDA'!S453+'Donnees_USDA'!S555),"") | T44: =AVERAGE(C44:S44) -> 0 | U44: ='Donnees_USDA'!S45/'Donnees_USDA'!S102 -> 0 | V44: ='Donnees_USDA'!S555/'Donnees_USDA'!S612 -> 0 | W44: ='Donnees_USDA'!S351/'Donnees_USDA'!S405 -> 0 | X44: =IF('Donnees_USDA'!S555>0,'Donnees_USDA'!S351/'Donnees_USDA'!S555*52,"") | Y44: -3.7588164e-06 | Z44: 0
A45: Nigeria | B45: ='Donnees_USDA'!S760 -> 0 | C45: =IF(('Donnees_USDA'!C454+'Donnees_USDA'!C556)>0,'Donnees_USDA'!C352/('Donnees_USDA'!C454+'Donnees_USDA'!C556),"") -> 0 | D45: =IF(('Donnees_USDA'!D454+'Donnees_USDA'!D556)>0,'Donnees_USDA'!D352/('Donnees_USDA'!D454+'Donnees_USDA'!D556),"") -> 0 | E45: =IF(('Donnees_USDA'!E454+'Donnees_USDA'!E556)>0,'Donnees_USDA'!E352/('Donnees_USDA'!E454+'Donnees_USDA'!E556),"") -> 0 | F45: =IF(('Donnees_USDA'!F454+'Donnees_USDA'!F556)>0,'Donnees_USDA'!F352/('Donnees_USDA'!F454+'Donnees_USDA'!F556),"") -> 0 | G45: =IF(('Donnees_USDA'!G454+'Donnees_USDA'!G556)>0,'Donnees_USDA'!G352/('Donnees_USDA'!G454+'Donnees_USDA'!G556),"") -> 0 | H45: =IF(('Donnees_USDA'!H454+'Donnees_USDA'!H556)>0,'Donnees_USDA'!H352/('Donnees_USDA'!H454+'Donnees_USDA'!H556),"") -> 0 | I45: =IF(('Donnees_USDA'!I454+'Donnees_USDA'!I556)>0,'Donnees_USDA'!I352/('Donnees_USDA'!I454+'Donnees_USDA'!I556),"") -> 0 | J45: =IF(('Donnees_USDA'!J454+'Donnees_USDA'!J556)>0,'Donnees_USDA'!J352/('Donnees_USDA'!J454+'Donnees_USDA'!J556),"") -> 0 | ... S45: =IF(('Donnees_USDA'!S454+'Donnees_USDA'!S556)>0,'Donnees_USDA'!S352/('Donnees_USDA'!S454+'Donnees_USDA'!S556),"") | T45: =AVERAGE(C45:S45) -> 0 | U45: ='Donnees_USDA'!S46/'Donnees_USDA'!S102 -> 0 | V45: ='Donnees_USDA'!S556/'Donnees_USDA'!S612 -> 0 | W45: ='Donnees_USDA'!S352/'Donnees_USDA'!S405 -> 0 | X45: =IF('Donnees_USDA'!S556>0,'Donnees_USDA'!S352/'Donnees_USDA'!S556*52,"") | Y45: -0.00021914711 | Z45: 0
A46: Yémen | B46: ='Donnees_USDA'!S761 -> 0 | C46: =IF(('Donnees_USDA'!C455+'Donnees_USDA'!C557)>0,'Donnees_USDA'!C353/('Donnees_USDA'!C455+'Donnees_USDA'!C557),"") -> 0 | D46: =IF(('Donnees_USDA'!D455+'Donnees_USDA'!D557)>0,'Donnees_USDA'!D353/('Donnees_USDA'!D455+'Donnees_USDA'!D557),"") -> 0 | E46: =IF(('Donnees_USDA'!E455+'Donnees_USDA'!E557)>0,'Donnees_USDA'!E353/('Donnees_USDA'!E455+'Donnees_USDA'!E557),"") -> 0 | F46: =IF(('Donnees_USDA'!F455+'Donnees_USDA'!F557)>0,'Donnees_USDA'!F353/('Donnees_USDA'!F455+'Donnees_USDA'!F557),"") -> 0 | G46: =IF(('Donnees_USDA'!G455+'Donnees_USDA'!G557)>0,'Donnees_USDA'!G353/('Donnees_USDA'!G455+'Donnees_USDA'!G557),"") -> 0 | H46: =IF(('Donnees_USDA'!H455+'Donnees_USDA'!H557)>0,'Donnees_USDA'!H353/('Donnees_USDA'!H455+'Donnees_USDA'!H557),"") | I46: =IF(('Donnees_USDA'!I455+'Donnees_USDA'!I557)>0,'Donnees_USDA'!I353/('Donnees_USDA'!I455+'Donnees_USDA'!I557),"") | J46: =IF(('Donnees_USDA'!J455+'Donnees_USDA'!J557)>0,'Donnees_USDA'!J353/('Donnees_USDA'!J455+'Donnees_USDA'!J557),"") | ... S46: =IF(('Donnees_USDA'!S455+'Donnees_USDA'!S557)>0,'Donnees_USDA'!S353/('Donnees_USDA'!S455+'Donnees_USDA'!S557),"") | T46: =AVERAGE(C46:S46) -> 0 | U46: ='Donnees_USDA'!S47/'Donnees_USDA'!S102 -> 0 | V46: ='Donnees_USDA'!S557/'Donnees_USDA'!S612 -> 0 | W46: ='Donnees_USDA'!S353/'Donnees_USDA'!S405 -> 0 | X46: =IF('Donnees_USDA'!S557>0,'Donnees_USDA'!S353/'Donnees_USDA'!S557*52,"") | Y46: 0.00077928412 | Z46: 0
A48: Comment lire l'importance d'un pays : un STU bas veut dire que le pays exporte presque tout ce qu'il produit, sans coussin. Il ne pèse sur le prix que s'il est gros. Ce qui compte, c'est la taille (part de la production et des exportations), la taille des chocs (poids dans les chocs de production) et le coussin en volume (part des stocks, semaines d'exportation). Poids = part de la variance des variations annuelles mondiales qui vient du pays (production mondiale ; stocks des pays d'origine). Corrélations r sur 16 campagnes, niveaux, logarithme des prix.

Sheet 5_Analyse
A1: 5 — Analyse : comment le prix réagit, et à quoi
A2: Valeurs calculées sur les onglets 1 à 4 (16 campagnes 2010/11-2025/26 ; 15 pour les stocks certifiés). Corrélations sur le logarithme du prix. p = probabilité d'obtenir la corrélation par hasard. Les séries annuelles sont très autocorrélées (≈ 4 à 7 observations indépendantes sur 16) : les deux colonnes p en tiennent compte ; sous 0,05 = significatif.
A4: A. Le prix réagit-il à la production, aux stocks de fin, aux stocks certifiés ?
A5: Mesure | B5: Prix | C5: r niveau | D5: p corrigé (autocorr.) | E5: r sans tendance | F5: p sans tendance | G5: r variations | H5: Lecture
A6: Production arabica mondiale | B6: KC | C6: -0.14340458 | D6: 0.65305335 | E6: -0.34680499 | F6: 0.22892315 | G6: -0.071948599 | H6: Pas de lien de niveau ; la récolte à venir compte (section B).
A7: STU arabica pays d'origine (stocks de fin) | B7: KC | C7: -0.39167907 | D7: 0.4243295 | E7: -0.25140996 | F7: 0.55263367 | G7: -0.36488806 | H7: Lien modéré, non significatif.
A8: STU arabica (certifiés NY) | B8: KC | C8: -0.60845556 | D8: 0.296052 | E8: -0.3396418 | F8: 0.25622011 | G8: -0.32434503 | H8: Net en niveau, surtout par la tendance commune (un peu par le point 2025/26).
A9: Production robusta mondiale | B9: DF | C9: 0.30892445 | D9: 0.75743235 | E9: -0.34458052 | F9: 0.42535908 | G9: -0.62335197 | H9: Positif en niveau (les deux montent) ; négatif et significatif en variations.
A10: STU robusta pays d'origine (stocks de fin) | B10: DF | C10: -0.53920472 | D10: 0.26343285 | E10: -0.36528915 | F10: 0.41311235 | G10: -0.11460181 | H10: Lien modéré, non significatif une fois corrigé.
A11: STU robusta (certifiés Londres) | B11: DF | C11: -0.56236767 | D11: 0.16413197 | E11: -0.29497651 | F11: 0.35826639 | G11: 0.20441974 | H11: Net en niveau, faible sans tendance.
A12: STU monde (stocks de fin) | B12: KC | C12: -0.62871705 | D12: 0.28520929 | E12: -0.57611328 | F12: 0.27048407 | G12: -0.12672066 | H12: Le plus fort, même sans tendance ; non significatif une fois l'autocorrélation corrigée ; porté par 2023/24-2025/26.
A13: STU monde (stocks de fin) | B13: DF | C13: -0.72138477 | D13: 0.32594275 | E13: -0.58537236 | F13: 0.32426671 | G13: -0.14135579 | H13: Idem.
A14: STU monde (certifiés) | B14: KC | C14: -0.62859878 | D14: 0.28514989 | E14: -0.38872754 | F14: 0.18928016 | G14: 0.045910021 | H14: Net en niveau, faible sans tendance.
A15: STU monde (certifiés) | B15: DF | C15: -0.65143366 | D15: 0.38100489 | E15: -0.34244212 | F15: 0.25206733 | G15: 0.17634295 | H15: Net en niveau, faible sans tendance.
A16: Production mondiale | B16: KC | C16: 0.081690688 | D16: 0.89789269 | E16: -0.43794079 | F16: 0.1950799 | G16: -0.21373861 | H16: Pas de lien de niveau ; −0,44 sans tendance (non significatif).
A17: Production mondiale | B17: DF | C17: 0.28714044 | D17: 0.71932609 | E17: -0.36118463 | F17: 0.30549465 | G17: 0.020345525 | H17: Pas de lien de niveau.
A19: B. La production : le prix anticipe la récolte
A20: Relation (variations d'une campagne à l'autre) | C20: r | D20: p | E20: Pente | H20: Lecture
A21: KC ↔ récolte arabica de la même campagne | C21: -0.079353851 | H21: Pas de lien : la récolte en cours est déjà connue.
A22: KC ↔ récolte arabica de la campagne suivante | C22: -0.48508962 | D22: 0.065946703 | E22: -1.3034548 | H22: +1 % de récolte à venir ≈ −1,3 % de KC.
A23: KC ↔ récolte arabica du Brésil, campagne suivante | C23: -0.45086124 | H23: Brésil et Colombie comptent tous les deux.
A24: KC ↔ récolte de la Colombie, campagne suivante | C24: -0.74561002 | H24: Plus fort que le Brésil seul (test exploratoire, n = 15).
A25: DF ↔ récolte robusta de la même campagne | C25: -0.62414706 | D25: 0.0139993 | E25: -2.0753602 | H25: +1 % de robusta ≈ −2 % de DF.
A26: DF ↔ récolte du Vietnam, même campagne | C26: -0.348313
A28: C. Les stocks certifiés réagissent-ils au prix ? (données mensuelles juin 2012 → août 2026)
A29: Relation | B29: Horizon | C29: New York / KC | D29: Londres / DF | H29: Lecture
A30: Hausse du prix sur k mois → variation des certifiés sur les k mois suivants | B30: 1 mois | C30: -0.11268045 | D30: -0.0047835847 | H30: Aucun effet détecté (fenêtres qui se recouvrent : peu de mois indépendants).
B31: 3 mois | C31: 0.017666622 | D31: 0.094555257
B32: 6 mois | C32: -0.15139405 | D32: 0.1609606
B33: 12 mois | C33: -0.13783451 | D33: -0.1175494
A34: Variation des certifiés sur k mois → variation du prix sur les k mois suivants | B34: 1 mois | C34: 0.001003393 | D34: 0.061108305 | H34: New York : rien. Londres : baisse des certifiés → DF plus haut à 6-12 mois (−0,2 à −0,3), non significatif.
B35: 3 mois | C35: 0.1033391 | D35: -0.10375286
B36: 6 mois | C36: 0.10988561 | D36: -0.28536838
B37: 12 mois | C37: 0.019799564 | D37: -0.19893445
A38: Niveau de la prime futures − physique → variation des certifiés sur k mois | B38: 1 mois | C38: 0.15817726 | D38: 0.069466328 | H38: Faible.
B39: 3 mois | C39: 0.18428935 | D39: 0.10069392
B40: 6 mois | C40: 0.13763081 | D40: 0.10835756
B41: 12 mois | C41: 0.021075911 | D41: -0.023120492
A42: Écart de la prime NY − Brazilian Naturals à sa moyenne des 12 derniers mois → certifiés NY | B42: 3 mois | C42: 0.39632745 | H42: Modéré mais instable selon la période (12 mois / 3 mois) : 2012-2016 0,74 ; 2017-2020 -0,03 ; 2021-2026 0,51. Brazilian Naturals n'est pas une qualité livrable.
B43: 6 mois | C43: 0.4928224
A44: Écart de la prime NY − Brazilian Naturals à sa moyenne des 24 derniers mois → certifiés NY | B44: 3 mois | C44: 0.41524094
B45: 6 mois | C45: 0.44787731
A47: D. Prix selon le STU mondial (stocks ÷ (conso + export)) : courbe ln(prix) = a + b ÷ STU
A48: STU mondial | C48: KC1 de courbe (c/lb) | D48: DF1 de courbe ($/t) | E48: −1 pt de STU : effet sur le KC
A49: 0.06 | C49: 356.08079 | D49: 5095.9107 | E49: 0.40412492 | H49: Extrapolé : le STU le plus bas observé est 6,9 %.
A50: 0.07 | C50: 279.4208 | D50: 3808.254 | E50: 0.27435322
A51: 0.08 | C51: 232.96537 | D51: 3060.9341 | E51: 0.19940917
A52: 0.09 | C52: 202.24244 | D52: 2582.6449 | E52: 0.15191136
A53: 0.1 | C53: 180.60803 | D53: 2254.412 | E53: 0.11978656
A54: 0.11 | C54: 164.64005 | D54: 2017.1345 | E54: 0.096987219
A55: 0.12 | C55: 152.41727 | D55: 1838.5953 | E55: 0.08019287
A56: 0.13 | C56: 142.78642 | D56: 1699.9242 | E56: 0.067449306
A57: 0.14 | C57: 135.01725 | D57: 1589.4183 | E57: 0.057542064
A58: 0.15 | C58: 128.62675 | D58: 1499.4743 | E58: 0.049682517
A59: 0.16 | C59: 123.28368 | D59: 1424.9586 | E59: 0.043339665
A60: Qualité : R² 0,51 (KC) et 0,71 (DF) ; zone à ±1 écart-type : de −22 % à +28 % autour de la courbe pour le KC.
A61: Forme : R² KC linéaire 0,40, log 0,46, 1/STU 0,51. Sans 2023/24-2025/26, R² 1/STU = 0,10 (KC) et 0,09 (DF) : la convexité est une hypothèse économique compatible avec les données, portée par l'épisode récent.
A63: E. Régimes observés
A64: STU mondial | B64: Campagnes | C64: KC1 moyen | D64: KC1 min | E64: KC1 max | F64: DF1 moyen ($/t)
A65: < 8 % | B65: 2023/24, 2024/25, 2025/26 | C65: 283.09056 | D65: 204.00167 | E65: 333.06 | F65: 3998.1516 | H65: Un seul épisode : trois campagnes consécutives.
A66: 8 – 11 % | B66: 2011/12, 2017/18, 2021/22, 2022/23 | C66: 178.43 | D66: 120.60083 | E66: 224.0875 | F66: 2026.9484
A67: 11 – 13 % | B67: 2010/11, 2015/16, 2016/17, 2018/19, 2019/20, 2020/21 | C67: 147.8725 | D67: 104.98083 | E67: 249.66 | F67: 1714.0818
A68: > 13 % | B68: 2012/13, 2013/14, 2014/15 | C68: 152.06222 | D68: 140.69833 | E68: 161.4675 | F68: 1897.929
A70: F. Chaîne production → STU → prix
A71: +1 % de production mondiale ≈ +0,20 point de STU ; +1 % de consommation ≈ -0,25 point (R² 0,38).
A72: Consommation : +1,8 % par an en moyenne, écart-type 2,3 %, contre 4,4 % pour la production. Elle ne suit pas le prix (r -0,05).
A73: Point d'équilibre : l'équation donne ≈ +3,0 % de production par an pour un STU stable, mais il est mal déterminé (effet de la consommation non significatif, t = -1,6). En comptabilité simple, la production doit suivre l'utilisation (+1,8 % par an).
A74: 2026/27 : la règle donne +0,13 point de STU, l'USDA prévoit +0,13 point. Écart-type de l'équation : 1,5 point, donc un seul point juste ne valide rien.
A75: Aujourd'hui : STU 2026/27 7,8 % → KC1 de courbe 242 c/lb, DF1 3208 $/t ; marché d'août 2026 : 313 c/lb et 3696 $/t.
A77: G. Robustesse : ce qui tient et ce qui ne tient pas
A78: Le sens de variation du STU donne-t-il le sens du prix (2012/13-2025/26) ? STU mondial → KC 8 fois sur 14 ; → DF 9 sur 14 ; STU arabica → KC 7 sur 14 ; STU robusta → DF 10 sur 14. Ce n'est pas une règle de trading pour le KC.
A79: Sans les trois campagnes 2023/24-2025/26 : STU mondial / KC -0,26, / DF -0,21 (sans tendance -0,42 et -0,36).
A80: Certifiés arabica / KC sans le point 2025/26 (fin août 2026) : -0,51 (p 0,06).
A81: Mois de relevé des certifiés (arabica / KC ; robusta / DF) : fin septembre -0,61 ; -0,56 · fin juin -0,65 ; -0,57 · décembre de début de campagne -0,63 ; -0,71 · décembre suivant -0,45 ; -0,58 · moyenne de campagne -0,68 ; -0,68.
A82: Stocks des pays consommateurs : 51 à 77 % des stocks mondiaux. Entre 2021/22 et 2024/25, les stocks mondiaux baissent de 9,9 M sacs, dont 5,8 M pour l'UE (estimation USDA) et 2,5 M pour les pays d'origine.
... A84: Autocorrélation d'ordre 1 : STU mondial 0,77, ln KC 0,71, ln DF 0,81. Les tests « p corrigé » en tiennent compte : aucun lien n'est significatif au sens strict, ni en niveau ni sans tendance (STU mondial sans tendance : p ≈ 0,27 pour le KC).

Sheet 6_Situations
A1: 6 — Comment le prix se comporte selon la situation des stocks (stocks de fin USDA et stocks certifiés)
A2: Chaque campagne est classée selon le sens de variation de deux ratios : STU stocks de fin USDA et STU certifié. Variation du prix = moyenne de campagne contre la campagne précédente. Peu de cas par situation : lecture descriptive, pas statistique. Les petites variations (ex. certifiés monde 2024/25 : +0,01 pt, où New York baisse et Londres monte) sont classées quand même. Lignes de synthèse : moyenne géométrique des variations.
A4: Monde (stocks USDA mondiaux et certifiés NY + Londres) — KC1 · pour le KC, lire plutôt le bloc Arabica (certifiés New York seuls)
A5: Campagne | B5: Situation | C5: Variation STU stocks de fin (pt) | D5: Variation STU certifié (pt) | E5: Variation du KC1 | F5: KC1 la campagne suivante
A6: 2012/13 | B6: stocks USDA ↑ / certifiés ↓ | C6: 3.3928982 | D6: -0.21072338 | E6: -0.28883366 | F6: 0.14761487
A7: 2013/14 | B7: stocks USDA ↑ / certifiés ↑ | C7: 1.8148965 | D7: 0.11683078 | E7: 0.14761487 | F7: -0.046118672
A8: 2014/15 | B8: stocks USDA ↑ / certifiés ↑ | C8: 0.82656865 | D8: 0.436043 | E8: -0.046118672 | F8: -0.1440606
A9: 2015/16 | B9: stocks USDA ↓ / certifiés ↓ | C9: -3.7279827 | D9: -0.80253972 | E9: -0.1440606 | F9: 0.090563151
A10: 2016/17 | B10: stocks USDA ↑ / certifiés ↑ | C10: 0.44943114 | D10: 0.27298075 | E10: 0.090563151 | F10: -0.16116411
A11: 2017/18 | B11: stocks USDA ↓ / certifiés ↓ | C11: -1.788006 | D11: -0.1478939 | E11: -0.16116411 | F11: -0.12951818
A12: 2018/19 | B12: stocks USDA ↑ / certifiés ↑ | C12: 1.1042916 | D12: 0.25923436 | E12: -0.12951818 | F12: 0.078641339
A13: 2019/20 | B13: stocks USDA ↓ / certifiés ↓ | C13: -0.060158189 | D13: -0.65531434 | E13: 0.078641339 | F13: 0.26949457
A14: 2020/21 | B14: stocks USDA ↑ / certifiés ↑ | C14: 0.32938484 | D14: 0.39129312 | E14: 0.26949457 | F14: 0.55883342
A15: 2021/22 | B15: stocks USDA ↓ / certifiés ↓ | C15: -1.9567156 | D15: -0.76831326 | E15: 0.55883342 | F15: -0.23605734
A16: 2022/23 | B16: stocks USDA ↓ / certifiés ↓ | C16: -1.3791222 | D16: -0.25294268 | E16: -0.23605734 | F16: 0.19166813
A17: 2023/24 | B17: stocks USDA ↓ / certifiés ↑ | C17: -1.3548091 | D17: 0.1216777 | E17: 0.19166813 | F17: 0.63263372
A18: 2024/25 | B18: stocks USDA ↓ / certifiés ↑ | C18: -0.63229204 | D18: 0.0083528263 | E18: 0.63263372 | F18: -0.062601333
A19: 2025/26 | B19: stocks USDA ↑ / certifiés ↓ | C19: 0.74116927 | D19: -0.19706764 | E19: -0.062601333
A20: Situation | B20: Nb de campagnes | C20: Variation moyenne du prix | D20: Campagnes en hausse | E20: Moyenne la campagne suivante | F20: Campagnes
A21: stocks USDA ↑ / certifiés ↑ | B21: 5 | C21: 0.056979046 | D21: 3 sur 5 | E21: 0.028627728 | F21: 2013/14, 2014/15, 2016/17, 2018/19, 2020/21
A22: stocks USDA ↑ / certifiés ↓ | B22: 2 | C22: -0.18351584 | D22: 0 sur 2 | E22: 0.14761487 | F22: 2012/13, 2025/26
A23: stocks USDA ↓ / certifiés ↑ | B23: 2 | C23: 0.39483245 | D23: 2 sur 2 | E23: 0.23710496 | F23: 2023/24, 2024/25
A24: stocks USDA ↓ / certifiés ↓ | B24: 5 | C24: -0.016053444 | D24: 2 sur 5 | E24: 0.018712163 | F24: 2015/16, 2017/18, 2019/20, 2021/22, 2022/23
A26: Monde — DF1
A27: Campagne | B27: Situation | C27: Variation STU stocks de fin (pt) | D27: Variation STU certifié (pt) | E27: Variation du DF1 | F27: DF1 la campagne suivante
A28: 2012/13 | B28: stocks USDA ↑ / certifiés ↓ | C28: 3.3928982 | D28: -0.21072338 | E28: -0.031770639 | F28: -0.029460241
A29: 2013/14 | B29: stocks USDA ↑ / certifiés ↑ | C29: 1.8148965 | D29: 0.11683078 | E29: -0.029460241 | F29: -0.02286291
A30: 2014/15 | B30: stocks USDA ↑ / certifiés ↑ | C30: 0.82656865 | D30: 0.436043 | E30: -0.02286291 | F30: -0.11729713
A31: 2015/16 | B31: stocks USDA ↓ / certifiés ↓ | C31: -3.7279827 | D31: -0.80253972 | E31: -0.11729713 | F31: 0.28426453
A32: 2016/17 | B32: stocks USDA ↑ / certifiés ↑ | C32: 0.44943114 | D32: 0.27298075 | E32: 0.28426453 | F32: -0.1770158
A33: 2017/18 | B33: stocks USDA ↓ / certifiés ↓ | C33: -1.788006 | D33: -0.1478939 | E33: -0.1770158 | F33: -0.13735071
A34: 2018/19 | B34: stocks USDA ↑ / certifiés ↑ | C34: 1.1042916 | D34: 0.25923436 | E34: -0.13735071 | F34: -0.12307654
A35: 2019/20 | B35: stocks USDA ↓ / certifiés ↓ | C35: -0.060158189 | D35: -0.65531434 | E35: -0.12307654 | F35: 0.18025751
A36: 2020/21 | B36: stocks USDA ↑ / certifiés ↑ | C36: 0.32938484 | D36: 0.39129312 | E36: 0.18025751 | F36: 0.39535022
A37: 2021/22 | B37: stocks USDA ↓ / certifiés ↓ | C37: -1.9567156 | D37: -0.76831326 | E37: 0.39535022 | F37: 0.031127441
A38: 2022/23 | B38: stocks USDA ↓ / certifiés ↓ | C38: -1.3791222 | D38: -0.25294268 | E38: 0.031127441 | F38: 0.58056978
A39: 2023/24 | B39: stocks USDA ↓ / certifiés ↑ | C39: -1.3548091 | D39: 0.1216777 | E39: 0.58056978 | F39: 0.34172696
A40: 2024/25 | B40: stocks USDA ↓ / certifiés ↑ | C40: -0.63229204 | D40: 0.0083528263 | E40: 0.34172696 | F40: -0.19424283
A41: 2025/26 | B41: stocks USDA ↑ / certifiés ↓ | C41: 0.74116927 | D41: -0.19706764 | E41: -0.19424283
A42: Situation | B42: Nb de campagnes | C42: Variation moyenne du prix | D42: Campagnes en hausse | E42: Moyenne la campagne suivante | F42: Campagnes
A43: stocks USDA ↑ / certifiés ↑ | B43: 5 | C43: 0.043967244 | D43: 2 sur 5 | E43: -0.027787302 | F43: 2013/14, 2014/15, 2016/17, 2018/19, 2020/21
A44: stocks USDA ↑ / certifiés ↓ | B44: 2 | C44: -0.11673461 | D44: 0 sur 2 | E44: -0.029460241 | F44: 2012/13, 2025/26
A45: stocks USDA ↓ / certifiés ↑ | B45: 2 | C45: 0.45625996 | D45: 2 sur 2 | E45: 0.039762532 | F45: 2023/24, 2024/25
A46: stocks USDA ↓ / certifiés ↓ | B46: 5 | C46: -0.01727352 | D46: 2 sur 5 | E46: 0.16337121 | F46: 2015/16, 2017/18, 2019/20, 2021/22, 2022/23
A48: Arabica (pays d'origine, certifiés New York) — KC1
A49: Campagne | B49: Situation | C49: Variation STU stocks de fin (pt) | D49: Variation STU certifié (pt) | E49: Variation du KC1 | F49: KC1 la campagne suivante
A50: 2012/13 | B50: stocks USDA ↑ / certifiés ↑ | C50: 5.6422725 | D50: 0.71343133 | E50: -0.28883366 | F50: 0.14761487
A51: 2013/14 | B51: stocks USDA ↑ / certifiés ↓ | C51: 2.5767052 | D51: -0.57188134 | E51: 0.14761487 | F51: -0.046118672
A52: 2014/15 | B52: stocks USDA ↓ / certifiés ↓ | C52: -2.5648443 | D52: -0.38435465 | E52: -0.046118672 | F52: -0.1440606
A53: 2015/16 | B53: stocks USDA ↓ / certifiés ↓ | C53: -4.9103336 | D53: -1.0168855 | E53: -0.1440606 | F53: 0.090563151
A54: 2016/17 | B54: stocks USDA ↑ / certifiés ↑ | C54: 0.28619412 | D54: 0.46404528 | E54: 0.090563151 | F54: -0.16116411
A55: 2017/18 | B55: stocks USDA ↓ / certifiés ↑ | C55: -0.20344918 | D55: 0.78684433 | E55: -0.16116411 | F55: -0.12951818
A56: 2018/19 | B56: stocks USDA ↓ / certifiés ↓ | C56: -0.12300265 | D56: -0.34216968 | E56: -0.12951818 | F56: 0.078641339
A57: 2019/20 | B57: stocks USDA ↓ / certifiés ↓ | C57: -1.0201457 | D57: -1.1629666 | E57: 0.078641339 | F57: 0.26949457
A58: 2020/21 | B58: stocks USDA ↑ / certifiés ↑ | C58: 1.358026 | D58: 0.9138713 | E58: 0.26949457 | F58: 0.55883342
A59: 2021/22 | B59: stocks USDA ↓ / certifiés ↓ | C59: -3.4703027 | D59: -1.7212426 | E59: 0.55883342 | F59: -0.23605734
A60: 2022/23 | B60: stocks USDA ↑ / certifiés ↑ | C60: 2.8133093 | D60: 0.072573151 | E60: -0.23605734 | F60: 0.19166813
A61: 2023/24 | B61: stocks USDA ↓ / certifiés ↑ | C61: -2.3836029 | D61: 0.30622586 | E61: 0.19166813 | F61: 0.63263372
A62: 2024/25 | B62: stocks USDA ↓ / certifiés ↓ | C62: -0.46975634 | D62: -0.27036094 | E62: 0.63263372 | F62: -0.062601333
A63: 2025/26 | B63: stocks USDA ↑ / certifiés ↓ | C63: 2.2660481 | D63: -0.33919814 | E63: -0.062601333
A64: Situation | B64: Nb de campagnes | C64: Variation moyenne du prix | D64: Campagnes en hausse | E64: Moyenne la campagne suivante | F64: Campagnes
A65: stocks USDA ↑ / certifiés ↑ | B65: 4 | C65: -0.068724014 | D65: 2 sur 4 | E65: 0.15639725 | F65: 2012/13, 2016/17, 2020/21, 2022/23
A66: stocks USDA ↑ / certifiés ↓ | B66: 2 | C66: 0.037194607 | D66: 1 sur 2 | E66: -0.046118672 | F66: 2013/14, 2025/26
A67: stocks USDA ↓ / certifiés ↑ | B67: 2 | C67: -0.00019302429 | D67: 1 sur 2 | E67: 0.19213169 | F67: 2017/18, 2023/24
A68: stocks USDA ↓ / certifiés ↓ | B68: 6 | C68: 0.11783345 | D68: 3 sur 6 | E68: -0.01463347 | F68: 2014/15, 2015/16, 2018/19, 2019/20, 2021/22, 2024/25
A70: Robusta (pays d'origine, certifiés Londres) — DF1
A71: Campagne | B71: Situation | C71: Variation STU stocks de fin (pt) | D71: Variation STU certifié (pt) | E71: Variation du DF1 | F71: DF1 la campagne suivante
A72: 2012/13 | B72: stocks USDA ↑ / certifiés ↓ | C72: 4.15029 | D72: -1.850866 | E72: -0.031770639 | F72: -0.029460241
A73: 2013/14 | B73: stocks USDA ↑ / certifiés ↑ | C73: 0.70375051 | D73: 1.1215946 | E73: -0.029460241 | F73: -0.02286291
A74: 2014/15 | B74: stocks USDA ↑ / certifiés ↑ | C74: 6.5590813 | D74: 2.3547583 | E74: -0.02286291 | F74: -0.11729713
A75: 2015/16 | B75: stocks USDA ↓ / certifiés ↓ | C75: -7.2746592 | D75: -1.8824804 | E75: -0.11729713 | F75: 0.28426453
A76: 2016/17 | B76: stocks USDA ↓ / certifiés ↑ | C76: -1.6742408 | D76: 0.70576488 | E76: 0.28426453 | F76: -0.1770158
A77: 2017/18 | B77: stocks USDA ↓ / certifiés ↓ | C77: -3.6426498 | D77: -1.7218541 | E77: -0.1770158 | F77: -0.13735071
A78: 2018/19 | B78: stocks USDA ↑ / certifiés ↑ | C78: 2.629014 | D78: 1.4075376 | E78: -0.13735071 | F78: -0.12307654
A79: 2019/20 | B79: stocks USDA ↑ / certifiés ↓ | C79: 0.78190198 | D79: -1.1433645 | E79: -0.12307654 | F79: 0.18025751
A80: 2020/21 | B80: stocks USDA ↑ / certifiés ↑ | C80: 1.9586945 | D80: 0.35071328 | E80: 0.18025751 | F80: 0.39535022
A81: 2021/22 | B81: stocks USDA ↓ / certifiés ↓ | C81: -3.4380642 | D81: -0.84275652 | E81: 0.39535022 | F81: 0.031127441
A82: 2022/23 | B82: stocks USDA ↓ / certifiés ↓ | C82: -1.5610935 | D82: -0.97041884 | E82: 0.031127441 | F82: 0.58056978
A83: 2023/24 | B83: stocks USDA ↓ / certifiés ↑ | C83: -1.4875308 | D83: 0.054504882 | E83: 0.58056978 | F83: 0.34172696
A84: 2024/25 | B84: stocks USDA ↑ / certifiés ↑ | C84: 0.01013299 | D84: 0.41440229 | E84: 0.34172696 | F84: -0.19424283
A85: 2025/26 | B85: stocks USDA ↑ / certifiés ↓ | C85: 0.97464364 | D85: -0.41322421 | E85: -0.19424283
A86: Situation | B86: Nb de campagnes | C86: Variation moyenne du prix | D86: Campagnes en hausse | E86: Moyenne la campagne suivante | F86: Campagnes
A87: stocks USDA ↑ / certifiés ↑ | B87: 5 | C87: 0.053146537 | D87: 2 sur 5 | E87: -0.031891961 | F87: 2013/14, 2014/15, 2018/19, 2020/21, 2024/25
A88: stocks USDA ↑ / certifiés ↓ | B88: 3 | C88: -0.11885367 | D88: 0 sur 3 | E88: 0.070274189 | F88: 2012/13, 2019/20, 2025/26
A89: stocks USDA ↓ / certifiés ↑ | B89: 2 | C89: 0.42473496 | D89: 2 sur 2 | E89: 0.050818767 | F89: 2016/17, 2023/24
A90: stocks USDA ↓ / certifiés ↓ | B90: 4 | C90: 0.011114646 | D90: 2 sur 4 | E90: 0.15918751 | F90: 2015/16, 2017/18, 2021/22, 2022/23
A92: Rendement des 12 mois suivants selon le niveau des stocks certifiés (mensuel, 2012-06 → 2025-08 ; fenêtres qui se recouvrent, peu d'épisodes indépendants)
A93: Stocks certifiés | B93: Marché | C93: Nb de mois | D93: Rendement 12 mois (moyenne géométrique) | E93: Médiane | F93: % de hausses | G93: Pire | H93: Meilleur
A94: < 0,8 M sacs | B94: New York / KC | C94: 19 | D94: 0.2840544 | E94: 0.47364793 | F94: 0.73684211 | G94: -0.29641679 | H94: 1.0940821
A95: 0,8 – 1,5 | B95: New York / KC | C95: 38 | D95: 0.024056745 | E95: -0.064332088 | F95: 0.47368421 | G95: -0.32325414 | H95: 0.93921025
A96: 1,5 – 2,5 | B96: New York / KC | C96: 56 | D96: 0.055536886 | E96: 0.045797593 | F96: 0.53571429 | G96: -0.31825958 | H96: 0.89205027
A97: > 2,5 | B97: New York / KC | C97: 46 | D97: -0.0063824562 | E97: -0.013068864 | F97: 0.47826087 | G97: -0.38392347 | H97: 0.79513029
A98: < 0,8 M sacs | B98: Londres / DF | C98: 24 | D98: 0.1730895 | E98: 0.16364828 | F98: 0.58333333 | G98: -0.36081293 | H98: 1.0627634
A99: 0,8 – 1,5 | B99: Londres / DF | C99: 29 | D99: 0.063241532 | E99: -0.076062393 | F99: 0.48275862 | G99: -0.32426657 | H99: 0.70682978
A100: 1,5 – 2,5 | B100: Londres / DF | C100: 68 | D100: 0.0035913525 | E100: -0.067736995 | F100: 0.44117647 | G100: -0.26486063 | H100: 0.66930955
A101: > 2,5 | B101: Londres / DF | C101: 38 | D101: 0.043778028 | E101: 0.023150684 | F101: 0.52631579 | G101: -0.27629234 | H101: 0.52641998

Sheet 7_Bresil_arabica
A1: 7 — Brésil seul : production d'arabica et stock-to-use (stocks de fin ÷ (consommation + exportations)), avec KC1
A2: Données USDA PSD, Brésil (campagne juillet-juin). L'USDA ne publie pour le Brésil qu'un seul chiffre de stocks de fin, de consommation et d'exportations, arabica et conilon ensemble (vérifié aussi dans les rapports USDA « Brazil Coffee Annual » 2013-2026).
A3: Avec la méthode des onglets 2 et 3 (stocks et utilisation × part d'arabica), la part s'annule : le STU arabica du Brésil (colonne L) est égal au STU du Brésil (colonne I). Colonne M : borne haute si tous les stocks brésiliens étaient de l'arabica.
A4: Campagne | B4: Production arabica Brésil (1000 sacs) | C4: Production arabica Brésil (M sacs) | D4: Production totale Brésil (1000 sacs) | E4: Part arabica de la production | F4: Stocks de fin Brésil, tous cafés (1000 sacs) | G4: Consommation domestique (1000 sacs) | H4: Exportations (1000 sacs) | I4: STU Brésil = stocks ÷ (conso + export) | J4: Stocks de fin × part arabica | K4: (Conso + export) × part arabica | L4: STU arabica Brésil (méthode par part) = J ÷ K | M4: Borne haute : tous les stocks = arabica (F ÷ K) | N4: Pour comparer : STU arabica des 42 pays d'origine | O4: KC1 (US c/lb)
A5: 2010/11 | B5: ='Donnees_USDA'!C108 -> 41800 | C5: =B5/1000 -> 41.8 | D5: ='Donnees_USDA'!C6 -> 54500 | E5: =B5/D5 -> 0.76697248 | F5: ='Donnees_USDA'!C312 -> 2906 | G5: ='Donnees_USDA'!C414 -> 19420 | H5: ='Donnees_USDA'!C516 -> 35010 | I5: =F5/(G5+H5) -> 0.053389675 | J5: =E5*F5 -> 2228.822 | K5: =E5*(G5+H5) -> 41746.312 | L5: =J5/K5 -> 0.053389675 | M5: =F5/K5 -> 0.06961094 | N5: ='2_Arabica'!F5 -> 0.049457868 | O5: ='Prix_ICE'!I5 -> 249.66
A6: 2011/12 | B6: ='Donnees_USDA'!D108 -> 34700 | C6: =B6/1000 -> 34.7 | D6: ='Donnees_USDA'!D6 -> 49200 | E6: =B6/D6 -> 0.70528455 | F6: ='Donnees_USDA'!D312 -> 2238 | G6: ='Donnees_USDA'!D414 -> 20025 | H6: ='Donnees_USDA'!D516 -> 29843 | I6: =F6/(G6+H6) -> 0.044878479 | J6: =E6*F6 -> 1578.4268 | K6: =E6*(G6+H6) -> 35171.13 | L6: =J6/K6 -> 0.044878479 | M6: =F6/K6 -> 0.063631734 | N6: ='2_Arabica'!F6 -> 0.050398172 | O6: ='Prix_ICE'!I6 -> 197.84167
A7: 2012/13 | B7: ='Donnees_USDA'!E108 -> 42100 | C7: =B7/1000 -> 42.1 | D7: ='Donnees_USDA'!E6 -> 57600 | E7: =B7/D7 -> 0.73090278 | F7: ='Donnees_USDA'!E312 -> 9068 | G7: ='Donnees_USDA'!E414 -> 20110 | H7: ='Donnees_USDA'!E516 -> 30660 | I7: =F7/(G7+H7) -> 0.17860942 | J7: =E7*F7 -> 6627.8264 | K7: =E7*(G7+H7) -> 37107.934 | L7: =J7/K7 -> 0.17860942 | M7: =F7/K7 -> 0.24436823 | N7: ='2_Arabica'!F7 -> 0.1068209 | O7: ='Prix_ICE'!I7 -> 140.69833
A8: 2013/14 | B8: ='Donnees_USDA'!F108 -> 41800 | C8: =B8/1000 -> 41.8 | D8: ='Donnees_USDA'!F6 -> 57200 | E8: =B8/D8 -> 0.73076923 | F8: ='Donnees_USDA'!F312 -> 11946 | G8: ='Donnees_USDA'!F414 -> 20210 | H8: ='Donnees_USDA'!F516 -> 34146 | I8: =F8/(G8+H8) -> 0.21977335 | J8: =E8*F8 -> 8729.7692 | K8: =E8*(G8+H8) -> 39721.692 | L8: =J8/K8 -> 0.21977335 | M8: =F8/K8 -> 0.30074247 | N8: ='2_Arabica'!F8 -> 0.13258795 | O8: ='Prix_ICE'!I8 -> 161.4675
A9: 2014/15 | B9: ='Donnees_USDA'!G108 -> 37300 | C9: =B9/1000 -> 37.3 | D9: ='Donnees_USDA'!G6 -> 54300 | E9: =B9/D9 -> 0.68692449 | F9: ='Donnees_USDA'!G312 -> 9305 | G9: ='Donnees_USDA'!G414 -> 20420 | H9: ='Donnees_USDA'!G516 -> 36573 | I9: =F9/(G9+H9) -> 0.16326566 | J9: =E9*F9 -> 6391.8324 | K9: =E9*(G9+H9) -> 39149.888 | L9: =J9/K9 -> 0.16326566 | M9: =F9/K9 -> 0.23767629 | N9: ='2_Arabica'!F9 -> 0.10693951 | O9: ='Prix_ICE'!I9 -> 154.02083
A10: 2015/16 | B10: ='Donnees_USDA'!H108 -> 36100 | C10: =B10/1000 -> 36.1 | D10: ='Donnees_USDA'!H6 -> 49400 | E10: =B10/D10 -> 0.73076923 | F10: ='Donnees_USDA'!H312 -> 2372 | G10: ='Donnees_USDA'!H414 -> 20855 | H10: ='Donnees_USDA'!H516 -> 35543 | I10: =F10/(G10+H10) -> 0.042058229 | J10: =E10*F10 -> 1733.3846 | K10: =E10*(G10+H10) -> 41213.923 | L10: =J10/K10 -> 0.042058229 | M10: =F10/K10 -> 0.057553366 | N10: ='2_Arabica'!F10 -> 0.057836169 | O10: ='Prix_ICE'!I10 -> 131.8325
A11: 2016/17 | B11: ='Donnees_USDA'!I108 -> 45600 | C11: =B11/1000 -> 45.6 | D11: ='Donnees_USDA'!I6 -> 56100 | E11: =B11/D11 -> 0.81283422 | F11: ='Donnees_USDA'!I312 -> 3828 | G11: ='Donnees_USDA'!I414 -> 21625 | H11: ='Donnees_USDA'!I516 -> 33081 | I11: =F11/(G11+H11) -> 0.069974043 | J11: =E11*F11 -> 3111.5294 | K11: =E11*(G11+H11) -> 44466.909 | L11: =J11/K11 -> 0.069974043 | M11: =F11/K11 -> 0.086086487 | N11: ='2_Arabica'!F11 -> 0.060698111 | O11: ='Prix_ICE'!I11 -> 143.77167
A12: 2017/18 | B12: ='Donnees_USDA'!J108 -> 39500 | C12: =B12/1000 -> 39.5 | D12: ='Donnees_USDA'!J6 -> 52100 | E12: =B12/D12 -> 0.75815739 | F12: ='Donnees_USDA'!J312 -> 3115 | G12: ='Donnees_USDA'!J414 -> 22420 | H12: ='Donnees_USDA'!J516 -> 30454 | I12: =F12/(G12+H12) -> 0.058913644 | J12: =E12*F12 -> 2361.6603 | K12: =E12*(G12+H12) -> 40086.814 | L12: =J12/K12 -> 0.058913644 | M12: =F12/K12 -> 0.07770635 | N12: ='2_Arabica'!F12 -> 0.058663619 | O12: ='Prix_ICE'!I12 -> 120.60083
A13: 2018/19 | B13: ='Donnees_USDA'!K108 -> 49700 | C13: =B13/1000 -> 49.7 | D13: ='Donnees_USDA'!K6 -> 66500 | E13: =B13/D13 -> 0.74736842 | F13: ='Donnees_USDA'!K312 -> 5056 | G13: ='Donnees_USDA'!K414 -> 23200 | H13: ='Donnees_USDA'!K516 -> 41426 | I13: =F13/(G13+H13) -> 0.078234766 | J13: =E13*F13 -> 3778.6947 | K13: =E13*(G13+H13) -> 48299.432 | L13: =J13/K13 -> 0.078234766 | M13: =F13/K13 -> 0.10468032 | N13: ='2_Arabica'!F13 -> 0.057433592 | O13: ='Prix_ICE'!I13 -> 104.98083
A14: 2019/20 | B14: ='Donnees_USDA'!L108 -> 42000 | C14: =B14/1000 -> 42 | D14: ='Donnees_USDA'!L6 -> 60500 | E14: =B14/D14 -> 0.69421488 | F14: ='Donnees_USDA'!L312 -> 2373 | G14: ='Donnees_USDA'!L414 -> 22994 | H14: ='Donnees_USDA'!L516 -> 40256 | I14: =F14/(G14+H14) -> 0.037517787 | J14: =E14*F14 -> 1647.3719 | K14: =E14*(G14+H14) -> 43909.091 | L14: =J14/K14 -> 0.037517787 | M14: =F14/K14 -> 0.054043478 | N14: ='2_Arabica'!F14 -> 0.047232135 | O14: ='Prix_ICE'!I14 -> 113.23667
A15: 2020/21 | B15: ='Donnees_USDA'!M108 -> 49700 | C15: =B15/1000 -> 49.7 | D15: ='Donnees_USDA'!M6 -> 69900 | E15: =B15/D15 -> 0.71101574 | F15: ='Donnees_USDA'!M312 -> 4390 | G15: ='Donnees_USDA'!M414 -> 22280 | H15: ='Donnees_USDA'!M516 -> 45675 | I15: =F15/(G15+H15) -> 0.064601575 | J15: =E15*F15 -> 3121.3591 | K15: =E15*(G15+H15) -> 48317.074 | L15: =J15/K15 -> 0.064601575 | M15: =F15/K15 -> 0.09085815 | N15: ='2_Arabica'!F15 -> 0.060812395 | O15: ='Prix_ICE'!I15 -> 143.75333
A16: 2021/22 | B16: ='Donnees_USDA'!N108 -> 36400 | C16: =B16/1000 -> 36.4 | D16: ='Donnees_USDA'!N6 -> 58100 | E16: =B16/D16 -> 0.62650602 | F16: ='Donnees_USDA'!N312 -> 540 | G16: ='Donnees_USDA'!N414 -> 22340 | H16: ='Donnees_USDA'!N516 -> 39685 | I16: =F16/(G16+H16) -> 0.0087061669 | J16: =E16*F16 -> 338.31325 | K16: =E16*(G16+H16) -> 38859.036 | L16: =J16/K16 -> 0.0087061669 | M16: =F16/K16 -> 0.013896382 | N16: ='2_Arabica'!F16 -> 0.026109367 | O16: ='Prix_ICE'!I16 -> 224.0875
A17: 2022/23 | B17: ='Donnees_USDA'!O108 -> 39800 | C17: =B17/1000 -> 39.8 | D17: ='Donnees_USDA'!O6 -> 62600 | E17: =B17/D17 -> 0.63578275 | F17: ='Donnees_USDA'!O312 -> 4620 | G17: ='Donnees_USDA'!O414 -> 22450 | H17: ='Donnees_USDA'!O516 -> 36145 | I17: =F17/(G17+H17) -> 0.078846318 | J17: =E17*F17 -> 2937.3163 | K17: =E17*(G17+H17) -> 37253.69 | L17: =J17/K17 -> 0.078846318 | M17: =F17/K17 -> 0.12401456 | N17: ='2_Arabica'!F17 -> 0.05424246 | O17: ='Prix_ICE'!I17 -> 171.19
A18: 2023/24 | B18: ='Donnees_USDA'!P108 -> 44900 | C18: =B18/1000 -> 44.9 | D18: ='Donnees_USDA'!P6 -> 66300 | E18: =B18/D18 -> 0.67722474 | F18: ='Donnees_USDA'!P312 -> 2085 | G18: ='Donnees_USDA'!P414 -> 22160 | H18: ='Donnees_USDA'!P516 -> 46750 | I18: =F18/(G18+H18) -> 0.030256857 | J18: =E18*F18 -> 1412.0136 | K18: =E18*(G18+H18) -> 46667.557 | L18: =J18/K18 -> 0.030256857 | M18: =F18/K18 -> 0.044677719 | N18: ='2_Arabica'!F18 -> 0.030406431 | O18: ='Prix_ICE'!I18 -> 204.00167
A19: 2024/25 | B19: ='Donnees_USDA'!Q108 -> 44500 | C19: =B19/1000 -> 44.5 | D19: ='Donnees_USDA'!Q6 -> 65500 | E19: =B19/D19 -> 0.67938931 | F19: ='Donnees_USDA'!Q312 -> 955 | G19: ='Donnees_USDA'!Q414 -> 21970 | H19: ='Donnees_USDA'!Q516 -> 44750 | I19: =F19/(G19+H19) -> 0.014313549 | J19: =E19*F19 -> 648.81679 | K19: =E19*(G19+H19) -> 45328.855 | L19: =J19/K19 -> 0.014313549 | M19: =F19/K19 -> 0.021068258 | N19: ='2_Arabica'!F19 -> 0.025708868 | O19: ='Prix_ICE'!I19 -> 333.06
A20: 2025/26 | B20: ='Donnees_USDA'!R108 -> 38000 | C20: =B20/1000 -> 38 | D20: ='Donnees_USDA'!R6 -> 63000 | E20: =B20/D20 -> 0.6031746 | F20: ='Donnees_USDA'!R312 -> 3895 | G20: ='Donnees_USDA'!R414 -> 22280 | H20: ='Donnees_USDA'!R516 -> 37870 | I20: =F20/(G20+H20) -> 0.06475478 | J20: =E20*F20 -> 2349.3651 | K20: =E20*(G20+H20) -> 36280.952 | L20: =J20/K20 -> 0.06475478 | M20: =F20/K20 -> 0.10735661 | N20: ='2_Arabica'!F20 -> 0.048369348 | O20: ='Prix_ICE'!I20 -> 312.21
A21: 2026/27 (prév.) | B21: ='Donnees_USDA'!S108 -> 47500 | C21: =B21/1000 -> 47.5 | D21: ='Donnees_USDA'!S6 -> 71900 | E21: =B21/D21 -> 0.66063978 | F21: ='Donnees_USDA'!S312 -> 4425 | G21: ='Donnees_USDA'!S414 -> 22390 | H21: ='Donnees_USDA'!S516 -> 49070 | I21: =F21/(G21+H21) -> 0.061922754 | J21: =E21*F21 -> 2923.331 | K21: =E21*(G21+H21) -> 47209.318 | L21: =J21/K21 -> 0.061922754 | M21: =F21/K21 -> 0.093731495 | N21: ='2_Arabica'!F21 -> 0.047226115
A23: Lecture : le STU du Brésil suit presque exactement le STU arabica des 42 pays d'origine (corrélation 0,98) : c'est le Brésil qui donne sa forme à la courbe arabica. Avec le KC, le lien est faible : -0,30 en niveau, -0,16 sans tendance, non significatif. Mais les deux campagnes où les stocks brésiliens sont tombés presque à zéro (0,9 % en 2021/22 et 1,4 % en 2024/25, moins d'une semaine d'utilisation) sont les deux plus fortes flambées du KC (224 et 333 c/lb). Le lien joue dans les deux sens : selon l'USDA, en 2024 la petite récolte et les prix élevés ont poussé les producteurs à exporter, ce qui a presque vidé les stocks.
A29: KC1 selon le niveau du STU du Brésil (campagnes 2010/11-2025/26)
A30: STU du Brésil | B30: Nb de campagnes | C30: KC1 moyen (c/lb) | D30: KC1 min – max | E30: Campagnes
A31: < 3 % | B31: 2 | C31: 278.57375 | D31: 224 – 333 | E31: 2021/22, 2024/25
A32: 3 – 6 % | B32: 6 | C32: 169.52889 | D32: 113 – 250 | E32: 2010/11, 2011/12, 2015/16, 2017/18, 2019/20, 2023/24
A33: 6 – 10 % | B33: 5 | C33: 175.18117 | D33: 105 – 312 | E33: 2016/17, 2018/19, 2020/21, 2022/23, 2025/26
A34: > 10 % | B34: 3 | C34: 152.06222 | D34: 141 – 161 | E34: 2012/13, 2013/14, 2014/15
A36: Peu de campagnes par classe : lecture descriptive. Valeurs calculées sur les colonnes I et O.

Sheet 8_Graphiques_pays
A1: 8 — Production du Brésil et du Vietnam, STU mondial, STU par pays et STU des stocks certifiés, avec KC1 et DF1 (2010/11 → 2026/27)
A2: STU = stocks de fin ÷ (consommation domestique + exportations), USDA PSD (juillet 2026). Prix = moyenne octobre-septembre ICE (proxy KC1 / DF1), 2025/26 sur 11 mois ; 2026/27 = prévision USDA, sans prix. Toutes les colonnes sont des formules reliées aux onglets de données : on peut tout vérifier.
A3: L'USDA ne sépare pas les stocks du Brésil par espèce : le STU « Brésil » est le même dans le graphique arabica et dans le graphique robusta.
A4: Campagne | B4: Brésil arabica (M sacs) | C4: Brésil conilon / robusta (M sacs) | D4: Brésil total (M sacs) | E4: Brésil : variation sur un an | F4: Vietnam (M sacs) | G4: Vietnam : variation sur un an | H4: STU mondial = stocks ÷ (conso + export) | I4: STU mondial = stocks ÷ conso (déf. USDA/ICO) | J4: STU Brésil | K4: STU Vietnam | L4: STU Colombie | M4: STU Éthiopie | N4: STU Inde | O4: STU Ouganda | P4: STU Indonésie | Q4: STU certifié arabica (New York) | R4: STU certifié robusta (Londres) | S4: KC1 (US c/lb) | T4: DF1 (US c/lb) | U4: DF1 (US$/t) | V4: STU UE = stocks ÷ (conso + export) | W4: UE : stocks ÷ conso | X4: UE : stocks ÷ (conso + import) — variante | Y4: STU États-Unis = stocks ÷ (conso + export) | Z4: États-Unis : stocks ÷ conso | AA4: États-Unis : stocks ÷ (conso + import) — variante
A5: 2010/11 | B5: ='Donnees_USDA'!C108/1000 -> 41.8 | C5: ='Donnees_USDA'!C210/1000 -> 12.7 | D5: ='Donnees_USDA'!C6/1000 -> 54.5 | F5: ='Donnees_USDA'!C7/1000 -> 19.415 | H5: ='1_Monde'!G5 -> 0.11343473 | I5: ='1_Monde'!N5 -> 0.21135284 | J5: ='Donnees_USDA'!C312/('Donnees_USDA'!C414+'Donnees_USDA'!C516) -> 0.053389675 | K5: ='Donnees_USDA'!C313/('Donnees_USDA'!C415+'Donnees_USDA'!C517) -> 0.040046053 | L5: ='Donnees_USDA'!C314/('Donnees_USDA'!C416+'Donnees_USDA'!C518) -> 0.010415571 | M5: ='Donnees_USDA'!C315/('Donnees_USDA'!C417+'Donnees_USDA'!C519) -> 0.016406891 | N5: ='Donnees_USDA'!C318/('Donnees_USDA'!C420+'Donnees_USDA'!C522) -> 0.2582271 | O5: ='Donnees_USDA'!C317/('Donnees_USDA'!C419+'Donnees_USDA'!C521) -> 0.18575758 | P5: ='Donnees_USDA'!C316/('Donnees_USDA'!C418+'Donnees_USDA'!C520) -> 0.0072934974 | S5: ='Prix_ICE'!I5 -> 249.66 | T5: ='Prix_ICE'!J5 -> 100.65583 | U5: ='Prix_ICE'!K5 -> 2219.0813 | V5: ='Donnees_USDA'!C359/('Donnees_USDA'!C461+'Donnees_USDA'!C563) -> 0.3031015 | W5: ='Donnees_USDA'!C359/'Donnees_USDA'!C461 -> 0.31197098 | X5: ='Donnees_USDA'!C359/('Donnees_USDA'!C461+'Donnees_USDA'!C665) -> 0.1500698 | Y5: ='Donnees_USDA'!C354/('Donnees_USDA'!C456+'Donnees_USDA'!C558) -> 0.20058687 | Z5: ='Donnees_USDA'!C354/'Donnees_USDA'!C456 -> 0.20461958 | AA5: ='Donnees_USDA'!C354/('Donnees_USDA'!C456+'Donnees_USDA'!C660) -> 0.10067483
A6: 2011/12 | B6: ='Donnees_USDA'!D108/1000 -> 34.7 | C6: ='Donnees_USDA'!D210/1000 -> 14.5 | D6: ='Donnees_USDA'!D6/1000 -> 49.2 | E6: =D6/D5-1 -> -0.097247706 | F6: ='Donnees_USDA'!D7/1000 -> 26 | G6: =F6/F5-1 -> 0.33917074 | H6: ='1_Monde'!G6 -> 0.098703529 | I6: ='1_Monde'!N6 -> 0.18026899 | J6: ='Donnees_USDA'!D312/('Donnees_USDA'!D414+'Donnees_USDA'!D516) -> 0.044878479 | K6: ='Donnees_USDA'!D313/('Donnees_USDA'!D415+'Donnees_USDA'!D517) -> 0.041666667 | L6: ='Donnees_USDA'!D314/('Donnees_USDA'!D416+'Donnees_USDA'!D518) -> 0.028886311 | M6: ='Donnees_USDA'!D315/('Donnees_USDA'!D417+'Donnees_USDA'!D519) -> 0.037156704 | N6: ='Donnees_USDA'!D318/('Donnees_USDA'!D420+'Donnees_USDA'!D522) -> 0.23048036 | O6: ='Donnees_USDA'!D317/('Donnees_USDA'!D419+'Donnees_USDA'!D521) -> 0.17079365 | P6: ='Donnees_USDA'!D316/('Donnees_USDA'!D418+'Donnees_USDA'!D520) -> 0.0094929881 | Q6: ='2_Arabica'!H6 -> 0.028004909 | R6: ='3_Robusta'!H6 -> 0.033471901 | S6: ='Prix_ICE'!I6 -> 197.84167 | T6: ='Prix_ICE'!J6 -> 91.384167 | U6: ='Prix_ICE'!K6 -> 2014.676 | V6: ='Donnees_USDA'!D359/('Donnees_USDA'!D461+'Donnees_USDA'!D563) -> 0.22389666 | W6: ='Donnees_USDA'!D359/'Donnees_USDA'!D461 -> 0.22983425 | X6: ='Donnees_USDA'!D359/('Donnees_USDA'!D461+'Donnees_USDA'!D665) -> 0.11659193 | Y6: ='Donnees_USDA'!D354/('Donnees_USDA'!D456+'Donnees_USDA'!D558) -> 0.21840606 | Z6: ='Donnees_USDA'!D354/'Donnees_USDA'!D456 -> 0.22226096 | AA6: ='Donnees_USDA'!D354/('Donnees_USDA'!D456+'Donnees_USDA'!D660) -> 0.10904193
A7: 2012/13 | B7: ='Donnees_USDA'!E108/1000 -> 42.1 | C7: ='Donnees_USDA'!E210/1000 -> 15.5 | D7: ='Donnees_USDA'!E6/1000 -> 57.6 | E7: =D7/D6-1 -> 0.17073171 | F7: ='Donnees_USDA'!E7/1000 -> 26.5 | G7: =F7/F6-1 -> 0.019230769 | H7: ='1_Monde'!G7 -> 0.13263251 | I7: ='1_Monde'!N7 -> 0.24661785 | J7: ='Donnees_USDA'!E312/('Donnees_USDA'!E414+'Donnees_USDA'!E516) -> 0.17860942 | K7: ='Donnees_USDA'!E313/('Donnees_USDA'!E415+'Donnees_USDA'!E517) -> 0.073522744 | L7: ='Donnees_USDA'!E314/('Donnees_USDA'!E416+'Donnees_USDA'!E518) -> 0.07667827 | M7: ='Donnees_USDA'!E315/('Donnees_USDA'!E417+'Donnees_USDA'!E519) -> 0.015082956 | N7: ='Donnees_USDA'!E318/('Donnees_USDA'!E420+'Donnees_USDA'!E522) -> 0.33266197 | O7: ='Donnees_USDA'!E317/('Donnees_USDA'!E419+'Donnees_USDA'!E521) -> 0.09615894 | P7: ='Donnees_USDA'!E316/('Donnees_USDA'!E418+'Donnees_USDA'!E520) -> 0.0074581431 | Q7: ='2_Arabica'!H7 -> 0.035139222 | R7: ='3_Robusta'!H7 -> 0.014963241 | S7: ='Prix_ICE'!I7 -> 140.69833 | T7: ='Prix_ICE'!J7 -> 88.480833 | U7: ='Prix_ICE'!K7 -> 1950.6685 | V7: ='Donnees_USDA'!E359/('Donnees_USDA'!E461+'Donnees_USDA'!E563) -> 0.24302521 | W7: ='Donnees_USDA'!E359/'Donnees_USDA'!E461 -> 0.25060659 | X7: ='Donnees_USDA'!E359/('Donnees_USDA'!E461+'Donnees_USDA'!E665) -> 0.12275737 | Y7: ='Donnees_USDA'!E354/('Donnees_USDA'!E456+'Donnees_USDA'!E558) -> 0.23298564 | Z7: ='Donnees_USDA'!E354/'Donnees_USDA'!E456 -> 0.23667868 | AA7: ='Donnees_USDA'!E354/('Donnees_USDA'!E456+'Donnees_USDA'!E660) -> 0.11663492
A8: 2013/14 | B8: ='Donnees_USDA'!F108/1000 -> 41.8 | C8: ='Donnees_USDA'!F210/1000 -> 15.4 | D8: ='Donnees_USDA'!F6/1000 -> 57.2 | E8: =D8/D7-1 -> -0.0069444444 | F8: ='Donnees_USDA'!F7/1000 -> 29.833 | G8: =F8/F7-1 -> 0.12577358 | H8: ='1_Monde'!G8 -> 0.15078148 | I8: ='1_Monde'!N8 -> 0.2862445 | J8: ='Donnees_USDA'!F312/('Donnees_USDA'!F414+'Donnees_USDA'!F516) -> 0.21977335 | K8: ='Donnees_USDA'!F313/('Donnees_USDA'!F415+'Donnees_USDA'!F517) -> 0.07030399 | L8: ='Donnees_USDA'!F314/('Donnees_USDA'!F416+'Donnees_USDA'!F518) -> 0.077876823 | M8: ='Donnees_USDA'!F315/('Donnees_USDA'!F417+'Donnees_USDA'!F519) -> 0.006245121 | N8: ='Donnees_USDA'!F318/('Donnees_USDA'!F420+'Donnees_USDA'!F522) -> 0.32767265 | O8: ='Donnees_USDA'!F317/('Donnees_USDA'!F419+'Donnees_USDA'!F521) -> 0.10287958 | P8: ='Donnees_USDA'!F316/('Donnees_USDA'!F418+'Donnees_USDA'!F520) -> 0.0037151703 | Q8: ='2_Arabica'!H8 -> 0.029420409 | R8: ='3_Robusta'!H8 -> 0.026179187 | S8: ='Prix_ICE'!I8 -> 161.4675 | T8: ='Prix_ICE'!J8 -> 85.874167 | U8: ='Prix_ICE'!K8 -> 1893.2013 | V8: ='Donnees_USDA'!F359/('Donnees_USDA'!F461+'Donnees_USDA'!F563) -> 0.2877364 | W8: ='Donnees_USDA'!F359/'Donnees_USDA'!F461 -> 0.29897529 | X8: ='Donnees_USDA'!F359/('Donnees_USDA'!F461+'Donnees_USDA'!F665) -> 0.14397678 | Y8: ='Donnees_USDA'!F354/('Donnees_USDA'!F456+'Donnees_USDA'!F558) -> 0.24701734 | Z8: ='Donnees_USDA'!F354/'Donnees_USDA'!F456 -> 0.25303431 | AA8: ='Donnees_USDA'!F354/('Donnees_USDA'!F456+'Donnees_USDA'!F660) -> 0.12365062
A9: 2014/15 | B9: ='Donnees_USDA'!G108/1000 -> 37.3 | C9: ='Donnees_USDA'!G210/1000 -> 17 | D9: ='Donnees_USDA'!G6/1000 -> 54.3 | E9: =D9/D8-1 -> -0.050699301 | F9: ='Donnees_USDA'!G7/1000 -> 27.4 | G9: =F9/F8-1 -> -0.081553984 | H9: ='1_Monde'!G9 -> 0.15904716 | I9: ='1_Monde'!N9 -> 0.29308998 | J9: ='Donnees_USDA'!G312/('Donnees_USDA'!G414+'Donnees_USDA'!G516) -> 0.16326566 | K9: ='Donnees_USDA'!G313/('Donnees_USDA'!G415+'Donnees_USDA'!G517) -> 0.26639758 | L9: ='Donnees_USDA'!G314/('Donnees_USDA'!G416+'Donnees_USDA'!G518) -> 0.048552822 | M9: ='Donnees_USDA'!G315/('Donnees_USDA'!G417+'Donnees_USDA'!G519) -> 0.0046260601 | N9: ='Donnees_USDA'!G318/('Donnees_USDA'!G420+'Donnees_USDA'!G522) -> 0.42497946 | O9: ='Donnees_USDA'!G317/('Donnees_USDA'!G419+'Donnees_USDA'!G521) -> 0.087430168 | P9: ='Donnees_USDA'!G316/('Donnees_USDA'!G418+'Donnees_USDA'!G520) -> 0.0045611015 | Q9: ='2_Arabica'!H9 -> 0.025576862 | R9: ='3_Robusta'!H9 -> 0.04972677 | S9: ='Prix_ICE'!I9 -> 154.02083 | T9: ='Prix_ICE'!J9 -> 83.910833 | U9: ='Prix_ICE'!K9 -> 1849.9172 | V9: ='Donnees_USDA'!G359/('Donnees_USDA'!G461+'Donnees_USDA'!G563) -> 0.26977822 | W9: ='Donnees_USDA'!G359/'Donnees_USDA'!G461 -> 0.27866424 | X9: ='Donnees_USDA'!G359/('Donnees_USDA'!G461+'Donnees_USDA'!G665) -> 0.13734412 | Y9: ='Donnees_USDA'!G354/('Donnees_USDA'!G456+'Donnees_USDA'!G558) -> 0.25542843 | Z9: ='Donnees_USDA'!G354/'Donnees_USDA'!G456 -> 0.25954684 | AA9: ='Donnees_USDA'!G354/('Donnees_USDA'!G456+'Donnees_USDA'!G660) -> 0.12860837
A10: 2015/16 | B10: ='Donnees_USDA'!H108/1000 -> 36.1 | C10: ='Donnees_USDA'!H210/1000 -> 13.3 | D10: ='Donnees_USDA'!H6/1000 -> 49.4 | E10: =D10/D9-1 -> -0.090239411 | F10: ='Donnees_USDA'!H7/1000 -> 28.93 | G10: =F10/F9-1 -> 0.055839416 | H10: ='1_Monde'!G10 -> 0.12176734 | I10: ='1_Monde'!N10 -> 0.22816054 | J10: ='Donnees_USDA'!H312/('Donnees_USDA'!H414+'Donnees_USDA'!H516) -> 0.042058229 | K10: ='Donnees_USDA'!H313/('Donnees_USDA'!H415+'Donnees_USDA'!H517) -> 0.13254457 | L10: ='Donnees_USDA'!H314/('Donnees_USDA'!H416+'Donnees_USDA'!H518) -> 0.081926838 | M10: ='Donnees_USDA'!H315/('Donnees_USDA'!H417+'Donnees_USDA'!H519) -> 0.0038372985 | N10: ='Donnees_USDA'!H318/('Donnees_USDA'!H420+'Donnees_USDA'!H522) -> 0.38095924 | O10: ='Donnees_USDA'!H317/('Donnees_USDA'!H419+'Donnees_USDA'!H521) -> 0.088169014 | P10: ='Donnees_USDA'!H316/('Donnees_USDA'!H418+'Donnees_USDA'!H520) -> 0.0035192411 | Q10: ='2_Arabica'!H10 -> 0.015408008 | R10: ='3_Robusta'!H10 -> 0.030901966 | S10: ='Prix_ICE'!I10 -> 131.8325 | T10: ='Prix_ICE'!J10 -> 74.068333 | U10: ='Prix_ICE'!K10 -> 1632.9272 | V10: ='Donnees_USDA'!H359/('Donnees_USDA'!H461+'Donnees_USDA'!H563) -> 0.26148028 | W10: ='Donnees_USDA'!H359/'Donnees_USDA'!H461 -> 0.27440753 | X10: ='Donnees_USDA'!H359/('Donnees_USDA'!H461+'Donnees_USDA'!H665) -> 0.13407945 | Y10: ='Donnees_USDA'!H354/('Donnees_USDA'!H456+'Donnees_USDA'!H558) -> 0.24654974 | Z10: ='Donnees_USDA'!H354/'Donnees_USDA'!H456 -> 0.2471395 | AA10: ='Donnees_USDA'!H354/('Donnees_USDA'!H456+'Donnees_USDA'!H660) -> 0.12331901
A11: 2016/17 | B11: ='Donnees_USDA'!I108/1000 -> 45.6 | C11: ='Donnees_USDA'!I210/1000 -> 10.5 | D11: ='Donnees_USDA'!I6/1000 -> 56.1 | E11: =D11/D10-1 -> 0.13562753 | F11: ='Donnees_USDA'!I7/1000 -> 26.7 | G11: =F11/F10-1 -> -0.077082613 | H11: ='1_Monde'!G11 -> 0.12626165 | I11: ='1_Monde'!N11 -> 0.23502295 | J11: ='Donnees_USDA'!I312/('Donnees_USDA'!I414+'Donnees_USDA'!I516) -> 0.069974043 | K11: ='Donnees_USDA'!I313/('Donnees_USDA'!I415+'Donnees_USDA'!I517) -> 0.091752225 | L11: ='Donnees_USDA'!I314/('Donnees_USDA'!I416+'Donnees_USDA'!I518) -> 0.058270306 | M11: ='Donnees_USDA'!I315/('Donnees_USDA'!I417+'Donnees_USDA'!I519) -> 0.0021573422 | N11: ='Donnees_USDA'!I318/('Donnees_USDA'!I420+'Donnees_USDA'!I522) -> 0.25455287 | O11: ='Donnees_USDA'!I317/('Donnees_USDA'!I419+'Donnees_USDA'!I521) -> 0.069690722 | P11: ='Donnees_USDA'!I316/('Donnees_USDA'!I418+'Donnees_USDA'!I520) -> 0.0010547596 | Q11: ='2_Arabica'!H11 -> 0.020048461 | R11: ='3_Robusta'!H11 -> 0.037959615 | S11: ='Prix_ICE'!I11 -> 143.77167 | T11: ='Prix_ICE'!J11 -> 95.123333 | U11: ='Prix_ICE'!K11 -> 2097.1105 | V11: ='Donnees_USDA'!I359/('Donnees_USDA'!I461+'Donnees_USDA'!I563) -> 0.33393393 | W11: ='Donnees_USDA'!I359/'Donnees_USDA'!I461 -> 0.35599949 | X11: ='Donnees_USDA'!I359/('Donnees_USDA'!I461+'Donnees_USDA'!I665) -> 0.16854614 | Y11: ='Donnees_USDA'!I354/('Donnees_USDA'!I456+'Donnees_USDA'!I558) -> 0.28182816 | Z11: ='Donnees_USDA'!I354/'Donnees_USDA'!I456 -> 0.28182816 | AA11: ='Donnees_USDA'!I354/('Donnees_USDA'!I456+'Donnees_USDA'!I660) -> 0.13831711
A12: 2017/18 | B12: ='Donnees_USDA'!J108/1000 -> 39.5 | C12: ='Donnees_USDA'!J210/1000 -> 12.6 | D12: ='Donnees_USDA'!J6/1000 -> 52.1 | E12: =D12/D11-1 -> -0.071301248 | F12: ='Donnees_USDA'!J7/1000 -> 29.3 | G12: =F12/F11-1 -> 0.097378277 | H12: ='1_Monde'!G12 -> 0.10838159 | I12: ='1_Monde'!N12 -> 0.19891425 | J12: ='Donnees_USDA'!J312/('Donnees_USDA'!J414+'Donnees_USDA'!J516) -> 0.058913644 | K12: ='Donnees_USDA'!J313/('Donnees_USDA'!J415+'Donnees_USDA'!J517) -> 0.0077469729 | L12: ='Donnees_USDA'!J314/('Donnees_USDA'!J416+'Donnees_USDA'!J518) -> 0.077286957 | M12: ='Donnees_USDA'!J315/('Donnees_USDA'!J417+'Donnees_USDA'!J519) -> 0.0038335936 | N12: ='Donnees_USDA'!J318/('Donnees_USDA'!J420+'Donnees_USDA'!J522) -> 0.16949613 | O12: ='Donnees_USDA'!J317/('Donnees_USDA'!J419+'Donnees_USDA'!J521) -> 0.085274725 | P12: ='Donnees_USDA'!J316/('Donnees_USDA'!J418+'Donnees_USDA'!J520) -> 0.051253241 | Q12: ='2_Arabica'!H12 -> 0.027916904 | R12: ='3_Robusta'!H12 -> 0.020741073 | S12: ='Prix_ICE'!I12 -> 120.60083 | T12: ='Prix_ICE'!J12 -> 78.285 | U12: ='Prix_ICE'!K12 -> 1725.8888 | V12: ='Donnees_USDA'!J359/('Donnees_USDA'!J461+'Donnees_USDA'!J563) -> 0.3006012 | W12: ='Donnees_USDA'!J359/'Donnees_USDA'!J461 -> 0.32093189 | X12: ='Donnees_USDA'!J359/('Donnees_USDA'!J461+'Donnees_USDA'!J665) -> 0.15593416 | Y12: ='Donnees_USDA'!J354/('Donnees_USDA'!J456+'Donnees_USDA'!J558) -> 0.25198576 | Z12: ='Donnees_USDA'!J354/'Donnees_USDA'!J456 -> 0.25198576 | AA12: ='Donnees_USDA'!J354/('Donnees_USDA'!J456+'Donnees_USDA'!J660) -> 0.12795041
A13: 2018/19 | B13: ='Donnees_USDA'!K108/1000 -> 49.7 | C13: ='Donnees_USDA'!K210/1000 -> 16.8 | D13: ='Donnees_USDA'!K6/1000 -> 66.5 | E13: =D13/D12-1 -> 0.27639155 | F13: ='Donnees_USDA'!K7/1000 -> 30.4 | G13: =F13/F12-1 -> 0.037542662 | H13: ='1_Monde'!G13 -> 0.1194245 | I13: ='1_Monde'!N13 -> 0.22256224 | J13: ='Donnees_USDA'!K312/('Donnees_USDA'!K414+'Donnees_USDA'!K516) -> 0.078234766 | K13: ='Donnees_USDA'!K313/('Donnees_USDA'!K415+'Donnees_USDA'!K517) -> 0.017787446 | L13: ='Donnees_USDA'!K314/('Donnees_USDA'!K416+'Donnees_USDA'!K518) -> 0.035521236 | M13: ='Donnees_USDA'!K315/('Donnees_USDA'!K417+'Donnees_USDA'!K519) -> 0.0013574046 | N13: ='Donnees_USDA'!K318/('Donnees_USDA'!K420+'Donnees_USDA'!K522) -> 0.13247012 | O13: ='Donnees_USDA'!K317/('Donnees_USDA'!K419+'Donnees_USDA'!K521) -> 0.071914894 | P13: ='Donnees_USDA'!K316/('Donnees_USDA'!K418+'Donnees_USDA'!K520) -> 0.23148325 | Q13: ='2_Arabica'!H13 -> 0.024495207 | R13: ='3_Robusta'!H13 -> 0.034816449 | S13: ='Prix_ICE'!I13 -> 104.98083 | T13: ='Prix_ICE'!J13 -> 67.5325 | U13: ='Prix_ICE'!K13 -> 1488.8368 | V13: ='Donnees_USDA'!K359/('Donnees_USDA'!K461+'Donnees_USDA'!K563) -> 0.31807892 | W13: ='Donnees_USDA'!K359/'Donnees_USDA'!K461 -> 0.34049226 | X13: ='Donnees_USDA'!K359/('Donnees_USDA'!K461+'Donnees_USDA'!K665) -> 0.16289696 | Y13: ='Donnees_USDA'!K354/('Donnees_USDA'!K456+'Donnees_USDA'!K558) -> 0.27067226 | Z13: ='Donnees_USDA'!K354/'Donnees_USDA'!K456 -> 0.27067226 | AA13: ='Donnees_USDA'!K354/('Donnees_USDA'!K456+'Donnees_USDA'!K660) -> 0.13323185
A14: 2019/20 | B14: ='Donnees_USDA'!L108/1000 -> 42 | C14: ='Donnees_USDA'!L210/1000 -> 18.5 | D14: ='Donnees_USDA'!L6/1000 -> 60.5 | E14: =D14/D13-1 -> -0.090225564 | F14: ='Donnees_USDA'!L7/1000 -> 31.3 | G14: =F14/F13-1 -> 0.029605263 | H14: ='1_Monde'!G14 -> 0.11882292 | I14: ='1_Monde'!N14 -> 0.22055372 | J14: ='Donnees_USDA'!L312/('Donnees_USDA'!L414+'Donnees_USDA'!L516) -> 0.037517787 | K14: ='Donnees_USDA'!L313/('Donnees_USDA'!L415+'Donnees_USDA'!L517) -> 0.070005916 | L14: ='Donnees_USDA'!L314/('Donnees_USDA'!L416+'Donnees_USDA'!L518) -> 0.057645467 | M14: ='Donnees_USDA'!L315/('Donnees_USDA'!L417+'Donnees_USDA'!L519) -> 0.028865979 | N14: ='Donnees_USDA'!L318/('Donnees_USDA'!L420+'Donnees_USDA'!L522) -> 0.15310779 | O14: ='Donnees_USDA'!L317/('Donnees_USDA'!L419+'Donnees_USDA'!L521) -> 0.066605505 | P14: ='Donnees_USDA'!L316/('Donnees_USDA'!L418+'Donnees_USDA'!L520) -> 0.19067375 | Q14: ='2_Arabica'!H14 -> 0.012865541 | R14: ='3_Robusta'!H14 -> 0.023382805 | S14: ='Prix_ICE'!I14 -> 113.23667 | T14: ='Prix_ICE'!J14 -> 59.220833 | U14: ='Prix_ICE'!K14 -> 1305.5959 | V14: ='Donnees_USDA'!L359/('Donnees_USDA'!L461+'Donnees_USDA'!L563) -> 0.34369429 | W14: ='Donnees_USDA'!L359/'Donnees_USDA'!L461 -> 0.373485 | X14: ='Donnees_USDA'!L359/('Donnees_USDA'!L461+'Donnees_USDA'!L665) -> 0.17749398 | Y14: ='Donnees_USDA'!L354/('Donnees_USDA'!L456+'Donnees_USDA'!L558) -> 0.24576759 | Z14: ='Donnees_USDA'!L354/'Donnees_USDA'!L456 -> 0.24576759 | AA14: ='Donnees_USDA'!L354/('Donnees_USDA'!L456+'Donnees_USDA'!L660) -> 0.1252617
A15: 2020/21 | B15: ='Donnees_USDA'!M108/1000 -> 49.7 | C15: ='Donnees_USDA'!M210/1000 -> 20.2 | D15: ='Donnees_USDA'!M6/1000 -> 69.9 | E15: =D15/D14-1 -> 0.1553719 | F15: ='Donnees_USDA'!M7/1000 -> 29 | G15: =F15/F14-1 -> -0.073482428 | H15: ='1_Monde'!G15 -> 0.12211677 | I15: ='1_Monde'!N15 -> 0.23131165 | J15: ='Donnees_USDA'!M312/('Donnees_USDA'!M414+'Donnees_USDA'!M516) -> 0.064601575 | K15: ='Donnees_USDA'!M313/('Donnees_USDA'!M415+'Donnees_USDA'!M517) -> 0.13062099 | L15: ='Donnees_USDA'!M314/('Donnees_USDA'!M416+'Donnees_USDA'!M518) -> 0.083249073 | M15: ='Donnees_USDA'!M315/('Donnees_USDA'!M417+'Donnees_USDA'!M519) -> 0.017589577 | N15: ='Donnees_USDA'!M318/('Donnees_USDA'!M420+'Donnees_USDA'!M522) -> 0.13062805 | O15: ='Donnees_USDA'!M317/('Donnees_USDA'!M419+'Donnees_USDA'!M521) -> 0.057302691 | P15: ='Donnees_USDA'!M316/('Donnees_USDA'!M418+'Donnees_USDA'!M520) -> 0.13544879 | Q15: ='2_Arabica'!H15 -> 0.022004254 | R15: ='3_Robusta'!H15 -> 0.026889937 | S15: ='Prix_ICE'!I15 -> 143.75333 | T15: ='Prix_ICE'!J15 -> 69.895833 | U15: ='Prix_ICE'!K15 -> 1540.9394 | V15: ='Donnees_USDA'!M359/('Donnees_USDA'!M461+'Donnees_USDA'!M563) -> 0.30494396 | W15: ='Donnees_USDA'!M359/'Donnees_USDA'!M461 -> 0.33357563 | X15: ='Donnees_USDA'!M359/('Donnees_USDA'!M461+'Donnees_USDA'!M665) -> 0.16168698 | Y15: ='Donnees_USDA'!M354/('Donnees_USDA'!M456+'Donnees_USDA'!M558) -> 0.2323509 | Z15: ='Donnees_USDA'!M354/'Donnees_USDA'!M456 -> 0.2323509 | AA15: ='Donnees_USDA'!M354/('Donnees_USDA'!M456+'Donnees_USDA'!M660) -> 0.11710608
A16: 2021/22 | B16: ='Donnees_USDA'!N108/1000 -> 36.4 | C16: ='Donnees_USDA'!N210/1000 -> 21.7 | D16: ='Donnees_USDA'!N6/1000 -> 58.1 | E16: =D16/D15-1 -> -0.16881259 | F16: ='Donnees_USDA'!N7/1000 -> 31.58 | G16: =F16/F15-1 -> 0.088965517 | H16: ='1_Monde'!G16 -> 0.10254961 | I16: ='1_Monde'!N16 -> 0.19025948 | J16: ='Donnees_USDA'!N312/('Donnees_USDA'!N414+'Donnees_USDA'!N516) -> 0.0087061669 | K16: ='Donnees_USDA'!N313/('Donnees_USDA'!N415+'Donnees_USDA'!N517) -> 0.11114561 | L16: ='Donnees_USDA'!N314/('Donnees_USDA'!N416+'Donnees_USDA'!N518) -> 0.052377671 | M16: ='Donnees_USDA'!N315/('Donnees_USDA'!N417+'Donnees_USDA'!N519) -> 0.010982306 | N16: ='Donnees_USDA'!N318/('Donnees_USDA'!N420+'Donnees_USDA'!N522) -> 0.020656584 | O16: ='Donnees_USDA'!N317/('Donnees_USDA'!N419+'Donnees_USDA'!N521) -> 0.075983264 | P16: ='Donnees_USDA'!N316/('Donnees_USDA'!N418+'Donnees_USDA'!N520) -> 0.086713746 | Q16: ='2_Arabica'!H16 -> 0.0047918276 | R16: ='3_Robusta'!H16 -> 0.018462372 | S16: ='Prix_ICE'!I16 -> 224.0875 | T16: ='Prix_ICE'!J16 -> 97.529167 | U16: ='Prix_ICE'!K16 -> 2150.1501 | V16: ='Donnees_USDA'!N359/('Donnees_USDA'!N461+'Donnees_USDA'!N563) -> 0.30184123 | W16: ='Donnees_USDA'!N359/'Donnees_USDA'!N461 -> 0.33420864 | X16: ='Donnees_USDA'!N359/('Donnees_USDA'!N461+'Donnees_USDA'!N665) -> 0.15818315 | Y16: ='Donnees_USDA'!N354/('Donnees_USDA'!N456+'Donnees_USDA'!N558) -> 0.23880485 | Z16: ='Donnees_USDA'!N354/'Donnees_USDA'!N456 -> 0.23880485 | AA16: ='Donnees_USDA'!N354/('Donnees_USDA'!N456+'Donnees_USDA'!N660) -> 0.11869801
A17: 2022/23 | B17: ='Donnees_USDA'!O108/1000 -> 39.8 | C17: ='Donnees_USDA'!O210/1000 -> 22.8 | D17: ='Donnees_USDA'!O6/1000 -> 62.6 | E17: =D17/D16-1 -> 0.077452668 | F17: ='Donnees_USDA'!O7/1000 -> 28.3 | G17: =F17/F16-1 -> -0.1038632 | H17: ='1_Monde'!G17 -> 0.088758391 | I17: ='1_Monde'!N17 -> 0.15960511 | J17: ='Donnees_USDA'!O312/('Donnees_USDA'!O414+'Donnees_USDA'!O516) -> 0.078846318 | K17: ='Donnees_USDA'!O313/('Donnees_USDA'!O415+'Donnees_USDA'!O517) -> 0.026601141 | L17: ='Donnees_USDA'!O314/('Donnees_USDA'!O416+'Donnees_USDA'!O518) -> 0.069357367 | M17: ='Donnees_USDA'!O315/('Donnees_USDA'!O417+'Donnees_USDA'!O519) -> 0.0068119891 | N17: ='Donnees_USDA'!O318/('Donnees_USDA'!O420+'Donnees_USDA'!O522) -> 0.06489071 | O17: ='Donnees_USDA'!O317/('Donnees_USDA'!O419+'Donnees_USDA'!O521) -> 0.071603053 | P17: ='Donnees_USDA'!O316/('Donnees_USDA'!O418+'Donnees_USDA'!O520) -> 0.039673094 | Q17: ='2_Arabica'!H17 -> 0.0055175591 | R17: ='3_Robusta'!H17 -> 0.0087581838 | S17: ='Prix_ICE'!I17 -> 171.19 | T17: ='Prix_ICE'!J17 -> 100.565 | U17: ='Prix_ICE'!K17 -> 2217.0787 | V17: ='Donnees_USDA'!O359/('Donnees_USDA'!O461+'Donnees_USDA'!O563) -> 0.18928092 | W17: ='Donnees_USDA'!O359/'Donnees_USDA'!O461 -> 0.20929501 | X17: ='Donnees_USDA'!O359/('Donnees_USDA'!O461+'Donnees_USDA'!O665) -> 0.10462634 | Y17: ='Donnees_USDA'!O354/('Donnees_USDA'!O456+'Donnees_USDA'!O558) -> 0.23149088 | Z17: ='Donnees_USDA'!O354/'Donnees_USDA'!O456 -> 0.23149088 | AA17: ='Donnees_USDA'!O354/('Donnees_USDA'!O456+'Donnees_USDA'!O660) -> 0.11745796
A18: 2023/24 | B18: ='Donnees_USDA'!P108/1000 -> 44.9 | C18: ='Donnees_USDA'!P210/1000 -> 21.4 | D18: ='Donnees_USDA'!P6/1000 -> 66.3 | E18: =D18/D17-1 -> 0.059105431 | F18: ='Donnees_USDA'!P7/1000 -> 27.55 | G18: =F18/F17-1 -> -0.026501767 | H18: ='1_Monde'!G18 -> 0.0752103 | I18: ='1_Monde'!N18 -> 0.14102986 | J18: ='Donnees_USDA'!P312/('Donnees_USDA'!P414+'Donnees_USDA'!P516) -> 0.030256857 | K18: ='Donnees_USDA'!P313/('Donnees_USDA'!P415+'Donnees_USDA'!P517) -> 0.031413428 | L18: ='Donnees_USDA'!P314/('Donnees_USDA'!P416+'Donnees_USDA'!P518) -> 0.047731333 | M18: ='Donnees_USDA'!P315/('Donnees_USDA'!P417+'Donnees_USDA'!P519) -> 0.0054764513 | N18: ='Donnees_USDA'!P318/('Donnees_USDA'!P420+'Donnees_USDA'!P522) -> 0.029671408 | O18: ='Donnees_USDA'!P317/('Donnees_USDA'!P419+'Donnees_USDA'!P521) -> 0.036830189 | P18: ='Donnees_USDA'!P316/('Donnees_USDA'!P418+'Donnees_USDA'!P520) -> 0.047384008 | Q18: ='2_Arabica'!H18 -> 0.0085798177 | R18: ='3_Robusta'!H18 -> 0.0093032326 | S18: ='Prix_ICE'!I18 -> 204.00167 | T18: ='Prix_ICE'!J18 -> 158.95 | U18: ='Prix_ICE'!K18 -> 3504.2477 | V18: ='Donnees_USDA'!P359/('Donnees_USDA'!P461+'Donnees_USDA'!P563) -> 0.19307474 | W18: ='Donnees_USDA'!P359/'Donnees_USDA'!P461 -> 0.2177568 | X18: ='Donnees_USDA'!P359/('Donnees_USDA'!P461+'Donnees_USDA'!P665) -> 0.10317812 | Y18: ='Donnees_USDA'!P354/('Donnees_USDA'!P456+'Donnees_USDA'!P558) -> 0.24208962 | Z18: ='Donnees_USDA'!P354/'Donnees_USDA'!P456 -> 0.24208962 | AA18: ='Donnees_USDA'!P354/('Donnees_USDA'!P456+'Donnees_USDA'!P660) -> 0.12117347
A19: 2024/25 | B19: ='Donnees_USDA'!Q108/1000 -> 44.5 | C19: ='Donnees_USDA'!Q210/1000 -> 21 | D19: ='Donnees_USDA'!Q6/1000 -> 65.5 | E19: =D19/D18-1 -> -0.012066365 | F19: ='Donnees_USDA'!Q7/1000 -> 29 | G19: =F19/F18-1 -> 0.052631579 | H19: ='1_Monde'!G19 -> 0.06888738 | I19: ='1_Monde'!N19 -> 0.12814318 | J19: ='Donnees_USDA'!Q312/('Donnees_USDA'!Q414+'Donnees_USDA'!Q516) -> 0.014313549 | K19: ='Donnees_USDA'!Q313/('Donnees_USDA'!Q415+'Donnees_USDA'!Q517) -> 0.0363 | L19: ='Donnees_USDA'!Q314/('Donnees_USDA'!Q416+'Donnees_USDA'!Q518) -> 0.059384259 | M19: ='Donnees_USDA'!Q315/('Donnees_USDA'!Q417+'Donnees_USDA'!Q519) -> 0.0069991251 | N19: ='Donnees_USDA'!Q318/('Donnees_USDA'!Q420+'Donnees_USDA'!Q522) -> 0.044155844 | O19: ='Donnees_USDA'!Q317/('Donnees_USDA'!Q419+'Donnees_USDA'!Q521) -> 0.040299625 | P19: ='Donnees_USDA'!Q316/('Donnees_USDA'!Q418+'Donnees_USDA'!Q520) -> 0.05115973 | Q19: ='2_Arabica'!H19 -> 0.0058762083 | R19: ='3_Robusta'!H19 -> 0.013447256 | S19: ='Prix_ICE'!I19 -> 333.06 | T19: ='Prix_ICE'!J19 -> 213.2675 | U19: ='Prix_ICE'!K19 -> 4701.7435 | V19: ='Donnees_USDA'!Q359/('Donnees_USDA'!Q461+'Donnees_USDA'!Q563) -> 0.17499893 | W19: ='Donnees_USDA'!Q359/'Donnees_USDA'!Q461 -> 0.19812785 | X19: ='Donnees_USDA'!Q359/('Donnees_USDA'!Q461+'Donnees_USDA'!Q665) -> 0.093407724 | Y19: ='Donnees_USDA'!Q354/('Donnees_USDA'!Q456+'Donnees_USDA'!Q558) -> 0.21801492 | Z19: ='Donnees_USDA'!Q354/'Donnees_USDA'!Q456 -> 0.21801492 | AA19: ='Donnees_USDA'!Q354/('Donnees_USDA'!Q456+'Donnees_USDA'!Q660) -> 0.10911179
A20: 2025/26 | B20: ='Donnees_USDA'!R108/1000 -> 38 | C20: ='Donnees_USDA'!R210/1000 -> 25 | D20: ='Donnees_USDA'!R6/1000 -> 63 | E20: =D20/D19-1 -> -0.038167939 | F20: ='Donnees_USDA'!R7/1000 -> 31.7 | G20: =F20/F19-1 -> 0.093103448 | H20: ='1_Monde'!G20 -> 0.076299072 | I20: ='1_Monde'!N20 -> 0.1404943 | J20: ='Donnees_USDA'!R312/('Donnees_USDA'!R414+'Donnees_USDA'!R516) -> 0.06475478 | K20: ='Donnees_USDA'!R313/('Donnees_USDA'!R415+'Donnees_USDA'!R517) -> 0.020628743 | L20: ='Donnees_USDA'!R314/('Donnees_USDA'!R416+'Donnees_USDA'!R518) -> 0.05769487 | M20: ='Donnees_USDA'!R315/('Donnees_USDA'!R417+'Donnees_USDA'!R519) -> 0.015263846 | N20: ='Donnees_USDA'!R318/('Donnees_USDA'!R420+'Donnees_USDA'!R522) -> 0.063807394 | O20: ='Donnees_USDA'!R317/('Donnees_USDA'!R419+'Donnees_USDA'!R521) -> 0.047510669 | P20: ='Donnees_USDA'!R316/('Donnees_USDA'!R418+'Donnees_USDA'!R520) -> 0.055010255 | Q20: ='2_Arabica'!H20 -> 0.0024842269 | R20: ='3_Robusta'!H20 -> 0.0093150134 | S20: ='Prix_ICE'!I20 -> 312.21 | T20: ='Prix_ICE'!J20 -> 171.84182 | U20: ='Prix_ICE'!K20 -> 3788.4636 | V20: ='Donnees_USDA'!R359/('Donnees_USDA'!R461+'Donnees_USDA'!R563) -> 0.15899936 | W20: ='Donnees_USDA'!R359/'Donnees_USDA'!R461 -> 0.18041857 | X20: ='Donnees_USDA'!R359/('Donnees_USDA'!R461+'Donnees_USDA'!R665) -> 0.085159532 | Y20: ='Donnees_USDA'!R354/('Donnees_USDA'!R456+'Donnees_USDA'!R558) -> 0.22309198 | Z20: ='Donnees_USDA'!R354/'Donnees_USDA'!R456 -> 0.22309198 | AA20: ='Donnees_USDA'!R354/('Donnees_USDA'!R456+'Donnees_USDA'!R660) -> 0.11165524
A21: 2026/27 (prév.) | B21: ='Donnees_USDA'!S108/1000 -> 47.5 | C21: ='Donnees_USDA'!S210/1000 -> 24.4 | D21: ='Donnees_USDA'!S6/1000 -> 71.9 | E21: =D21/D20-1 -> 0.14126984 | F21: ='Donnees_USDA'!S7/1000 -> 32.5 | G21: =F21/F20-1 -> 0.025236593 | H21: ='1_Monde'!G21 -> 0.077620271 | I21: ='1_Monde'!N21 -> 0.14623114 | J21: ='Donnees_USDA'!S312/('Donnees_USDA'!S414+'Donnees_USDA'!S516) -> 0.061922754 | K21: ='Donnees_USDA'!S313/('Donnees_USDA'!S415+'Donnees_USDA'!S517) -> 0.014403535 | L21: ='Donnees_USDA'!S314/('Donnees_USDA'!S416+'Donnees_USDA'!S518) -> 0.042948718 | M21: ='Donnees_USDA'!S315/('Donnees_USDA'!S417+'Donnees_USDA'!S519) -> 0.011953833 | N21: ='Donnees_USDA'!S318/('Donnees_USDA'!S420+'Donnees_USDA'!S522) -> 0.027695858 | O21: ='Donnees_USDA'!S317/('Donnees_USDA'!S419+'Donnees_USDA'!S521) -> 0.045917655 | P21: ='Donnees_USDA'!S316/('Donnees_USDA'!S418+'Donnees_USDA'!S520) -> 0.052096273 | V21: ='Donnees_USDA'!S359/('Donnees_USDA'!S461+'Donnees_USDA'!S563) -> 0.19294606 | W21: ='Donnees_USDA'!S359/'Donnees_USDA'!S461 -> 0.21882353 | X21: ='Donnees_USDA'!S359/('Donnees_USDA'!S461+'Donnees_USDA'!S665) -> 0.10054054 | Y21: ='Donnees_USDA'!S354/('Donnees_USDA'!S456+'Donnees_USDA'!S558) -> 0.21150278 | Z21: ='Donnees_USDA'!S354/'Donnees_USDA'!S456 -> 0.21150278 | AA21: ='Donnees_USDA'!S354/('Donnees_USDA'!S456+'Donnees_USDA'!S660) -> 0.10584958
A23: 1. Production du Brésil (avec le KC1) et du Vietnam (avec le DF1)
A48: 2. Stock-to-use mondial, avec KC1 et DF1
A73: 3. Stock-to-use du Brésil (avec le KC1) et du Vietnam (avec le DF1)
A98: 4. Arabica : Brésil, Colombie, Éthiopie (avec le KC1) — Robusta : Vietnam, Brésil, Inde, Ouganda, Indonésie (avec le DF1)
A123: 5. Stock-to-use des stocks certifiés ICE : arabica (New York, avec le KC1) et robusta (Londres, avec le DF1)
A148: 6. Pays consommateurs : stock-to-use de l'Union européenne et des États-Unis, avec KC1 et DF1
A173: UE et États-Unis : les exportations sont des réexportations (torréfié, soluble) ; les États-Unis n'exportent plus rien depuis 2016/17 dans les données USDA, donc leur STU = stocks ÷ conso. Variante stocks ÷ (conso + import) : même courbe (corrélation 0,99), niveau divisé par deux, car les importations ≈ conso + réexportations. Les stocks américains sont figés à 5,7 M sacs depuis 2022/23 dans les données USDA.

Sheet Donnees_USDA
A1: Données USDA PSD Online, café — fichier de juillet 2026 (2026/27 = prévision USDA de juin 2026), milliers de sacs de 60 kg
A2: Une ligne par pays, une colonne par campagne (année commerciale locale). Ordre : 42 pays d'origine (producteurs exportateurs nets, par production 2026/27), 5 producteurs importateurs nets (États-Unis, Philippines, Chine, Panama, Venezuela), 46 pays importateurs.
A3: Source : apps.fas.usda.gov/psdonline, téléchargement « Coffee » (CSV), attributs Production, Arabica Production, Robusta Production, Ending Stocks, Domestic Consumption, Exports, Imports. L'USDA ne découpe par espèce que la production.
A5: Production | B5: Groupe | C5: 2010/11 | D5: 2011/12 | E5: 2012/13 | F5: 2013/14 | G5: 2014/15 | H5: 2015/16 | I5: 2016/17 | J5: 2017/18 | K5: 2018/19 | L5: 2019/20 | M5: 2020/21 | N5: 2021/22 | O5: 2022/23 | P5: 2023/24 | Q5: 2024/25 | R5: 2025/26 | S5: 2026/27
A6: Brazil | B6: Origine | C6: 54500 | D6: 49200 | E6: 57600 | F6: 57200 | G6: 54300 | H6: 49400 | I6: 56100 | J6: 52100 | K6: 66500 | L6: 60500 | M6: 69900 | N6: 58100 | O6: 62600 | P6: 66300 | Q6: 65500 | R6: 63000 | S6: 71900
A7: Vietnam | B7: Origine | C7: 19415 | D7: 26000 | E7: 26500 | F7: 29833 | G7: 27400 | H7: 28930 | I7: 26700 | J7: 29300 | K7: 30400 | L7: 31300 | M7: 29000 | N7: 31580 | O7: 28300 | P7: 27550 | Q7: 29000 | R7: 31700 | S7: 32500
A8: Colombia | B8: Origine | C8: 8525 | D8: 7655 | E8: 9927 | F8: 12075 | G8: 13300 | H8: 14000 | I8: 14600 | J8: 13825 | K8: 13870 | L8: 14100 | M8: 13400 | N8: 11800 | O8: 10700 | P8: 12760 | Q8: 14800 | R8: 12500 | S8: 13400
A9: Ethiopia | B9: Origine | C9: 6125 | D9: 6320 | E9: 6500 | F9: 6345 | G9: 6475 | H9: 6510 | I9: 6943 | J9: 7055 | K9: 7350 | L9: 7475 | M9: 7600 | N9: 8150 | O9: 7300 | P9: 9130 | Q9: 11460 | R9: 11560 | S9: 12100
A10: Indonesia | B10: Origine | C10: 9325 | D10: 7970 | E10: 11900 | F10: 11900 | G10: 10470 | H10: 12100 | I10: 10600 | J10: 10400 | K10: 10600 | L10: 10700 | M10: 10700 | N10: 10580 | O10: 10700 | P10: 8150 | Q10: 10700 | R10: 12370 | S10: 11380
A11: Uganda | B11: Origine | C11: 3212 | D11: 3075 | E11: 3600 | F11: 3850 | G11: 3500 | H11: 3550 | I11: 4875 | J11: 4600 | K11: 4650 | L11: 5475 | M11: 6630 | N11: 6050 | O11: 6565 | P11: 6400 | Q11: 6700 | R11: 7095 | S11: 7160
A12: India | B12: Origine | C12: 5035 | D12: 5230 | E12: 5303 | F12: 5075 | G12: 5440 | H12: 5800 | I12: 5200 | J12: 5266 | K12: 5325 | L12: 4967 | M12: 5567 | N12: 5700 | O12: 5867 | P12: 6560 | Q12: 6059 | R12: 6430 | S12: 6140
A13: Honduras | B13: Origine | C13: 3975 | D13: 5600 | E13: 4725 | F13: 4400 | G13: 5100 | H13: 5300 | I13: 7510 | J13: 7600 | K13: 7100 | L13: 5200 | M13: 6500 | N13: 4800 | O13: 5700 | P13: 5050 | Q13: 5200 | R13: 5530 | S13: 6030
A14: Peru | B14: Origine | C14: 4100 | D14: 5200 | E14: 4300 | F14: 4250 | G14: 2900 | H14: 3500 | I14: 4225 | J14: 4375 | K14: 4390 | L14: 3925 | M14: 3369 | N14: 4200 | O14: 3475 | P14: 3912 | Q14: 4120 | R14: 4764 | S14: 4780
A15: Mexico | B15: Origine | C15: 4000 | D15: 4300 | E15: 4650 | F15: 3950 | G15: 3180 | H15: 2300 | I15: 3300 | J15: 4000 | K15: 3550 | L15: 3700 | M15: 3530 | N15: 3740 | O15: 3545 | P15: 3856 | Q15: 3928 | R15: 4080 | S15: 4135
A16: Guatemala | B16: Origine | C16: 3960 | D16: 4410 | E16: 4010 | F16: 3515 | G16: 3185 | H16: 3295 | I16: 3570 | J16: 3780 | K16: 3770 | L16: 3645 | M16: 3930 | N16: 3540 | O16: 3270 | P16: 3469 | Q16: 3270 | R16: 3155 | S16: 3260
A17: Nicaragua | B17: Origine | C17: 1740 | D17: 2100 | E17: 1925 | F17: 2000 | G17: 2125 | H17: 2125 | I17: 2625 | J17: 2730 | K17: 2950 | L17: 2755 | M17: 2650 | N17: 2838 | O17: 2590 | P17: 2347 | Q17: 2660 | R17: 2560 | S17: 2440
... A98: Zimbabwe | B98: Importateur | C98: 0 | D98: 0 | E98: 0 | F98: 0 | G98: 0 | H98: 0 | I98: 0 | J98: 0 | K98: 0 | L98: 0 | M98: 0 | N98: 0 | O98: 0 | P98: 0 | Q98: 0 | R98: 0 | S98: 0
A99: Total pays d'origine (42) | C99: =SUM(C6:C47) -> 139319 | D99: =SUM(D6:D47) -> 142446 | E99: =SUM(E6:E47) -> 155156 | F99: =SUM(F6:F47) -> 156811 | G99: =SUM(G6:G47) -> 150571 | H99: =SUM(H6:H47) -> 149454 | I99: =SUM(I6:I47) -> 158046 | J99: =SUM(J6:J47) -> 156757 | ... S99: =SUM(S6:S47) -> 186642
A100: Total producteurs importateurs nets (5) | C100: =SUM(C48:C52) -> 2090 | D100: =SUM(D48:D52) -> 2391 | E100: =SUM(E48:E52) -> 2862 | F100: =SUM(F48:F52) -> 3243 | G100: =SUM(G48:G52) -> 3225 | H100: =SUM(H48:H52) -> 2975 | I100: =SUM(I48:I52) -> 3033 | J100: =SUM(J48:J52) -> 3057 | ... S100: =SUM(S48:S52) -> 3025
A101: Total pays importateurs (46) | C101: =SUM(C53:C98) -> 0 | D101: =SUM(D53:D98) -> 0 | E101: =SUM(E53:E98) -> 0 | F101: =SUM(F53:F98) -> 0 | G101: =SUM(G53:G98) -> 0 | H101: =SUM(H53:H98) -> 0 | I101: =SUM(I53:I98) -> 0 | J101: =SUM(J53:J98) -> 0 | ... S101: =SUM(S53:S98) -> 0
A102: MONDE | C102: =C99+C100+C101 -> 141409 | D102: =D99+D100+D101 -> 144837 | E102: =E99+E100+E101 -> 158018 | F102: =F99+F100+F101 -> 160054 | G102: =G99+G100+G101 -> 153796 | H102: =H99+H100+H101 -> 152429 | I102: =I99+I100+I101 -> 161079 | J102: =J99+J100+J101 -> 159814 | ... S102: =S99+S100+S101 -> 189667
A107: Production arabica | B107: Groupe | C107: 2010/11 | D107: 2011/12 | E107: 2012/13 | F107: 2013/14 | G107: 2014/15 | H107: 2015/16 | I107: 2016/17 | J107: 2017/18 | K107: 2018/19 | L107: 2019/20 | M107: 2020/21 | N107: 2021/22 | O107: 2022/23 | P107: 2023/24 | Q107: 2024/25 | R107: 2025/26 | S107: 2026/27
A108: Brazil | B108: Origine | C108: 41800 | D108: 34700 | E108: 42100 | F108: 41800 | G108: 37300 | H108: 36100 | I108: 45600 | J108: 39500 | K108: 49700 | L108: 42000 | M108: 49700 | N108: 36400 | O108: 39800 | P108: 44900 | Q108: 44500 | R108: 38000 | S108: 47500
A109: Vietnam | B109: Origine | C109: 650 | D109: 800 | E109: 900 | F109: 1175 | G109: 1050 | H109: 1100 | I109: 1100 | J109: 1026 | K109: 1064 | L109: 1100 | M109: 950 | N109: 1100 | O109: 1000 | P109: 1000 | Q109: 1000 | R109: 1200 | S109: 1100
A110: Colombia | B110: Origine | C110: 8525 | D110: 7655 | E110: 9927 | F110: 12075 | G110: 13300 | H110: 14000 | I110: 14600 | J110: 13825 | K110: 13870 | L110: 14100 | M110: 13400 | N110: 11800 | O110: 10700 | P110: 12760 | Q110: 14800 | R110: 12500 | S110: 13400
A111: Ethiopia | B111: Origine | C111: 6125 | D111: 6320 | E111: 6500 | F111: 6345 | G111: 6475 | H111: 6510 | I111: 6943 | J111: 7055 | K111: 7350 | L111: 7475 | M111: 7600 | N111: 8150 | O111: 7300 | P111: 9130 | Q111: 11460 | R111: 11560 | S111: 12100
A112: Indonesia | B112: Origine | C112: 1375 | D112: 1300 | E112: 2000 | F112: 1900 | G112: 1270 | H112: 1500 | I112: 1300 | J112: 1000 | K112: 1200 | L112: 1250 | M112: 1300 | N112: 1280 | O112: 1200 | P112: 1350 | Q112: 1400 | R112: 1370 | S112: 1380
A113: Uganda | B113: Origine | C113: 644 | D113: 875 | E113: 800 | F113: 850 | G113: 800 | H113: 950 | I113: 1100 | J113: 1200 | K113: 1050 | L113: 1025 | M113: 730 | N113: 990 | O113: 990 | P113: 1000 | Q113: 1030 | R113: 1120 | S113: 1135
A114: India | B114: Origine | C114: 1570 | D114: 1690 | E114: 1643 | F114: 1703 | G114: 1630 | H114: 1725 | I114: 1583 | J114: 1583 | K114: 1583 | L114: 1450 | M114: 1650 | N114: 1583 | O114: 1667 | P114: 1480 | Q114: 1762 | R114: 1730 | S114: 1560
A115: Honduras | B115: Origine | C115: 3975 | D115: 5600 | E115: 4725 | F115: 4400 | G115: 5100 | H115: 5300 | I115: 7510 | J115: 7600 | K115: 7100 | L115: 5200 | M115: 6500 | N115: 4800 | O115: 5700 | P115: 5050 | Q115: 5200 | R115: 5530 | S115: 6030
A116: Peru | B116: Origine | C116: 4100 | D116: 5200 | E116: 4300 | F116: 4250 | G116: 2900 | H116: 3500 | I116: 4225 | J116: 4375 | K116: 4390 | L116: 3925 | M116: 3369 | N116: 4200 | O116: 3475 | P116: 3912 | Q116: 4120 | R116: 4764 | S116: 4780
A117: Mexico | B117: Origine | C117: 3800 | D117: 4100 | E117: 4450 | F117: 3750 | G117: 2980 | H117: 2125 | I117: 3100 | J117: 3800 | K117: 3100 | L117: 3150 | M117: 3000 | N117: 3200 | O117: 3000 | P117: 3356 | Q117: 3588 | R117: 3580 | S117: 3575
A118: Guatemala | B118: Origine | C118: 3950 | D118: 4400 | E118: 4000 | F118: 3500 | G118: 3125 | H118: 3125 | I118: 3400 | J118: 3600 | K118: 3520 | L118: 3515 | M118: 3810 | N118: 3410 | O118: 3150 | P118: 3339 | Q118: 3140 | R118: 3025 | S118: 3130
A119: Nicaragua | B119: Origine | C119: 1740 | D119: 2100 | E119: 1925 | F119: 2000 | G119: 2100 | H119: 2100 | I119: 2600 | J119: 2700 | K119: 2900 | L119: 2675 | M119: 2550 | N119: 2718 | O119: 2430 | P119: 2187 | Q119: 2500 | R119: 2400 | S119: 2300
... A200: Zimbabwe | B200: Importateur | C200: 0 | D200: 0 | E200: 0 | F200: 0 | G200: 0 | H200: 0 | I200: 0 | J200: 0 | K200: 0 | L200: 0 | M200: 0 | N200: 0 | O200: 0 | P200: 0 | Q200: 0 | R200: 0 | S200: 0
A201: Total pays d'origine (42) | C201: =SUM(C108:C149) -> 86278 | D201: =SUM(D108:D149) -> 82576 | E201: =SUM(E108:E149) -> 90435 | F201: =SUM(F108:F149) -> 89647 | G201: =SUM(G108:G149) -> 83913 | H201: =SUM(H108:H149) -> 83560 | I201: =SUM(I108:I149) -> 98553 | J201: =SUM(J108:J149) -> 92592 | ... S201: =SUM(S108:S149) -> 103292
A202: Total producteurs importateurs nets (5) | C202: =SUM(C150:C154) -> 1665 | D202: =SUM(D150:D154) -> 1966 | E202: =SUM(E150:E154) -> 2437 | F202: =SUM(F150:F154) -> 2818 | G202: =SUM(G150:G154) -> 2775 | H202: =SUM(H150:H154) -> 2575 | I202: =SUM(I150:I154) -> 2583 | J202: =SUM(J150:J154) -> 2632 | ... S202: =SUM(S150:S154) -> 2575
A203: Total pays importateurs (46) | C203: =SUM(C155:C200) -> 0 | D203: =SUM(D155:D200) -> 0 | E203: =SUM(E155:E200) -> 0 | F203: =SUM(F155:F200) -> 0 | G203: =SUM(G155:G200) -> 0 | H203: =SUM(H155:H200) -> 0 | I203: =SUM(I155:I200) -> 0 | J203: =SUM(J155:J200) -> 0 | ... S203: =SUM(S155:S200) -> 0
A204: MONDE | C204: =C201+C202+C203 -> 87943 | D204: =D201+D202+D203 -> 84542 | E204: =E201+E202+E203 -> 92872 | F204: =F201+F202+F203 -> 92465 | G204: =G201+G202+G203 -> 86688 | H204: =H201+H202+H203 -> 86135 | I204: =I201+I202+I203 -> 101136 | J204: =J201+J202+J203 -> 95224 | ... S204: =S201+S202+S203 -> 105867
A209: Production robusta | B209: Groupe | C209: 2010/11 | D209: 2011/12 | E209: 2012/13 | F209: 2013/14 | G209: 2014/15 | H209: 2015/16 | I209: 2016/17 | J209: 2017/18 | K209: 2018/19 | L209: 2019/20 | M209: 2020/21 | N209: 2021/22 | O209: 2022/23 | P209: 2023/24 | Q209: 2024/25 | R209: 2025/26 | S209: 2026/27
A210: Brazil | B210: Origine | C210: 12700 | D210: 14500 | E210: 15500 | F210: 15400 | G210: 17000 | H210: 13300 | I210: 10500 | J210: 12600 | K210: 16800 | L210: 18500 | M210: 20200 | N210: 21700 | O210: 22800 | P210: 21400 | Q210: 21000 | R210: 25000 | S210: 24400
A211: Vietnam | B211: Origine | C211: 18765 | D211: 25200 | E211: 25600 | F211: 28658 | G211: 26350 | H211: 27830 | I211: 25600 | J211: 28274 | K211: 29336 | L211: 30200 | M211: 28050 | N211: 30480 | O211: 27300 | P211: 26550 | Q211: 28000 | R211: 30500 | S211: 31400
A212: Colombia | B212: Origine | C212: 0 | D212: 0 | E212: 0 | F212: 0 | G212: 0 | H212: 0 | I212: 0 | J212: 0 | K212: 0 | L212: 0 | M212: 0 | N212: 0 | O212: 0 | P212: 0 | Q212: 0 | R212: 0 | S212: 0
A213: Ethiopia | B213: Origine | C213: 0 | D213: 0 | E213: 0 | F213: 0 | G213: 0 | H213: 0 | I213: 0 | J213: 0 | K213: 0 | L213: 0 | M213: 0 | N213: 0 | O213: 0 | P213: 0 | Q213: 0 | R213: 0 | S213: 0
A214: Indonesia | B214: Origine | C214: 7950 | D214: 6670 | E214: 9900 | F214: 10000 | G214: 9200 | H214: 10600 | I214: 9300 | J214: 9400 | K214: 9400 | L214: 9450 | M214: 9400 | N214: 9300 | O214: 9500 | P214: 6800 | Q214: 9300 | R214: 11000 | S214: 10000
A215: Uganda | B215: Origine | C215: 2568 | D215: 2200 | E215: 2800 | F215: 3000 | G215: 2700 | H215: 2600 | I215: 3775 | J215: 3400 | K215: 3600 | L215: 4450 | M215: 5900 | N215: 5060 | O215: 5575 | P215: 5400 | Q215: 5670 | R215: 5975 | S215: 6025
A216: India | B216: Origine | C216: 3465 | D216: 3540 | E216: 3660 | F216: 3372 | G216: 3810 | H216: 4075 | I216: 3617 | J216: 3683 | K216: 3742 | L216: 3517 | M216: 3917 | N216: 4117 | O216: 4200 | P216: 5080 | Q216: 4297 | R216: 4700 | S216: 4580
A217: Honduras | B217: Origine | C217: 0 | D217: 0 | E217: 0 | F217: 0 | G217: 0 | H217: 0 | I217: 0 | J217: 0 | K217: 0 | L217: 0 | M217: 0 | N217: 0 | O217: 0 | P217: 0 | Q217: 0 | R217: 0 | S217: 0
A218: Peru | B218: Origine | C218: 0 | D218: 0 | E218: 0 | F218: 0 | G218: 0 | H218: 0 | I218: 0 | J218: 0 | K218: 0 | L218: 0 | M218: 0 | N218: 0 | O218: 0 | P218: 0 | Q218: 0 | R218: 0 | S218: 0
A219: Mexico | B219: Origine | C219: 200 | D219: 200 | E219: 200 | F219: 200 | G219: 200 | H219: 175 | I219: 200 | J219: 200 | K219: 450 | L219: 550 | M219: 530 | N219: 540 | O219: 545 | P219: 500 | Q219: 340 | R219: 500 | S219: 560
A220: Guatemala | B220: Origine | C220: 10 | D220: 10 | E220: 10 | F220: 15 | G220: 60 | H220: 170 | I220: 170 | J220: 180 | K220: 250 | L220: 130 | M220: 120 | N220: 130 | O220: 120 | P220: 130 | Q220: 130 | R220: 130 | S220: 130
A221: Nicaragua | B221: Origine | C221: 0 | D221: 0 | E221: 0 | F221: 0 | G221: 25 | H221: 25 | I221: 25 | J221: 30 | K221: 50 | L221: 80 | M221: 100 | N221: 120 | O221: 160 | P221: 160 | Q221: 160 | R221: 160 | S221: 140
... A302: Zimbabwe | B302: Importateur | C302: 0 | D302: 0 | E302: 0 | F302: 0 | G302: 0 | H302: 0 | I302: 0 | J302: 0 | K302: 0 | L302: 0 | M302: 0 | N302: 0 | O302: 0 | P302: 0 | Q302: 0 | R302: 0 | S302: 0
A303: Total pays d'origine (42) | C303: =SUM(C210:C251) -> 53041 | D303: =SUM(D210:D251) -> 59870 | E303: =SUM(E210:E251) -> 64721 | F303: =SUM(F210:F251) -> 67164 | G303: =SUM(G210:G251) -> 66658 | H303: =SUM(H210:H251) -> 65894 | I303: =SUM(I210:I251) -> 59493 | J303: =SUM(J210:J251) -> 64165 | ... S303: =SUM(S210:S251) -> 83350
A304: Total producteurs importateurs nets (5) | C304: =SUM(C252:C256) -> 425 | D304: =SUM(D252:D256) -> 425 | E304: =SUM(E252:E256) -> 425 | F304: =SUM(F252:F256) -> 425 | G304: =SUM(G252:G256) -> 450 | H304: =SUM(H252:H256) -> 400 | I304: =SUM(I252:I256) -> 450 | J304: =SUM(J252:J256) -> 425 | ... S304: =SUM(S252:S256) -> 450
A305: Total pays importateurs (46) | C305: =SUM(C257:C302) -> 0 | D305: =SUM(D257:D302) -> 0 | E305: =SUM(E257:E302) -> 0 | F305: =SUM(F257:F302) -> 0 | G305: =SUM(G257:G302) -> 0 | H305: =SUM(H257:H302) -> 0 | I305: =SUM(I257:I302) -> 0 | J305: =SUM(J257:J302) -> 0 | ... S305: =SUM(S257:S302) -> 0
A306: MONDE | C306: =C303+C304+C305 -> 53466 | D306: =D303+D304+D305 -> 60295 | E306: =E303+E304+E305 -> 65146 | F306: =F303+F304+F305 -> 67589 | G306: =G303+G304+G305 -> 67108 | H306: =H303+H304+H305 -> 66294 | I306: =I303+I304+I305 -> 59943 | J306: =J303+J304+J305 -> 64590 | ... S306: =S303+S304+S305 -> 83800
A311: Stocks de fin | B311: Groupe | C311: 2010/11 | D311: 2011/12 | E311: 2012/13 | F311: 2013/14 | G311: 2014/15 | H311: 2015/16 | I311: 2016/17 | J311: 2017/18 | K311: 2018/19 | L311: 2019/20 | M311: 2020/21 | N311: 2021/22 | O311: 2022/23 | P311: 2023/24 | Q311: 2024/25 | R311: 2025/26 | S311: 2026/27
A312: Brazil | B312: Origine | C312: 2906 | D312: 2238 | E312: 9068 | F312: 11946 | G312: 9305 | H312: 2372 | I312: 3828 | J312: 3115 | K312: 5056 | L312: 2373 | M312: 4390 | N312: 540 | O312: 4620 | P312: 2085 | Q312: 955 | R312: 3895 | S312: 4425
A313: Vietnam | B313: Origine | C313: 800 | D313: 1090 | E313: 1946 | F313: 2130 | G313: 6336 | H313: 4201 | I313: 2681 | J313: 254 | K313: 556 | L313: 2130 | M313: 3660 | N313: 3580 | O313: 839 | P313: 889 | Q313: 1089 | R313: 689 | S313: 489
A314: Colombia | B314: Origine | C314: 99 | D314: 249 | E314: 771 | F314: 961 | G314: 671 | H314: 1131 | I314: 886 | J314: 1111 | K314: 552 | L314: 852 | M314: 1235 | N314: 760 | O314: 885 | P314: 668 | Q314: 922 | R314: 866 | S314: 670
A315: Ethiopia | B315: Origine | C315: 100 | D315: 230 | E315: 100 | F315: 40 | G315: 30 | H315: 25 | I315: 15 | J315: 27 | K315: 10 | L315: 210 | M315: 135 | N315: 90 | O315: 50 | P315: 50 | Q315: 80 | R315: 175 | S315: 145
A316: Indonesia | B316: Origine | C316: 83 | D316: 88 | E316: 98 | F316: 48 | G316: 53 | H316: 46 | I316: 12 | J316: 593 | K316: 2419 | L316: 2298 | M316: 1669 | N316: 1056 | O316: 500 | P316: 480 | Q316: 622 | R316: 751 | S316: 671
A317: Uganda | B317: Origine | C317: 613 | D317: 538 | E317: 363 | F317: 393 | G317: 313 | H317: 313 | I317: 338 | J317: 388 | K317: 338 | L317: 363 | M317: 379 | N317: 454 | O317: 469 | P317: 244 | Q317: 269 | R317: 334 | S317: 329
A318: India | B318: Origine | C318: 1742 | D318: 1473 | E318: 1982 | F318: 2026 | G318: 2586 | H318: 2645 | I318: 1873 | J318: 1248 | K318: 931 | L318: 973 | M318: 911 | N318: 168 | O318: 475 | P318: 242 | Q318: 323 | R318: 485 | S318: 216
A319: Honduras | B319: Origine | C319: 30 | D319: 90 | E319: 140 | F319: 300 | G319: 340 | H319: 315 | I319: 300 | J319: 325 | K319: 162 | L319: 124 | M319: 269 | N319: 67 | O319: 112 | P319: 143 | Q319: 178 | R319: 435 | S319: 707
A320: Peru | B320: Origine | C320: 124 | D320: 14 | E320: 44 | F320: 24 | G320: 4 | H320: 44 | I320: 75 | J320: 85 | K320: 12 | L320: 126 | M320: 85 | N320: 95 | O320: 95 | P320: 28 | Q320: 23 | R320: 21 | S320: 26
A321: Mexico | B321: Origine | C321: 89 | D321: 62 | E321: 61 | F321: 169 | G321: 125 | H321: 210 | I321: 153 | J321: 183 | K321: 25 | L321: 99 | M321: 17 | N321: 99 | O321: 79 | P321: 17 | Q321: 20 | R321: 20 | S321: 5
A322: Guatemala | B322: Origine | C322: 237 | D322: 387 | E322: 212 | F322: 215 | G322: 15 | H322: 26 | I322: 36 | J322: 106 | K322: 26 | L322: 120 | M322: 111 | N322: 21 | O322: 22 | P322: 15 | Q322: 6 | R322: 11 | S322: 16
A323: Nicaragua | B323: Origine | C323: 22 | D323: 252 | E323: 17 | F323: 22 | G323: 102 | H323: 37 | I323: 72 | J323: 142 | K323: 147 | L323: 37 | M323: 37 | N323: 25 | O323: 25 | P323: 140 | Q323: 75 | R323: 55 | S323: 85
... A404: Zimbabwe | B404: Importateur | C404: 0 | D404: 0 | E404: 0 | F404: 0 | G404: 0 | H404: 0 | I404: 0 | J404: 0 | K404: 0 | L404: 0 | M404: 0 | N404: 0 | O404: 0 | P404: 0 | Q404: 0 | R404: 0 | S404: 0
A405: Total pays d'origine (42) | C405: =SUM(C312:C353) -> 8328 | D405: =SUM(D312:D353) -> 7840 | E405: =SUM(E312:E353) -> 15926 | F405: =SUM(F312:F353) -> 19404 | G405: =SUM(G312:G353) -> 21094 | H405: =SUM(H312:H353) -> 12452 | I405: =SUM(I312:I353) -> 11332 | J405: =SUM(J312:J353) -> 8709 | ... S405: =SUM(S312:S353) -> 8283
A406: Total producteurs importateurs nets (5) | C406: =SUM(C354:C358) -> 4902 | D406: =SUM(D354:D358) -> 5368 | E406: =SUM(E354:E358) -> 5614 | F406: =SUM(F354:F358) -> 6280 | G406: =SUM(G354:G358) -> 6463 | H406: =SUM(H354:H358) -> 6914 | I406: =SUM(I354:I358) -> 7916 | J406: =SUM(J354:J358) -> 6948 | ... S406: =SUM(S354:S358) -> 6400
A407: Total pays importateurs (46) | C407: =SUM(C359:C404) -> 15410 | D407: =SUM(D359:D404) -> 12540 | E407: =SUM(E359:E404) -> 13825 | F407: =SUM(F359:F404) -> 15500 | G407: =SUM(G359:G404) -> 15575 | H407: =SUM(H359:H404) -> 15585 | I407: =SUM(I359:I404) -> 17205 | J407: =SUM(J359:J404) -> 16294 | ... S407: =SUM(S359:S404) -> 11600
A408: MONDE | C408: =C405+C406+C407 -> 28640 | D408: =D405+D406+D407 -> 25748 | E408: =E405+E406+E407 -> 35365 | F408: =F405+F406+F407 -> 41184 | G408: =G405+G406+G407 -> 43132 | H408: =H405+H406+H407 -> 34951 | I408: =I405+I406+I407 -> 36453 | J408: =J405+J406+J407 -> 31951 | ... S408: =S405+S406+S407 -> 26283
A413: Consommation domestique | B413: Groupe | C413: 2010/11 | D413: 2011/12 | E413: 2012/13 | F413: 2013/14 | G413: 2014/15 | H413: 2015/16 | I413: 2016/17 | J413: 2017/18 | K413: 2018/19 | L413: 2019/20 | M413: 2020/21 | N413: 2021/22 | O413: 2022/23 | P413: 2023/24 | Q413: 2024/25 | R413: 2025/26 | S413: 2026/27
A414: Brazil | B414: Origine | C414: 19420 | D414: 20025 | E414: 20110 | F414: 20210 | G414: 20420 | H414: 20855 | I414: 21625 | J414: 22420 | K414: 23200 | L414: 22994 | M414: 22280 | N414: 22340 | O414: 22450 | P414: 22160 | Q414: 21970 | R414: 22280 | S414: 22390
A415: Vietnam | B415: Origine | C415: 1337 | D415: 1665 | E415: 1825 | F415: 2008 | G415: 2217 | H415: 2630 | I415: 2770 | J415: 2880 | K415: 2940 | L415: 3100 | M415: 2720 | N415: 3200 | O415: 3200 | P415: 3900 | Q415: 4800 | R415: 4900 | S415: 5000
A416: Colombia | B416: Origine | C416: 1120 | D416: 1260 | E416: 1200 | F416: 1300 | G416: 1400 | H416: 1415 | I416: 1450 | J416: 1650 | K416: 1925 | L416: 1775 | M416: 2080 | N416: 2145 | O416: 2150 | P416: 2225 | Q416: 2149 | R416: 2200 | S416: 2200
A417: Ethiopia | B417: Origine | C417: 2860 | D417: 3050 | E417: 3130 | F417: 3120 | G417: 2985 | H417: 3110 | I417: 3100 | J417: 3150 | K417: 3193 | L417: 3140 | M417: 3000 | N417: 3364 | O417: 3430 | P417: 3500 | Q417: 4000 | R417: 4500 | S417: 5000
A418: Indonesia | B418: Origine | C418: 1650 | D418: 2125 | E418: 2815 | F418: 2540 | G418: 2900 | H418: 3175 | I418: 3203 | J418: 3560 | K418: 4300 | L418: 4900 | M418: 4450 | N418: 4750 | O418: 4771 | P418: 4775 | Q418: 4873 | R418: 4810 | S418: 4830
A419: Uganda | B419: Origine | C419: 150 | D419: 150 | E419: 200 | F419: 220 | G419: 230 | H419: 250 | I419: 250 | J419: 250 | K419: 250 | L419: 100 | M419: 100 | N419: 125 | O419: 300 | P419: 325 | Q419: 325 | R419: 330 | S419: 335
A420: India | B420: Origine | C420: 1231 | D420: 1168 | E420: 1100 | F420: 1170 | G420: 1191 | H420: 1250 | I420: 1200 | J420: 1215 | K420: 1250 | L420: 1170 | M420: 1180 | N420: 875 | O420: 900 | P420: 1250 | Q420: 1150 | R420: 1575 | S420: 1580
A421: Honduras | B421: Origine | C421: 286 | D421: 265 | E421: 210 | F421: 315 | G421: 320 | H421: 345 | I421: 375 | J421: 375 | K421: 365 | L421: 366 | M421: 369 | N421: 373 | O421: 367 | P421: 340 | Q421: 335 | R421: 380 | S421: 415
A422: Peru | B422: Origine | C422: 170 | D422: 170 | E422: 170 | F422: 170 | G422: 170 | H422: 160 | I422: 169 | J422: 180 | K422: 170 | L422: 210 | M422: 222 | N422: 245 | O422: 240 | P422: 282 | Q422: 292 | R422: 300 | S422: 305
A423: Mexico | B423: Origine | C423: 2620 | D423: 2287 | E423: 2170 | F423: 2731 | G423: 2339 | H423: 2325 | I423: 2057 | J423: 2295 | K423: 2580 | L423: 2620 | M423: 2589 | N423: 2850 | O423: 3035 | P423: 3100 | Q423: 3100 | R423: 3160 | S423: 3240
A424: Guatemala | B424: Origine | C424: 425 | D424: 600 | E424: 600 | F424: 552 | G424: 500 | H424: 430 | I424: 455 | J424: 485 | K424: 495 | L424: 635 | M424: 609 | N424: 625 | O424: 600 | P424: 718 | Q424: 861 | R424: 875 | S424: 900
A425: Nicaragua | B425: Origine | C425: 130 | D425: 110 | E425: 105 | F425: 100 | G425: 150 | H425: 160 | I425: 180 | J425: 170 | K425: 180 | L425: 150 | M425: 175 | N425: 165 | O425: 155 | P425: 160 | Q425: 160 | R425: 160 | S425: 160
... A506: Zimbabwe | B506: Importateur | C506: 0 | D506: 0 | E506: 0 | F506: 0 | G506: 0 | H506: 0 | I506: 0 | J506: 0 | K506: 0 | L506: 0 | M506: 0 | N506: 0 | O506: 0 | P506: 0 | Q506: 0 | R506: 0 | S506: 0
A507: Total pays d'origine (42) | C507: =SUM(C414:C455) -> 35828 | D507: =SUM(D414:D455) -> 37449 | E507: =SUM(E414:E455) -> 37841 | F507: =SUM(F414:F455) -> 38570 | G507: =SUM(G414:G455) -> 38850 | H507: =SUM(H414:H455) -> 39511 | I507: =SUM(I414:I455) -> 40162 | J507: =SUM(J414:J455) -> 41878 | ... S507: =SUM(S414:S455) -> 50146
A508: Total producteurs importateurs nets (5) | C508: =SUM(C456:C460) -> 27705 | D508: =SUM(D456:D460) -> 29107 | E508: =SUM(E456:E460) -> 30494 | F508: =SUM(F456:F460) -> 30947 | G508: =SUM(G456:G460) -> 31433 | H508: =SUM(H456:H460) -> 35006 | I508: =SUM(I456:I460) -> 36068 | J508: =SUM(J456:J460) -> 36138 | ... S508: =SUM(S456:S460) -> 41125
A509: Total pays importateurs (46) | C509: =SUM(C461:C506) -> 71975 | D509: =SUM(D461:D506) -> 76275 | E509: =SUM(E461:E506) -> 75065 | F509: =SUM(F461:F506) -> 74360 | G509: =SUM(G461:G506) -> 76880 | H509: =SUM(H461:H506) -> 78669 | I509: =SUM(I461:I506) -> 78874 | J509: =SUM(J461:J506) -> 82611 | ... S509: =SUM(S461:S506) -> 88465
A510: MONDE | C510: =C507+C508+C509 -> 135508 | D510: =D507+D508+D509 -> 142831 | E510: =E507+E508+E509 -> 143400 | F510: =F507+F508+F509 -> 143877 | G510: =G507+G508+G509 -> 147163 | H510: =H507+H508+H509 -> 153186 | I510: =I507+I508+I509 -> 155104 | J510: =J507+J508+J509 -> 160627 | ... S510: =S507+S508+S509 -> 179736
A515: Exportations | B515: Groupe | C515: 2010/11 | D515: 2011/12 | E515: 2012/13 | F515: 2013/14 | G515: 2014/15 | H515: 2015/16 | I515: 2016/17 | J515: 2017/18 | K515: 2018/19 | L515: 2019/20 | M515: 2020/21 | N515: 2021/22 | O515: 2022/23 | P515: 2023/24 | Q515: 2024/25 | R515: 2025/26 | S515: 2026/27
A516: Brazil | B516: Origine | C516: 35010 | D516: 29843 | E516: 30660 | F516: 34146 | G516: 36573 | H516: 35543 | I516: 33081 | J516: 30454 | K516: 41426 | L516: 40256 | M516: 45675 | N516: 39685 | O516: 36145 | P516: 46750 | Q516: 44750 | R516: 37870 | S516: 49070
A517: Vietnam | B517: Origine | C517: 18640 | D517: 24495 | E517: 24643 | F517: 28289 | G517: 21567 | H517: 29065 | I517: 26450 | J517: 29907 | K517: 28318 | L517: 27326 | M517: 25300 | N517: 29010 | O517: 28340 | P517: 24400 | Q517: 25200 | R517: 28500 | S517: 28950
A518: Colombia | B518: Origine | C518: 8385 | D518: 7360 | E518: 8855 | F518: 11040 | G518: 12420 | H518: 12390 | I518: 13755 | J518: 12725 | K518: 13615 | L518: 13005 | M518: 12755 | N518: 12365 | O518: 10610 | P518: 11770 | Q518: 13377 | R518: 12810 | S518: 13400
A519: Ethiopia | B519: Origine | C519: 3235 | D519: 3140 | E519: 3500 | F519: 3285 | G519: 3500 | H519: 3405 | I519: 3853 | J519: 3893 | K519: 4174 | L519: 4135 | M519: 4675 | N519: 4831 | O519: 3910 | P519: 5630 | Q519: 7430 | R519: 6965 | S519: 7130
A520: Indonesia | B520: Origine | C520: 9730 | D520: 7145 | E520: 10325 | F520: 10380 | G520: 8720 | H520: 9896 | I520: 8174 | J520: 8010 | K520: 6150 | L520: 7152 | M520: 7872 | N520: 7428 | O520: 7832 | P520: 5355 | Q520: 7285 | R520: 8842 | S520: 8050
A521: Uganda | B521: Origine | C521: 3150 | D521: 3000 | E521: 3575 | F521: 3600 | G521: 3350 | H521: 3300 | I521: 4600 | J521: 4300 | K521: 4450 | L521: 5350 | M521: 6514 | N521: 5850 | O521: 6250 | P521: 6300 | Q521: 6350 | R521: 6700 | S521: 6830
...

Sheet Prix_ICE
A1: Prix : moyennes mensuelles ICE New York (arabica, KC) et ICE Londres (robusta, DF)
A2: Source : ICO, Coffee Market Report, tableau 1 (moyenne des 2e et 3e positions = proxy de KC1 / DF1 ; l'écart avec la 1re position est de quelques % en moyenne annuelle).
