Workbook

Sheet Lisez-moi
A1: Café — stock-to-use (USDA) vs prix KC1 / DF1, campagnes 2010/11 → 2026/27
A3: Ce que contient ce classeur
A4: 1_Monde — STU mondial en colonnes (%) avec KC1 et DF1 en courbes sur l'axe secondaire.
A5: 2_Arabica_Robusta — STU arabica et STU robusta (tous les pays producteurs), avec KC1 pour l'arabica et DF1 pour le robusta.
A6: 3_Groupes_pays — même chose en additionnant les pays demandés : arabica = Brésil, Colombie, Honduras, Éthiopie, Pérou, Mexique, Guatemala, Costa Rica ; robusta = Brésil, Vietnam, Indonésie, Ouganda.
A7: 4_Deux_pays — deux colonnes par an : Brésil + Colombie (avec KC1) et Vietnam + Brésil (avec DF1).
A8: 5_Bresil_Vietnam — un seul pays : Brésil (KC1) et Vietnam (DF1).
A9: 6_Surplus — le « surplus » à la place des stocks USDA : Brésil seul, arabica 6 pays (Brésil, Colombie, Honduras, Mexique, Pérou, Nicaragua), Vietnam seul, robusta 4 pays (Vietnam, Brésil, Ouganda, Indonésie).
A10: Tableau_STU — années en colonnes, pays en lignes, avec couleurs (rouge = tendu, vert = confortable).
A11: Analyse — corrélations, courbe prix = f(STU), application à 2026/27, régimes de prix, pays qui font bouger l'offre, conclusions.
A12: Prix_ICE — les 191 moyennes mensuelles (oct. 2010 → août 2026) et les moyennes de campagne. Donnees_USDA — toutes les données pays par pays (93 pays).
A13: Réponse : stock-to-use = stocks ÷ consommation, ou stocks ÷ (consommation + exportations) ?
... A24: 16 campagnes seulement : les corrélations donnent des ordres de grandeur. Les stocks USDA des pays producteurs sont des estimations résiduelles (le Brésil en particulier). Les prix ne sont pas corrigés de l'inflation ni du real brésilien (BRL), qui pèse lourd (≈1,7 R$/US$ en 2011, ≈5,2 depuis 2020). Toutes les formules sont vivantes : modifiez Donnees_USDA et les graphiques se mettent à jour.

Sheet 1_Monde
A1: 1 — Stock-to-use MONDE (USDA) vs prix KC1 et DF1
A2: STU monde = stocks de fin mondiaux ÷ consommation mondiale (définition USDA/ICO). Colonne F = stocks ÷ (conso + exportations), pour comparaison.
A3: Barres = STU (axe gauche) ; courbes = KC et robusta Londres en US cents/lb (axe droit), moyennes de campagne oct.–sept.
A4: Campagne | B4: Stocks de fin monde (1000 sacs) | C4: Consommation monde | D4: Exportations monde | E4: STU monde (stocks ÷ conso) | F4: STU (stocks ÷ (conso + export)) | G4: KC1 NY (US c/lb) | H4: DF1 Londres (US c/lb) | I4: DF1 Londres (US$/t)
A5: 2010/11 | B5: ='Donnees_USDA'!C801 -> 28640 | C5: ='Donnees_USDA'!C601 -> 135508 | D5: ='Donnees_USDA'!C701 -> 116972 | E5: =B5/C5 -> 0.21135284 | F5: =B5/(C5+D5) -> 0.11343473 | G5: ='Prix_ICE'!J5 -> 249.66 | H5: ='Prix_ICE'!K5 -> 100.65583 | I5: ='Prix_ICE'!L5 -> 2219.0813
A6: 2011/12 | B6: ='Donnees_USDA'!D801 -> 25748 | C6: ='Donnees_USDA'!D601 -> 142831 | D6: ='Donnees_USDA'!D701 -> 118031 | E6: =B6/C6 -> 0.18026899 | F6: =B6/(C6+D6) -> 0.098703529 | G6: ='Prix_ICE'!J6 -> 197.84167 | H6: ='Prix_ICE'!K6 -> 91.384167 | I6: ='Prix_ICE'!L6 -> 2014.676
A7: 2012/13 | B7: ='Donnees_USDA'!E801 -> 35365 | C7: ='Donnees_USDA'!E601 -> 143400 | D7: ='Donnees_USDA'!E701 -> 123239 | E7: =B7/C7 -> 0.24661785 | F7: =B7/(C7+D7) -> 0.13263251 | G7: ='Prix_ICE'!J7 -> 140.69833 | H7: ='Prix_ICE'!K7 -> 88.480833 | I7: ='Prix_ICE'!L7 -> 1950.6685
A8: 2013/14 | B8: ='Donnees_USDA'!F801 -> 41184 | C8: ='Donnees_USDA'!F601 -> 143877 | D8: ='Donnees_USDA'!F701 -> 129260 | E8: =B8/C8 -> 0.2862445 | F8: =B8/(C8+D8) -> 0.15078148 | G8: ='Prix_ICE'!J8 -> 161.4675 | H8: ='Prix_ICE'!K8 -> 85.874167 | I8: ='Prix_ICE'!L8 -> 1893.2013
A9: 2014/15 | B9: ='Donnees_USDA'!G801 -> 43132 | C9: ='Donnees_USDA'!G601 -> 147163 | D9: ='Donnees_USDA'!G701 -> 124027 | E9: =B9/C9 -> 0.29308998 | F9: =B9/(C9+D9) -> 0.15904716 | G9: ='Prix_ICE'!J9 -> 154.02083 | H9: ='Prix_ICE'!K9 -> 83.910833 | I9: ='Prix_ICE'!L9 -> 1849.9172
A10: 2015/16 | B10: ='Donnees_USDA'!H801 -> 34951 | C10: ='Donnees_USDA'!H601 -> 153186 | D10: ='Donnees_USDA'!H701 -> 133845 | E10: =B10/C10 -> 0.22816054 | F10: =B10/(C10+D10) -> 0.12176734 | G10: ='Prix_ICE'!J10 -> 131.8325 | H10: ='Prix_ICE'!K10 -> 74.068333 | I10: ='Prix_ICE'!L10 -> 1632.9272
A11: 2016/17 | B11: ='Donnees_USDA'!I801 -> 36453 | C11: ='Donnees_USDA'!I601 -> 155104 | D11: ='Donnees_USDA'!I701 -> 133606 | E11: =B11/C11 -> 0.23502295 | F11: =B11/(C11+D11) -> 0.12626165 | G11: ='Prix_ICE'!J11 -> 143.77167 | H11: ='Prix_ICE'!K11 -> 95.123333 | I11: ='Prix_ICE'!L11 -> 2097.1105
A12: 2017/18 | B12: ='Donnees_USDA'!J801 -> 31951 | C12: ='Donnees_USDA'!J601 -> 160627 | D12: ='Donnees_USDA'!J701 -> 134174 | E12: =B12/C12 -> 0.19891425 | F12: =B12/(C12+D12) -> 0.10838159 | G12: ='Prix_ICE'!J12 -> 120.60083 | H12: ='Prix_ICE'!K12 -> 78.285 | I12: ='Prix_ICE'!L12 -> 1725.8888
A13: 2018/19 | B13: ='Donnees_USDA'!K801 -> 36946 | C13: ='Donnees_USDA'!K601 -> 166003 | D13: ='Donnees_USDA'!K701 -> 143364 | E13: =B13/C13 -> 0.22256224 | F13: =B13/(C13+D13) -> 0.1194245 | G13: ='Prix_ICE'!J13 -> 104.98083 | H13: ='Prix_ICE'!K13 -> 67.5325 | I13: ='Prix_ICE'!L13 -> 1488.8368
A14: 2019/20 | B14: ='Donnees_USDA'!L801 -> 35808 | C14: ='Donnees_USDA'!L601 -> 162355 | D14: ='Donnees_USDA'!L701 -> 139001 | E14: =B14/C14 -> 0.22055372 | F14: =B14/(C14+D14) -> 0.11882292 | G14: ='Prix_ICE'!J14 -> 113.23667 | H14: ='Prix_ICE'!K14 -> 59.220833 | I14: ='Prix_ICE'!L14 -> 1305.5959
A15: 2020/21 | B15: ='Donnees_USDA'!M801 -> 37494 | C15: ='Donnees_USDA'!M601 -> 162093 | D15: ='Donnees_USDA'!M701 -> 144941 | E15: =B15/C15 -> 0.23131165 | F15: =B15/(C15+D15) -> 0.12211677 | G15: ='Prix_ICE'!J15 -> 143.75333 | H15: ='Prix_ICE'!K15 -> 69.895833 | I15: ='Prix_ICE'!L15 -> 1540.9394
A16: 2021/22 | B16: ='Donnees_USDA'!N801 -> 31940 | C16: ='Donnees_USDA'!N601 -> 167876 | D16: ='Donnees_USDA'!N701 -> 143583 | E16: =B16/C16 -> 0.19025948 | F16: =B16/(C16+D16) -> 0.10254961 | G16: ='Prix_ICE'!J16 -> 224.0875 | H16: ='Prix_ICE'!K16 -> 97.529167 | I16: ='Prix_ICE'!L16 -> 2150.1501
A17: 2022/23 | B17: ='Donnees_USDA'!O801 -> 26934 | C17: ='Donnees_USDA'!O601 -> 168754 | D17: ='Donnees_USDA'!O701 -> 134699 | E17: =B17/C17 -> 0.15960511 | F17: =B17/(C17+D17) -> 0.088758391 | G17: ='Prix_ICE'!J17 -> 171.19 | H17: ='Prix_ICE'!K17 -> 100.565 | I17: ='Prix_ICE'!L17 -> 2217.0787
A18: 2023/24 | B18: ='Donnees_USDA'!P801 -> 23121 | C18: ='Donnees_USDA'!P601 -> 163944 | D18: ='Donnees_USDA'!P701 -> 143474 | E18: =B18/C18 -> 0.14102986 | F18: =B18/(C18+D18) -> 0.0752103 | G18: ='Prix_ICE'!J18 -> 204.00167 | H18: ='Prix_ICE'!K18 -> 158.95 | I18: ='Prix_ICE'!L18 -> 3504.2477
A19: 2024/25 | B19: ='Donnees_USDA'!Q801 -> 22010 | C19: ='Donnees_USDA'!Q601 -> 171761 | D19: ='Donnees_USDA'!Q701 -> 147746 | E19: =B19/C19 -> 0.12814318 | F19: =B19/(C19+D19) -> 0.06888738 | G19: ='Prix_ICE'!J19 -> 333.06 | H19: ='Prix_ICE'!K19 -> 213.2675 | I19: ='Prix_ICE'!L19 -> 4701.7435
A20: 2025/26 | B20: ='Donnees_USDA'!R801 -> 24370 | C20: ='Donnees_USDA'!R601 -> 173459 | D20: ='Donnees_USDA'!R701 -> 145942 | E20: =B20/C20 -> 0.1404943 | F20: =B20/(C20+D20) -> 0.076299072 | G20: ='Prix_ICE'!J20 -> 312.21 | H20: ='Prix_ICE'!K20 -> 171.84182 | I20: ='Prix_ICE'!L20 -> 3788.4636
A21: 2026/27 (prév.) | B21: ='Donnees_USDA'!S801 -> 26283 | C21: ='Donnees_USDA'!S601 -> 179736 | D21: ='Donnees_USDA'!S701 -> 158874 | E21: =B21/C21 -> 0.14623114 | F21: =B21/(C21+D21) -> 0.077620271
A24: Lecture : quand le STU mondial passe sous ~16 %, les prix changent de régime (2023/24-2025/26) ; au-dessus de ~20 %, ils restent bas (2015/16-2020/21). Les deux définitions ont exactement la même forme (corrélation 0,99).
A28: Pourquoi diviser par la consommation seule au niveau mondial : les exportations d'un pays sont les importations d'un autre ; les ajouter compterait deux fois les mêmes sacs. Pour un pays exportateur, on divise par conso + exportations.

Sheet 2_Arabica_Robusta
A1: 2 — Stock-to-use ARABICA et ROBUSTA (total des 47 pays producteurs) vs KC1 / DF1
A2: L'USDA ne publie ni stocks ni consommation par espèce : chaque pays producteur est pondéré par la part arabica (ou robusta) de sa production de l'année.
A3: STU espèce = Σ(stocks × part) ÷ Σ((conso + export) × part). Les stocks des pays importateurs (UE, É.-U., Japon…) ne sont pas ventilables : ils sont exclus ici (voir onglet 1).
A4: Campagne | B4: Stocks arabica (1000 sacs, pondérés) | C4: Conso + export arabica (pondérés) | D4: STU ARABICA | E4: Stocks robusta (pondérés) | F4: Conso + export robusta (pondérés) | G4: STU ROBUSTA | H4: KC1 NY (US c/lb) | I4: DF1 Londres (US$/t)
A5: 2010/11 | B5: =SUMPRODUCT('Donnees_USDA'!C706:C752,'Donnees_USDA'!C806:C852) -> 9293.2165 | C5: =SUMPRODUCT('Donnees_USDA'!C506:C552,'Donnees_USDA'!C806:C852)+SUMPRODUCT('Donnees_USDA'!C606:C652,'Donnees_USDA'!C806:C852) -> 116870.24 | D5: =B5/C5 -> 0.079517394 | E5: =SUMPRODUCT('Donnees_USDA'!C706:C752,'Donnees_USDA'!C906:C952) -> 3936.7835 | F5: =SUMPRODUCT('Donnees_USDA'!C506:C552,'Donnees_USDA'!C906:C952)+SUMPRODUCT('Donnees_USDA'!C606:C652,'Donnees_USDA'!C906:C952) -> 61324.764 | G5: =E5/F5 -> 0.064195656 | H5: ='Prix_ICE'!J5 -> 249.66 | I5: ='Prix_ICE'!L5 -> 2219.0813
A6: 2011/12 | B6: =SUMPRODUCT('Donnees_USDA'!D706:D752,'Donnees_USDA'!D806:D852) -> 9586.9538 | C6: =SUMPRODUCT('Donnees_USDA'!D506:D552,'Donnees_USDA'!D806:D852)+SUMPRODUCT('Donnees_USDA'!D606:D652,'Donnees_USDA'!D806:D852) -> 114087.82 | D6: =B6/C6 -> 0.084031352 | E6: =SUMPRODUCT('Donnees_USDA'!D706:D752,'Donnees_USDA'!D906:D952) -> 3621.0462 | F6: =SUMPRODUCT('Donnees_USDA'!D506:D552,'Donnees_USDA'!D906:D952)+SUMPRODUCT('Donnees_USDA'!D606:D652,'Donnees_USDA'!D906:D952) -> 68249.179 | G6: =E6/F6 -> 0.05305626 | H6: ='Prix_ICE'!J6 -> 197.84167 | I6: ='Prix_ICE'!L6 -> 2014.676
A7: 2012/13 | B7: =SUMPRODUCT('Donnees_USDA'!E706:E752,'Donnees_USDA'!E806:E852) -> 15040.255 | C7: =SUMPRODUCT('Donnees_USDA'!E506:E552,'Donnees_USDA'!E806:E852)+SUMPRODUCT('Donnees_USDA'!E606:E652,'Donnees_USDA'!E806:E852) -> 117410.69 | D7: =B7/C7 -> 0.12809954 | E7: =SUMPRODUCT('Donnees_USDA'!E706:E752,'Donnees_USDA'!E906:E952) -> 6499.7446 | F7: =SUMPRODUCT('Donnees_USDA'!E506:E552,'Donnees_USDA'!E906:E952)+SUMPRODUCT('Donnees_USDA'!E606:E652,'Donnees_USDA'!E906:E952) -> 71613.307 | G7: =E7/F7 -> 0.090761688 | H7: ='Prix_ICE'!J7 -> 140.69833 | I7: ='Prix_ICE'!L7 -> 1950.6685
A8: 2013/14 | B8: =SUMPRODUCT('Donnees_USDA'!F706:F752,'Donnees_USDA'!F806:F852) -> 18263.42 | C8: =SUMPRODUCT('Donnees_USDA'!F506:F552,'Donnees_USDA'!F806:F852)+SUMPRODUCT('Donnees_USDA'!F606:F652,'Donnees_USDA'!F806:F852) -> 120683.67 | D8: =B8/C8 -> 0.15133298 | E8: =SUMPRODUCT('Donnees_USDA'!F706:F752,'Donnees_USDA'!F906:F952) -> 7420.5803 | F8: =SUMPRODUCT('Donnees_USDA'!F506:F552,'Donnees_USDA'!F906:F952)+SUMPRODUCT('Donnees_USDA'!F606:F652,'Donnees_USDA'!F906:F952) -> 75203.328 | G8: =E8/F8 -> 0.098673563 | H8: ='Prix_ICE'!J8 -> 161.4675 | I8: ='Prix_ICE'!L8 -> 1893.2013
A9: 2014/15 | B9: =SUMPRODUCT('Donnees_USDA'!G706:G752,'Donnees_USDA'!G806:G852) -> 15901.179 | C9: =SUMPRODUCT('Donnees_USDA'!G506:G552,'Donnees_USDA'!G806:G852)+SUMPRODUCT('Donnees_USDA'!G606:G652,'Donnees_USDA'!G806:G852) -> 118555.7 | D9: =B9/C9 -> 0.13412412 | E9: =SUMPRODUCT('Donnees_USDA'!G706:G752,'Donnees_USDA'!G906:G952) -> 11655.821 | F9: =SUMPRODUCT('Donnees_USDA'!G506:G552,'Donnees_USDA'!G906:G952)+SUMPRODUCT('Donnees_USDA'!G606:G652,'Donnees_USDA'!G906:G952) -> 72984.3 | G9: =E9/F9 -> 0.15970313 | H9: ='Prix_ICE'!J9 -> 154.02083 | I9: ='Prix_ICE'!L9 -> 1849.9172
A10: 2015/16 | B10: =SUMPRODUCT('Donnees_USDA'!H706:H752,'Donnees_USDA'!H806:H852) -> 11773.586 | C10: =SUMPRODUCT('Donnees_USDA'!H506:H552,'Donnees_USDA'!H806:H852)+SUMPRODUCT('Donnees_USDA'!H606:H652,'Donnees_USDA'!H806:H852) -> 123881.16 | D10: =B10/C10 -> 0.095039352 | E10: =SUMPRODUCT('Donnees_USDA'!H706:H752,'Donnees_USDA'!H906:H952) -> 7592.4144 | F10: =SUMPRODUCT('Donnees_USDA'!H506:H552,'Donnees_USDA'!H906:H952)+SUMPRODUCT('Donnees_USDA'!H606:H652,'Donnees_USDA'!H906:H952) -> 80920.835 | G10: =E10/F10 -> 0.09382521 | H10: ='Prix_ICE'!J10 -> 131.8325 | I10: ='Prix_ICE'!L10 -> 1632.9272
A11: 2016/17 | B11: =SUMPRODUCT('Donnees_USDA'!I706:I752,'Donnees_USDA'!I806:I852) -> 13683.019 | C11: =SUMPRODUCT('Donnees_USDA'!I506:I552,'Donnees_USDA'!I806:I852)+SUMPRODUCT('Donnees_USDA'!I606:I652,'Donnees_USDA'!I806:I852) -> 132742.82 | D11: =B11/C11 -> 0.10307917 | E11: =SUMPRODUCT('Donnees_USDA'!I706:I752,'Donnees_USDA'!I906:I952) -> 5564.981 | F11: =SUMPRODUCT('Donnees_USDA'!I506:I552,'Donnees_USDA'!I906:I952)+SUMPRODUCT('Donnees_USDA'!I606:I652,'Donnees_USDA'!I906:I952) -> 73013.185 | G11: =E11/F11 -> 0.07621885 | H11: ='Prix_ICE'!J11 -> 143.77167 | I11: ='Prix_ICE'!L11 -> 2097.1105
A12: 2017/18 | B12: =SUMPRODUCT('Donnees_USDA'!J706:J752,'Donnees_USDA'!J806:J852) -> 12243.909 | C12: =SUMPRODUCT('Donnees_USDA'!J506:J552,'Donnees_USDA'!J806:J852)+SUMPRODUCT('Donnees_USDA'!J606:J652,'Donnees_USDA'!J806:J852) -> 128761.49 | D12: =B12/C12 -> 0.095089841 | E12: =SUMPRODUCT('Donnees_USDA'!J706:J752,'Donnees_USDA'!J906:J952) -> 3413.0909 | F12: =SUMPRODUCT('Donnees_USDA'!J506:J552,'Donnees_USDA'!J906:J952)+SUMPRODUCT('Donnees_USDA'!J606:J652,'Donnees_USDA'!J906:J952) -> 78988.515 | G12: =E12/F12 -> 0.043209964 | H12: ='Prix_ICE'!J12 -> 120.60083 | I12: ='Prix_ICE'!L12 -> 1725.8888
A13: 2018/19 | B13: =SUMPRODUCT('Donnees_USDA'!K706:K752,'Donnees_USDA'!K806:K852) -> 13528.245 | C13: =SUMPRODUCT('Donnees_USDA'!K506:K552,'Donnees_USDA'!K806:K852)+SUMPRODUCT('Donnees_USDA'!K606:K652,'Donnees_USDA'!K806:K852) -> 139660.51 | D13: =B13/C13 -> 0.096865213 | E13: =SUMPRODUCT('Donnees_USDA'!K706:K752,'Donnees_USDA'!K906:K952) -> 5868.7551 | F13: =SUMPRODUCT('Donnees_USDA'!K506:K552,'Donnees_USDA'!K906:K952)+SUMPRODUCT('Donnees_USDA'!K606:K652,'Donnees_USDA'!K906:K952) -> 81016.492 | G13: =E13/F13 -> 0.072439018 | H13: ='Prix_ICE'!J13 -> 104.98083 | I13: ='Prix_ICE'!L13 -> 1488.8368
A14: 2019/20 | B14: =SUMPRODUCT('Donnees_USDA'!L706:L752,'Donnees_USDA'!L806:L852) -> 11120.172 | C14: =SUMPRODUCT('Donnees_USDA'!L506:L552,'Donnees_USDA'!L806:L852)+SUMPRODUCT('Donnees_USDA'!L606:L652,'Donnees_USDA'!L806:L852) -> 129910.03 | D14: =B14/C14 -> 0.085599027 | E14: =SUMPRODUCT('Donnees_USDA'!L706:L752,'Donnees_USDA'!L906:L952) -> 6752.8277 | F14: =SUMPRODUCT('Donnees_USDA'!L506:L552,'Donnees_USDA'!L906:L952)+SUMPRODUCT('Donnees_USDA'!L606:L652,'Donnees_USDA'!L906:L952) -> 84897.969 | G14: =E14/F14 -> 0.07954051 | H14: ='Prix_ICE'!J14 -> 113.23667 | I14: ='Prix_ICE'!L14 -> 1305.5959
A15: 2020/21 | B15: =SUMPRODUCT('Donnees_USDA'!M706:M752,'Donnees_USDA'!M806:M852) -> 12831.579 | C15: =SUMPRODUCT('Donnees_USDA'!M506:M552,'Donnees_USDA'!M806:M852)+SUMPRODUCT('Donnees_USDA'!M606:M652,'Donnees_USDA'!M806:M852) -> 135351.22 | D15: =B15/C15 -> 0.094802092 | E15: =SUMPRODUCT('Donnees_USDA'!M706:M752,'Donnees_USDA'!M906:M952) -> 8202.4207 | F15: =SUMPRODUCT('Donnees_USDA'!M506:M552,'Donnees_USDA'!M906:M952)+SUMPRODUCT('Donnees_USDA'!M606:M652,'Donnees_USDA'!M906:M952) -> 84293.775 | G15: =E15/F15 -> 0.097307549 | H15: ='Prix_ICE'!J15 -> 143.75333 | I15: ='Prix_ICE'!L15 -> 1540.9394
A16: 2021/22 | B16: =SUMPRODUCT('Donnees_USDA'!N706:N752,'Donnees_USDA'!N806:N852) -> 9221.2611 | C16: =SUMPRODUCT('Donnees_USDA'!N506:N552,'Donnees_USDA'!N806:N852)+SUMPRODUCT('Donnees_USDA'!N606:N652,'Donnees_USDA'!N806:N852) -> 127772.33 | D16: =B16/C16 -> 0.072169466 | E16: =SUMPRODUCT('Donnees_USDA'!N706:N752,'Donnees_USDA'!N906:N952) -> 5820.7389 | F16: =SUMPRODUCT('Donnees_USDA'!N506:N552,'Donnees_USDA'!N906:N952)+SUMPRODUCT('Donnees_USDA'!N606:N652,'Donnees_USDA'!N906:N952) -> 92911.666 | G16: =E16/F16 -> 0.062648095 | H16: ='Prix_ICE'!J16 -> 224.0875 | I16: ='Prix_ICE'!L16 -> 2150.1501
A17: 2022/23 | B17: =SUMPRODUCT('Donnees_USDA'!O706:O752,'Donnees_USDA'!O806:O852) -> 10846.447 | C17: =SUMPRODUCT('Donnees_USDA'!O506:O552,'Donnees_USDA'!O806:O852)+SUMPRODUCT('Donnees_USDA'!O606:O652,'Donnees_USDA'!O806:O852) -> 120505.65 | D17: =B17/C17 -> 0.090007788 | E17: =SUMPRODUCT('Donnees_USDA'!O706:O752,'Donnees_USDA'!O906:O952) -> 4257.5531 | F17: =SUMPRODUCT('Donnees_USDA'!O506:O552,'Donnees_USDA'!O906:O952)+SUMPRODUCT('Donnees_USDA'!O606:O652,'Donnees_USDA'!O906:O952) -> 89475.351 | G17: =E17/F17 -> 0.047583531 | H17: ='Prix_ICE'!J17 -> 171.19 | I17: ='Prix_ICE'!L17 -> 2217.0787
A18: 2023/24 | B18: =SUMPRODUCT('Donnees_USDA'!P706:P752,'Donnees_USDA'!P806:P852) -> 9357.9018 | C18: =SUMPRODUCT('Donnees_USDA'!P506:P552,'Donnees_USDA'!P806:P852)+SUMPRODUCT('Donnees_USDA'!P606:P652,'Donnees_USDA'!P806:P852) -> 133041.87 | D18: =B18/C18 -> 0.070338022 | E18: =SUMPRODUCT('Donnees_USDA'!P706:P752,'Donnees_USDA'!P906:P952) -> 2711.0982 | F18: =SUMPRODUCT('Donnees_USDA'!P506:P552,'Donnees_USDA'!P906:P952)+SUMPRODUCT('Donnees_USDA'!P606:P652,'Donnees_USDA'!P906:P952) -> 85766.133 | G18: =E18/F18 -> 0.031610359 | H18: ='Prix_ICE'!J18 -> 204.00167 | I18: ='Prix_ICE'!L18 -> 3504.2477
A19: 2024/25 | B19: =SUMPRODUCT('Donnees_USDA'!Q706:Q752,'Donnees_USDA'!Q806:Q852) -> 8829.2148 | C19: =SUMPRODUCT('Donnees_USDA'!Q506:Q552,'Donnees_USDA'!Q806:Q852)+SUMPRODUCT('Donnees_USDA'!Q606:Q652,'Donnees_USDA'!Q806:Q852) -> 140002.1 | D19: =B19/C19 -> 0.063064873 | E19: =SUMPRODUCT('Donnees_USDA'!Q706:Q752,'Donnees_USDA'!Q906:Q952) -> 2742.7852 | F19: =SUMPRODUCT('Donnees_USDA'!Q506:Q552,'Donnees_USDA'!Q906:Q952)+SUMPRODUCT('Donnees_USDA'!Q606:Q652,'Donnees_USDA'!Q906:Q952) -> 86159.897 | G19: =E19/F19 -> 0.031833664 | H19: ='Prix_ICE'!J19 -> 333.06 | I19: ='Prix_ICE'!L19 -> 4701.7435
A20: 2025/26 | B20: =SUMPRODUCT('Donnees_USDA'!R706:R752,'Donnees_USDA'!R806:R852) -> 10789.607 | C20: =SUMPRODUCT('Donnees_USDA'!R506:R552,'Donnees_USDA'!R806:R852)+SUMPRODUCT('Donnees_USDA'!R606:R652,'Donnees_USDA'!R806:R852) -> 130872.03 | D20: =B20/C20 -> 0.082443946 | E20: =SUMPRODUCT('Donnees_USDA'!R706:R752,'Donnees_USDA'!R906:R952) -> 3880.3932 | F20: =SUMPRODUCT('Donnees_USDA'!R506:R552,'Donnees_USDA'!R906:R952)+SUMPRODUCT('Donnees_USDA'!R606:R652,'Donnees_USDA'!R906:R952) -> 95265.968 | G20: =E20/F20 -> 0.040732208 | H20: ='Prix_ICE'!J20 -> 312.21 | I20: ='Prix_ICE'!L20 -> 3788.4636
A21: 2026/27 (prév.) | B21: =SUMPRODUCT('Donnees_USDA'!S706:S752,'Donnees_USDA'!S806:S852) -> 11284.833 | C21: =SUMPRODUCT('Donnees_USDA'!S506:S552,'Donnees_USDA'!S806:S852)+SUMPRODUCT('Donnees_USDA'!S606:S652,'Donnees_USDA'!S806:S852) -> 145437.03 | D21: =B21/C21 -> 0.077592572 | E21: =SUMPRODUCT('Donnees_USDA'!S706:S752,'Donnees_USDA'!S906:S952) -> 3398.1665 | F21: =SUMPRODUCT('Donnees_USDA'!S506:S552,'Donnees_USDA'!S906:S952)+SUMPRODUCT('Donnees_USDA'!S606:S652,'Donnees_USDA'!S906:S952) -> 96607.967 | G21: =E21/F21 -> 0.035174806

Sheet 3_Groupes_pays
A1: 3 — STU par addition des pays : ARABICA (8 pays) et ROBUSTA (4 pays) vs KC1 / DF1
A2: Arabica : Brésil, Colombie, Honduras, Éthiopie, Pérou, Mexique, Guatemala, Costa Rica. Robusta : Brésil, Vietnam, Indonésie, Ouganda.
A3: Chaque pays : stocks de fin USDA et conso + export USDA, additionnés. Le Brésil (présent dans les deux listes) est réparti selon sa part arabica / robusta de l'année ; colonnes J-K = addition brute (Brésil compté à 100 % dans les deux) pour comparaison.
A4: Campagne | B4: Stocks arabica 8 pays | C4: Conso + export arabica 8 pays | D4: STU ARABICA 8 pays | E4: Stocks robusta 4 pays | F4: Conso + export robusta 4 pays | G4: STU ROBUSTA 4 pays | H4: KC1 NY (US c/lb) | I4: DF1 Londres (US$/t) | J4: STU arabica 8 pays — addition brute | K4: STU robusta 4 pays — addition brute
A5: 2010/11 | B5: ='Donnees_USDA'!C706*'Donnees_USDA'!C806+'Donnees_USDA'!C708*'Donnees_USDA'!C808+'Donnees_USDA'!C713*'Donnees_USDA'!C813+'Donnees_USDA'!C709*'Donnees_USDA'!C809+'Donnees_USDA'!C714*'Donnees_USDA'!C814+'Donnees_USDA'!C715*'Donnees_USDA'!C815+'Donnees_USDA'!C716*'Donnees_USDA'!C816+'Donnees_USDA'!C722*'Donnees_USDA'!C822 -> 3102.7735 | C5: =('Donnees_USDA'!C506+'Donnees_USDA'!C606)*'Donnees_USDA'!C806+('Donnees_USDA'!C508+'Donnees_USDA'!C608)*'Donnees_USDA'!C808+('Donnees_USDA'!C513+'Donnees_USDA'!C613)*'Donnees_USDA'!C813+('Donnees_USDA'!C509+'Donnees_USDA'!C609)*'Donnees_USDA'!C809+('Donnees_USDA'!C514+'Donnees_USDA'!C614)*'Donnees_USDA'!C814+('Donnees_USDA'!C515+'Donnees_USDA'!C615)*'Donnees_USDA'!C815+('Donnees_USDA'!C516+'Donnees_USDA'!C616)*'Donnees_USDA'!C816+('Donnees_USDA'!C522+'Donnees_USDA'!C622)*'Donnees_USDA'!C822 -> 76339.832 | D5: =B5/C5 -> 0.040644228 | E5: ='Donnees_USDA'!C706*'Donnees_USDA'!C906+'Donnees_USDA'!C707*'Donnees_USDA'!C907+'Donnees_USDA'!C710*'Donnees_USDA'!C910+'Donnees_USDA'!C711*'Donnees_USDA'!C911 -> 2011.2506 | F5: =('Donnees_USDA'!C506+'Donnees_USDA'!C606)*'Donnees_USDA'!C906+('Donnees_USDA'!C507+'Donnees_USDA'!C607)*'Donnees_USDA'!C907+('Donnees_USDA'!C510+'Donnees_USDA'!C610)*'Donnees_USDA'!C910+('Donnees_USDA'!C511+'Donnees_USDA'!C611)*'Donnees_USDA'!C911 -> 44332.213 | G5: =E5/F5 -> 0.045367702 | H5: ='Prix_ICE'!J5 -> 249.66 | I5: ='Prix_ICE'!L5 -> 2219.0813 | J5: =('Donnees_USDA'!C706+'Donnees_USDA'!C708+'Donnees_USDA'!C713+'Donnees_USDA'!C709+'Donnees_USDA'!C714+'Donnees_USDA'!C715+'Donnees_USDA'!C716+'Donnees_USDA'!C722)/('Donnees_USDA'!C506+'Donnees_USDA'!C606+'Donnees_USDA'!C508+'Donnees_USDA'!C608+'Donnees_USDA'!C513+'Donnees_USDA'!C613+'Donnees_USDA'!C509+'Donnees_USDA'!C609+'Donnees_USDA'!C514+'Donnees_USDA'!C614+'Donnees_USDA'!C515+'Donnees_USDA'!C615+'Donnees_USDA'!C516+'Donnees_USDA'!C616+'Donnees_USDA'!C522+'Donnees_USDA'!C622) -> 0.042388541 | K5: =('Donnees_USDA'!C706+'Donnees_USDA'!C707+'Donnees_USDA'!C710+'Donnees_USDA'!C711)/('Donnees_USDA'!C506+'Donnees_USDA'!C606+'Donnees_USDA'!C507+'Donnees_USDA'!C607+'Donnees_USDA'!C510+'Donnees_USDA'!C610+'Donnees_USDA'!C511+'Donnees_USDA'!C611) -> 0.049412372
A6: 2011/12 | B6: ='Donnees_USDA'!D706*'Donnees_USDA'!D806+'Donnees_USDA'!D708*'Donnees_USDA'!D808+'Donnees_USDA'!D713*'Donnees_USDA'!D813+'Donnees_USDA'!D709*'Donnees_USDA'!D809+'Donnees_USDA'!D714*'Donnees_USDA'!D814+'Donnees_USDA'!D715*'Donnees_USDA'!D815+'Donnees_USDA'!D716*'Donnees_USDA'!D816+'Donnees_USDA'!D722*'Donnees_USDA'!D822 -> 2846.6656 | C6: =('Donnees_USDA'!D506+'Donnees_USDA'!D606)*'Donnees_USDA'!D806+('Donnees_USDA'!D508+'Donnees_USDA'!D608)*'Donnees_USDA'!D808+('Donnees_USDA'!D513+'Donnees_USDA'!D613)*'Donnees_USDA'!D813+('Donnees_USDA'!D509+'Donnees_USDA'!D609)*'Donnees_USDA'!D809+('Donnees_USDA'!D514+'Donnees_USDA'!D614)*'Donnees_USDA'!D814+('Donnees_USDA'!D515+'Donnees_USDA'!D615)*'Donnees_USDA'!D815+('Donnees_USDA'!D516+'Donnees_USDA'!D616)*'Donnees_USDA'!D816+('Donnees_USDA'!D522+'Donnees_USDA'!D622)*'Donnees_USDA'!D822 -> 72489.178 | D6: =B6/C6 -> 0.039270214 | E6: ='Donnees_USDA'!D706*'Donnees_USDA'!D906+'Donnees_USDA'!D707*'Donnees_USDA'!D907+'Donnees_USDA'!D710*'Donnees_USDA'!D910+'Donnees_USDA'!D711*'Donnees_USDA'!D911 -> 2174.5915 | F6: =('Donnees_USDA'!D506+'Donnees_USDA'!D606)*'Donnees_USDA'!D906+('Donnees_USDA'!D507+'Donnees_USDA'!D607)*'Donnees_USDA'!D907+('Donnees_USDA'!D510+'Donnees_USDA'!D610)*'Donnees_USDA'!D910+('Donnees_USDA'!D511+'Donnees_USDA'!D611)*'Donnees_USDA'!D911 -> 50063.56 | G6: =E6/F6 -> 0.043436612 | H6: ='Prix_ICE'!J6 -> 197.84167 | I6: ='Prix_ICE'!L6 -> 2014.676 | J6: =('Donnees_USDA'!D706+'Donnees_USDA'!D708+'Donnees_USDA'!D713+'Donnees_USDA'!D709+'Donnees_USDA'!D714+'Donnees_USDA'!D715+'Donnees_USDA'!D716+'Donnees_USDA'!D722)/('Donnees_USDA'!D506+'Donnees_USDA'!D606+'Donnees_USDA'!D508+'Donnees_USDA'!D608+'Donnees_USDA'!D513+'Donnees_USDA'!D613+'Donnees_USDA'!D509+'Donnees_USDA'!D609+'Donnees_USDA'!D514+'Donnees_USDA'!D614+'Donnees_USDA'!D515+'Donnees_USDA'!D615+'Donnees_USDA'!D516+'Donnees_USDA'!D616+'Donnees_USDA'!D522+'Donnees_USDA'!D622) -> 0.040133091 | K6: =('Donnees_USDA'!D706+'Donnees_USDA'!D707+'Donnees_USDA'!D710+'Donnees_USDA'!D711)/('Donnees_USDA'!D506+'Donnees_USDA'!D606+'Donnees_USDA'!D507+'Donnees_USDA'!D607+'Donnees_USDA'!D510+'Donnees_USDA'!D610+'Donnees_USDA'!D511+'Donnees_USDA'!D611) -> 0.044704233
A7: 2012/13 | B7: ='Donnees_USDA'!E706*'Donnees_USDA'!E806+'Donnees_USDA'!E708*'Donnees_USDA'!E808+'Donnees_USDA'!E713*'Donnees_USDA'!E813+'Donnees_USDA'!E709*'Donnees_USDA'!E809+'Donnees_USDA'!E714*'Donnees_USDA'!E814+'Donnees_USDA'!E715*'Donnees_USDA'!E815+'Donnees_USDA'!E716*'Donnees_USDA'!E816+'Donnees_USDA'!E722*'Donnees_USDA'!E822 -> 8142.6741 | C7: =('Donnees_USDA'!E506+'Donnees_USDA'!E606)*'Donnees_USDA'!E806+('Donnees_USDA'!E508+'Donnees_USDA'!E608)*'Donnees_USDA'!E808+('Donnees_USDA'!E513+'Donnees_USDA'!E613)*'Donnees_USDA'!E813+('Donnees_USDA'!E509+'Donnees_USDA'!E609)*'Donnees_USDA'!E809+('Donnees_USDA'!E514+'Donnees_USDA'!E614)*'Donnees_USDA'!E814+('Donnees_USDA'!E515+'Donnees_USDA'!E615)*'Donnees_USDA'!E815+('Donnees_USDA'!E516+'Donnees_USDA'!E616)*'Donnees_USDA'!E816+('Donnees_USDA'!E522+'Donnees_USDA'!E622)*'Donnees_USDA'!E822 -> 74429.176 | D7: =B7/C7 -> 0.10940164 | E7: ='Donnees_USDA'!E706*'Donnees_USDA'!E906+'Donnees_USDA'!E707*'Donnees_USDA'!E907+'Donnees_USDA'!E710*'Donnees_USDA'!E910+'Donnees_USDA'!E711*'Donnees_USDA'!E911 -> 4683.9458 | F7: =('Donnees_USDA'!E506+'Donnees_USDA'!E606)*'Donnees_USDA'!E906+('Donnees_USDA'!E507+'Donnees_USDA'!E607)*'Donnees_USDA'!E907+('Donnees_USDA'!E510+'Donnees_USDA'!E610)*'Donnees_USDA'!E910+('Donnees_USDA'!E511+'Donnees_USDA'!E611)*'Donnees_USDA'!E911 -> 53098.861 | G7: =E7/F7 -> 0.088211795 | H7: ='Prix_ICE'!J7 -> 140.69833 | I7: ='Prix_ICE'!L7 -> 1950.6685 | J7: =('Donnees_USDA'!E706+'Donnees_USDA'!E708+'Donnees_USDA'!E713+'Donnees_USDA'!E709+'Donnees_USDA'!E714+'Donnees_USDA'!E715+'Donnees_USDA'!E716+'Donnees_USDA'!E722)/('Donnees_USDA'!E506+'Donnees_USDA'!E606+'Donnees_USDA'!E508+'Donnees_USDA'!E608+'Donnees_USDA'!E513+'Donnees_USDA'!E613+'Donnees_USDA'!E509+'Donnees_USDA'!E609+'Donnees_USDA'!E514+'Donnees_USDA'!E614+'Donnees_USDA'!E515+'Donnees_USDA'!E615+'Donnees_USDA'!E516+'Donnees_USDA'!E616+'Donnees_USDA'!E522+'Donnees_USDA'!E622) -> 0.11981755 | K7: =('Donnees_USDA'!E706+'Donnees_USDA'!E707+'Donnees_USDA'!E710+'Donnees_USDA'!E711)/('Donnees_USDA'!E506+'Donnees_USDA'!E606+'Donnees_USDA'!E507+'Donnees_USDA'!E607+'Donnees_USDA'!E510+'Donnees_USDA'!E610+'Donnees_USDA'!E511+'Donnees_USDA'!E611) -> 0.1218761
A8: 2013/14 | B8: ='Donnees_USDA'!F706*'Donnees_USDA'!F806+'Donnees_USDA'!F708*'Donnees_USDA'!F808+'Donnees_USDA'!F713*'Donnees_USDA'!F813+'Donnees_USDA'!F709*'Donnees_USDA'!F809+'Donnees_USDA'!F714*'Donnees_USDA'!F814+'Donnees_USDA'!F715*'Donnees_USDA'!F815+'Donnees_USDA'!F716*'Donnees_USDA'!F816+'Donnees_USDA'!F722*'Donnees_USDA'!F822 -> 10559.295 | C8: =('Donnees_USDA'!F506+'Donnees_USDA'!F606)*'Donnees_USDA'!F806+('Donnees_USDA'!F508+'Donnees_USDA'!F608)*'Donnees_USDA'!F808+('Donnees_USDA'!F513+'Donnees_USDA'!F613)*'Donnees_USDA'!F813+('Donnees_USDA'!F509+'Donnees_USDA'!F609)*'Donnees_USDA'!F809+('Donnees_USDA'!F514+'Donnees_USDA'!F614)*'Donnees_USDA'!F814+('Donnees_USDA'!F515+'Donnees_USDA'!F615)*'Donnees_USDA'!F815+('Donnees_USDA'!F516+'Donnees_USDA'!F616)*'Donnees_USDA'!F816+('Donnees_USDA'!F522+'Donnees_USDA'!F622)*'Donnees_USDA'!F822 -> 77602.534 | D8: =B8/C8 -> 0.13606894 | E8: ='Donnees_USDA'!F706*'Donnees_USDA'!F906+'Donnees_USDA'!F707*'Donnees_USDA'!F907+'Donnees_USDA'!F710*'Donnees_USDA'!F910+'Donnees_USDA'!F711*'Donnees_USDA'!F911 -> 5608.9087 | F8: =('Donnees_USDA'!F506+'Donnees_USDA'!F606)*'Donnees_USDA'!F906+('Donnees_USDA'!F507+'Donnees_USDA'!F607)*'Donnees_USDA'!F907+('Donnees_USDA'!F510+'Donnees_USDA'!F610)*'Donnees_USDA'!F910+('Donnees_USDA'!F511+'Donnees_USDA'!F611)*'Donnees_USDA'!F911 -> 57571.799 | G8: =E8/F8 -> 0.097424586 | H8: ='Prix_ICE'!J8 -> 161.4675 | I8: ='Prix_ICE'!L8 -> 1893.2013 | J8: =('Donnees_USDA'!F706+'Donnees_USDA'!F708+'Donnees_USDA'!F713+'Donnees_USDA'!F709+'Donnees_USDA'!F714+'Donnees_USDA'!F715+'Donnees_USDA'!F716+'Donnees_USDA'!F722)/('Donnees_USDA'!F506+'Donnees_USDA'!F606+'Donnees_USDA'!F508+'Donnees_USDA'!F608+'Donnees_USDA'!F513+'Donnees_USDA'!F613+'Donnees_USDA'!F509+'Donnees_USDA'!F609+'Donnees_USDA'!F514+'Donnees_USDA'!F614+'Donnees_USDA'!F515+'Donnees_USDA'!F615+'Donnees_USDA'!F516+'Donnees_USDA'!F616+'Donnees_USDA'!F522+'Donnees_USDA'!F622) -> 0.14898032 | K8: =('Donnees_USDA'!F706+'Donnees_USDA'!F707+'Donnees_USDA'!F710+'Donnees_USDA'!F711)/('Donnees_USDA'!F506+'Donnees_USDA'!F606+'Donnees_USDA'!F507+'Donnees_USDA'!F607+'Donnees_USDA'!F510+'Donnees_USDA'!F610+'Donnees_USDA'!F511+'Donnees_USDA'!F611) -> 0.14317556
A9: 2014/15 | B9: ='Donnees_USDA'!G706*'Donnees_USDA'!G806+'Donnees_USDA'!G708*'Donnees_USDA'!G808+'Donnees_USDA'!G713*'Donnees_USDA'!G813+'Donnees_USDA'!G709*'Donnees_USDA'!G809+'Donnees_USDA'!G714*'Donnees_USDA'!G814+'Donnees_USDA'!G715*'Donnees_USDA'!G815+'Donnees_USDA'!G716*'Donnees_USDA'!G816+'Donnees_USDA'!G722*'Donnees_USDA'!G822 -> 7682.6882 | C9: =('Donnees_USDA'!G506+'Donnees_USDA'!G606)*'Donnees_USDA'!G806+('Donnees_USDA'!G508+'Donnees_USDA'!G608)*'Donnees_USDA'!G808+('Donnees_USDA'!G513+'Donnees_USDA'!G613)*'Donnees_USDA'!G813+('Donnees_USDA'!G509+'Donnees_USDA'!G609)*'Donnees_USDA'!G809+('Donnees_USDA'!G514+'Donnees_USDA'!G614)*'Donnees_USDA'!G814+('Donnees_USDA'!G515+'Donnees_USDA'!G615)*'Donnees_USDA'!G815+('Donnees_USDA'!G516+'Donnees_USDA'!G616)*'Donnees_USDA'!G816+('Donnees_USDA'!G522+'Donnees_USDA'!G622)*'Donnees_USDA'!G822 -> 77125.522 | D9: =B9/C9 -> 0.099612787 | E9: ='Donnees_USDA'!G706*'Donnees_USDA'!G906+'Donnees_USDA'!G707*'Donnees_USDA'!G907+'Donnees_USDA'!G710*'Donnees_USDA'!G910+'Donnees_USDA'!G711*'Donnees_USDA'!G911 -> 9294.393 | F9: =('Donnees_USDA'!G506+'Donnees_USDA'!G606)*'Donnees_USDA'!G906+('Donnees_USDA'!G507+'Donnees_USDA'!G607)*'Donnees_USDA'!G907+('Donnees_USDA'!G510+'Donnees_USDA'!G610)*'Donnees_USDA'!G910+('Donnees_USDA'!G511+'Donnees_USDA'!G611)*'Donnees_USDA'!G911 -> 53687.902 | G9: =E9/F9 -> 0.17311894 | H9: ='Prix_ICE'!J9 -> 154.02083 | I9: ='Prix_ICE'!L9 -> 1849.9172 | J9: =('Donnees_USDA'!G706+'Donnees_USDA'!G708+'Donnees_USDA'!G713+'Donnees_USDA'!G709+'Donnees_USDA'!G714+'Donnees_USDA'!G715+'Donnees_USDA'!G716+'Donnees_USDA'!G722)/('Donnees_USDA'!G506+'Donnees_USDA'!G606+'Donnees_USDA'!G508+'Donnees_USDA'!G608+'Donnees_USDA'!G513+'Donnees_USDA'!G613+'Donnees_USDA'!G509+'Donnees_USDA'!G609+'Donnees_USDA'!G514+'Donnees_USDA'!G614+'Donnees_USDA'!G515+'Donnees_USDA'!G615+'Donnees_USDA'!G516+'Donnees_USDA'!G616+'Donnees_USDA'!G522+'Donnees_USDA'!G622) -> 0.11121833 | K9: =('Donnees_USDA'!G706+'Donnees_USDA'!G707+'Donnees_USDA'!G710+'Donnees_USDA'!G711)/('Donnees_USDA'!G506+'Donnees_USDA'!G606+'Donnees_USDA'!G507+'Donnees_USDA'!G607+'Donnees_USDA'!G510+'Donnees_USDA'!G610+'Donnees_USDA'!G511+'Donnees_USDA'!G611) -> 0.16677954
A10: 2015/16 | B10: ='Donnees_USDA'!H706*'Donnees_USDA'!H806+'Donnees_USDA'!H708*'Donnees_USDA'!H808+'Donnees_USDA'!H713*'Donnees_USDA'!H813+'Donnees_USDA'!H709*'Donnees_USDA'!H809+'Donnees_USDA'!H714*'Donnees_USDA'!H814+'Donnees_USDA'!H715*'Donnees_USDA'!H815+'Donnees_USDA'!H716*'Donnees_USDA'!H816+'Donnees_USDA'!H722*'Donnees_USDA'!H822 -> 3783.0649 | C10: =('Donnees_USDA'!H506+'Donnees_USDA'!H606)*'Donnees_USDA'!H806+('Donnees_USDA'!H508+'Donnees_USDA'!H608)*'Donnees_USDA'!H808+('Donnees_USDA'!H513+'Donnees_USDA'!H613)*'Donnees_USDA'!H813+('Donnees_USDA'!H509+'Donnees_USDA'!H609)*'Donnees_USDA'!H809+('Donnees_USDA'!H514+'Donnees_USDA'!H614)*'Donnees_USDA'!H814+('Donnees_USDA'!H515+'Donnees_USDA'!H615)*'Donnees_USDA'!H815+('Donnees_USDA'!H516+'Donnees_USDA'!H616)*'Donnees_USDA'!H816+('Donnees_USDA'!H522+'Donnees_USDA'!H622)*'Donnees_USDA'!H822 -> 79548.742 | D10: =B10/C10 -> 0.047556565 | E10: ='Donnees_USDA'!H706*'Donnees_USDA'!H906+'Donnees_USDA'!H707*'Donnees_USDA'!H907+'Donnees_USDA'!H710*'Donnees_USDA'!H910+'Donnees_USDA'!H711*'Donnees_USDA'!H911 -> 4949.4185 | F10: =('Donnees_USDA'!H506+'Donnees_USDA'!H606)*'Donnees_USDA'!H906+('Donnees_USDA'!H507+'Donnees_USDA'!H607)*'Donnees_USDA'!H907+('Donnees_USDA'!H510+'Donnees_USDA'!H610)*'Donnees_USDA'!H910+('Donnees_USDA'!H511+'Donnees_USDA'!H611)*'Donnees_USDA'!H911 -> 59724.572 | G10: =E10/F10 -> 0.082870724 | H10: ='Prix_ICE'!J10 -> 131.8325 | I10: ='Prix_ICE'!L10 -> 1632.9272 | J10: =('Donnees_USDA'!H706+'Donnees_USDA'!H708+'Donnees_USDA'!H713+'Donnees_USDA'!H709+'Donnees_USDA'!H714+'Donnees_USDA'!H715+'Donnees_USDA'!H716+'Donnees_USDA'!H722)/('Donnees_USDA'!H506+'Donnees_USDA'!H606+'Donnees_USDA'!H508+'Donnees_USDA'!H608+'Donnees_USDA'!H513+'Donnees_USDA'!H613+'Donnees_USDA'!H509+'Donnees_USDA'!H609+'Donnees_USDA'!H514+'Donnees_USDA'!H614+'Donnees_USDA'!H515+'Donnees_USDA'!H615+'Donnees_USDA'!H516+'Donnees_USDA'!H616+'Donnees_USDA'!H522+'Donnees_USDA'!H622) -> 0.046595358 | K10: =('Donnees_USDA'!H706+'Donnees_USDA'!H707+'Donnees_USDA'!H710+'Donnees_USDA'!H711)/('Donnees_USDA'!H506+'Donnees_USDA'!H606+'Donnees_USDA'!H507+'Donnees_USDA'!H607+'Donnees_USDA'!H510+'Donnees_USDA'!H610+'Donnees_USDA'!H511+'Donnees_USDA'!H611) -> 0.066199362
A11: 2016/17 | B11: ='Donnees_USDA'!I706*'Donnees_USDA'!I806+'Donnees_USDA'!I708*'Donnees_USDA'!I808+'Donnees_USDA'!I713*'Donnees_USDA'!I813+'Donnees_USDA'!I709*'Donnees_USDA'!I809+'Donnees_USDA'!I714*'Donnees_USDA'!I814+'Donnees_USDA'!I715*'Donnees_USDA'!I815+'Donnees_USDA'!I716*'Donnees_USDA'!I816+'Donnees_USDA'!I722*'Donnees_USDA'!I822 -> 4791.5424 | C11: =('Donnees_USDA'!I506+'Donnees_USDA'!I606)*'Donnees_USDA'!I806+('Donnees_USDA'!I508+'Donnees_USDA'!I608)*'Donnees_USDA'!I808+('Donnees_USDA'!I513+'Donnees_USDA'!I613)*'Donnees_USDA'!I813+('Donnees_USDA'!I509+'Donnees_USDA'!I609)*'Donnees_USDA'!I809+('Donnees_USDA'!I514+'Donnees_USDA'!I614)*'Donnees_USDA'!I814+('Donnees_USDA'!I515+'Donnees_USDA'!I615)*'Donnees_USDA'!I815+('Donnees_USDA'!I516+'Donnees_USDA'!I616)*'Donnees_USDA'!I816+('Donnees_USDA'!I522+'Donnees_USDA'!I622)*'Donnees_USDA'!I822 -> 88107.368 | D11: =B11/C11 -> 0.054382993 | E11: ='Donnees_USDA'!I706*'Donnees_USDA'!I906+'Donnees_USDA'!I707*'Donnees_USDA'!I907+'Donnees_USDA'!I710*'Donnees_USDA'!I910+'Donnees_USDA'!I711*'Donnees_USDA'!I911 -> 3559.279 | F11: =('Donnees_USDA'!I506+'Donnees_USDA'!I606)*'Donnees_USDA'!I906+('Donnees_USDA'!I507+'Donnees_USDA'!I607)*'Donnees_USDA'!I907+('Donnees_USDA'!I510+'Donnees_USDA'!I610)*'Donnees_USDA'!I910+('Donnees_USDA'!I511+'Donnees_USDA'!I611)*'Donnees_USDA'!I911 -> 51992.619 | G11: =E11/F11 -> 0.068457391 | H11: ='Prix_ICE'!J11 -> 143.77167 | I11: ='Prix_ICE'!L11 -> 2097.1105 | J11: =('Donnees_USDA'!I706+'Donnees_USDA'!I708+'Donnees_USDA'!I713+'Donnees_USDA'!I709+'Donnees_USDA'!I714+'Donnees_USDA'!I715+'Donnees_USDA'!I716+'Donnees_USDA'!I722)/('Donnees_USDA'!I506+'Donnees_USDA'!I606+'Donnees_USDA'!I508+'Donnees_USDA'!I608+'Donnees_USDA'!I513+'Donnees_USDA'!I613+'Donnees_USDA'!I509+'Donnees_USDA'!I609+'Donnees_USDA'!I514+'Donnees_USDA'!I614+'Donnees_USDA'!I515+'Donnees_USDA'!I615+'Donnees_USDA'!I516+'Donnees_USDA'!I616+'Donnees_USDA'!I522+'Donnees_USDA'!I622) -> 0.055846193 | K11: =('Donnees_USDA'!I706+'Donnees_USDA'!I707+'Donnees_USDA'!I710+'Donnees_USDA'!I711)/('Donnees_USDA'!I506+'Donnees_USDA'!I606+'Donnees_USDA'!I507+'Donnees_USDA'!I607+'Donnees_USDA'!I510+'Donnees_USDA'!I610+'Donnees_USDA'!I511+'Donnees_USDA'!I611) -> 0.068485218
A12: 2017/18 | B12: ='Donnees_USDA'!J706*'Donnees_USDA'!J806+'Donnees_USDA'!J708*'Donnees_USDA'!J808+'Donnees_USDA'!J713*'Donnees_USDA'!J813+'Donnees_USDA'!J709*'Donnees_USDA'!J809+'Donnees_USDA'!J714*'Donnees_USDA'!J814+'Donnees_USDA'!J715*'Donnees_USDA'!J815+'Donnees_USDA'!J716*'Donnees_USDA'!J816+'Donnees_USDA'!J722*'Donnees_USDA'!J822 -> 4440.4626 | C12: =('Donnees_USDA'!J506+'Donnees_USDA'!J606)*'Donnees_USDA'!J806+('Donnees_USDA'!J508+'Donnees_USDA'!J608)*'Donnees_USDA'!J808+('Donnees_USDA'!J513+'Donnees_USDA'!J613)*'Donnees_USDA'!J813+('Donnees_USDA'!J509+'Donnees_USDA'!J609)*'Donnees_USDA'!J809+('Donnees_USDA'!J514+'Donnees_USDA'!J614)*'Donnees_USDA'!J814+('Donnees_USDA'!J515+'Donnees_USDA'!J615)*'Donnees_USDA'!J815+('Donnees_USDA'!J516+'Donnees_USDA'!J616)*'Donnees_USDA'!J816+('Donnees_USDA'!J522+'Donnees_USDA'!J622)*'Donnees_USDA'!J822 -> 84057.969 | D12: =B12/C12 -> 0.052826195 | E12: ='Donnees_USDA'!J706*'Donnees_USDA'!J906+'Donnees_USDA'!J707*'Donnees_USDA'!J907+'Donnees_USDA'!J710*'Donnees_USDA'!J910+'Donnees_USDA'!J711*'Donnees_USDA'!J911 -> 1821.2088 | F12: =('Donnees_USDA'!J506+'Donnees_USDA'!J606)*'Donnees_USDA'!J906+('Donnees_USDA'!J507+'Donnees_USDA'!J607)*'Donnees_USDA'!J907+('Donnees_USDA'!J510+'Donnees_USDA'!J610)*'Donnees_USDA'!J910+('Donnees_USDA'!J511+'Donnees_USDA'!J611)*'Donnees_USDA'!J911 -> 58246.625 | G12: =E12/F12 -> 0.031267198 | H12: ='Prix_ICE'!J12 -> 120.60083 | I12: ='Prix_ICE'!L12 -> 1725.8888 | J12: =('Donnees_USDA'!J706+'Donnees_USDA'!J708+'Donnees_USDA'!J713+'Donnees_USDA'!J709+'Donnees_USDA'!J714+'Donnees_USDA'!J715+'Donnees_USDA'!J716+'Donnees_USDA'!J722)/('Donnees_USDA'!J506+'Donnees_USDA'!J606+'Donnees_USDA'!J508+'Donnees_USDA'!J608+'Donnees_USDA'!J513+'Donnees_USDA'!J613+'Donnees_USDA'!J509+'Donnees_USDA'!J609+'Donnees_USDA'!J514+'Donnees_USDA'!J614+'Donnees_USDA'!J515+'Donnees_USDA'!J615+'Donnees_USDA'!J516+'Donnees_USDA'!J616+'Donnees_USDA'!J522+'Donnees_USDA'!J622) -> 0.053520229 | K12: =('Donnees_USDA'!J706+'Donnees_USDA'!J707+'Donnees_USDA'!J710+'Donnees_USDA'!J711)/('Donnees_USDA'!J506+'Donnees_USDA'!J606+'Donnees_USDA'!J507+'Donnees_USDA'!J607+'Donnees_USDA'!J510+'Donnees_USDA'!J610+'Donnees_USDA'!J511+'Donnees_USDA'!J611) -> 0.042738822
A13: 2018/19 | B13: ='Donnees_USDA'!K706*'Donnees_USDA'!K806+'Donnees_USDA'!K708*'Donnees_USDA'!K808+'Donnees_USDA'!K713*'Donnees_USDA'!K813+'Donnees_USDA'!K709*'Donnees_USDA'!K809+'Donnees_USDA'!K714*'Donnees_USDA'!K814+'Donnees_USDA'!K715*'Donnees_USDA'!K815+'Donnees_USDA'!K716*'Donnees_USDA'!K816+'Donnees_USDA'!K722*'Donnees_USDA'!K822 -> 4786.8016 | C13: =('Donnees_USDA'!K506+'Donnees_USDA'!K606)*'Donnees_USDA'!K806+('Donnees_USDA'!K508+'Donnees_USDA'!K608)*'Donnees_USDA'!K808+('Donnees_USDA'!K513+'Donnees_USDA'!K613)*'Donnees_USDA'!K813+('Donnees_USDA'!K509+'Donnees_USDA'!K609)*'Donnees_USDA'!K809+('Donnees_USDA'!K514+'Donnees_USDA'!K614)*'Donnees_USDA'!K814+('Donnees_USDA'!K515+'Donnees_USDA'!K615)*'Donnees_USDA'!K815+('Donnees_USDA'!K516+'Donnees_USDA'!K616)*'Donnees_USDA'!K816+('Donnees_USDA'!K522+'Donnees_USDA'!K622)*'Donnees_USDA'!K822 -> 93063.474 | D13: =B13/C13 -> 0.051435879 | E13: ='Donnees_USDA'!K706*'Donnees_USDA'!K906+'Donnees_USDA'!K707*'Donnees_USDA'!K907+'Donnees_USDA'!K710*'Donnees_USDA'!K910+'Donnees_USDA'!K711*'Donnees_USDA'!K911 -> 4220.6736 | F13: =('Donnees_USDA'!K506+'Donnees_USDA'!K606)*'Donnees_USDA'!K906+('Donnees_USDA'!K507+'Donnees_USDA'!K607)*'Donnees_USDA'!K907+('Donnees_USDA'!K510+'Donnees_USDA'!K610)*'Donnees_USDA'!K910+('Donnees_USDA'!K511+'Donnees_USDA'!K611)*'Donnees_USDA'!K911 -> 59396.229 | G13: =E13/F13 -> 0.071059622 | H13: ='Prix_ICE'!J13 -> 104.98083 | I13: ='Prix_ICE'!L13 -> 1488.8368 | J13: =('Donnees_USDA'!K706+'Donnees_USDA'!K708+'Donnees_USDA'!K713+'Donnees_USDA'!K709+'Donnees_USDA'!K714+'Donnees_USDA'!K715+'Donnees_USDA'!K716+'Donnees_USDA'!K722)/('Donnees_USDA'!K506+'Donnees_USDA'!K606+'Donnees_USDA'!K508+'Donnees_USDA'!K608+'Donnees_USDA'!K513+'Donnees_USDA'!K613+'Donnees_USDA'!K509+'Donnees_USDA'!K609+'Donnees_USDA'!K514+'Donnees_USDA'!K614+'Donnees_USDA'!K515+'Donnees_USDA'!K615+'Donnees_USDA'!K516+'Donnees_USDA'!K616+'Donnees_USDA'!K522+'Donnees_USDA'!K622) -> 0.054994744 | K13: =('Donnees_USDA'!K706+'Donnees_USDA'!K707+'Donnees_USDA'!K710+'Donnees_USDA'!K711)/('Donnees_USDA'!K506+'Donnees_USDA'!K606+'Donnees_USDA'!K507+'Donnees_USDA'!K607+'Donnees_USDA'!K510+'Donnees_USDA'!K610+'Donnees_USDA'!K511+'Donnees_USDA'!K611) -> 0.075373309
A14: 2019/20 | B14: ='Donnees_USDA'!L706*'Donnees_USDA'!L806+'Donnees_USDA'!L708*'Donnees_USDA'!L808+'Donnees_USDA'!L713*'Donnees_USDA'!L813+'Donnees_USDA'!L709*'Donnees_USDA'!L809+'Donnees_USDA'!L714*'Donnees_USDA'!L814+'Donnees_USDA'!L715*'Donnees_USDA'!L815+'Donnees_USDA'!L716*'Donnees_USDA'!L816+'Donnees_USDA'!L722*'Donnees_USDA'!L822 -> 3458.3758 | C14: =('Donnees_USDA'!L506+'Donnees_USDA'!L606)*'Donnees_USDA'!L806+('Donnees_USDA'!L508+'Donnees_USDA'!L608)*'Donnees_USDA'!L808+('Donnees_USDA'!L513+'Donnees_USDA'!L613)*'Donnees_USDA'!L813+('Donnees_USDA'!L509+'Donnees_USDA'!L609)*'Donnees_USDA'!L809+('Donnees_USDA'!L514+'Donnees_USDA'!L614)*'Donnees_USDA'!L814+('Donnees_USDA'!L515+'Donnees_USDA'!L615)*'Donnees_USDA'!L815+('Donnees_USDA'!L516+'Donnees_USDA'!L616)*'Donnees_USDA'!L816+('Donnees_USDA'!L522+'Donnees_USDA'!L622)*'Donnees_USDA'!L822 -> 85253.277 | D14: =B14/C14 -> 0.040565899 | E14: ='Donnees_USDA'!L706*'Donnees_USDA'!L906+'Donnees_USDA'!L707*'Donnees_USDA'!L907+'Donnees_USDA'!L710*'Donnees_USDA'!L910+'Donnees_USDA'!L711*'Donnees_USDA'!L911 -> 5105.355 | F14: =('Donnees_USDA'!L506+'Donnees_USDA'!L606)*'Donnees_USDA'!L906+('Donnees_USDA'!L507+'Donnees_USDA'!L607)*'Donnees_USDA'!L907+('Donnees_USDA'!L510+'Donnees_USDA'!L610)*'Donnees_USDA'!L910+('Donnees_USDA'!L511+'Donnees_USDA'!L611)*'Donnees_USDA'!L911 -> 63771.361 | G14: =E14/F14 -> 0.080057175 | H14: ='Prix_ICE'!J14 -> 113.23667 | I14: ='Prix_ICE'!L14 -> 1305.5959 | J14: =('Donnees_USDA'!L706+'Donnees_USDA'!L708+'Donnees_USDA'!L713+'Donnees_USDA'!L709+'Donnees_USDA'!L714+'Donnees_USDA'!L715+'Donnees_USDA'!L716+'Donnees_USDA'!L722)/('Donnees_USDA'!L506+'Donnees_USDA'!L606+'Donnees_USDA'!L508+'Donnees_USDA'!L608+'Donnees_USDA'!L513+'Donnees_USDA'!L613+'Donnees_USDA'!L509+'Donnees_USDA'!L609+'Donnees_USDA'!L514+'Donnees_USDA'!L614+'Donnees_USDA'!L515+'Donnees_USDA'!L615+'Donnees_USDA'!L516+'Donnees_USDA'!L616+'Donnees_USDA'!L522+'Donnees_USDA'!L622) -> 0.039814332 | K14: =('Donnees_USDA'!L706+'Donnees_USDA'!L707+'Donnees_USDA'!L710+'Donnees_USDA'!L711)/('Donnees_USDA'!L506+'Donnees_USDA'!L606+'Donnees_USDA'!L507+'Donnees_USDA'!L607+'Donnees_USDA'!L510+'Donnees_USDA'!L610+'Donnees_USDA'!L511+'Donnees_USDA'!L611) -> 0.064437209
A15: 2020/21 | B15: ='Donnees_USDA'!M706*'Donnees_USDA'!M806+'Donnees_USDA'!M708*'Donnees_USDA'!M808+'Donnees_USDA'!M713*'Donnees_USDA'!M813+'Donnees_USDA'!M709*'Donnees_USDA'!M809+'Donnees_USDA'!M714*'Donnees_USDA'!M814+'Donnees_USDA'!M715*'Donnees_USDA'!M815+'Donnees_USDA'!M716*'Donnees_USDA'!M816+'Donnees_USDA'!M722*'Donnees_USDA'!M822 -> 5248.4174 | C15: =('Donnees_USDA'!M506+'Donnees_USDA'!M606)*'Donnees_USDA'!M806+('Donnees_USDA'!M508+'Donnees_USDA'!M608)*'Donnees_USDA'!M808+('Donnees_USDA'!M513+'Donnees_USDA'!M613)*'Donnees_USDA'!M813+('Donnees_USDA'!M509+'Donnees_USDA'!M609)*'Donnees_USDA'!M809+('Donnees_USDA'!M514+'Donnees_USDA'!M614)*'Donnees_USDA'!M814+('Donnees_USDA'!M515+'Donnees_USDA'!M615)*'Donnees_USDA'!M815+('Donnees_USDA'!M516+'Donnees_USDA'!M616)*'Donnees_USDA'!M816+('Donnees_USDA'!M522+'Donnees_USDA'!M622)*'Donnees_USDA'!M822 -> 91328.584 | D15: =B15/C15 -> 0.057467412 | E15: ='Donnees_USDA'!M706*'Donnees_USDA'!M906+'Donnees_USDA'!M707*'Donnees_USDA'!M907+'Donnees_USDA'!M710*'Donnees_USDA'!M910+'Donnees_USDA'!M711*'Donnees_USDA'!M911 -> 6612.2386 | F15: =('Donnees_USDA'!M506+'Donnees_USDA'!M606)*'Donnees_USDA'!M906+('Donnees_USDA'!M507+'Donnees_USDA'!M607)*'Donnees_USDA'!M907+('Donnees_USDA'!M510+'Donnees_USDA'!M610)*'Donnees_USDA'!M910+('Donnees_USDA'!M511+'Donnees_USDA'!M611)*'Donnees_USDA'!M911 -> 63450.725 | G15: =E15/F15 -> 0.10421061 | H15: ='Prix_ICE'!J15 -> 143.75333 | I15: ='Prix_ICE'!L15 -> 1540.9394 | J15: =('Donnees_USDA'!M706+'Donnees_USDA'!M708+'Donnees_USDA'!M713+'Donnees_USDA'!M709+'Donnees_USDA'!M714+'Donnees_USDA'!M715+'Donnees_USDA'!M716+'Donnees_USDA'!M722)/('Donnees_USDA'!M506+'Donnees_USDA'!M606+'Donnees_USDA'!M508+'Donnees_USDA'!M608+'Donnees_USDA'!M513+'Donnees_USDA'!M613+'Donnees_USDA'!M509+'Donnees_USDA'!M609+'Donnees_USDA'!M514+'Donnees_USDA'!M614+'Donnees_USDA'!M515+'Donnees_USDA'!M615+'Donnees_USDA'!M516+'Donnees_USDA'!M616+'Donnees_USDA'!M522+'Donnees_USDA'!M622) -> 0.05827333 | K15: =('Donnees_USDA'!M706+'Donnees_USDA'!M707+'Donnees_USDA'!M710+'Donnees_USDA'!M711)/('Donnees_USDA'!M506+'Donnees_USDA'!M606+'Donnees_USDA'!M507+'Donnees_USDA'!M607+'Donnees_USDA'!M510+'Donnees_USDA'!M610+'Donnees_USDA'!M511+'Donnees_USDA'!M611) -> 0.087876705
A16: 2021/22 | B16: ='Donnees_USDA'!N706*'Donnees_USDA'!N806+'Donnees_USDA'!N708*'Donnees_USDA'!N808+'Donnees_USDA'!N713*'Donnees_USDA'!N813+'Donnees_USDA'!N709*'Donnees_USDA'!N809+'Donnees_USDA'!N714*'Donnees_USDA'!N814+'Donnees_USDA'!N715*'Donnees_USDA'!N815+'Donnees_USDA'!N716*'Donnees_USDA'!N816+'Donnees_USDA'!N722*'Donnees_USDA'!N822 -> 1696.2479 | C16: =('Donnees_USDA'!N506+'Donnees_USDA'!N606)*'Donnees_USDA'!N806+('Donnees_USDA'!N508+'Donnees_USDA'!N608)*'Donnees_USDA'!N808+('Donnees_USDA'!N513+'Donnees_USDA'!N613)*'Donnees_USDA'!N813+('Donnees_USDA'!N509+'Donnees_USDA'!N609)*'Donnees_USDA'!N809+('Donnees_USDA'!N514+'Donnees_USDA'!N614)*'Donnees_USDA'!N814+('Donnees_USDA'!N515+'Donnees_USDA'!N615)*'Donnees_USDA'!N815+('Donnees_USDA'!N516+'Donnees_USDA'!N616)*'Donnees_USDA'!N816+('Donnees_USDA'!N522+'Donnees_USDA'!N622)*'Donnees_USDA'!N822 -> 81137.936 | D16: =B16/C16 -> 0.020905732 | E16: ='Donnees_USDA'!N706*'Donnees_USDA'!N906+'Donnees_USDA'!N707*'Donnees_USDA'!N907+'Donnees_USDA'!N710*'Donnees_USDA'!N910+'Donnees_USDA'!N711*'Donnees_USDA'!N911 -> 4964.9386 | F16: =('Donnees_USDA'!N506+'Donnees_USDA'!N606)*'Donnees_USDA'!N906+('Donnees_USDA'!N507+'Donnees_USDA'!N607)*'Donnees_USDA'!N907+('Donnees_USDA'!N510+'Donnees_USDA'!N610)*'Donnees_USDA'!N910+('Donnees_USDA'!N511+'Donnees_USDA'!N611)*'Donnees_USDA'!N911 -> 69955.962 | G16: =E16/F16 -> 0.070972345 | H16: ='Prix_ICE'!J16 -> 224.0875 | I16: ='Prix_ICE'!L16 -> 2150.1501 | J16: =('Donnees_USDA'!N706+'Donnees_USDA'!N708+'Donnees_USDA'!N713+'Donnees_USDA'!N709+'Donnees_USDA'!N714+'Donnees_USDA'!N715+'Donnees_USDA'!N716+'Donnees_USDA'!N722)/('Donnees_USDA'!N506+'Donnees_USDA'!N606+'Donnees_USDA'!N508+'Donnees_USDA'!N608+'Donnees_USDA'!N513+'Donnees_USDA'!N613+'Donnees_USDA'!N509+'Donnees_USDA'!N609+'Donnees_USDA'!N514+'Donnees_USDA'!N614+'Donnees_USDA'!N515+'Donnees_USDA'!N615+'Donnees_USDA'!N516+'Donnees_USDA'!N616+'Donnees_USDA'!N522+'Donnees_USDA'!N622) -> 0.01816973 | K16: =('Donnees_USDA'!N706+'Donnees_USDA'!N707+'Donnees_USDA'!N710+'Donnees_USDA'!N711)/('Donnees_USDA'!N506+'Donnees_USDA'!N606+'Donnees_USDA'!N507+'Donnees_USDA'!N607+'Donnees_USDA'!N510+'Donnees_USDA'!N610+'Donnees_USDA'!N511+'Donnees_USDA'!N611) -> 0.050094316
A17: 2022/23 | B17: ='Donnees_USDA'!O706*'Donnees_USDA'!O806+'Donnees_USDA'!O708*'Donnees_USDA'!O808+'Donnees_USDA'!O713*'Donnees_USDA'!O813+'Donnees_USDA'!O709*'Donnees_USDA'!O809+'Donnees_USDA'!O714*'Donnees_USDA'!O814+'Donnees_USDA'!O715*'Donnees_USDA'!O815+'Donnees_USDA'!O716*'Donnees_USDA'!O816+'Donnees_USDA'!O722*'Donnees_USDA'!O822 -> 4348.3637 | C17: =('Donnees_USDA'!O506+'Donnees_USDA'!O606)*'Donnees_USDA'!O806+('Donnees_USDA'!O508+'Donnees_USDA'!O608)*'Donnees_USDA'!O808+('Donnees_USDA'!O513+'Donnees_USDA'!O613)*'Donnees_USDA'!O813+('Donnees_USDA'!O509+'Donnees_USDA'!O609)*'Donnees_USDA'!O809+('Donnees_USDA'!O514+'Donnees_USDA'!O614)*'Donnees_USDA'!O814+('Donnees_USDA'!O515+'Donnees_USDA'!O615)*'Donnees_USDA'!O815+('Donnees_USDA'!O516+'Donnees_USDA'!O616)*'Donnees_USDA'!O816+('Donnees_USDA'!O522+'Donnees_USDA'!O622)*'Donnees_USDA'!O822 -> 76210.952 | D17: =B17/C17 -> 0.05705694 | E17: ='Donnees_USDA'!O706*'Donnees_USDA'!O906+'Donnees_USDA'!O707*'Donnees_USDA'!O907+'Donnees_USDA'!O710*'Donnees_USDA'!O910+'Donnees_USDA'!O711*'Donnees_USDA'!O911 -> 3334.2372 | F17: =('Donnees_USDA'!O506+'Donnees_USDA'!O606)*'Donnees_USDA'!O906+('Donnees_USDA'!O507+'Donnees_USDA'!O607)*'Donnees_USDA'!O907+('Donnees_USDA'!O510+'Donnees_USDA'!O610)*'Donnees_USDA'!O910+('Donnees_USDA'!O511+'Donnees_USDA'!O611)*'Donnees_USDA'!O911 -> 68518.664 | G17: =E17/F17 -> 0.048661738 | H17: ='Prix_ICE'!J17 -> 171.19 | I17: ='Prix_ICE'!L17 -> 2217.0787 | J17: =('Donnees_USDA'!O706+'Donnees_USDA'!O708+'Donnees_USDA'!O713+'Donnees_USDA'!O709+'Donnees_USDA'!O714+'Donnees_USDA'!O715+'Donnees_USDA'!O716+'Donnees_USDA'!O722)/('Donnees_USDA'!O506+'Donnees_USDA'!O606+'Donnees_USDA'!O508+'Donnees_USDA'!O608+'Donnees_USDA'!O513+'Donnees_USDA'!O613+'Donnees_USDA'!O509+'Donnees_USDA'!O609+'Donnees_USDA'!O514+'Donnees_USDA'!O614+'Donnees_USDA'!O515+'Donnees_USDA'!O615+'Donnees_USDA'!O516+'Donnees_USDA'!O616+'Donnees_USDA'!O522+'Donnees_USDA'!O622) -> 0.061331764 | K17: =('Donnees_USDA'!O706+'Donnees_USDA'!O707+'Donnees_USDA'!O710+'Donnees_USDA'!O711)/('Donnees_USDA'!O506+'Donnees_USDA'!O606+'Donnees_USDA'!O507+'Donnees_USDA'!O607+'Donnees_USDA'!O510+'Donnees_USDA'!O610+'Donnees_USDA'!O511+'Donnees_USDA'!O611) -> 0.05881707
A18: 2023/24 | B18: ='Donnees_USDA'!P706*'Donnees_USDA'!P806+'Donnees_USDA'!P708*'Donnees_USDA'!P808+'Donnees_USDA'!P713*'Donnees_USDA'!P813+'Donnees_USDA'!P709*'Donnees_USDA'!P809+'Donnees_USDA'!P714*'Donnees_USDA'!P814+'Donnees_USDA'!P715*'Donnees_USDA'!P815+'Donnees_USDA'!P716*'Donnees_USDA'!P816+'Donnees_USDA'!P722*'Donnees_USDA'!P822 -> 2497.2471 | C18: =('Donnees_USDA'!P506+'Donnees_USDA'!P606)*'Donnees_USDA'!P806+('Donnees_USDA'!P508+'Donnees_USDA'!P608)*'Donnees_USDA'!P808+('Donnees_USDA'!P513+'Donnees_USDA'!P613)*'Donnees_USDA'!P813+('Donnees_USDA'!P509+'Donnees_USDA'!P609)*'Donnees_USDA'!P809+('Donnees_USDA'!P514+'Donnees_USDA'!P614)*'Donnees_USDA'!P814+('Donnees_USDA'!P515+'Donnees_USDA'!P615)*'Donnees_USDA'!P815+('Donnees_USDA'!P516+'Donnees_USDA'!P616)*'Donnees_USDA'!P816+('Donnees_USDA'!P522+'Donnees_USDA'!P622)*'Donnees_USDA'!P822 -> 89277.803 | D18: =B18/C18 -> 0.027971646 | E18: ='Donnees_USDA'!P706*'Donnees_USDA'!P906+'Donnees_USDA'!P707*'Donnees_USDA'!P907+'Donnees_USDA'!P710*'Donnees_USDA'!P910+'Donnees_USDA'!P711*'Donnees_USDA'!P911 -> 2136.0836 | F18: =('Donnees_USDA'!P506+'Donnees_USDA'!P606)*'Donnees_USDA'!P906+('Donnees_USDA'!P507+'Donnees_USDA'!P607)*'Donnees_USDA'!P907+('Donnees_USDA'!P510+'Donnees_USDA'!P610)*'Donnees_USDA'!P910+('Donnees_USDA'!P511+'Donnees_USDA'!P611)*'Donnees_USDA'!P911 -> 63557.088 | G18: =E18/F18 -> 0.033608897 | H18: ='Prix_ICE'!J18 -> 204.00167 | I18: ='Prix_ICE'!L18 -> 3504.2477 | J18: =('Donnees_USDA'!P706+'Donnees_USDA'!P708+'Donnees_USDA'!P713+'Donnees_USDA'!P709+'Donnees_USDA'!P714+'Donnees_USDA'!P715+'Donnees_USDA'!P716+'Donnees_USDA'!P722)/('Donnees_USDA'!P506+'Donnees_USDA'!P606+'Donnees_USDA'!P508+'Donnees_USDA'!P608+'Donnees_USDA'!P513+'Donnees_USDA'!P613+'Donnees_USDA'!P509+'Donnees_USDA'!P609+'Donnees_USDA'!P514+'Donnees_USDA'!P614+'Donnees_USDA'!P515+'Donnees_USDA'!P615+'Donnees_USDA'!P516+'Donnees_USDA'!P616+'Donnees_USDA'!P522+'Donnees_USDA'!P622) -> 0.028224766 | K18: =('Donnees_USDA'!P706+'Donnees_USDA'!P707+'Donnees_USDA'!P710+'Donnees_USDA'!P711)/('Donnees_USDA'!P506+'Donnees_USDA'!P606+'Donnees_USDA'!P507+'Donnees_USDA'!P607+'Donnees_USDA'!P510+'Donnees_USDA'!P610+'Donnees_USDA'!P511+'Donnees_USDA'!P611) -> 0.032448559
A19: 2024/25 | B19: ='Donnees_USDA'!Q706*'Donnees_USDA'!Q806+'Donnees_USDA'!Q708*'Donnees_USDA'!Q808+'Donnees_USDA'!Q713*'Donnees_USDA'!Q813+'Donnees_USDA'!Q709*'Donnees_USDA'!Q809+'Donnees_USDA'!Q714*'Donnees_USDA'!Q814+'Donnees_USDA'!Q715*'Donnees_USDA'!Q815+'Donnees_USDA'!Q716*'Donnees_USDA'!Q816+'Donnees_USDA'!Q722*'Donnees_USDA'!Q822 -> 2068.8471 | C19: =('Donnees_USDA'!Q506+'Donnees_USDA'!Q606)*'Donnees_USDA'!Q806+('Donnees_USDA'!Q508+'Donnees_USDA'!Q608)*'Donnees_USDA'!Q808+('Donnees_USDA'!Q513+'Donnees_USDA'!Q613)*'Donnees_USDA'!Q813+('Donnees_USDA'!Q509+'Donnees_USDA'!Q609)*'Donnees_USDA'!Q809+('Donnees_USDA'!Q514+'Donnees_USDA'!Q614)*'Donnees_USDA'!Q814+('Donnees_USDA'!Q515+'Donnees_USDA'!Q615)*'Donnees_USDA'!Q815+('Donnees_USDA'!Q516+'Donnees_USDA'!Q616)*'Donnees_USDA'!Q816+('Donnees_USDA'!Q522+'Donnees_USDA'!Q622)*'Donnees_USDA'!Q822 -> 92890.543 | D19: =B19/C19 -> 0.022271881 | E19: ='Donnees_USDA'!Q706*'Donnees_USDA'!Q906+'Donnees_USDA'!Q707*'Donnees_USDA'!Q907+'Donnees_USDA'!Q710*'Donnees_USDA'!Q910+'Donnees_USDA'!Q711*'Donnees_USDA'!Q911 -> 2125.8946 | F19: =('Donnees_USDA'!Q506+'Donnees_USDA'!Q606)*'Donnees_USDA'!Q906+('Donnees_USDA'!Q507+'Donnees_USDA'!Q607)*'Donnees_USDA'!Q907+('Donnees_USDA'!Q510+'Donnees_USDA'!Q610)*'Donnees_USDA'!Q910+('Donnees_USDA'!Q511+'Donnees_USDA'!Q611)*'Donnees_USDA'!Q911 -> 66572.739 | G19: =E19/F19 -> 0.03193341 | H19: ='Prix_ICE'!J19 -> 333.06 | I19: ='Prix_ICE'!L19 -> 4701.7435 | J19: =('Donnees_USDA'!Q706+'Donnees_USDA'!Q708+'Donnees_USDA'!Q713+'Donnees_USDA'!Q709+'Donnees_USDA'!Q714+'Donnees_USDA'!Q715+'Donnees_USDA'!Q716+'Donnees_USDA'!Q722)/('Donnees_USDA'!Q506+'Donnees_USDA'!Q606+'Donnees_USDA'!Q508+'Donnees_USDA'!Q608+'Donnees_USDA'!Q513+'Donnees_USDA'!Q613+'Donnees_USDA'!Q509+'Donnees_USDA'!Q609+'Donnees_USDA'!Q514+'Donnees_USDA'!Q614+'Donnees_USDA'!Q515+'Donnees_USDA'!Q615+'Donnees_USDA'!Q516+'Donnees_USDA'!Q616+'Donnees_USDA'!Q522+'Donnees_USDA'!Q622) -> 0.020669026 | K19: =('Donnees_USDA'!Q706+'Donnees_USDA'!Q707+'Donnees_USDA'!Q710+'Donnees_USDA'!Q711)/('Donnees_USDA'!Q506+'Donnees_USDA'!Q606+'Donnees_USDA'!Q507+'Donnees_USDA'!Q607+'Donnees_USDA'!Q510+'Donnees_USDA'!Q610+'Donnees_USDA'!Q511+'Donnees_USDA'!Q611) -> 0.0253996
A20: 2025/26 | B20: ='Donnees_USDA'!R706*'Donnees_USDA'!R806+'Donnees_USDA'!R708*'Donnees_USDA'!R808+'Donnees_USDA'!R713*'Donnees_USDA'!R813+'Donnees_USDA'!R709*'Donnees_USDA'!R809+'Donnees_USDA'!R714*'Donnees_USDA'!R814+'Donnees_USDA'!R715*'Donnees_USDA'!R815+'Donnees_USDA'!R716*'Donnees_USDA'!R816+'Donnees_USDA'!R722*'Donnees_USDA'!R822 -> 4007.4609 | C20: =('Donnees_USDA'!R506+'Donnees_USDA'!R606)*'Donnees_USDA'!R806+('Donnees_USDA'!R508+'Donnees_USDA'!R608)*'Donnees_USDA'!R808+('Donnees_USDA'!R513+'Donnees_USDA'!R613)*'Donnees_USDA'!R813+('Donnees_USDA'!R509+'Donnees_USDA'!R609)*'Donnees_USDA'!R809+('Donnees_USDA'!R514+'Donnees_USDA'!R614)*'Donnees_USDA'!R814+('Donnees_USDA'!R515+'Donnees_USDA'!R615)*'Donnees_USDA'!R815+('Donnees_USDA'!R516+'Donnees_USDA'!R616)*'Donnees_USDA'!R816+('Donnees_USDA'!R522+'Donnees_USDA'!R622)*'Donnees_USDA'!R822 -> 83848.06 | D20: =B20/C20 -> 0.047794318 | E20: ='Donnees_USDA'!R706*'Donnees_USDA'!R906+'Donnees_USDA'!R707*'Donnees_USDA'!R907+'Donnees_USDA'!R710*'Donnees_USDA'!R910+'Donnees_USDA'!R711*'Donnees_USDA'!R911 -> 3157.6538 | F20: =('Donnees_USDA'!R506+'Donnees_USDA'!R606)*'Donnees_USDA'!R906+('Donnees_USDA'!R507+'Donnees_USDA'!R607)*'Donnees_USDA'!R907+('Donnees_USDA'!R510+'Donnees_USDA'!R610)*'Donnees_USDA'!R910+('Donnees_USDA'!R511+'Donnees_USDA'!R611)*'Donnees_USDA'!R911 -> 74064.971 | G20: =E20/F20 -> 0.042633566 | H20: ='Prix_ICE'!J20 -> 312.21 | I20: ='Prix_ICE'!L20 -> 3788.4636 | J20: =('Donnees_USDA'!R706+'Donnees_USDA'!R708+'Donnees_USDA'!R713+'Donnees_USDA'!R709+'Donnees_USDA'!R714+'Donnees_USDA'!R715+'Donnees_USDA'!R716+'Donnees_USDA'!R722)/('Donnees_USDA'!R506+'Donnees_USDA'!R606+'Donnees_USDA'!R508+'Donnees_USDA'!R608+'Donnees_USDA'!R513+'Donnees_USDA'!R613+'Donnees_USDA'!R509+'Donnees_USDA'!R609+'Donnees_USDA'!R514+'Donnees_USDA'!R614+'Donnees_USDA'!R515+'Donnees_USDA'!R615+'Donnees_USDA'!R516+'Donnees_USDA'!R616+'Donnees_USDA'!R522+'Donnees_USDA'!R622) -> 0.051119739 | K20: =('Donnees_USDA'!R706+'Donnees_USDA'!R707+'Donnees_USDA'!R710+'Donnees_USDA'!R711)/('Donnees_USDA'!R506+'Donnees_USDA'!R606+'Donnees_USDA'!R507+'Donnees_USDA'!R607+'Donnees_USDA'!R510+'Donnees_USDA'!R610+'Donnees_USDA'!R511+'Donnees_USDA'!R611) -> 0.049627075
A21: 2026/27 (prév.) | B21: ='Donnees_USDA'!S706*'Donnees_USDA'!S806+'Donnees_USDA'!S708*'Donnees_USDA'!S808+'Donnees_USDA'!S713*'Donnees_USDA'!S813+'Donnees_USDA'!S709*'Donnees_USDA'!S809+'Donnees_USDA'!S714*'Donnees_USDA'!S814+'Donnees_USDA'!S715*'Donnees_USDA'!S815+'Donnees_USDA'!S716*'Donnees_USDA'!S816+'Donnees_USDA'!S722*'Donnees_USDA'!S822 -> 4559.0158 | C21: =('Donnees_USDA'!S506+'Donnees_USDA'!S606)*'Donnees_USDA'!S806+('Donnees_USDA'!S508+'Donnees_USDA'!S608)*'Donnees_USDA'!S808+('Donnees_USDA'!S513+'Donnees_USDA'!S613)*'Donnees_USDA'!S813+('Donnees_USDA'!S509+'Donnees_USDA'!S609)*'Donnees_USDA'!S809+('Donnees_USDA'!S514+'Donnees_USDA'!S614)*'Donnees_USDA'!S814+('Donnees_USDA'!S515+'Donnees_USDA'!S615)*'Donnees_USDA'!S815+('Donnees_USDA'!S516+'Donnees_USDA'!S616)*'Donnees_USDA'!S816+('Donnees_USDA'!S522+'Donnees_USDA'!S622)*'Donnees_USDA'!S822 -> 96782.217 | D21: =B21/C21 -> 0.047105925 | E21: ='Donnees_USDA'!S706*'Donnees_USDA'!S906+'Donnees_USDA'!S707*'Donnees_USDA'!S907+'Donnees_USDA'!S710*'Donnees_USDA'!S910+'Donnees_USDA'!S711*'Donnees_USDA'!S911 -> 2840.5962 | F21: =('Donnees_USDA'!S506+'Donnees_USDA'!S606)*'Donnees_USDA'!S906+('Donnees_USDA'!S507+'Donnees_USDA'!S607)*'Donnees_USDA'!S907+('Donnees_USDA'!S510+'Donnees_USDA'!S610)*'Donnees_USDA'!S910+('Donnees_USDA'!S511+'Donnees_USDA'!S611)*'Donnees_USDA'!S911 -> 74398.914 | G21: =E21/F21 -> 0.038180614 | J21: =('Donnees_USDA'!S706+'Donnees_USDA'!S708+'Donnees_USDA'!S713+'Donnees_USDA'!S709+'Donnees_USDA'!S714+'Donnees_USDA'!S715+'Donnees_USDA'!S716+'Donnees_USDA'!S722)/('Donnees_USDA'!S506+'Donnees_USDA'!S606+'Donnees_USDA'!S508+'Donnees_USDA'!S608+'Donnees_USDA'!S513+'Donnees_USDA'!S613+'Donnees_USDA'!S509+'Donnees_USDA'!S609+'Donnees_USDA'!S514+'Donnees_USDA'!S614+'Donnees_USDA'!S515+'Donnees_USDA'!S615+'Donnees_USDA'!S516+'Donnees_USDA'!S616+'Donnees_USDA'!S522+'Donnees_USDA'!S622) -> 0.04964905 | K21: =('Donnees_USDA'!S706+'Donnees_USDA'!S707+'Donnees_USDA'!S710+'Donnees_USDA'!S711)/('Donnees_USDA'!S506+'Donnees_USDA'!S606+'Donnees_USDA'!S507+'Donnees_USDA'!S607+'Donnees_USDA'!S510+'Donnees_USDA'!S610+'Donnees_USDA'!S511+'Donnees_USDA'!S611) -> 0.047140409

Sheet 4_Deux_pays
A1: 4 — STU pays par pays (2 colonnes par an) : Brésil + Colombie (arabica) et Vietnam + Brésil (robusta)
A2: STU pays = stocks de fin USDA ÷ (consommation domestique + exportations) — même ratio que la colonne « Stocks / Use » du bilan.
A3: Le ratio d'un pays ne dépend pas de la répartition arabica/robusta (stocks et utilisation sont répartis dans la même proportion).
A4: Campagne | B4: STU Brésil | C4: STU Colombie | D4: STU Vietnam | E4: KC1 NY (US c/lb) | F4: DF1 Londres (US$/t)
A5: 2010/11 | B5: ='Donnees_USDA'!C706/('Donnees_USDA'!C506+'Donnees_USDA'!C606) -> 0.053389675 | C5: ='Donnees_USDA'!C708/('Donnees_USDA'!C508+'Donnees_USDA'!C608) -> 0.010415571 | D5: ='Donnees_USDA'!C707/('Donnees_USDA'!C507+'Donnees_USDA'!C607) -> 0.040046053 | E5: ='Prix_ICE'!J5 -> 249.66 | F5: ='Prix_ICE'!L5 -> 2219.0813
A6: 2011/12 | B6: ='Donnees_USDA'!D706/('Donnees_USDA'!D506+'Donnees_USDA'!D606) -> 0.044878479 | C6: ='Donnees_USDA'!D708/('Donnees_USDA'!D508+'Donnees_USDA'!D608) -> 0.028886311 | D6: ='Donnees_USDA'!D707/('Donnees_USDA'!D507+'Donnees_USDA'!D607) -> 0.041666667 | E6: ='Prix_ICE'!J6 -> 197.84167 | F6: ='Prix_ICE'!L6 -> 2014.676
A7: 2012/13 | B7: ='Donnees_USDA'!E706/('Donnees_USDA'!E506+'Donnees_USDA'!E606) -> 0.17860942 | C7: ='Donnees_USDA'!E708/('Donnees_USDA'!E508+'Donnees_USDA'!E608) -> 0.07667827 | D7: ='Donnees_USDA'!E707/('Donnees_USDA'!E507+'Donnees_USDA'!E607) -> 0.073522744 | E7: ='Prix_ICE'!J7 -> 140.69833 | F7: ='Prix_ICE'!L7 -> 1950.6685
A8: 2013/14 | B8: ='Donnees_USDA'!F706/('Donnees_USDA'!F506+'Donnees_USDA'!F606) -> 0.21977335 | C8: ='Donnees_USDA'!F708/('Donnees_USDA'!F508+'Donnees_USDA'!F608) -> 0.077876823 | D8: ='Donnees_USDA'!F707/('Donnees_USDA'!F507+'Donnees_USDA'!F607) -> 0.07030399 | E8: ='Prix_ICE'!J8 -> 161.4675 | F8: ='Prix_ICE'!L8 -> 1893.2013
A9: 2014/15 | B9: ='Donnees_USDA'!G706/('Donnees_USDA'!G506+'Donnees_USDA'!G606) -> 0.16326566 | C9: ='Donnees_USDA'!G708/('Donnees_USDA'!G508+'Donnees_USDA'!G608) -> 0.048552822 | D9: ='Donnees_USDA'!G707/('Donnees_USDA'!G507+'Donnees_USDA'!G607) -> 0.26639758 | E9: ='Prix_ICE'!J9 -> 154.02083 | F9: ='Prix_ICE'!L9 -> 1849.9172
A10: 2015/16 | B10: ='Donnees_USDA'!H706/('Donnees_USDA'!H506+'Donnees_USDA'!H606) -> 0.042058229 | C10: ='Donnees_USDA'!H708/('Donnees_USDA'!H508+'Donnees_USDA'!H608) -> 0.081926838 | D10: ='Donnees_USDA'!H707/('Donnees_USDA'!H507+'Donnees_USDA'!H607) -> 0.13254457 | E10: ='Prix_ICE'!J10 -> 131.8325 | F10: ='Prix_ICE'!L10 -> 1632.9272
A11: 2016/17 | B11: ='Donnees_USDA'!I706/('Donnees_USDA'!I506+'Donnees_USDA'!I606) -> 0.069974043 | C11: ='Donnees_USDA'!I708/('Donnees_USDA'!I508+'Donnees_USDA'!I608) -> 0.058270306 | D11: ='Donnees_USDA'!I707/('Donnees_USDA'!I507+'Donnees_USDA'!I607) -> 0.091752225 | E11: ='Prix_ICE'!J11 -> 143.77167 | F11: ='Prix_ICE'!L11 -> 2097.1105
A12: 2017/18 | B12: ='Donnees_USDA'!J706/('Donnees_USDA'!J506+'Donnees_USDA'!J606) -> 0.058913644 | C12: ='Donnees_USDA'!J708/('Donnees_USDA'!J508+'Donnees_USDA'!J608) -> 0.077286957 | D12: ='Donnees_USDA'!J707/('Donnees_USDA'!J507+'Donnees_USDA'!J607) -> 0.0077469729 | E12: ='Prix_ICE'!J12 -> 120.60083 | F12: ='Prix_ICE'!L12 -> 1725.8888
A13: 2018/19 | B13: ='Donnees_USDA'!K706/('Donnees_USDA'!K506+'Donnees_USDA'!K606) -> 0.078234766 | C13: ='Donnees_USDA'!K708/('Donnees_USDA'!K508+'Donnees_USDA'!K608) -> 0.035521236 | D13: ='Donnees_USDA'!K707/('Donnees_USDA'!K507+'Donnees_USDA'!K607) -> 0.017787446 | E13: ='Prix_ICE'!J13 -> 104.98083 | F13: ='Prix_ICE'!L13 -> 1488.8368
A14: 2019/20 | B14: ='Donnees_USDA'!L706/('Donnees_USDA'!L506+'Donnees_USDA'!L606) -> 0.037517787 | C14: ='Donnees_USDA'!L708/('Donnees_USDA'!L508+'Donnees_USDA'!L608) -> 0.057645467 | D14: ='Donnees_USDA'!L707/('Donnees_USDA'!L507+'Donnees_USDA'!L607) -> 0.070005916 | E14: ='Prix_ICE'!J14 -> 113.23667 | F14: ='Prix_ICE'!L14 -> 1305.5959
A15: 2020/21 | B15: ='Donnees_USDA'!M706/('Donnees_USDA'!M506+'Donnees_USDA'!M606) -> 0.064601575 | C15: ='Donnees_USDA'!M708/('Donnees_USDA'!M508+'Donnees_USDA'!M608) -> 0.083249073 | D15: ='Donnees_USDA'!M707/('Donnees_USDA'!M507+'Donnees_USDA'!M607) -> 0.13062099 | E15: ='Prix_ICE'!J15 -> 143.75333 | F15: ='Prix_ICE'!L15 -> 1540.9394
A16: 2021/22 | B16: ='Donnees_USDA'!N706/('Donnees_USDA'!N506+'Donnees_USDA'!N606) -> 0.0087061669 | C16: ='Donnees_USDA'!N708/('Donnees_USDA'!N508+'Donnees_USDA'!N608) -> 0.052377671 | D16: ='Donnees_USDA'!N707/('Donnees_USDA'!N507+'Donnees_USDA'!N607) -> 0.11114561 | E16: ='Prix_ICE'!J16 -> 224.0875 | F16: ='Prix_ICE'!L16 -> 2150.1501
A17: 2022/23 | B17: ='Donnees_USDA'!O706/('Donnees_USDA'!O506+'Donnees_USDA'!O606) -> 0.078846318 | C17: ='Donnees_USDA'!O708/('Donnees_USDA'!O508+'Donnees_USDA'!O608) -> 0.069357367 | D17: ='Donnees_USDA'!O707/('Donnees_USDA'!O507+'Donnees_USDA'!O607) -> 0.026601141 | E17: ='Prix_ICE'!J17 -> 171.19 | F17: ='Prix_ICE'!L17 -> 2217.0787
A18: 2023/24 | B18: ='Donnees_USDA'!P706/('Donnees_USDA'!P506+'Donnees_USDA'!P606) -> 0.030256857 | C18: ='Donnees_USDA'!P708/('Donnees_USDA'!P508+'Donnees_USDA'!P608) -> 0.047731333 | D18: ='Donnees_USDA'!P707/('Donnees_USDA'!P507+'Donnees_USDA'!P607) -> 0.031413428 | E18: ='Prix_ICE'!J18 -> 204.00167 | F18: ='Prix_ICE'!L18 -> 3504.2477
A19: 2024/25 | B19: ='Donnees_USDA'!Q706/('Donnees_USDA'!Q506+'Donnees_USDA'!Q606) -> 0.014313549 | C19: ='Donnees_USDA'!Q708/('Donnees_USDA'!Q508+'Donnees_USDA'!Q608) -> 0.059384259 | D19: ='Donnees_USDA'!Q707/('Donnees_USDA'!Q507+'Donnees_USDA'!Q607) -> 0.0363 | E19: ='Prix_ICE'!J19 -> 333.06 | F19: ='Prix_ICE'!L19 -> 4701.7435
A20: 2025/26 | B20: ='Donnees_USDA'!R706/('Donnees_USDA'!R506+'Donnees_USDA'!R606) -> 0.06475478 | C20: ='Donnees_USDA'!R708/('Donnees_USDA'!R508+'Donnees_USDA'!R608) -> 0.05769487 | D20: ='Donnees_USDA'!R707/('Donnees_USDA'!R507+'Donnees_USDA'!R607) -> 0.020628743 | E20: ='Prix_ICE'!J20 -> 312.21 | F20: ='Prix_ICE'!L20 -> 3788.4636
A21: 2026/27 (prév.) | B21: ='Donnees_USDA'!S706/('Donnees_USDA'!S506+'Donnees_USDA'!S606) -> 0.061922754 | C21: ='Donnees_USDA'!S708/('Donnees_USDA'!S508+'Donnees_USDA'!S608) -> 0.042948718 | D21: ='Donnees_USDA'!S707/('Donnees_USDA'!S507+'Donnees_USDA'!S607) -> 0.014403535

Sheet 5_Bresil_Vietnam
A1: 5 — Un seul pays : BRÉSIL (arabica, KC1) et VIETNAM (robusta, DF1)
A2: STU = stocks de fin ÷ (conso domestique + exportations), données USDA par pays (campagne locale : Brésil juil.–juin, Vietnam oct.–sept.).
A3: Attention : les stocks USDA du Brésil sont une estimation résiduelle (CONAB et le privé publient des chiffres différents).
A4: Campagne | B4: Stocks fin Brésil | C4: Conso Brésil | D4: Export Brésil | E4: STU BRÉSIL | F4: KC1 NY (US c/lb) | G4: Stocks fin Vietnam | H4: Conso Vietnam | I4: Export Vietnam | J4: STU VIETNAM | K4: DF1 Londres (US$/t)
A5: 2010/11 | B5: ='Donnees_USDA'!C706 -> 2906 | C5: ='Donnees_USDA'!C506 -> 19420 | D5: ='Donnees_USDA'!C606 -> 35010 | E5: =B5/(C5+D5) -> 0.053389675 | F5: ='Prix_ICE'!J5 -> 249.66 | G5: ='Donnees_USDA'!C707 -> 800 | H5: ='Donnees_USDA'!C507 -> 1337 | I5: ='Donnees_USDA'!C607 -> 18640 | J5: =G5/(H5+I5) -> 0.040046053 | K5: ='Prix_ICE'!L5 -> 2219.0813
A6: 2011/12 | B6: ='Donnees_USDA'!D706 -> 2238 | C6: ='Donnees_USDA'!D506 -> 20025 | D6: ='Donnees_USDA'!D606 -> 29843 | E6: =B6/(C6+D6) -> 0.044878479 | F6: ='Prix_ICE'!J6 -> 197.84167 | G6: ='Donnees_USDA'!D707 -> 1090 | H6: ='Donnees_USDA'!D507 -> 1665 | I6: ='Donnees_USDA'!D607 -> 24495 | J6: =G6/(H6+I6) -> 0.041666667 | K6: ='Prix_ICE'!L6 -> 2014.676
A7: 2012/13 | B7: ='Donnees_USDA'!E706 -> 9068 | C7: ='Donnees_USDA'!E506 -> 20110 | D7: ='Donnees_USDA'!E606 -> 30660 | E7: =B7/(C7+D7) -> 0.17860942 | F7: ='Prix_ICE'!J7 -> 140.69833 | G7: ='Donnees_USDA'!E707 -> 1946 | H7: ='Donnees_USDA'!E507 -> 1825 | I7: ='Donnees_USDA'!E607 -> 24643 | J7: =G7/(H7+I7) -> 0.073522744 | K7: ='Prix_ICE'!L7 -> 1950.6685
A8: 2013/14 | B8: ='Donnees_USDA'!F706 -> 11946 | C8: ='Donnees_USDA'!F506 -> 20210 | D8: ='Donnees_USDA'!F606 -> 34146 | E8: =B8/(C8+D8) -> 0.21977335 | F8: ='Prix_ICE'!J8 -> 161.4675 | G8: ='Donnees_USDA'!F707 -> 2130 | H8: ='Donnees_USDA'!F507 -> 2008 | I8: ='Donnees_USDA'!F607 -> 28289 | J8: =G8/(H8+I8) -> 0.07030399 | K8: ='Prix_ICE'!L8 -> 1893.2013
A9: 2014/15 | B9: ='Donnees_USDA'!G706 -> 9305 | C9: ='Donnees_USDA'!G506 -> 20420 | D9: ='Donnees_USDA'!G606 -> 36573 | E9: =B9/(C9+D9) -> 0.16326566 | F9: ='Prix_ICE'!J9 -> 154.02083 | G9: ='Donnees_USDA'!G707 -> 6336 | H9: ='Donnees_USDA'!G507 -> 2217 | I9: ='Donnees_USDA'!G607 -> 21567 | J9: =G9/(H9+I9) -> 0.26639758 | K9: ='Prix_ICE'!L9 -> 1849.9172
A10: 2015/16 | B10: ='Donnees_USDA'!H706 -> 2372 | C10: ='Donnees_USDA'!H506 -> 20855 | D10: ='Donnees_USDA'!H606 -> 35543 | E10: =B10/(C10+D10) -> 0.042058229 | F10: ='Prix_ICE'!J10 -> 131.8325 | G10: ='Donnees_USDA'!H707 -> 4201 | H10: ='Donnees_USDA'!H507 -> 2630 | I10: ='Donnees_USDA'!H607 -> 29065 | J10: =G10/(H10+I10) -> 0.13254457 | K10: ='Prix_ICE'!L10 -> 1632.9272
A11: 2016/17 | B11: ='Donnees_USDA'!I706 -> 3828 | C11: ='Donnees_USDA'!I506 -> 21625 | D11: ='Donnees_USDA'!I606 -> 33081 | E11: =B11/(C11+D11) -> 0.069974043 | F11: ='Prix_ICE'!J11 -> 143.77167 | G11: ='Donnees_USDA'!I707 -> 2681 | H11: ='Donnees_USDA'!I507 -> 2770 | I11: ='Donnees_USDA'!I607 -> 26450 | J11: =G11/(H11+I11) -> 0.091752225 | K11: ='Prix_ICE'!L11 -> 2097.1105
A12: 2017/18 | B12: ='Donnees_USDA'!J706 -> 3115 | C12: ='Donnees_USDA'!J506 -> 22420 | D12: ='Donnees_USDA'!J606 -> 30454 | E12: =B12/(C12+D12) -> 0.058913644 | F12: ='Prix_ICE'!J12 -> 120.60083 | G12: ='Donnees_USDA'!J707 -> 254 | H12: ='Donnees_USDA'!J507 -> 2880 | I12: ='Donnees_USDA'!J607 -> 29907 | J12: =G12/(H12+I12) -> 0.0077469729 | K12: ='Prix_ICE'!L12 -> 1725.8888
A13: 2018/19 | B13: ='Donnees_USDA'!K706 -> 5056 | C13: ='Donnees_USDA'!K506 -> 23200 | D13: ='Donnees_USDA'!K606 -> 41426 | E13: =B13/(C13+D13) -> 0.078234766 | F13: ='Prix_ICE'!J13 -> 104.98083 | G13: ='Donnees_USDA'!K707 -> 556 | H13: ='Donnees_USDA'!K507 -> 2940 | I13: ='Donnees_USDA'!K607 -> 28318 | J13: =G13/(H13+I13) -> 0.017787446 | K13: ='Prix_ICE'!L13 -> 1488.8368
A14: 2019/20 | B14: ='Donnees_USDA'!L706 -> 2373 | C14: ='Donnees_USDA'!L506 -> 22994 | D14: ='Donnees_USDA'!L606 -> 40256 | E14: =B14/(C14+D14) -> 0.037517787 | F14: ='Prix_ICE'!J14 -> 113.23667 | G14: ='Donnees_USDA'!L707 -> 2130 | H14: ='Donnees_USDA'!L507 -> 3100 | I14: ='Donnees_USDA'!L607 -> 27326 | J14: =G14/(H14+I14) -> 0.070005916 | K14: ='Prix_ICE'!L14 -> 1305.5959
A15: 2020/21 | B15: ='Donnees_USDA'!M706 -> 4390 | C15: ='Donnees_USDA'!M506 -> 22280 | D15: ='Donnees_USDA'!M606 -> 45675 | E15: =B15/(C15+D15) -> 0.064601575 | F15: ='Prix_ICE'!J15 -> 143.75333 | G15: ='Donnees_USDA'!M707 -> 3660 | H15: ='Donnees_USDA'!M507 -> 2720 | I15: ='Donnees_USDA'!M607 -> 25300 | J15: =G15/(H15+I15) -> 0.13062099 | K15: ='Prix_ICE'!L15 -> 1540.9394
A16: 2021/22 | B16: ='Donnees_USDA'!N706 -> 540 | C16: ='Donnees_USDA'!N506 -> 22340 | D16: ='Donnees_USDA'!N606 -> 39685 | E16: =B16/(C16+D16) -> 0.0087061669 | F16: ='Prix_ICE'!J16 -> 224.0875 | G16: ='Donnees_USDA'!N707 -> 3580 | H16: ='Donnees_USDA'!N507 -> 3200 | I16: ='Donnees_USDA'!N607 -> 29010 | J16: =G16/(H16+I16) -> 0.11114561 | K16: ='Prix_ICE'!L16 -> 2150.1501
A17: 2022/23 | B17: ='Donnees_USDA'!O706 -> 4620 | C17: ='Donnees_USDA'!O506 -> 22450 | D17: ='Donnees_USDA'!O606 -> 36145 | E17: =B17/(C17+D17) -> 0.078846318 | F17: ='Prix_ICE'!J17 -> 171.19 | G17: ='Donnees_USDA'!O707 -> 839 | H17: ='Donnees_USDA'!O507 -> 3200 | I17: ='Donnees_USDA'!O607 -> 28340 | J17: =G17/(H17+I17) -> 0.026601141 | K17: ='Prix_ICE'!L17 -> 2217.0787
A18: 2023/24 | B18: ='Donnees_USDA'!P706 -> 2085 | C18: ='Donnees_USDA'!P506 -> 22160 | D18: ='Donnees_USDA'!P606 -> 46750 | E18: =B18/(C18+D18) -> 0.030256857 | F18: ='Prix_ICE'!J18 -> 204.00167 | G18: ='Donnees_USDA'!P707 -> 889 | H18: ='Donnees_USDA'!P507 -> 3900 | I18: ='Donnees_USDA'!P607 -> 24400 | J18: =G18/(H18+I18) -> 0.031413428 | K18: ='Prix_ICE'!L18 -> 3504.2477
A19: 2024/25 | B19: ='Donnees_USDA'!Q706 -> 955 | C19: ='Donnees_USDA'!Q506 -> 21970 | D19: ='Donnees_USDA'!Q606 -> 44750 | E19: =B19/(C19+D19) -> 0.014313549 | F19: ='Prix_ICE'!J19 -> 333.06 | G19: ='Donnees_USDA'!Q707 -> 1089 | H19: ='Donnees_USDA'!Q507 -> 4800 | I19: ='Donnees_USDA'!Q607 -> 25200 | J19: =G19/(H19+I19) -> 0.0363 | K19: ='Prix_ICE'!L19 -> 4701.7435
A20: 2025/26 | B20: ='Donnees_USDA'!R706 -> 3895 | C20: ='Donnees_USDA'!R506 -> 22280 | D20: ='Donnees_USDA'!R606 -> 37870 | E20: =B20/(C20+D20) -> 0.06475478 | F20: ='Prix_ICE'!J20 -> 312.21 | G20: ='Donnees_USDA'!R707 -> 689 | H20: ='Donnees_USDA'!R507 -> 4900 | I20: ='Donnees_USDA'!R607 -> 28500 | J20: =G20/(H20+I20) -> 0.020628743 | K20: ='Prix_ICE'!L20 -> 3788.4636
A21: 2026/27 (prév.) | B21: ='Donnees_USDA'!S706 -> 4425 | C21: ='Donnees_USDA'!S506 -> 22390 | D21: ='Donnees_USDA'!S606 -> 49070 | E21: =B21/(C21+D21) -> 0.061922754 | G21: ='Donnees_USDA'!S707 -> 489 | H21: ='Donnees_USDA'!S507 -> 5000 | I21: ='Donnees_USDA'!S607 -> 28950 | J21: =G21/(H21+I21) -> 0.014403535

Sheet 6_Surplus
A1: 6 — « Surplus » au lieu des stocks USDA : (production + import − conso − export) ÷ (conso + export)
A2: Surplus de l'année = production + importations − consommation domestique − exportations : ce qui reste de l'offre de l'année (= variation des stocks, sans utiliser leur niveau). > 0 : stocks reconstitués ; < 0 : stocks entamés.
A3: Espèces : chaque pays pondéré par sa part arabica (robusta) de production. Arabica 6 pays : Brésil, Colombie, Honduras, Mexique, Pérou, Nicaragua. Robusta 4 pays : Vietnam, Brésil, Ouganda, Indonésie.
A4: Campagne | B4: Surplus arabica Brésil (prod + import − conso − export) | C4: Conso + export arabica Brésil | D4: RATIO Brésil arabica | E4: Surplus arabica 6 pays | F4: Conso + export arabica 6 pays | G4: RATIO arabica 6 pays | H4: KC1 NY (US c/lb) | I4: Surplus robusta Vietnam | J4: Conso + export robusta Vietnam | K4: RATIO Vietnam robusta | L4: Surplus robusta 4 pays | M4: Conso + export robusta 4 pays | N4: RATIO robusta 4 pays | O4: DF1 Londres (US$/t)
A5: 2010/11 | B5: =('Donnees_USDA'!C6+'Donnees_USDA'!C406-'Donnees_USDA'!C506-'Donnees_USDA'!C606)*'Donnees_USDA'!C806 -> 53.688073 | C5: =('Donnees_USDA'!C506+'Donnees_USDA'!C606)*'Donnees_USDA'!C806 -> 41746.312 | D5: =B5/C5 -> 0.0012860555 | E5: =('Donnees_USDA'!C6+'Donnees_USDA'!C406-'Donnees_USDA'!C506-'Donnees_USDA'!C606)*'Donnees_USDA'!C806+('Donnees_USDA'!C8+'Donnees_USDA'!C408-'Donnees_USDA'!C508-'Donnees_USDA'!C608)*'Donnees_USDA'!C808+('Donnees_USDA'!C13+'Donnees_USDA'!C413-'Donnees_USDA'!C513-'Donnees_USDA'!C613)*'Donnees_USDA'!C813+('Donnees_USDA'!C15+'Donnees_USDA'!C415-'Donnees_USDA'!C515-'Donnees_USDA'!C615)*'Donnees_USDA'!C815+('Donnees_USDA'!C14+'Donnees_USDA'!C414-'Donnees_USDA'!C514-'Donnees_USDA'!C614)*'Donnees_USDA'!C814+('Donnees_USDA'!C17+'Donnees_USDA'!C417-'Donnees_USDA'!C517-'Donnees_USDA'!C617)*'Donnees_USDA'!C817 -> -317.56193 | F5: =('Donnees_USDA'!C506+'Donnees_USDA'!C606)*'Donnees_USDA'!C806+('Donnees_USDA'!C508+'Donnees_USDA'!C608)*'Donnees_USDA'!C808+('Donnees_USDA'!C513+'Donnees_USDA'!C613)*'Donnees_USDA'!C813+('Donnees_USDA'!C515+'Donnees_USDA'!C615)*'Donnees_USDA'!C815+('Donnees_USDA'!C514+'Donnees_USDA'!C614)*'Donnees_USDA'!C814+('Donnees_USDA'!C517+'Donnees_USDA'!C617)*'Donnees_USDA'!C817 -> 66213.312 | G5: =E5/F5 -> -0.0047960435 | H5: ='Prix_ICE'!J5 -> 249.66 | I5: =('Donnees_USDA'!C7+'Donnees_USDA'!C407-'Donnees_USDA'!C507-'Donnees_USDA'!C607)*'Donnees_USDA'!C907 -> -204.9024 | J5: =('Donnees_USDA'!C507+'Donnees_USDA'!C607)*'Donnees_USDA'!C907 -> 19308.185 | K5: =I5/J5 -> -0.010612204 | L5: =('Donnees_USDA'!C7+'Donnees_USDA'!C407-'Donnees_USDA'!C507-'Donnees_USDA'!C607)*'Donnees_USDA'!C907+('Donnees_USDA'!C6+'Donnees_USDA'!C406-'Donnees_USDA'!C506-'Donnees_USDA'!C606)*'Donnees_USDA'!C906+('Donnees_USDA'!C11+'Donnees_USDA'!C411-'Donnees_USDA'!C511-'Donnees_USDA'!C611)*'Donnees_USDA'!C911+('Donnees_USDA'!C10+'Donnees_USDA'!C410-'Donnees_USDA'!C510-'Donnees_USDA'!C610)*'Donnees_USDA'!C910 -> -1554.8179 | M5: =('Donnees_USDA'!C507+'Donnees_USDA'!C607)*'Donnees_USDA'!C907+('Donnees_USDA'!C506+'Donnees_USDA'!C606)*'Donnees_USDA'!C906+('Donnees_USDA'!C511+'Donnees_USDA'!C611)*'Donnees_USDA'!C911+('Donnees_USDA'!C510+'Donnees_USDA'!C610)*'Donnees_USDA'!C910 -> 44332.213 | N5: =L5/M5 -> -0.035071968 | O5: ='Prix_ICE'!L5 -> 2219.0813
A6: 2011/12 | B6: =('Donnees_USDA'!D6+'Donnees_USDA'!D406-'Donnees_USDA'!D506-'Donnees_USDA'!D606)*'Donnees_USDA'!D806 -> -471.13008 | C6: =('Donnees_USDA'!D506+'Donnees_USDA'!D606)*'Donnees_USDA'!D806 -> 35171.13 | D6: =B6/C6 -> -0.013395364 | E6: =('Donnees_USDA'!D6+'Donnees_USDA'!D406-'Donnees_USDA'!D506-'Donnees_USDA'!D606)*'Donnees_USDA'!D806+('Donnees_USDA'!D8+'Donnees_USDA'!D408-'Donnees_USDA'!D508-'Donnees_USDA'!D608)*'Donnees_USDA'!D808+('Donnees_USDA'!D13+'Donnees_USDA'!D413-'Donnees_USDA'!D513-'Donnees_USDA'!D613)*'Donnees_USDA'!D813+('Donnees_USDA'!D15+'Donnees_USDA'!D415-'Donnees_USDA'!D515-'Donnees_USDA'!D615)*'Donnees_USDA'!D815+('Donnees_USDA'!D14+'Donnees_USDA'!D414-'Donnees_USDA'!D514-'Donnees_USDA'!D614)*'Donnees_USDA'!D814+('Donnees_USDA'!D17+'Donnees_USDA'!D417-'Donnees_USDA'!D517-'Donnees_USDA'!D617)*'Donnees_USDA'!D817 -> -166.87427 | F6: =('Donnees_USDA'!D506+'Donnees_USDA'!D606)*'Donnees_USDA'!D806+('Donnees_USDA'!D508+'Donnees_USDA'!D608)*'Donnees_USDA'!D808+('Donnees_USDA'!D513+'Donnees_USDA'!D613)*'Donnees_USDA'!D813+('Donnees_USDA'!D515+'Donnees_USDA'!D615)*'Donnees_USDA'!D815+('Donnees_USDA'!D514+'Donnees_USDA'!D614)*'Donnees_USDA'!D814+('Donnees_USDA'!D517+'Donnees_USDA'!D617)*'Donnees_USDA'!D817 -> 61950.246 | G6: =E6/F6 -> -0.0026936821 | H6: ='Prix_ICE'!J6 -> 197.84167 | I6: =('Donnees_USDA'!D7+'Donnees_USDA'!D407-'Donnees_USDA'!D507-'Donnees_USDA'!D607)*'Donnees_USDA'!D907 -> 281.07692 | J6: =('Donnees_USDA'!D507+'Donnees_USDA'!D607)*'Donnees_USDA'!D907 -> 25355.077 | K6: =I6/J6 -> 0.011085627 | L6: =('Donnees_USDA'!D7+'Donnees_USDA'!D407-'Donnees_USDA'!D507-'Donnees_USDA'!D607)*'Donnees_USDA'!D907+('Donnees_USDA'!D6+'Donnees_USDA'!D406-'Donnees_USDA'!D506-'Donnees_USDA'!D606)*'Donnees_USDA'!D906+('Donnees_USDA'!D11+'Donnees_USDA'!D411-'Donnees_USDA'!D511-'Donnees_USDA'!D611)*'Donnees_USDA'!D911+('Donnees_USDA'!D10+'Donnees_USDA'!D410-'Donnees_USDA'!D510-'Donnees_USDA'!D610)*'Donnees_USDA'!D910 -> 34.732909 | M6: =('Donnees_USDA'!D507+'Donnees_USDA'!D607)*'Donnees_USDA'!D907+('Donnees_USDA'!D506+'Donnees_USDA'!D606)*'Donnees_USDA'!D906+('Donnees_USDA'!D511+'Donnees_USDA'!D611)*'Donnees_USDA'!D911+('Donnees_USDA'!D510+'Donnees_USDA'!D610)*'Donnees_USDA'!D910 -> 50063.56 | N6: =L6/M6 -> 0.00069377626 | O6: ='Prix_ICE'!L6 -> 2014.676
A7: 2012/13 | B7: =('Donnees_USDA'!E6+'Donnees_USDA'!E406-'Donnees_USDA'!E506-'Donnees_USDA'!E606)*'Donnees_USDA'!E806 -> 4992.066 | C7: =('Donnees_USDA'!E506+'Donnees_USDA'!E606)*'Donnees_USDA'!E806 -> 37107.934 | D7: =B7/C7 -> 0.13452826 | E7: =('Donnees_USDA'!E6+'Donnees_USDA'!E406-'Donnees_USDA'!E506-'Donnees_USDA'!E606)*'Donnees_USDA'!E806+('Donnees_USDA'!E8+'Donnees_USDA'!E408-'Donnees_USDA'!E508-'Donnees_USDA'!E608)*'Donnees_USDA'!E808+('Donnees_USDA'!E13+'Donnees_USDA'!E413-'Donnees_USDA'!E513-'Donnees_USDA'!E613)*'Donnees_USDA'!E813+('Donnees_USDA'!E15+'Donnees_USDA'!E415-'Donnees_USDA'!E515-'Donnees_USDA'!E615)*'Donnees_USDA'!E815+('Donnees_USDA'!E14+'Donnees_USDA'!E414-'Donnees_USDA'!E514-'Donnees_USDA'!E614)*'Donnees_USDA'!E814+('Donnees_USDA'!E17+'Donnees_USDA'!E417-'Donnees_USDA'!E517-'Donnees_USDA'!E617)*'Donnees_USDA'!E817 -> 5358.109 | F7: =('Donnees_USDA'!E506+'Donnees_USDA'!E606)*'Donnees_USDA'!E806+('Donnees_USDA'!E508+'Donnees_USDA'!E608)*'Donnees_USDA'!E808+('Donnees_USDA'!E513+'Donnees_USDA'!E613)*'Donnees_USDA'!E813+('Donnees_USDA'!E515+'Donnees_USDA'!E615)*'Donnees_USDA'!E815+('Donnees_USDA'!E514+'Donnees_USDA'!E614)*'Donnees_USDA'!E814+('Donnees_USDA'!E517+'Donnees_USDA'!E617)*'Donnees_USDA'!E817 -> 63850.074 | G7: =E7/F7 -> 0.083917037 | H7: ='Prix_ICE'!J7 -> 140.69833 | I7: =('Donnees_USDA'!E7+'Donnees_USDA'!E407-'Donnees_USDA'!E507-'Donnees_USDA'!E607)*'Donnees_USDA'!E907 -> 826.9283 | J7: =('Donnees_USDA'!E507+'Donnees_USDA'!E607)*'Donnees_USDA'!E907 -> 25569.087 | K7: =I7/J7 -> 0.03234094 | L7: =('Donnees_USDA'!E7+'Donnees_USDA'!E407-'Donnees_USDA'!E507-'Donnees_USDA'!E607)*'Donnees_USDA'!E907+('Donnees_USDA'!E6+'Donnees_USDA'!E406-'Donnees_USDA'!E506-'Donnees_USDA'!E606)*'Donnees_USDA'!E906+('Donnees_USDA'!E11+'Donnees_USDA'!E411-'Donnees_USDA'!E511-'Donnees_USDA'!E611)*'Donnees_USDA'!E911+('Donnees_USDA'!E10+'Donnees_USDA'!E410-'Donnees_USDA'!E510-'Donnees_USDA'!E610)*'Donnees_USDA'!E910 -> 2537.0705 | M7: =('Donnees_USDA'!E507+'Donnees_USDA'!E607)*'Donnees_USDA'!E907+('Donnees_USDA'!E506+'Donnees_USDA'!E606)*'Donnees_USDA'!E906+('Donnees_USDA'!E511+'Donnees_USDA'!E611)*'Donnees_USDA'!E911+('Donnees_USDA'!E510+'Donnees_USDA'!E610)*'Donnees_USDA'!E910 -> 53098.861 | N7: =L7/M7 -> 0.047780132 | O7: ='Prix_ICE'!L7 -> 1950.6685
A8: 2013/14 | B8: =('Donnees_USDA'!F6+'Donnees_USDA'!F406-'Donnees_USDA'!F506-'Donnees_USDA'!F606)*'Donnees_USDA'!F806 -> 2103.1538 | C8: =('Donnees_USDA'!F506+'Donnees_USDA'!F606)*'Donnees_USDA'!F806 -> 39721.692 | D8: =B8/C8 -> 0.052947237 | E8: =('Donnees_USDA'!F6+'Donnees_USDA'!F406-'Donnees_USDA'!F506-'Donnees_USDA'!F606)*'Donnees_USDA'!F806+('Donnees_USDA'!F8+'Donnees_USDA'!F408-'Donnees_USDA'!F508-'Donnees_USDA'!F608)*'Donnees_USDA'!F808+('Donnees_USDA'!F13+'Donnees_USDA'!F413-'Donnees_USDA'!F513-'Donnees_USDA'!F613)*'Donnees_USDA'!F813+('Donnees_USDA'!F15+'Donnees_USDA'!F415-'Donnees_USDA'!F515-'Donnees_USDA'!F615)*'Donnees_USDA'!F815+('Donnees_USDA'!F14+'Donnees_USDA'!F414-'Donnees_USDA'!F514-'Donnees_USDA'!F614)*'Donnees_USDA'!F814+('Donnees_USDA'!F17+'Donnees_USDA'!F417-'Donnees_USDA'!F517-'Donnees_USDA'!F617)*'Donnees_USDA'!F817 -> 2540.6855 | F8: =('Donnees_USDA'!F506+'Donnees_USDA'!F606)*'Donnees_USDA'!F806+('Donnees_USDA'!F508+'Donnees_USDA'!F608)*'Donnees_USDA'!F808+('Donnees_USDA'!F513+'Donnees_USDA'!F613)*'Donnees_USDA'!F813+('Donnees_USDA'!F515+'Donnees_USDA'!F615)*'Donnees_USDA'!F815+('Donnees_USDA'!F514+'Donnees_USDA'!F614)*'Donnees_USDA'!F814+('Donnees_USDA'!F517+'Donnees_USDA'!F617)*'Donnees_USDA'!F817 -> 67786.439 | G8: =E8/F8 -> 0.037480734 | H8: ='Prix_ICE'!J8 -> 161.4675 | I8: =('Donnees_USDA'!F7+'Donnees_USDA'!F407-'Donnees_USDA'!F507-'Donnees_USDA'!F607)*'Donnees_USDA'!F907 -> 176.75299 | J8: =('Donnees_USDA'!F507+'Donnees_USDA'!F607)*'Donnees_USDA'!F907 -> 29103.725 | K8: =I8/J8 -> 0.0060732086 | L8: =('Donnees_USDA'!F7+'Donnees_USDA'!F407-'Donnees_USDA'!F507-'Donnees_USDA'!F607)*'Donnees_USDA'!F907+('Donnees_USDA'!F6+'Donnees_USDA'!F406-'Donnees_USDA'!F506-'Donnees_USDA'!F606)*'Donnees_USDA'!F906+('Donnees_USDA'!F11+'Donnees_USDA'!F411-'Donnees_USDA'!F511-'Donnees_USDA'!F611)*'Donnees_USDA'!F911+('Donnees_USDA'!F10+'Donnees_USDA'!F410-'Donnees_USDA'!F510-'Donnees_USDA'!F610)*'Donnees_USDA'!F910 -> 932.95896 | M8: =('Donnees_USDA'!F507+'Donnees_USDA'!F607)*'Donnees_USDA'!F907+('Donnees_USDA'!F506+'Donnees_USDA'!F606)*'Donnees_USDA'!F906+('Donnees_USDA'!F511+'Donnees_USDA'!F611)*'Donnees_USDA'!F911+('Donnees_USDA'!F510+'Donnees_USDA'!F610)*'Donnees_USDA'!F910 -> 57571.799 | N8: =L8/M8 -> 0.016205138 | O8: ='Prix_ICE'!L8 -> 1893.2013
A9: 2014/15 | B9: =('Donnees_USDA'!G6+'Donnees_USDA'!G406-'Donnees_USDA'!G506-'Donnees_USDA'!G606)*'Donnees_USDA'!G806 -> -1814.1676 | C9: =('Donnees_USDA'!G506+'Donnees_USDA'!G606)*'Donnees_USDA'!G806 -> 39149.888 | D9: =B9/C9 -> -0.046339024 | E9: =('Donnees_USDA'!G6+'Donnees_USDA'!G406-'Donnees_USDA'!G506-'Donnees_USDA'!G606)*'Donnees_USDA'!G806+('Donnees_USDA'!G8+'Donnees_USDA'!G408-'Donnees_USDA'!G508-'Donnees_USDA'!G608)*'Donnees_USDA'!G808+('Donnees_USDA'!G13+'Donnees_USDA'!G413-'Donnees_USDA'!G513-'Donnees_USDA'!G613)*'Donnees_USDA'!G813+('Donnees_USDA'!G15+'Donnees_USDA'!G415-'Donnees_USDA'!G515-'Donnees_USDA'!G615)*'Donnees_USDA'!G815+('Donnees_USDA'!G14+'Donnees_USDA'!G414-'Donnees_USDA'!G514-'Donnees_USDA'!G614)*'Donnees_USDA'!G814+('Donnees_USDA'!G17+'Donnees_USDA'!G417-'Donnees_USDA'!G517-'Donnees_USDA'!G617)*'Donnees_USDA'!G817 -> -2046.3415 | F9: =('Donnees_USDA'!G506+'Donnees_USDA'!G606)*'Donnees_USDA'!G806+('Donnees_USDA'!G508+'Donnees_USDA'!G608)*'Donnees_USDA'!G808+('Donnees_USDA'!G513+'Donnees_USDA'!G613)*'Donnees_USDA'!G813+('Donnees_USDA'!G515+'Donnees_USDA'!G615)*'Donnees_USDA'!G815+('Donnees_USDA'!G514+'Donnees_USDA'!G614)*'Donnees_USDA'!G814+('Donnees_USDA'!G517+'Donnees_USDA'!G617)*'Donnees_USDA'!G817 -> 67611.363 | G9: =E9/F9 -> -0.030266236 | H9: ='Prix_ICE'!J9 -> 154.02083 | I9: =('Donnees_USDA'!G7+'Donnees_USDA'!G407-'Donnees_USDA'!G507-'Donnees_USDA'!G607)*'Donnees_USDA'!G907 -> 4044.8212 | J9: =('Donnees_USDA'!G507+'Donnees_USDA'!G607)*'Donnees_USDA'!G907 -> 22872.569 | K9: =I9/J9 -> 0.17684157 | L9: =('Donnees_USDA'!G7+'Donnees_USDA'!G407-'Donnees_USDA'!G507-'Donnees_USDA'!G607)*'Donnees_USDA'!G907+('Donnees_USDA'!G6+'Donnees_USDA'!G406-'Donnees_USDA'!G506-'Donnees_USDA'!G606)*'Donnees_USDA'!G906+('Donnees_USDA'!G11+'Donnees_USDA'!G411-'Donnees_USDA'!G511-'Donnees_USDA'!G611)*'Donnees_USDA'!G911+('Donnees_USDA'!G10+'Donnees_USDA'!G410-'Donnees_USDA'!G510-'Donnees_USDA'!G610)*'Donnees_USDA'!G910 -> 3160.668 | M9: =('Donnees_USDA'!G507+'Donnees_USDA'!G607)*'Donnees_USDA'!G907+('Donnees_USDA'!G506+'Donnees_USDA'!G606)*'Donnees_USDA'!G906+('Donnees_USDA'!G511+'Donnees_USDA'!G611)*'Donnees_USDA'!G911+('Donnees_USDA'!G510+'Donnees_USDA'!G610)*'Donnees_USDA'!G910 -> 53687.902 | N9: =L9/M9 -> 0.058871139 | O9: ='Prix_ICE'!L9 -> 1849.9172
A10: 2015/16 | B10: =('Donnees_USDA'!H6+'Donnees_USDA'!H406-'Donnees_USDA'!H506-'Donnees_USDA'!H606)*'Donnees_USDA'!H806 -> -5066.4231 | C10: =('Donnees_USDA'!H506+'Donnees_USDA'!H606)*'Donnees_USDA'!H806 -> 41213.923 | D10: =B10/C10 -> -0.12292989 | E10: =('Donnees_USDA'!H6+'Donnees_USDA'!H406-'Donnees_USDA'!H506-'Donnees_USDA'!H606)*'Donnees_USDA'!H806+('Donnees_USDA'!H8+'Donnees_USDA'!H408-'Donnees_USDA'!H508-'Donnees_USDA'!H608)*'Donnees_USDA'!H808+('Donnees_USDA'!H13+'Donnees_USDA'!H413-'Donnees_USDA'!H513-'Donnees_USDA'!H613)*'Donnees_USDA'!H813+('Donnees_USDA'!H15+'Donnees_USDA'!H415-'Donnees_USDA'!H515-'Donnees_USDA'!H615)*'Donnees_USDA'!H815+('Donnees_USDA'!H14+'Donnees_USDA'!H414-'Donnees_USDA'!H514-'Donnees_USDA'!H614)*'Donnees_USDA'!H814+('Donnees_USDA'!H17+'Donnees_USDA'!H417-'Donnees_USDA'!H517-'Donnees_USDA'!H617)*'Donnees_USDA'!H817 -> -4577.1258 | F10: =('Donnees_USDA'!H506+'Donnees_USDA'!H606)*'Donnees_USDA'!H806+('Donnees_USDA'!H508+'Donnees_USDA'!H608)*'Donnees_USDA'!H808+('Donnees_USDA'!H513+'Donnees_USDA'!H613)*'Donnees_USDA'!H813+('Donnees_USDA'!H515+'Donnees_USDA'!H615)*'Donnees_USDA'!H815+('Donnees_USDA'!H514+'Donnees_USDA'!H614)*'Donnees_USDA'!H814+('Donnees_USDA'!H517+'Donnees_USDA'!H617)*'Donnees_USDA'!H817 -> 70327.86 | G10: =E10/F10 -> -0.065082682 | H10: ='Prix_ICE'!J10 -> 131.8325 | I10: =('Donnees_USDA'!H7+'Donnees_USDA'!H407-'Donnees_USDA'!H507-'Donnees_USDA'!H607)*'Donnees_USDA'!H907 -> -2053.8213 | J10: =('Donnees_USDA'!H507+'Donnees_USDA'!H607)*'Donnees_USDA'!H907 -> 30489.867 | K10: =I10/J10 -> -0.067360782 | L10: =('Donnees_USDA'!H7+'Donnees_USDA'!H407-'Donnees_USDA'!H507-'Donnees_USDA'!H607)*'Donnees_USDA'!H907+('Donnees_USDA'!H6+'Donnees_USDA'!H406-'Donnees_USDA'!H506-'Donnees_USDA'!H606)*'Donnees_USDA'!H906+('Donnees_USDA'!H11+'Donnees_USDA'!H411-'Donnees_USDA'!H511-'Donnees_USDA'!H611)*'Donnees_USDA'!H911+('Donnees_USDA'!H10+'Donnees_USDA'!H410-'Donnees_USDA'!H510-'Donnees_USDA'!H610)*'Donnees_USDA'!H910 -> -3926.5304 | M10: =('Donnees_USDA'!H507+'Donnees_USDA'!H607)*'Donnees_USDA'!H907+('Donnees_USDA'!H506+'Donnees_USDA'!H606)*'Donnees_USDA'!H906+('Donnees_USDA'!H511+'Donnees_USDA'!H611)*'Donnees_USDA'!H911+('Donnees_USDA'!H510+'Donnees_USDA'!H610)*'Donnees_USDA'!H910 -> 59724.572 | N10: =L10/M10 -> -0.06574397 | O10: ='Prix_ICE'!L10 -> 1632.9272
A11: 2016/17 | B11: =('Donnees_USDA'!I6+'Donnees_USDA'!I406-'Donnees_USDA'!I506-'Donnees_USDA'!I606)*'Donnees_USDA'!I806 -> 1183.4866 | C11: =('Donnees_USDA'!I506+'Donnees_USDA'!I606)*'Donnees_USDA'!I806 -> 44466.909 | D11: =B11/C11 -> 0.026614997 | E11: =('Donnees_USDA'!I6+'Donnees_USDA'!I406-'Donnees_USDA'!I506-'Donnees_USDA'!I606)*'Donnees_USDA'!I806+('Donnees_USDA'!I8+'Donnees_USDA'!I408-'Donnees_USDA'!I508-'Donnees_USDA'!I608)*'Donnees_USDA'!I808+('Donnees_USDA'!I13+'Donnees_USDA'!I413-'Donnees_USDA'!I513-'Donnees_USDA'!I613)*'Donnees_USDA'!I813+('Donnees_USDA'!I15+'Donnees_USDA'!I415-'Donnees_USDA'!I515-'Donnees_USDA'!I615)*'Donnees_USDA'!I815+('Donnees_USDA'!I14+'Donnees_USDA'!I414-'Donnees_USDA'!I514-'Donnees_USDA'!I614)*'Donnees_USDA'!I814+('Donnees_USDA'!I17+'Donnees_USDA'!I417-'Donnees_USDA'!I517-'Donnees_USDA'!I617)*'Donnees_USDA'!I817 -> 935.60784 | F11: =('Donnees_USDA'!I506+'Donnees_USDA'!I606)*'Donnees_USDA'!I806+('Donnees_USDA'!I508+'Donnees_USDA'!I608)*'Donnees_USDA'!I808+('Donnees_USDA'!I513+'Donnees_USDA'!I613)*'Donnees_USDA'!I813+('Donnees_USDA'!I515+'Donnees_USDA'!I615)*'Donnees_USDA'!I815+('Donnees_USDA'!I514+'Donnees_USDA'!I614)*'Donnees_USDA'!I814+('Donnees_USDA'!I517+'Donnees_USDA'!I617)*'Donnees_USDA'!I817 -> 78644.558 | G11: =E11/F11 -> 0.011896663 | H11: ='Prix_ICE'!J11 -> 143.77167 | I11: =('Donnees_USDA'!I7+'Donnees_USDA'!I407-'Donnees_USDA'!I507-'Donnees_USDA'!I607)*'Donnees_USDA'!I907 -> -1457.3783 | J11: =('Donnees_USDA'!I507+'Donnees_USDA'!I607)*'Donnees_USDA'!I907 -> 28016.18 | K11: =I11/J11 -> -0.052019165 | L11: =('Donnees_USDA'!I7+'Donnees_USDA'!I407-'Donnees_USDA'!I507-'Donnees_USDA'!I607)*'Donnees_USDA'!I907+('Donnees_USDA'!I6+'Donnees_USDA'!I406-'Donnees_USDA'!I506-'Donnees_USDA'!I606)*'Donnees_USDA'!I906+('Donnees_USDA'!I11+'Donnees_USDA'!I411-'Donnees_USDA'!I511-'Donnees_USDA'!I611)*'Donnees_USDA'!I911+('Donnees_USDA'!I10+'Donnees_USDA'!I410-'Donnees_USDA'!I510-'Donnees_USDA'!I610)*'Donnees_USDA'!I910 -> -1195.3361 | M11: =('Donnees_USDA'!I507+'Donnees_USDA'!I607)*'Donnees_USDA'!I907+('Donnees_USDA'!I506+'Donnees_USDA'!I606)*'Donnees_USDA'!I906+('Donnees_USDA'!I511+'Donnees_USDA'!I611)*'Donnees_USDA'!I911+('Donnees_USDA'!I510+'Donnees_USDA'!I610)*'Donnees_USDA'!I910 -> 51992.619 | N11: =L11/M11 -> -0.022990496 | O11: ='Prix_ICE'!L11 -> 2097.1105
A12: 2017/18 | B12: =('Donnees_USDA'!J6+'Donnees_USDA'!J406-'Donnees_USDA'!J506-'Donnees_USDA'!J606)*'Donnees_USDA'!J806 -> -540.56622 | C12: =('Donnees_USDA'!J506+'Donnees_USDA'!J606)*'Donnees_USDA'!J806 -> 40086.814 | D12: =B12/C12 -> -0.013484889 | E12: =('Donnees_USDA'!J6+'Donnees_USDA'!J406-'Donnees_USDA'!J506-'Donnees_USDA'!J606)*'Donnees_USDA'!J806+('Donnees_USDA'!J8+'Donnees_USDA'!J408-'Donnees_USDA'!J508-'Donnees_USDA'!J608)*'Donnees_USDA'!J808+('Donnees_USDA'!J13+'Donnees_USDA'!J413-'Donnees_USDA'!J513-'Donnees_USDA'!J613)*'Donnees_USDA'!J813+('Donnees_USDA'!J15+'Donnees_USDA'!J415-'Donnees_USDA'!J515-'Donnees_USDA'!J615)*'Donnees_USDA'!J815+('Donnees_USDA'!J14+'Donnees_USDA'!J414-'Donnees_USDA'!J514-'Donnees_USDA'!J614)*'Donnees_USDA'!J814+('Donnees_USDA'!J17+'Donnees_USDA'!J417-'Donnees_USDA'!J517-'Donnees_USDA'!J617)*'Donnees_USDA'!J817 -> -182.83545 | F12: =('Donnees_USDA'!J506+'Donnees_USDA'!J606)*'Donnees_USDA'!J806+('Donnees_USDA'!J508+'Donnees_USDA'!J608)*'Donnees_USDA'!J808+('Donnees_USDA'!J513+'Donnees_USDA'!J613)*'Donnees_USDA'!J813+('Donnees_USDA'!J515+'Donnees_USDA'!J615)*'Donnees_USDA'!J815+('Donnees_USDA'!J514+'Donnees_USDA'!J614)*'Donnees_USDA'!J814+('Donnees_USDA'!J517+'Donnees_USDA'!J617)*'Donnees_USDA'!J817 -> 74321.558 | G12: =E12/F12 -> -0.0024600594 | H12: ='Prix_ICE'!J12 -> 120.60083 | I12: =('Donnees_USDA'!J7+'Donnees_USDA'!J407-'Donnees_USDA'!J507-'Donnees_USDA'!J607)*'Donnees_USDA'!J907 -> -2342.0136 | J12: =('Donnees_USDA'!J507+'Donnees_USDA'!J607)*'Donnees_USDA'!J907 -> 31638.895 | K12: =I12/J12 -> -0.074023241 | L12: =('Donnees_USDA'!J7+'Donnees_USDA'!J407-'Donnees_USDA'!J507-'Donnees_USDA'!J607)*'Donnees_USDA'!J907+('Donnees_USDA'!J6+'Donnees_USDA'!J406-'Donnees_USDA'!J506-'Donnees_USDA'!J606)*'Donnees_USDA'!J906+('Donnees_USDA'!J11+'Donnees_USDA'!J411-'Donnees_USDA'!J511-'Donnees_USDA'!J611)*'Donnees_USDA'!J911+('Donnees_USDA'!J10+'Donnees_USDA'!J410-'Donnees_USDA'!J510-'Donnees_USDA'!J610)*'Donnees_USDA'!J910 -> -1952.3562 | M12: =('Donnees_USDA'!J507+'Donnees_USDA'!J607)*'Donnees_USDA'!J907+('Donnees_USDA'!J506+'Donnees_USDA'!J606)*'Donnees_USDA'!J906+('Donnees_USDA'!J511+'Donnees_USDA'!J611)*'Donnees_USDA'!J911+('Donnees_USDA'!J510+'Donnees_USDA'!J610)*'Donnees_USDA'!J910 -> 58246.625 | N12: =L12/M12 -> -0.033518787 | O12: ='Prix_ICE'!L12 -> 1725.8888
A13: 2018/19 | B13: =('Donnees_USDA'!K6+'Donnees_USDA'!K406-'Donnees_USDA'!K506-'Donnees_USDA'!K606)*'Donnees_USDA'!K806 -> 1450.6421 | C13: =('Donnees_USDA'!K506+'Donnees_USDA'!K606)*'Donnees_USDA'!K806 -> 48299.432 | D13: =B13/C13 -> 0.030034351 | E13: =('Donnees_USDA'!K6+'Donnees_USDA'!K406-'Donnees_USDA'!K506-'Donnees_USDA'!K606)*'Donnees_USDA'!K806+('Donnees_USDA'!K8+'Donnees_USDA'!K408-'Donnees_USDA'!K508-'Donnees_USDA'!K608)*'Donnees_USDA'!K808+('Donnees_USDA'!K13+'Donnees_USDA'!K413-'Donnees_USDA'!K513-'Donnees_USDA'!K613)*'Donnees_USDA'!K813+('Donnees_USDA'!K15+'Donnees_USDA'!K415-'Donnees_USDA'!K515-'Donnees_USDA'!K615)*'Donnees_USDA'!K815+('Donnees_USDA'!K14+'Donnees_USDA'!K414-'Donnees_USDA'!K514-'Donnees_USDA'!K614)*'Donnees_USDA'!K814+('Donnees_USDA'!K17+'Donnees_USDA'!K417-'Donnees_USDA'!K517-'Donnees_USDA'!K617)*'Donnees_USDA'!K817 -> 522.58553 | F13: =('Donnees_USDA'!K506+'Donnees_USDA'!K606)*'Donnees_USDA'!K806+('Donnees_USDA'!K508+'Donnees_USDA'!K608)*'Donnees_USDA'!K808+('Donnees_USDA'!K513+'Donnees_USDA'!K613)*'Donnees_USDA'!K813+('Donnees_USDA'!K515+'Donnees_USDA'!K615)*'Donnees_USDA'!K815+('Donnees_USDA'!K514+'Donnees_USDA'!K614)*'Donnees_USDA'!K814+('Donnees_USDA'!K517+'Donnees_USDA'!K617)*'Donnees_USDA'!K817 -> 83278.952 | G13: =E13/F13 -> 0.0062751214 | H13: ='Prix_ICE'!J13 -> 104.98083 | I13: =('Donnees_USDA'!K7+'Donnees_USDA'!K407-'Donnees_USDA'!K507-'Donnees_USDA'!K607)*'Donnees_USDA'!K907 -> 291.43 | J13: =('Donnees_USDA'!K507+'Donnees_USDA'!K607)*'Donnees_USDA'!K907 -> 30163.97 | K13: =I13/J13 -> 0.0096615266 | L13: =('Donnees_USDA'!K7+'Donnees_USDA'!K407-'Donnees_USDA'!K507-'Donnees_USDA'!K607)*'Donnees_USDA'!K907+('Donnees_USDA'!K6+'Donnees_USDA'!K406-'Donnees_USDA'!K506-'Donnees_USDA'!K606)*'Donnees_USDA'!K906+('Donnees_USDA'!K11+'Donnees_USDA'!K411-'Donnees_USDA'!K511-'Donnees_USDA'!K611)*'Donnees_USDA'!K911+('Donnees_USDA'!K10+'Donnees_USDA'!K410-'Donnees_USDA'!K510-'Donnees_USDA'!K610)*'Donnees_USDA'!K910 -> 2362.3612 | M13: =('Donnees_USDA'!K507+'Donnees_USDA'!K607)*'Donnees_USDA'!K907+('Donnees_USDA'!K506+'Donnees_USDA'!K606)*'Donnees_USDA'!K906+('Donnees_USDA'!K511+'Donnees_USDA'!K611)*'Donnees_USDA'!K911+('Donnees_USDA'!K510+'Donnees_USDA'!K610)*'Donnees_USDA'!K910 -> 59396.229 | N13: =L13/M13 -> 0.039772916 | O13: ='Prix_ICE'!L13 -> 1488.8368
A14: 2019/20 | B14: =('Donnees_USDA'!L6+'Donnees_USDA'!L406-'Donnees_USDA'!L506-'Donnees_USDA'!L606)*'Donnees_USDA'!L806 -> -1862.5785 | C14: =('Donnees_USDA'!L506+'Donnees_USDA'!L606)*'Donnees_USDA'!L806 -> 43909.091 | D14: =B14/C14 -> -0.042418972 | E14: =('Donnees_USDA'!L6+'Donnees_USDA'!L406-'Donnees_USDA'!L506-'Donnees_USDA'!L606)*'Donnees_USDA'!L806+('Donnees_USDA'!L8+'Donnees_USDA'!L408-'Donnees_USDA'!L508-'Donnees_USDA'!L608)*'Donnees_USDA'!L808+('Donnees_USDA'!L13+'Donnees_USDA'!L413-'Donnees_USDA'!L513-'Donnees_USDA'!L613)*'Donnees_USDA'!L813+('Donnees_USDA'!L15+'Donnees_USDA'!L415-'Donnees_USDA'!L515-'Donnees_USDA'!L615)*'Donnees_USDA'!L815+('Donnees_USDA'!L14+'Donnees_USDA'!L414-'Donnees_USDA'!L514-'Donnees_USDA'!L614)*'Donnees_USDA'!L814+('Donnees_USDA'!L17+'Donnees_USDA'!L417-'Donnees_USDA'!L517-'Donnees_USDA'!L617)*'Donnees_USDA'!L817 -> -1530.3843 | F14: =('Donnees_USDA'!L506+'Donnees_USDA'!L606)*'Donnees_USDA'!L806+('Donnees_USDA'!L508+'Donnees_USDA'!L608)*'Donnees_USDA'!L808+('Donnees_USDA'!L513+'Donnees_USDA'!L613)*'Donnees_USDA'!L813+('Donnees_USDA'!L515+'Donnees_USDA'!L615)*'Donnees_USDA'!L815+('Donnees_USDA'!L514+'Donnees_USDA'!L614)*'Donnees_USDA'!L814+('Donnees_USDA'!L517+'Donnees_USDA'!L617)*'Donnees_USDA'!L817 -> 75463.846 | G14: =E14/F14 -> -0.020279702 | H14: ='Prix_ICE'!J14 -> 113.23667 | I14: =('Donnees_USDA'!L7+'Donnees_USDA'!L407-'Donnees_USDA'!L507-'Donnees_USDA'!L607)*'Donnees_USDA'!L907 -> 1518.6837 | J14: =('Donnees_USDA'!L507+'Donnees_USDA'!L607)*'Donnees_USDA'!L907 -> 29356.716 | K14: =I14/J14 -> 0.051732071 | L14: =('Donnees_USDA'!L7+'Donnees_USDA'!L407-'Donnees_USDA'!L507-'Donnees_USDA'!L607)*'Donnees_USDA'!L907+('Donnees_USDA'!L6+'Donnees_USDA'!L406-'Donnees_USDA'!L506-'Donnees_USDA'!L606)*'Donnees_USDA'!L906+('Donnees_USDA'!L11+'Donnees_USDA'!L411-'Donnees_USDA'!L511-'Donnees_USDA'!L611)*'Donnees_USDA'!L911+('Donnees_USDA'!L10+'Donnees_USDA'!L410-'Donnees_USDA'!L510-'Donnees_USDA'!L610)*'Donnees_USDA'!L910 -> 611.71737 | M14: =('Donnees_USDA'!L507+'Donnees_USDA'!L607)*'Donnees_USDA'!L907+('Donnees_USDA'!L506+'Donnees_USDA'!L606)*'Donnees_USDA'!L906+('Donnees_USDA'!L511+'Donnees_USDA'!L611)*'Donnees_USDA'!L911+('Donnees_USDA'!L510+'Donnees_USDA'!L610)*'Donnees_USDA'!L910 -> 63771.361 | N14: =L14/M14 -> 0.0095923524 | O14: ='Prix_ICE'!L14 -> 1305.5959
A15: 2020/21 | B15: =('Donnees_USDA'!M6+'Donnees_USDA'!M406-'Donnees_USDA'!M506-'Donnees_USDA'!M606)*'Donnees_USDA'!M806 -> 1434.1187 | C15: =('Donnees_USDA'!M506+'Donnees_USDA'!M606)*'Donnees_USDA'!M806 -> 48317.074 | D15: =B15/C15 -> 0.029681407 | E15: =('Donnees_USDA'!M6+'Donnees_USDA'!M406-'Donnees_USDA'!M506-'Donnees_USDA'!M606)*'Donnees_USDA'!M806+('Donnees_USDA'!M8+'Donnees_USDA'!M408-'Donnees_USDA'!M508-'Donnees_USDA'!M608)*'Donnees_USDA'!M808+('Donnees_USDA'!M13+'Donnees_USDA'!M413-'Donnees_USDA'!M513-'Donnees_USDA'!M613)*'Donnees_USDA'!M813+('Donnees_USDA'!M15+'Donnees_USDA'!M415-'Donnees_USDA'!M515-'Donnees_USDA'!M615)*'Donnees_USDA'!M815+('Donnees_USDA'!M14+'Donnees_USDA'!M414-'Donnees_USDA'!M514-'Donnees_USDA'!M614)*'Donnees_USDA'!M814+('Donnees_USDA'!M17+'Donnees_USDA'!M417-'Donnees_USDA'!M517-'Donnees_USDA'!M617)*'Donnees_USDA'!M817 -> 1851.4304 | F15: =('Donnees_USDA'!M506+'Donnees_USDA'!M606)*'Donnees_USDA'!M806+('Donnees_USDA'!M508+'Donnees_USDA'!M608)*'Donnees_USDA'!M808+('Donnees_USDA'!M513+'Donnees_USDA'!M613)*'Donnees_USDA'!M813+('Donnees_USDA'!M515+'Donnees_USDA'!M615)*'Donnees_USDA'!M815+('Donnees_USDA'!M514+'Donnees_USDA'!M614)*'Donnees_USDA'!M814+('Donnees_USDA'!M517+'Donnees_USDA'!M617)*'Donnees_USDA'!M817 -> 80408.938 | G15: =E15/F15 -> 0.023025181 | H15: ='Prix_ICE'!J15 -> 143.75333 | I15: =('Donnees_USDA'!M7+'Donnees_USDA'!M407-'Donnees_USDA'!M507-'Donnees_USDA'!M607)*'Donnees_USDA'!M907 -> 1479.8793 | J15: =('Donnees_USDA'!M507+'Donnees_USDA'!M607)*'Donnees_USDA'!M907 -> 27102.103 | K15: =I15/J15 -> 0.054603854 | L15: =('Donnees_USDA'!M7+'Donnees_USDA'!M407-'Donnees_USDA'!M507-'Donnees_USDA'!M607)*'Donnees_USDA'!M907+('Donnees_USDA'!M6+'Donnees_USDA'!M406-'Donnees_USDA'!M506-'Donnees_USDA'!M606)*'Donnees_USDA'!M906+('Donnees_USDA'!M11+'Donnees_USDA'!M411-'Donnees_USDA'!M511-'Donnees_USDA'!M611)*'Donnees_USDA'!M911+('Donnees_USDA'!M10+'Donnees_USDA'!M410-'Donnees_USDA'!M510-'Donnees_USDA'!M610)*'Donnees_USDA'!M910 -> 1524.4194 | M15: =('Donnees_USDA'!M507+'Donnees_USDA'!M607)*'Donnees_USDA'!M907+('Donnees_USDA'!M506+'Donnees_USDA'!M606)*'Donnees_USDA'!M906+('Donnees_USDA'!M511+'Donnees_USDA'!M611)*'Donnees_USDA'!M911+('Donnees_USDA'!M510+'Donnees_USDA'!M610)*'Donnees_USDA'!M910 -> 63450.725 | N15: =L15/M15 -> 0.024025248 | O15: ='Prix_ICE'!L15 -> 1540.9394
A16: 2021/22 | B16: =('Donnees_USDA'!N6+'Donnees_USDA'!N406-'Donnees_USDA'!N506-'Donnees_USDA'!N606)*'Donnees_USDA'!N806 -> -2412.0482 | C16: =('Donnees_USDA'!N506+'Donnees_USDA'!N606)*'Donnees_USDA'!N806 -> 38859.036 | D16: =B16/C16 -> -0.062071745 | E16: =('Donnees_USDA'!N6+'Donnees_USDA'!N406-'Donnees_USDA'!N506-'Donnees_USDA'!N606)*'Donnees_USDA'!N806+('Donnees_USDA'!N8+'Donnees_USDA'!N408-'Donnees_USDA'!N508-'Donnees_USDA'!N608)*'Donnees_USDA'!N808+('Donnees_USDA'!N13+'Donnees_USDA'!N413-'Donnees_USDA'!N513-'Donnees_USDA'!N613)*'Donnees_USDA'!N813+('Donnees_USDA'!N15+'Donnees_USDA'!N415-'Donnees_USDA'!N515-'Donnees_USDA'!N615)*'Donnees_USDA'!N815+('Donnees_USDA'!N14+'Donnees_USDA'!N414-'Donnees_USDA'!N514-'Donnees_USDA'!N614)*'Donnees_USDA'!N814+('Donnees_USDA'!N17+'Donnees_USDA'!N417-'Donnees_USDA'!N517-'Donnees_USDA'!N617)*'Donnees_USDA'!N817 -> -3020.3804 | F16: =('Donnees_USDA'!N506+'Donnees_USDA'!N606)*'Donnees_USDA'!N806+('Donnees_USDA'!N508+'Donnees_USDA'!N608)*'Donnees_USDA'!N808+('Donnees_USDA'!N513+'Donnees_USDA'!N613)*'Donnees_USDA'!N813+('Donnees_USDA'!N515+'Donnees_USDA'!N615)*'Donnees_USDA'!N815+('Donnees_USDA'!N514+'Donnees_USDA'!N614)*'Donnees_USDA'!N814+('Donnees_USDA'!N517+'Donnees_USDA'!N617)*'Donnees_USDA'!N817 -> 70403.493 | G16: =E16/F16 -> -0.042901002 | H16: ='Prix_ICE'!J16 -> 224.0875 | I16: =('Donnees_USDA'!N7+'Donnees_USDA'!N407-'Donnees_USDA'!N507-'Donnees_USDA'!N607)*'Donnees_USDA'!N907 -> -77.213426 | J16: =('Donnees_USDA'!N507+'Donnees_USDA'!N607)*'Donnees_USDA'!N907 -> 31088.056 | K16: =I16/J16 -> -0.0024837007 | L16: =('Donnees_USDA'!N7+'Donnees_USDA'!N407-'Donnees_USDA'!N507-'Donnees_USDA'!N607)*'Donnees_USDA'!N907+('Donnees_USDA'!N6+'Donnees_USDA'!N406-'Donnees_USDA'!N506-'Donnees_USDA'!N606)*'Donnees_USDA'!N906+('Donnees_USDA'!N11+'Donnees_USDA'!N411-'Donnees_USDA'!N511-'Donnees_USDA'!N611)*'Donnees_USDA'!N911+('Donnees_USDA'!N10+'Donnees_USDA'!N410-'Donnees_USDA'!N510-'Donnees_USDA'!N610)*'Donnees_USDA'!N910 -> -1991.2754 | M16: =('Donnees_USDA'!N507+'Donnees_USDA'!N607)*'Donnees_USDA'!N907+('Donnees_USDA'!N506+'Donnees_USDA'!N606)*'Donnees_USDA'!N906+('Donnees_USDA'!N511+'Donnees_USDA'!N611)*'Donnees_USDA'!N911+('Donnees_USDA'!N510+'Donnees_USDA'!N610)*'Donnees_USDA'!N910 -> 69955.962 | N16: =L16/M16 -> -0.028464699 | O16: ='Prix_ICE'!L16 -> 2150.1501
A17: 2022/23 | B17: =('Donnees_USDA'!O6+'Donnees_USDA'!O406-'Donnees_USDA'!O506-'Donnees_USDA'!O606)*'Donnees_USDA'!O806 -> 2593.9936 | C17: =('Donnees_USDA'!O506+'Donnees_USDA'!O606)*'Donnees_USDA'!O806 -> 37253.69 | D17: =B17/C17 -> 0.069630515 | E17: =('Donnees_USDA'!O6+'Donnees_USDA'!O406-'Donnees_USDA'!O506-'Donnees_USDA'!O606)*'Donnees_USDA'!O806+('Donnees_USDA'!O8+'Donnees_USDA'!O408-'Donnees_USDA'!O508-'Donnees_USDA'!O608)*'Donnees_USDA'!O808+('Donnees_USDA'!O13+'Donnees_USDA'!O413-'Donnees_USDA'!O513-'Donnees_USDA'!O613)*'Donnees_USDA'!O813+('Donnees_USDA'!O15+'Donnees_USDA'!O415-'Donnees_USDA'!O515-'Donnees_USDA'!O615)*'Donnees_USDA'!O815+('Donnees_USDA'!O14+'Donnees_USDA'!O414-'Donnees_USDA'!O514-'Donnees_USDA'!O614)*'Donnees_USDA'!O814+('Donnees_USDA'!O17+'Donnees_USDA'!O417-'Donnees_USDA'!O517-'Donnees_USDA'!O617)*'Donnees_USDA'!O817 -> 2747.0684 | F17: =('Donnees_USDA'!O506+'Donnees_USDA'!O606)*'Donnees_USDA'!O806+('Donnees_USDA'!O508+'Donnees_USDA'!O608)*'Donnees_USDA'!O808+('Donnees_USDA'!O513+'Donnees_USDA'!O613)*'Donnees_USDA'!O813+('Donnees_USDA'!O515+'Donnees_USDA'!O615)*'Donnees_USDA'!O815+('Donnees_USDA'!O514+'Donnees_USDA'!O614)*'Donnees_USDA'!O814+('Donnees_USDA'!O517+'Donnees_USDA'!O617)*'Donnees_USDA'!O817 -> 66448.215 | G17: =E17/F17 -> 0.041341492 | H17: ='Prix_ICE'!J17 -> 171.19 | I17: =('Donnees_USDA'!O7+'Donnees_USDA'!O407-'Donnees_USDA'!O507-'Donnees_USDA'!O607)*'Donnees_USDA'!O907 -> -2644.1449 | J17: =('Donnees_USDA'!O507+'Donnees_USDA'!O607)*'Donnees_USDA'!O907 -> 30425.512 | K17: =I17/J17 -> -0.086905517 | L17: =('Donnees_USDA'!O7+'Donnees_USDA'!O407-'Donnees_USDA'!O507-'Donnees_USDA'!O607)*'Donnees_USDA'!O907+('Donnees_USDA'!O6+'Donnees_USDA'!O406-'Donnees_USDA'!O506-'Donnees_USDA'!O606)*'Donnees_USDA'!O906+('Donnees_USDA'!O11+'Donnees_USDA'!O411-'Donnees_USDA'!O511-'Donnees_USDA'!O611)*'Donnees_USDA'!O911+('Donnees_USDA'!O10+'Donnees_USDA'!O410-'Donnees_USDA'!O510-'Donnees_USDA'!O610)*'Donnees_USDA'!O910 -> -1639.0453 | M17: =('Donnees_USDA'!O507+'Donnees_USDA'!O607)*'Donnees_USDA'!O907+('Donnees_USDA'!O506+'Donnees_USDA'!O606)*'Donnees_USDA'!O906+('Donnees_USDA'!O511+'Donnees_USDA'!O611)*'Donnees_USDA'!O911+('Donnees_USDA'!O510+'Donnees_USDA'!O610)*'Donnees_USDA'!O910 -> 68518.664 | N17: =L17/M17 -> -0.023921152 | O17: ='Prix_ICE'!L17 -> 2217.0787
A18: 2023/24 | B18: =('Donnees_USDA'!P6+'Donnees_USDA'!P406-'Donnees_USDA'!P506-'Donnees_USDA'!P606)*'Donnees_USDA'!P806 -> -1716.7647 | C18: =('Donnees_USDA'!P506+'Donnees_USDA'!P606)*'Donnees_USDA'!P806 -> 46667.557 | D18: =B18/C18 -> -0.036787114 | E18: =('Donnees_USDA'!P6+'Donnees_USDA'!P406-'Donnees_USDA'!P506-'Donnees_USDA'!P606)*'Donnees_USDA'!P806+('Donnees_USDA'!P8+'Donnees_USDA'!P408-'Donnees_USDA'!P508-'Donnees_USDA'!P608)*'Donnees_USDA'!P808+('Donnees_USDA'!P13+'Donnees_USDA'!P413-'Donnees_USDA'!P513-'Donnees_USDA'!P613)*'Donnees_USDA'!P813+('Donnees_USDA'!P15+'Donnees_USDA'!P415-'Donnees_USDA'!P515-'Donnees_USDA'!P615)*'Donnees_USDA'!P815+('Donnees_USDA'!P14+'Donnees_USDA'!P414-'Donnees_USDA'!P514-'Donnees_USDA'!P614)*'Donnees_USDA'!P814+('Donnees_USDA'!P17+'Donnees_USDA'!P417-'Donnees_USDA'!P517-'Donnees_USDA'!P617)*'Donnees_USDA'!P817 -> -1916.5651 | F18: =('Donnees_USDA'!P506+'Donnees_USDA'!P606)*'Donnees_USDA'!P806+('Donnees_USDA'!P508+'Donnees_USDA'!P608)*'Donnees_USDA'!P808+('Donnees_USDA'!P513+'Donnees_USDA'!P613)*'Donnees_USDA'!P813+('Donnees_USDA'!P515+'Donnees_USDA'!P615)*'Donnees_USDA'!P815+('Donnees_USDA'!P514+'Donnees_USDA'!P614)*'Donnees_USDA'!P814+('Donnees_USDA'!P517+'Donnees_USDA'!P617)*'Donnees_USDA'!P817 -> 77131.581 | G18: =E18/F18 -> -0.024847994 | H18: ='Prix_ICE'!J18 -> 204.00167 | I18: =('Donnees_USDA'!P7+'Donnees_USDA'!P407-'Donnees_USDA'!P507-'Donnees_USDA'!P607)*'Donnees_USDA'!P907 -> 48.185118 | J18: =('Donnees_USDA'!P507+'Donnees_USDA'!P607)*'Donnees_USDA'!P907 -> 27272.777 | K18: =I18/J18 -> 0.0017667845 | L18: =('Donnees_USDA'!P7+'Donnees_USDA'!P407-'Donnees_USDA'!P507-'Donnees_USDA'!P607)*'Donnees_USDA'!P907+('Donnees_USDA'!P6+'Donnees_USDA'!P406-'Donnees_USDA'!P506-'Donnees_USDA'!P606)*'Donnees_USDA'!P906+('Donnees_USDA'!P11+'Donnees_USDA'!P411-'Donnees_USDA'!P511-'Donnees_USDA'!P611)*'Donnees_USDA'!P911+('Donnees_USDA'!P10+'Donnees_USDA'!P410-'Donnees_USDA'!P510-'Donnees_USDA'!P610)*'Donnees_USDA'!P910 -> -976.58104 | M18: =('Donnees_USDA'!P507+'Donnees_USDA'!P607)*'Donnees_USDA'!P907+('Donnees_USDA'!P506+'Donnees_USDA'!P606)*'Donnees_USDA'!P906+('Donnees_USDA'!P511+'Donnees_USDA'!P611)*'Donnees_USDA'!P911+('Donnees_USDA'!P510+'Donnees_USDA'!P610)*'Donnees_USDA'!P910 -> 63557.088 | N18: =L18/M18 -> -0.015365415 | O18: ='Prix_ICE'!L18 -> 3504.2477
A19: 2024/25 | B19: =('Donnees_USDA'!Q6+'Donnees_USDA'!Q406-'Donnees_USDA'!Q506-'Donnees_USDA'!Q606)*'Donnees_USDA'!Q806 -> -767.70992 | C19: =('Donnees_USDA'!Q506+'Donnees_USDA'!Q606)*'Donnees_USDA'!Q806 -> 45328.855 | D19: =B19/C19 -> -0.016936451 | E19: =('Donnees_USDA'!Q6+'Donnees_USDA'!Q406-'Donnees_USDA'!Q506-'Donnees_USDA'!Q606)*'Donnees_USDA'!Q806+('Donnees_USDA'!Q8+'Donnees_USDA'!Q408-'Donnees_USDA'!Q508-'Donnees_USDA'!Q608)*'Donnees_USDA'!Q808+('Donnees_USDA'!Q13+'Donnees_USDA'!Q413-'Donnees_USDA'!Q513-'Donnees_USDA'!Q613)*'Donnees_USDA'!Q813+('Donnees_USDA'!Q15+'Donnees_USDA'!Q415-'Donnees_USDA'!Q515-'Donnees_USDA'!Q615)*'Donnees_USDA'!Q815+('Donnees_USDA'!Q14+'Donnees_USDA'!Q414-'Donnees_USDA'!Q514-'Donnees_USDA'!Q614)*'Donnees_USDA'!Q814+('Donnees_USDA'!Q17+'Donnees_USDA'!Q417-'Donnees_USDA'!Q517-'Donnees_USDA'!Q617)*'Donnees_USDA'!Q817 -> -542.05982 | F19: =('Donnees_USDA'!Q506+'Donnees_USDA'!Q606)*'Donnees_USDA'!Q806+('Donnees_USDA'!Q508+'Donnees_USDA'!Q608)*'Donnees_USDA'!Q808+('Donnees_USDA'!Q513+'Donnees_USDA'!Q613)*'Donnees_USDA'!Q813+('Donnees_USDA'!Q515+'Donnees_USDA'!Q615)*'Donnees_USDA'!Q815+('Donnees_USDA'!Q514+'Donnees_USDA'!Q614)*'Donnees_USDA'!Q814+('Donnees_USDA'!Q517+'Donnees_USDA'!Q617)*'Donnees_USDA'!Q817 -> 78907.692 | G19: =E19/F19 -> -0.0068695435 | H19: ='Prix_ICE'!J19 -> 333.06 | I19: =('Donnees_USDA'!Q7+'Donnees_USDA'!Q407-'Donnees_USDA'!Q507-'Donnees_USDA'!Q607)*'Donnees_USDA'!Q907 -> 193.10345 | J19: =('Donnees_USDA'!Q507+'Donnees_USDA'!Q607)*'Donnees_USDA'!Q907 -> 28965.517 | K19: =I19/J19 -> 0.0066666667 | L19: =('Donnees_USDA'!Q7+'Donnees_USDA'!Q407-'Donnees_USDA'!Q507-'Donnees_USDA'!Q607)*'Donnees_USDA'!Q907+('Donnees_USDA'!Q6+'Donnees_USDA'!Q406-'Donnees_USDA'!Q506-'Donnees_USDA'!Q606)*'Donnees_USDA'!Q906+('Donnees_USDA'!Q11+'Donnees_USDA'!Q411-'Donnees_USDA'!Q511-'Donnees_USDA'!Q611)*'Donnees_USDA'!Q911+('Donnees_USDA'!Q10+'Donnees_USDA'!Q410-'Donnees_USDA'!Q510-'Donnees_USDA'!Q610)*'Donnees_USDA'!Q910 -> -24.609351 | M19: =('Donnees_USDA'!Q507+'Donnees_USDA'!Q607)*'Donnees_USDA'!Q907+('Donnees_USDA'!Q506+'Donnees_USDA'!Q606)*'Donnees_USDA'!Q906+('Donnees_USDA'!Q511+'Donnees_USDA'!Q611)*'Donnees_USDA'!Q911+('Donnees_USDA'!Q510+'Donnees_USDA'!Q610)*'Donnees_USDA'!Q910 -> 66572.739 | N19: =L19/M19 -> -0.00036966108 | O19: ='Prix_ICE'!L19 -> 4701.7435
A20: 2025/26 | B20: =('Donnees_USDA'!R6+'Donnees_USDA'!R406-'Donnees_USDA'!R506-'Donnees_USDA'!R606)*'Donnees_USDA'!R806 -> 1773.3333 | C20: =('Donnees_USDA'!R506+'Donnees_USDA'!R606)*'Donnees_USDA'!R806 -> 36280.952 | D20: =B20/C20 -> 0.048877805 | E20: =('Donnees_USDA'!R6+'Donnees_USDA'!R406-'Donnees_USDA'!R506-'Donnees_USDA'!R606)*'Donnees_USDA'!R806+('Donnees_USDA'!R8+'Donnees_USDA'!R408-'Donnees_USDA'!R508-'Donnees_USDA'!R608)*'Donnees_USDA'!R808+('Donnees_USDA'!R13+'Donnees_USDA'!R413-'Donnees_USDA'!R513-'Donnees_USDA'!R613)*'Donnees_USDA'!R813+('Donnees_USDA'!R15+'Donnees_USDA'!R415-'Donnees_USDA'!R515-'Donnees_USDA'!R615)*'Donnees_USDA'!R815+('Donnees_USDA'!R14+'Donnees_USDA'!R414-'Donnees_USDA'!R514-'Donnees_USDA'!R614)*'Donnees_USDA'!R814+('Donnees_USDA'!R17+'Donnees_USDA'!R417-'Donnees_USDA'!R517-'Donnees_USDA'!R617)*'Donnees_USDA'!R817 -> 1953.5833 | F20: =('Donnees_USDA'!R506+'Donnees_USDA'!R606)*'Donnees_USDA'!R806+('Donnees_USDA'!R508+'Donnees_USDA'!R608)*'Donnees_USDA'!R808+('Donnees_USDA'!R513+'Donnees_USDA'!R613)*'Donnees_USDA'!R813+('Donnees_USDA'!R515+'Donnees_USDA'!R615)*'Donnees_USDA'!R815+('Donnees_USDA'!R514+'Donnees_USDA'!R614)*'Donnees_USDA'!R814+('Donnees_USDA'!R517+'Donnees_USDA'!R617)*'Donnees_USDA'!R817 -> 69765.653 | G20: =E20/F20 -> 0.028002079 | H20: ='Prix_ICE'!J20 -> 312.21 | I20: =('Donnees_USDA'!R7+'Donnees_USDA'!R407-'Donnees_USDA'!R507-'Donnees_USDA'!R607)*'Donnees_USDA'!R907 -> -384.85804 | J20: =('Donnees_USDA'!R507+'Donnees_USDA'!R607)*'Donnees_USDA'!R907 -> 32135.647 | K20: =I20/J20 -> -0.011976048 | L20: =('Donnees_USDA'!R7+'Donnees_USDA'!R407-'Donnees_USDA'!R507-'Donnees_USDA'!R607)*'Donnees_USDA'!R907+('Donnees_USDA'!R6+'Donnees_USDA'!R406-'Donnees_USDA'!R506-'Donnees_USDA'!R606)*'Donnees_USDA'!R906+('Donnees_USDA'!R11+'Donnees_USDA'!R411-'Donnees_USDA'!R511-'Donnees_USDA'!R611)*'Donnees_USDA'!R911+('Donnees_USDA'!R10+'Donnees_USDA'!R410-'Donnees_USDA'!R510-'Donnees_USDA'!R610)*'Donnees_USDA'!R910 -> 951.26089 | M20: =('Donnees_USDA'!R507+'Donnees_USDA'!R607)*'Donnees_USDA'!R907+('Donnees_USDA'!R506+'Donnees_USDA'!R606)*'Donnees_USDA'!R906+('Donnees_USDA'!R511+'Donnees_USDA'!R611)*'Donnees_USDA'!R911+('Donnees_USDA'!R510+'Donnees_USDA'!R610)*'Donnees_USDA'!R910 -> 74064.971 | N20: =L20/M20 -> 0.0128436 | O20: ='Prix_ICE'!L20 -> 3788.4636
A21: 2026/27 (prév.) | B21: =('Donnees_USDA'!S6+'Donnees_USDA'!S406-'Donnees_USDA'!S506-'Donnees_USDA'!S606)*'Donnees_USDA'!S806 -> 350.13908 | C21: =('Donnees_USDA'!S506+'Donnees_USDA'!S606)*'Donnees_USDA'!S806 -> 47209.318 | D21: =B21/C21 -> 0.0074167366 | E21: =('Donnees_USDA'!S6+'Donnees_USDA'!S406-'Donnees_USDA'!S506-'Donnees_USDA'!S606)*'Donnees_USDA'!S806+('Donnees_USDA'!S8+'Donnees_USDA'!S408-'Donnees_USDA'!S508-'Donnees_USDA'!S608)*'Donnees_USDA'!S808+('Donnees_USDA'!S13+'Donnees_USDA'!S413-'Donnees_USDA'!S513-'Donnees_USDA'!S613)*'Donnees_USDA'!S813+('Donnees_USDA'!S15+'Donnees_USDA'!S415-'Donnees_USDA'!S515-'Donnees_USDA'!S615)*'Donnees_USDA'!S815+('Donnees_USDA'!S14+'Donnees_USDA'!S414-'Donnees_USDA'!S514-'Donnees_USDA'!S614)*'Donnees_USDA'!S814+('Donnees_USDA'!S17+'Donnees_USDA'!S417-'Donnees_USDA'!S517-'Donnees_USDA'!S617)*'Donnees_USDA'!S817 -> 446.44921 | F21: =('Donnees_USDA'!S506+'Donnees_USDA'!S606)*'Donnees_USDA'!S806+('Donnees_USDA'!S508+'Donnees_USDA'!S608)*'Donnees_USDA'!S808+('Donnees_USDA'!S513+'Donnees_USDA'!S613)*'Donnees_USDA'!S813+('Donnees_USDA'!S515+'Donnees_USDA'!S615)*'Donnees_USDA'!S815+('Donnees_USDA'!S514+'Donnees_USDA'!S614)*'Donnees_USDA'!S814+('Donnees_USDA'!S517+'Donnees_USDA'!S617)*'Donnees_USDA'!S817 -> 81607.435 | G21: =E21/F21 -> 0.0054706928 | I21: =('Donnees_USDA'!S7+'Donnees_USDA'!S407-'Donnees_USDA'!S507-'Donnees_USDA'!S607)*'Donnees_USDA'!S907 -> -193.23077 | J21: =('Donnees_USDA'!S507+'Donnees_USDA'!S607)*'Donnees_USDA'!S907 -> 32800.923 | K21: =I21/J21 -> -0.0058910162 | L21: =('Donnees_USDA'!S7+'Donnees_USDA'!S407-'Donnees_USDA'!S507-'Donnees_USDA'!S607)*'Donnees_USDA'!S907+('Donnees_USDA'!S6+'Donnees_USDA'!S406-'Donnees_USDA'!S506-'Donnees_USDA'!S606)*'Donnees_USDA'!S906+('Donnees_USDA'!S11+'Donnees_USDA'!S411-'Donnees_USDA'!S511-'Donnees_USDA'!S611)*'Donnees_USDA'!S911+('Donnees_USDA'!S10+'Donnees_USDA'!S410-'Donnees_USDA'!S510-'Donnees_USDA'!S610)*'Donnees_USDA'!S910 -> -87.876023 | M21: =('Donnees_USDA'!S507+'Donnees_USDA'!S607)*'Donnees_USDA'!S907+('Donnees_USDA'!S506+'Donnees_USDA'!S606)*'Donnees_USDA'!S906+('Donnees_USDA'!S511+'Donnees_USDA'!S611)*'Donnees_USDA'!S911+('Donnees_USDA'!S510+'Donnees_USDA'!S610)*'Donnees_USDA'!S910 -> 74398.914 | N21: =L21/M21 -> -0.0011811466
A24: Pour un seul pays, répartir arabica/robusta ne change pas le ratio : « Brésil arabica » = ratio Brésil total (idem Vietnam).

Sheet Tableau_STU
A1: Tableau — stock-to-use par pays (lignes) et par campagne (colonnes)
A2: Couleurs par ligne : rouge = ratio bas pour ce pays (marché tendu), vert = ratio haut (confortable). 2026/27 = prévision USDA juin 2026.
A4: Série | B4: Définition | C4: 2010/11 | D4: 2011/12 | E4: 2012/13 | F4: 2013/14 | G4: 2014/15 | H4: 2015/16 | I4: 2016/17 | J4: 2017/18 | K4: 2018/19 | L4: 2019/20 | M4: 2020/21 | N4: 2021/22 | O4: 2022/23 | P4: 2023/24 | Q4: 2024/25 | R4: 2025/26 | S4: 2026/27
A6: Agrégats
A7: MONDE | B7: stocks ÷ conso | C7: ='1_Monde'!E5 -> 0.21135284 | D7: ='1_Monde'!E6 -> 0.18026899 | E7: ='1_Monde'!E7 -> 0.24661785 | F7: ='1_Monde'!E8 -> 0.2862445 | G7: ='1_Monde'!E9 -> 0.29308998 | H7: ='1_Monde'!E10 -> 0.22816054 | I7: ='1_Monde'!E11 -> 0.23502295 | J7: ='1_Monde'!E12 -> 0.19891425 | K7: ='1_Monde'!E13 -> 0.22256224 | L7: ='1_Monde'!E14 -> 0.22055372 | M7: ='1_Monde'!E15 -> 0.23131165 | N7: ='1_Monde'!E16 -> 0.19025948 | O7: ='1_Monde'!E17 -> 0.15960511 | P7: ='1_Monde'!E18 -> 0.14102986 | Q7: ='1_Monde'!E19 -> 0.12814318 | R7: ='1_Monde'!E20 -> 0.1404943 | S7: ='1_Monde'!E21 -> 0.14623114
A8: MONDE | B8: stocks ÷ (conso + export) | C8: ='1_Monde'!F5 -> 0.11343473 | D8: ='1_Monde'!F6 -> 0.098703529 | E8: ='1_Monde'!F7 -> 0.13263251 | F8: ='1_Monde'!F8 -> 0.15078148 | G8: ='1_Monde'!F9 -> 0.15904716 | H8: ='1_Monde'!F10 -> 0.12176734 | I8: ='1_Monde'!F11 -> 0.12626165 | J8: ='1_Monde'!F12 -> 0.10838159 | K8: ='1_Monde'!F13 -> 0.1194245 | L8: ='1_Monde'!F14 -> 0.11882292 | M8: ='1_Monde'!F15 -> 0.12211677 | N8: ='1_Monde'!F16 -> 0.10254961 | O8: ='1_Monde'!F17 -> 0.088758391 | P8: ='1_Monde'!F18 -> 0.0752103 | Q8: ='1_Monde'!F19 -> 0.06888738 | R8: ='1_Monde'!F20 -> 0.076299072 | S8: ='1_Monde'!F21 -> 0.077620271
A9: Pays producteurs (47) | B9: stocks ÷ (conso + export) | C9: ='Donnees_USDA'!C799/('Donnees_USDA'!C599+'Donnees_USDA'!C699) -> 0.074244507 | D9: ='Donnees_USDA'!D799/('Donnees_USDA'!D599+'Donnees_USDA'!D699) -> 0.0724373 | E9: ='Donnees_USDA'!E799/('Donnees_USDA'!E599+'Donnees_USDA'!E699) -> 0.11395378 | F9: ='Donnees_USDA'!F799/('Donnees_USDA'!F599+'Donnees_USDA'!F699) -> 0.13111641 | G9: ='Donnees_USDA'!G799/('Donnees_USDA'!G599+'Donnees_USDA'!G699) -> 0.14387073 | H9: ='Donnees_USDA'!H799/('Donnees_USDA'!H599+'Donnees_USDA'!H699) -> 0.094552698 | I9: ='Donnees_USDA'!I799/('Donnees_USDA'!I599+'Donnees_USDA'!I699) -> 0.093547697 | J9: ='Donnees_USDA'!J799/('Donnees_USDA'!J599+'Donnees_USDA'!J699) -> 0.075364621 | ... S9: ='Donnees_USDA'!S799/('Donnees_USDA'!S599+'Donnees_USDA'!S699) -> 0.060662274
A10: Pays importateurs (46) | B10: stocks ÷ conso | C10: ='Donnees_USDA'!C800/'Donnees_USDA'!C600 -> 0.21410212 | D10: ='Donnees_USDA'!D800/'Donnees_USDA'!D600 -> 0.16440511 | E10: ='Donnees_USDA'!E800/'Donnees_USDA'!E600 -> 0.18417372 | F10: ='Donnees_USDA'!F800/'Donnees_USDA'!F600 -> 0.2084454 | G10: ='Donnees_USDA'!G800/'Donnees_USDA'!G600 -> 0.20258845 | H10: ='Donnees_USDA'!H800/'Donnees_USDA'!H600 -> 0.19810853 | I10: ='Donnees_USDA'!I800/'Donnees_USDA'!I600 -> 0.21813272 | J10: ='Donnees_USDA'!J800/'Donnees_USDA'!J600 -> 0.19723766 | ... S10: ='Donnees_USDA'!S800/'Donnees_USDA'!S600 -> 0.1311253
A11: ARABICA — total producteurs | B11: pondéré par espèce | C11: ='2_Arabica_Robusta'!D5 -> 0.079517394 | D11: ='2_Arabica_Robusta'!D6 -> 0.084031352 | E11: ='2_Arabica_Robusta'!D7 -> 0.12809954 | F11: ='2_Arabica_Robusta'!D8 -> 0.15133298 | G11: ='2_Arabica_Robusta'!D9 -> 0.13412412 | H11: ='2_Arabica_Robusta'!D10 -> 0.095039352 | I11: ='2_Arabica_Robusta'!D11 -> 0.10307917 | J11: ='2_Arabica_Robusta'!D12 -> 0.095089841 | K11: ='2_Arabica_Robusta'!D13 -> 0.096865213 | L11: ='2_Arabica_Robusta'!D14 -> 0.085599027 | M11: ='2_Arabica_Robusta'!D15 -> 0.094802092 | N11: ='2_Arabica_Robusta'!D16 -> 0.072169466 | O11: ='2_Arabica_Robusta'!D17 -> 0.090007788 | P11: ='2_Arabica_Robusta'!D18 -> 0.070338022 | Q11: ='2_Arabica_Robusta'!D19 -> 0.063064873 | R11: ='2_Arabica_Robusta'!D20 -> 0.082443946 | S11: ='2_Arabica_Robusta'!D21 -> 0.077592572
A12: ROBUSTA — total producteurs | B12: pondéré par espèce | C12: ='2_Arabica_Robusta'!G5 -> 0.064195656 | D12: ='2_Arabica_Robusta'!G6 -> 0.05305626 | E12: ='2_Arabica_Robusta'!G7 -> 0.090761688 | F12: ='2_Arabica_Robusta'!G8 -> 0.098673563 | G12: ='2_Arabica_Robusta'!G9 -> 0.15970313 | H12: ='2_Arabica_Robusta'!G10 -> 0.09382521 | I12: ='2_Arabica_Robusta'!G11 -> 0.07621885 | J12: ='2_Arabica_Robusta'!G12 -> 0.043209964 | K12: ='2_Arabica_Robusta'!G13 -> 0.072439018 | L12: ='2_Arabica_Robusta'!G14 -> 0.07954051 | M12: ='2_Arabica_Robusta'!G15 -> 0.097307549 | N12: ='2_Arabica_Robusta'!G16 -> 0.062648095 | O12: ='2_Arabica_Robusta'!G17 -> 0.047583531 | P12: ='2_Arabica_Robusta'!G18 -> 0.031610359 | Q12: ='2_Arabica_Robusta'!G19 -> 0.031833664 | R12: ='2_Arabica_Robusta'!G20 -> 0.040732208 | S12: ='2_Arabica_Robusta'!G21 -> 0.035174806
A13: Arabica — 8 pays | B13: Brésil réparti | C13: ='3_Groupes_pays'!D5 -> 0.040644228 | D13: ='3_Groupes_pays'!D6 -> 0.039270214 | E13: ='3_Groupes_pays'!D7 -> 0.10940164 | F13: ='3_Groupes_pays'!D8 -> 0.13606894 | G13: ='3_Groupes_pays'!D9 -> 0.099612787 | H13: ='3_Groupes_pays'!D10 -> 0.047556565 | I13: ='3_Groupes_pays'!D11 -> 0.054382993 | J13: ='3_Groupes_pays'!D12 -> 0.052826195 | K13: ='3_Groupes_pays'!D13 -> 0.051435879 | L13: ='3_Groupes_pays'!D14 -> 0.040565899 | M13: ='3_Groupes_pays'!D15 -> 0.057467412 | N13: ='3_Groupes_pays'!D16 -> 0.020905732 | O13: ='3_Groupes_pays'!D17 -> 0.05705694 | P13: ='3_Groupes_pays'!D18 -> 0.027971646 | Q13: ='3_Groupes_pays'!D19 -> 0.022271881 | R13: ='3_Groupes_pays'!D20 -> 0.047794318 | S13: ='3_Groupes_pays'!D21 -> 0.047105925
A14: Robusta — 4 pays | B14: Brésil réparti | C14: ='3_Groupes_pays'!G5 -> 0.045367702 | D14: ='3_Groupes_pays'!G6 -> 0.043436612 | E14: ='3_Groupes_pays'!G7 -> 0.088211795 | F14: ='3_Groupes_pays'!G8 -> 0.097424586 | G14: ='3_Groupes_pays'!G9 -> 0.17311894 | H14: ='3_Groupes_pays'!G10 -> 0.082870724 | I14: ='3_Groupes_pays'!G11 -> 0.068457391 | J14: ='3_Groupes_pays'!G12 -> 0.031267198 | K14: ='3_Groupes_pays'!G13 -> 0.071059622 | L14: ='3_Groupes_pays'!G14 -> 0.080057175 | M14: ='3_Groupes_pays'!G15 -> 0.10421061 | N14: ='3_Groupes_pays'!G16 -> 0.070972345 | O14: ='3_Groupes_pays'!G17 -> 0.048661738 | P14: ='3_Groupes_pays'!G18 -> 0.033608897 | Q14: ='3_Groupes_pays'!G19 -> 0.03193341 | R14: ='3_Groupes_pays'!G20 -> 0.042633566 | S14: ='3_Groupes_pays'!G21 -> 0.038180614
A16: Pays — stocks de fin ÷ (conso domestique + exportations)
A17: Brésil | B17: stocks ÷ (conso + export) | C17: ='Donnees_USDA'!C706/('Donnees_USDA'!C506+'Donnees_USDA'!C606) -> 0.053389675 | D17: ='Donnees_USDA'!D706/('Donnees_USDA'!D506+'Donnees_USDA'!D606) -> 0.044878479 | E17: ='Donnees_USDA'!E706/('Donnees_USDA'!E506+'Donnees_USDA'!E606) -> 0.17860942 | F17: ='Donnees_USDA'!F706/('Donnees_USDA'!F506+'Donnees_USDA'!F606) -> 0.21977335 | G17: ='Donnees_USDA'!G706/('Donnees_USDA'!G506+'Donnees_USDA'!G606) -> 0.16326566 | H17: ='Donnees_USDA'!H706/('Donnees_USDA'!H506+'Donnees_USDA'!H606) -> 0.042058229 | I17: ='Donnees_USDA'!I706/('Donnees_USDA'!I506+'Donnees_USDA'!I606) -> 0.069974043 | J17: ='Donnees_USDA'!J706/('Donnees_USDA'!J506+'Donnees_USDA'!J606) -> 0.058913644 | ... S17: ='Donnees_USDA'!S706/('Donnees_USDA'!S506+'Donnees_USDA'!S606) -> 0.061922754
A18: Vietnam | B18: stocks ÷ (conso + export) | C18: ='Donnees_USDA'!C707/('Donnees_USDA'!C507+'Donnees_USDA'!C607) -> 0.040046053 | D18: ='Donnees_USDA'!D707/('Donnees_USDA'!D507+'Donnees_USDA'!D607) -> 0.041666667 | E18: ='Donnees_USDA'!E707/('Donnees_USDA'!E507+'Donnees_USDA'!E607) -> 0.073522744 | F18: ='Donnees_USDA'!F707/('Donnees_USDA'!F507+'Donnees_USDA'!F607) -> 0.07030399 | G18: ='Donnees_USDA'!G707/('Donnees_USDA'!G507+'Donnees_USDA'!G607) -> 0.26639758 | H18: ='Donnees_USDA'!H707/('Donnees_USDA'!H507+'Donnees_USDA'!H607) -> 0.13254457 | I18: ='Donnees_USDA'!I707/('Donnees_USDA'!I507+'Donnees_USDA'!I607) -> 0.091752225 | J18: ='Donnees_USDA'!J707/('Donnees_USDA'!J507+'Donnees_USDA'!J607) -> 0.0077469729 | ... S18: ='Donnees_USDA'!S707/('Donnees_USDA'!S507+'Donnees_USDA'!S607) -> 0.014403535
A19: Colombie | B19: stocks ÷ (conso + export) | C19: ='Donnees_USDA'!C708/('Donnees_USDA'!C508+'Donnees_USDA'!C608) -> 0.010415571 | D19: ='Donnees_USDA'!D708/('Donnees_USDA'!D508+'Donnees_USDA'!D608) -> 0.028886311 | E19: ='Donnees_USDA'!E708/('Donnees_USDA'!E508+'Donnees_USDA'!E608) -> 0.07667827 | F19: ='Donnees_USDA'!F708/('Donnees_USDA'!F508+'Donnees_USDA'!F608) -> 0.077876823 | G19: ='Donnees_USDA'!G708/('Donnees_USDA'!G508+'Donnees_USDA'!G608) -> 0.048552822 | H19: ='Donnees_USDA'!H708/('Donnees_USDA'!H508+'Donnees_USDA'!H608) -> 0.081926838 | I19: ='Donnees_USDA'!I708/('Donnees_USDA'!I508+'Donnees_USDA'!I608) -> 0.058270306 | J19: ='Donnees_USDA'!J708/('Donnees_USDA'!J508+'Donnees_USDA'!J608) -> 0.077286957 | ... S19: ='Donnees_USDA'!S708/('Donnees_USDA'!S508+'Donnees_USDA'!S608) -> 0.042948718
A20: Indonésie | B20: stocks ÷ (conso + export) | C20: ='Donnees_USDA'!C710/('Donnees_USDA'!C510+'Donnees_USDA'!C610) -> 0.0072934974 | D20: ='Donnees_USDA'!D710/('Donnees_USDA'!D510+'Donnees_USDA'!D610) -> 0.0094929881 | E20: ='Donnees_USDA'!E710/('Donnees_USDA'!E510+'Donnees_USDA'!E610) -> 0.0074581431 | F20: ='Donnees_USDA'!F710/('Donnees_USDA'!F510+'Donnees_USDA'!F610) -> 0.0037151703 | G20: ='Donnees_USDA'!G710/('Donnees_USDA'!G510+'Donnees_USDA'!G610) -> 0.0045611015 | H20: ='Donnees_USDA'!H710/('Donnees_USDA'!H510+'Donnees_USDA'!H610) -> 0.0035192411 | I20: ='Donnees_USDA'!I710/('Donnees_USDA'!I510+'Donnees_USDA'!I610) -> 0.0010547596 | J20: ='Donnees_USDA'!J710/('Donnees_USDA'!J510+'Donnees_USDA'!J610) -> 0.051253241 | ... S20: ='Donnees_USDA'!S710/('Donnees_USDA'!S510+'Donnees_USDA'!S610) -> 0.052096273
A21: Éthiopie | B21: stocks ÷ (conso + export) | C21: ='Donnees_USDA'!C709/('Donnees_USDA'!C509+'Donnees_USDA'!C609) -> 0.016406891 | D21: ='Donnees_USDA'!D709/('Donnees_USDA'!D509+'Donnees_USDA'!D609) -> 0.037156704 | E21: ='Donnees_USDA'!E709/('Donnees_USDA'!E509+'Donnees_USDA'!E609) -> 0.015082956 | F21: ='Donnees_USDA'!F709/('Donnees_USDA'!F509+'Donnees_USDA'!F609) -> 0.006245121 | G21: ='Donnees_USDA'!G709/('Donnees_USDA'!G509+'Donnees_USDA'!G609) -> 0.0046260601 | H21: ='Donnees_USDA'!H709/('Donnees_USDA'!H509+'Donnees_USDA'!H609) -> 0.0038372985 | I21: ='Donnees_USDA'!I709/('Donnees_USDA'!I509+'Donnees_USDA'!I609) -> 0.0021573422 | J21: ='Donnees_USDA'!J709/('Donnees_USDA'!J509+'Donnees_USDA'!J609) -> 0.0038335936 | ... S21: ='Donnees_USDA'!S709/('Donnees_USDA'!S509+'Donnees_USDA'!S609) -> 0.011953833
A22: Ouganda | B22: stocks ÷ (conso + export) | C22: ='Donnees_USDA'!C711/('Donnees_USDA'!C511+'Donnees_USDA'!C611) -> 0.18575758 | D22: ='Donnees_USDA'!D711/('Donnees_USDA'!D511+'Donnees_USDA'!D611) -> 0.17079365 | E22: ='Donnees_USDA'!E711/('Donnees_USDA'!E511+'Donnees_USDA'!E611) -> 0.09615894 | F22: ='Donnees_USDA'!F711/('Donnees_USDA'!F511+'Donnees_USDA'!F611) -> 0.10287958 | G22: ='Donnees_USDA'!G711/('Donnees_USDA'!G511+'Donnees_USDA'!G611) -> 0.087430168 | H22: ='Donnees_USDA'!H711/('Donnees_USDA'!H511+'Donnees_USDA'!H611) -> 0.088169014 | I22: ='Donnees_USDA'!I711/('Donnees_USDA'!I511+'Donnees_USDA'!I611) -> 0.069690722 | J22: ='Donnees_USDA'!J711/('Donnees_USDA'!J511+'Donnees_USDA'!J611) -> 0.085274725 | ... S22: ='Donnees_USDA'!S711/('Donnees_USDA'!S511+'Donnees_USDA'!S611) -> 0.045917655
A23: Honduras | B23: stocks ÷ (conso + export) | C23: ='Donnees_USDA'!C713/('Donnees_USDA'!C513+'Donnees_USDA'!C613) -> 0.0071667463 | D23: ='Donnees_USDA'!D713/('Donnees_USDA'!D513+'Donnees_USDA'!D613) -> 0.01620162 | E23: ='Donnees_USDA'!E713/('Donnees_USDA'!E513+'Donnees_USDA'!E613) -> 0.029850746 | F23: ='Donnees_USDA'!F713/('Donnees_USDA'!F513+'Donnees_USDA'!F613) -> 0.070505288 | G23: ='Donnees_USDA'!G713/('Donnees_USDA'!G513+'Donnees_USDA'!G613) -> 0.066929134 | H23: ='Donnees_USDA'!H713/('Donnees_USDA'!H513+'Donnees_USDA'!H613) -> 0.058933583 | I23: ='Donnees_USDA'!I713/('Donnees_USDA'!I513+'Donnees_USDA'!I613) -> 0.039735099 | J23: ='Donnees_USDA'!J713/('Donnees_USDA'!J513+'Donnees_USDA'!J613) -> 0.042763158 | ... S23: ='Donnees_USDA'!S713/('Donnees_USDA'!S513+'Donnees_USDA'!S613) -> 0.11946604
A24: Inde | B24: stocks ÷ (conso + export) | C24: ='Donnees_USDA'!C712/('Donnees_USDA'!C512+'Donnees_USDA'!C612) -> 0.2582271 | D24: ='Donnees_USDA'!D712/('Donnees_USDA'!D512+'Donnees_USDA'!D612) -> 0.23048036 | E24: ='Donnees_USDA'!E712/('Donnees_USDA'!E512+'Donnees_USDA'!E612) -> 0.33266197 | F24: ='Donnees_USDA'!F712/('Donnees_USDA'!F512+'Donnees_USDA'!F612) -> 0.32767265 | G24: ='Donnees_USDA'!G712/('Donnees_USDA'!G512+'Donnees_USDA'!G612) -> 0.42497946 | H24: ='Donnees_USDA'!H712/('Donnees_USDA'!H512+'Donnees_USDA'!H612) -> 0.38095924 | I24: ='Donnees_USDA'!I712/('Donnees_USDA'!I512+'Donnees_USDA'!I612) -> 0.25455287 | J24: ='Donnees_USDA'!J712/('Donnees_USDA'!J512+'Donnees_USDA'!J612) -> 0.16949613 | ... S24: ='Donnees_USDA'!S712/('Donnees_USDA'!S512+'Donnees_USDA'!S612) -> 0.027695858
A25: Pérou | B25: stocks ÷ (conso + export) | C25: ='Donnees_USDA'!C714/('Donnees_USDA'!C514+'Donnees_USDA'!C614) -> 0.030617284 | D25: ='Donnees_USDA'!D714/('Donnees_USDA'!D514+'Donnees_USDA'!D614) -> 0.0026365348 | E25: ='Donnees_USDA'!E714/('Donnees_USDA'!E514+'Donnees_USDA'!E614) -> 0.01030445 | F25: ='Donnees_USDA'!F714/('Donnees_USDA'!F514+'Donnees_USDA'!F614) -> 0.0056206089 | G25: ='Donnees_USDA'!G714/('Donnees_USDA'!G514+'Donnees_USDA'!G614) -> 0.001369863 | H25: ='Donnees_USDA'!H714/('Donnees_USDA'!H514+'Donnees_USDA'!H614) -> 0.012716763 | I25: ='Donnees_USDA'!I714/('Donnees_USDA'!I514+'Donnees_USDA'!I614) -> 0.01788269 | J25: ='Donnees_USDA'!J714/('Donnees_USDA'!J514+'Donnees_USDA'!J614) -> 0.019473081 | ... S25: ='Donnees_USDA'!S714/('Donnees_USDA'!S514+'Donnees_USDA'!S614) -> 0.0053508952
A26: Mexique | B26: stocks ÷ (conso + export) | C26: ='Donnees_USDA'!C715/('Donnees_USDA'!C515+'Donnees_USDA'!C615) -> 0.017181467 | D26: ='Donnees_USDA'!D715/('Donnees_USDA'!D515+'Donnees_USDA'!D615) -> 0.010969568 | E26: ='Donnees_USDA'!E715/('Donnees_USDA'!E515+'Donnees_USDA'!E615) -> 0.010542689 | F26: ='Donnees_USDA'!F715/('Donnees_USDA'!F515+'Donnees_USDA'!F615) -> 0.030975073 | G26: ='Donnees_USDA'!G715/('Donnees_USDA'!G515+'Donnees_USDA'!G615) -> 0.025515411 | H26: ='Donnees_USDA'!H715/('Donnees_USDA'!H515+'Donnees_USDA'!H615) -> 0.045016077 | I26: ='Donnees_USDA'!I715/('Donnees_USDA'!I515+'Donnees_USDA'!I615) -> 0.031084925 | J26: ='Donnees_USDA'!J715/('Donnees_USDA'!J515+'Donnees_USDA'!J615) -> 0.03318223 | ... S26: ='Donnees_USDA'!S715/('Donnees_USDA'!S515+'Donnees_USDA'!S615) -> 0.0007518797
A27: Guatemala | B27: stocks ÷ (conso + export) | C27: ='Donnees_USDA'!C716/('Donnees_USDA'!C516+'Donnees_USDA'!C616) -> 0.057108434 | D27: ='Donnees_USDA'!D716/('Donnees_USDA'!D516+'Donnees_USDA'!D616) -> 0.087162162 | E27: ='Donnees_USDA'!E716/('Donnees_USDA'!E516+'Donnees_USDA'!E616) -> 0.048512586 | F27: ='Donnees_USDA'!F716/('Donnees_USDA'!F516+'Donnees_USDA'!F616) -> 0.057687148 | G27: ='Donnees_USDA'!G716/('Donnees_USDA'!G516+'Donnees_USDA'!G616) -> 0.0042016807 | H27: ='Donnees_USDA'!H716/('Donnees_USDA'!H516+'Donnees_USDA'!H616) -> 0.0074841681 | I27: ='Donnees_USDA'!I716/('Donnees_USDA'!I516+'Donnees_USDA'!I616) -> 0.0095112285 | J27: ='Donnees_USDA'!J716/('Donnees_USDA'!J516+'Donnees_USDA'!J616) -> 0.026835443 | ... S27: ='Donnees_USDA'!S716/('Donnees_USDA'!S516+'Donnees_USDA'!S616) -> 0.003902439
A28: Nicaragua | B28: stocks ÷ (conso + export) | C28: ='Donnees_USDA'!C717/('Donnees_USDA'!C517+'Donnees_USDA'!C617) -> 0.012188366 | D28: ='Donnees_USDA'!D717/('Donnees_USDA'!D517+'Donnees_USDA'!D617) -> 0.13228346 | E28: ='Donnees_USDA'!E717/('Donnees_USDA'!E517+'Donnees_USDA'!E617) -> 0.0077625571 | F28: ='Donnees_USDA'!F717/('Donnees_USDA'!F517+'Donnees_USDA'!F617) -> 0.010891089 | G28: ='Donnees_USDA'!G717/('Donnees_USDA'!G517+'Donnees_USDA'!G617) -> 0.049156627 | H28: ='Donnees_USDA'!H717/('Donnees_USDA'!H517+'Donnees_USDA'!H617) -> 0.016666667 | I28: ='Donnees_USDA'!I717/('Donnees_USDA'!I517+'Donnees_USDA'!I617) -> 0.027376426 | J28: ='Donnees_USDA'!J717/('Donnees_USDA'!J517+'Donnees_USDA'!J617) -> 0.052886406 | ... S28: ='Donnees_USDA'!S717/('Donnees_USDA'!S517+'Donnees_USDA'!S617) -> 0.03526971
A29: Costa Rica | B29: stocks ÷ (conso + export) | C29: ='Donnees_USDA'!C722/('Donnees_USDA'!C522+'Donnees_USDA'!C622) -> 0.11785504 | D29: ='Donnees_USDA'!D722/('Donnees_USDA'!D522+'Donnees_USDA'!D622) -> 0.13157895 | E29: ='Donnees_USDA'!E722/('Donnees_USDA'!E522+'Donnees_USDA'!E622) -> 0.10674157 | F29: ='Donnees_USDA'!F722/('Donnees_USDA'!F522+'Donnees_USDA'!F622) -> 0.075581395 | G29: ='Donnees_USDA'!G722/('Donnees_USDA'!G522+'Donnees_USDA'!G622) -> 0.072289157 | H29: ='Donnees_USDA'!H722/('Donnees_USDA'!H522+'Donnees_USDA'!H622) -> 0.19688474 | I29: ='Donnees_USDA'!I722/('Donnees_USDA'!I522+'Donnees_USDA'!I622) -> 0.14966887 | J29: ='Donnees_USDA'!J722/('Donnees_USDA'!J522+'Donnees_USDA'!J622) -> 0.16131065 | ... S29: ='Donnees_USDA'!S722/('Donnees_USDA'!S522+'Donnees_USDA'!S622) -> 0.049275362
A31: Surplus (prod + import − conso − export) ÷ (conso + exportations)
A32: Arabica — Brésil | B32: (prod + import − conso − export) ÷ (conso + export) | C32: ='6_Surplus'!D5 -> 0.0012860555 | D32: ='6_Surplus'!D6 -> -0.013395364 | E32: ='6_Surplus'!D7 -> 0.13452826 | F32: ='6_Surplus'!D8 -> 0.052947237 | G32: ='6_Surplus'!D9 -> -0.046339024 | H32: ='6_Surplus'!D10 -> -0.12292989 | I32: ='6_Surplus'!D11 -> 0.026614997 | J32: ='6_Surplus'!D12 -> -0.013484889 | K32: ='6_Surplus'!D13 -> 0.030034351 | L32: ='6_Surplus'!D14 -> -0.042418972 | M32: ='6_Surplus'!D15 -> 0.029681407 | N32: ='6_Surplus'!D16 -> -0.062071745 | O32: ='6_Surplus'!D17 -> 0.069630515 | P32: ='6_Surplus'!D18 -> -0.036787114 | Q32: ='6_Surplus'!D19 -> -0.016936451 | R32: ='6_Surplus'!D20 -> 0.048877805 | S32: ='6_Surplus'!D21 -> 0.0074167366
A33: Arabica — 6 pays | B33: idem | C33: ='6_Surplus'!G5 -> -0.0047960435 | D33: ='6_Surplus'!G6 -> -0.0026936821 | E33: ='6_Surplus'!G7 -> 0.083917037 | F33: ='6_Surplus'!G8 -> 0.037480734 | G33: ='6_Surplus'!G9 -> -0.030266236 | H33: ='6_Surplus'!G10 -> -0.065082682 | I33: ='6_Surplus'!G11 -> 0.011896663 | J33: ='6_Surplus'!G12 -> -0.0024600594 | K33: ='6_Surplus'!G13 -> 0.0062751214 | L33: ='6_Surplus'!G14 -> -0.020279702 | M33: ='6_Surplus'!G15 -> 0.023025181 | N33: ='6_Surplus'!G16 -> -0.042901002 | O33: ='6_Surplus'!G17 -> 0.041341492 | P33: ='6_Surplus'!G18 -> -0.024847994 | Q33: ='6_Surplus'!G19 -> -0.0068695435 | R33: ='6_Surplus'!G20 -> 0.028002079 | S33: ='6_Surplus'!G21 -> 0.0054706928
A34: Robusta — Vietnam | B34: idem | C34: ='6_Surplus'!K5 -> -0.010612204 | D34: ='6_Surplus'!K6 -> 0.011085627 | E34: ='6_Surplus'!K7 -> 0.03234094 | F34: ='6_Surplus'!K8 -> 0.0060732086 | G34: ='6_Surplus'!K9 -> 0.17684157 | H34: ='6_Surplus'!K10 -> -0.067360782 | I34: ='6_Surplus'!K11 -> -0.052019165 | J34: ='6_Surplus'!K12 -> -0.074023241 | K34: ='6_Surplus'!K13 -> 0.0096615266 | L34: ='6_Surplus'!K14 -> 0.051732071 | M34: ='6_Surplus'!K15 -> 0.054603854 | N34: ='6_Surplus'!K16 -> -0.0024837007 | O34: ='6_Surplus'!K17 -> -0.086905517 | P34: ='6_Surplus'!K18 -> 0.0017667845 | Q34: ='6_Surplus'!K19 -> 0.0066666667 | R34: ='6_Surplus'!K20 -> -0.011976048 | S34: ='6_Surplus'!K21 -> -0.0058910162
A35: Robusta — 4 pays | B35: idem | C35: ='6_Surplus'!N5 -> -0.035071968 | D35: ='6_Surplus'!N6 -> 0.00069377626 | E35: ='6_Surplus'!N7 -> 0.047780132 | F35: ='6_Surplus'!N8 -> 0.016205138 | G35: ='6_Surplus'!N9 -> 0.058871139 | H35: ='6_Surplus'!N10 -> -0.06574397 | I35: ='6_Surplus'!N11 -> -0.022990496 | J35: ='6_Surplus'!N12 -> -0.033518787 | K35: ='6_Surplus'!N13 -> 0.039772916 | L35: ='6_Surplus'!N14 -> 0.0095923524 | M35: ='6_Surplus'!N15 -> 0.024025248 | N35: ='6_Surplus'!N16 -> -0.028464699 | O35: ='6_Surplus'!N17 -> -0.023921152 | P35: ='6_Surplus'!N18 -> -0.015365415 | Q35: ='6_Surplus'!N19 -> -0.00036966108 | R35: ='6_Surplus'!N20 -> 0.0128436 | S35: ='6_Surplus'!N21 -> -0.0011811466
A37: Prix — moyenne de campagne (oct.–sept.)
A38: KC1 — arabica ICE New York | B38: US cents/lb | C38: ='Prix_ICE'!J5 -> 249.66 | D38: ='Prix_ICE'!J6 -> 197.84167 | E38: ='Prix_ICE'!J7 -> 140.69833 | F38: ='Prix_ICE'!J8 -> 161.4675 | G38: ='Prix_ICE'!J9 -> 154.02083 | H38: ='Prix_ICE'!J10 -> 131.8325 | I38: ='Prix_ICE'!J11 -> 143.77167 | J38: ='Prix_ICE'!J12 -> 120.60083 | K38: ='Prix_ICE'!J13 -> 104.98083 | L38: ='Prix_ICE'!J14 -> 113.23667 | M38: ='Prix_ICE'!J15 -> 143.75333 | N38: ='Prix_ICE'!J16 -> 224.0875 | O38: ='Prix_ICE'!J17 -> 171.19 | P38: ='Prix_ICE'!J18 -> 204.00167 | Q38: ='Prix_ICE'!J19 -> 333.06 | R38: ='Prix_ICE'!J20 -> 312.21
A39: DF1 — robusta ICE Londres | B39: US cents/lb | C39: ='Prix_ICE'!K5 -> 100.65583 | D39: ='Prix_ICE'!K6 -> 91.384167 | E39: ='Prix_ICE'!K7 -> 88.480833 | F39: ='Prix_ICE'!K8 -> 85.874167 | G39: ='Prix_ICE'!K9 -> 83.910833 | H39: ='Prix_ICE'!K10 -> 74.068333 | I39: ='Prix_ICE'!K11 -> 95.123333 | J39: ='Prix_ICE'!K12 -> 78.285 | K39: ='Prix_ICE'!K13 -> 67.5325 | L39: ='Prix_ICE'!K14 -> 59.220833 | M39: ='Prix_ICE'!K15 -> 69.895833 | N39: ='Prix_ICE'!K16 -> 97.529167 | O39: ='Prix_ICE'!K17 -> 100.565 | P39: ='Prix_ICE'!K18 -> 158.95 | Q39: ='Prix_ICE'!K19 -> 213.2675 | R39: ='Prix_ICE'!K20 -> 171.84182
A40: DF1 — robusta ICE Londres | B40: US$/t | C40: ='Prix_ICE'!L5 -> 2219.0813 | D40: ='Prix_ICE'!L6 -> 2014.676 | E40: ='Prix_ICE'!L7 -> 1950.6685 | F40: ='Prix_ICE'!L8 -> 1893.2013 | G40: ='Prix_ICE'!L9 -> 1849.9172 | H40: ='Prix_ICE'!L10 -> 1632.9272 | I40: ='Prix_ICE'!L11 -> 2097.1105 | J40: ='Prix_ICE'!L12 -> 1725.8888 | K40: ='Prix_ICE'!L13 -> 1488.8368 | L40: ='Prix_ICE'!L14 -> 1305.5959 | M40: ='Prix_ICE'!L15 -> 1540.9394 | N40: ='Prix_ICE'!L16 -> 2150.1501 | O40: ='Prix_ICE'!L17 -> 2217.0787 | P40: ='Prix_ICE'!L18 -> 3504.2477 | Q40: ='Prix_ICE'!L19 -> 4701.7435 | R40: ='Prix_ICE'!L20 -> 3788.4636
A42: Sources : USDA PSD Online (juillet 2026) ; ICO Coffee Market Reports (prix). Détail des calculs dans les onglets 1 à 6.

Sheet Analyse
A1: Analyse — ce que disent 16 campagnes de STU et de prix (2010/11 → 2025/26)
A2: Corrélations et courbe calculées par formules à partir des onglets du classeur ; tableaux « régimes » et « volatilité » figés (calcul Python sur les mêmes données).
A4: A. Corrélation entre le niveau de STU et le niveau de prix (log), 16 campagnes
A5: Série | B5: Définition | C5: r avec ln(KC1) | D5: r avec ln(DF1) | E5: Lecture
A6: Monde | B6: stocks ÷ conso | C6: =CORREL('Tableau_STU'!C7:R7,$C$93:$R$93) -> -0.62189698 | D6: =CORREL('Tableau_STU'!C7:R7,$C$94:$R$94) -> -0.71384119 | E6: Relation nette : stocks bas = prix hauts.
A7: Monde | B7: stocks ÷ (conso + export) | C7: =CORREL('Tableau_STU'!C8:R8,$C$93:$R$93) -> -0.62871705 | D7: =CORREL('Tableau_STU'!C8:R8,$C$94:$R$94) -> -0.72138477
A8: Pays importateurs (UE, É.-U., Japon…) | B8: stocks ÷ conso | C8: =CORREL('Tableau_STU'!C10:R10,$C$93:$R$93) -> -0.67828411 | D8: =CORREL('Tableau_STU'!C10:R10,$C$94:$R$94) -> -0.83259137 | E8: Meilleur indicateur : les stocks « visibles » des pays consommateurs.
A9: Pays producteurs | B9: stocks ÷ (conso + export) | C9: =CORREL('Tableau_STU'!C9:R9,$C$93:$R$93) -> -0.51001912 | D9: =CORREL('Tableau_STU'!C9:R9,$C$94:$R$94) -> -0.54710767
A10: Arabica total | B10: pondéré | C10: =CORREL('Tableau_STU'!C11:R11,$C$93:$R$93) -> -0.47539212 | D10: =CORREL('Tableau_STU'!C11:R11,$C$94:$R$94) -> -0.44711928
A11: Robusta total | B11: pondéré | C11: =CORREL('Tableau_STU'!C12:R12,$C$93:$R$93) -> -0.46844409 | D11: =CORREL('Tableau_STU'!C12:R12,$C$94:$R$94) -> -0.5768679
A12: Arabica 8 pays | C12: =CORREL('Tableau_STU'!C13:R13,$C$93:$R$93) -> -0.3501999 | D12: =CORREL('Tableau_STU'!C13:R13,$C$94:$R$94) -> -0.32195006
A13: Robusta 4 pays | C13: =CORREL('Tableau_STU'!C14:R14,$C$93:$R$93) -> -0.40951668 | D13: =CORREL('Tableau_STU'!C14:R14,$C$94:$R$94) -> -0.4979781
A14: Brésil | C14: =CORREL('Tableau_STU'!C17:R17,$C$93:$R$93) -> -0.2965362 | D14: =CORREL('Tableau_STU'!C17:R17,$C$94:$R$94) -> -0.25921205 | E14: Un pays seul explique peu : ses stocks USDA sont mal mesurés.
A15: Colombie | C15: =CORREL('Tableau_STU'!C19:R19,$C$93:$R$93) -> -0.3290299 | D15: =CORREL('Tableau_STU'!C19:R19,$C$94:$R$94) -> -0.15949983
A16: Vietnam | C16: =CORREL('Tableau_STU'!C18:R18,$C$93:$R$93) -> -0.20225458 | D16: =CORREL('Tableau_STU'!C18:R18,$C$94:$R$94) -> -0.31546639
A17: Indonésie | C17: =CORREL('Tableau_STU'!C20:R20,$C$93:$R$93) -> -0.36876234 | D17: =CORREL('Tableau_STU'!C20:R20,$C$94:$R$94) -> -0.3488393
A18: Surplus arabica Brésil | B18: flux | C18: =CORREL('Tableau_STU'!C32:R32,$C$93:$R$93) -> -0.0040576758 | D18: =CORREL('Tableau_STU'!C32:R32,$C$94:$R$94) -> 0.07399211 | E18: Le surplus (flux) n'explique pas le niveau…
A19: Surplus arabica 6 pays | B19: flux | C19: =CORREL('Tableau_STU'!C33:R33,$C$93:$R$93) -> -0.022654928 | D19: =CORREL('Tableau_STU'!C33:R33,$C$94:$R$94) -> 0.052829136
A20: Surplus robusta Vietnam | B20: flux | C20: =CORREL('Tableau_STU'!C34:R34,$C$93:$R$93) -> -0.043160051 | D20: =CORREL('Tableau_STU'!C34:R34,$C$94:$R$94) -> -0.13886886
A21: Surplus robusta 4 pays | B21: flux | C21: =CORREL('Tableau_STU'!C35:R35,$C$93:$R$93) -> -0.15523963 | D21: =CORREL('Tableau_STU'!C35:R35,$C$94:$R$94) -> -0.11003857 | E21: … mais il annonce la direction (voir B).
A24: B. Courbe prix = f(STU monde) : ln(prix) = a + b ÷ STU (forme convexe : plus le STU est bas, plus le prix réagit)
A39: Paramètre | C39: KC1 | D39: DF1 (US$/t)
A40: a (constante) | C40: =INTERCEPT($C$93:$R$93,$C$95:$R$95) -> 4.1972467 | D40: =INTERCEPT($C$94:$R$94,$C$95:$R$95) -> 6.5239638
A41: b (pente sur 1/STU) | C41: =SLOPE($C$93:$R$93,$C$95:$R$95) -> 0.18509026 | D41: =SLOPE($C$94:$R$94,$C$95:$R$95) -> 0.22165979
A42: R² (part de la variance du prix expliquée) | C42: =RSQ($C$93:$R$93,$C$95:$R$95) -> 0.50095512 | D42: =RSQ($C$94:$R$94,$C$95:$R$95) -> 0.69666482
A44: STU monde (stocks ÷ conso) | C44: KC1 « de courbe » (c/lb) | D44: DF1 « de courbe » (US$/t) | E44: Sensibilité : variation du prix pour −1 pt de STU
A45: 0.11 | C45: =EXP($C$40+$C$41/A45) -> 357.76825 | D45: =EXP($D$40+$D$41/A45) -> 5110.5015 | E45: =EXP($C$41*(1/(A45-0.01)-1/A45))-1 -> 0.1832488
A46: 0.12 | C46: =EXP($C$40+$C$41/A46) -> 310.96038 | D46: =EXP($D$40+$D$41/A46) -> 4320.51 | E46: =EXP($C$41*(1/(A46-0.01)-1/A46))-1 -> 0.15052677
A47: 0.13 | C47: =EXP($C$40+$C$41/A47) -> 276.17036 | D47: =EXP($D$40+$D$41/A47) -> 3748.2304 | E47: =EXP($C$41*(1/(A47-0.01)-1/A47))-1 -> 0.12597306
A48: 0.14 | C48: =EXP($C$40+$C$41/A48) -> 249.46534 | D48: =EXP($D$40+$D$41/A48) -> 3318.4332 | E48: =EXP($C$41*(1/(A48-0.01)-1/A48))-1 -> 0.10704903
A49: 0.15 | C49: =EXP($C$40+$C$41/A49) -> 228.41902 | D49: =EXP($D$40+$D$41/A49) -> 2986.0172 | E49: =EXP($C$41*(1/(A49-0.01)-1/A49))-1 -> 0.092139068
A50: 0.16 | C50: =EXP($C$40+$C$41/A50) -> 211.46528 | D50: =EXP($D$40+$D$41/A50) -> 2722.5861 | E50: =EXP($C$41*(1/(A50-0.01)-1/A50))-1 -> 0.080172708
A51: 0.18 | C51: =EXP($C$40+$C$41/A51) -> 185.95894 | D51: =EXP($D$40+$D$41/A51) -> 2334.1593 | E51: =EXP($C$41*(1/(A51-0.01)-1/A51))-1 -> 0.062353802
A52: 0.2 | C52: =EXP($C$40+$C$41/A52) -> 167.78745 | D52: =EXP($D$40+$D$41/A52) -> 2063.7144 | E52: =EXP($C$41*(1/(A52-0.01)-1/A52))-1 -> 0.049913694
A53: 0.22 | C53: =EXP($C$40+$C$41/A53) -> 154.24867 | D53: =EXP($D$40+$D$41/A53) -> 1865.9177 | E53: =EXP($C$41*(1/(A53-0.01)-1/A53))-1 -> 0.040876168
A54: 0.25 | C54: =EXP($C$40+$C$41/A54) -> 139.43628 | D54: =EXP($D$40+$D$41/A54) -> 1653.423 | E54: =EXP($C$41*(1/(A54-0.01)-1/A54))-1 -> 0.031329119
A55: 0.28 | C55: =EXP($C$40+$C$41/A55) -> 128.8029 | D55: =EXP($D$40+$D$41/A55) -> 1503.5825 | E55: =EXP($C$41*(1/(A55-0.01)-1/A55))-1 -> 0.024785005
A56: Zone à ±1 écart-type des résidus : de −22 % à +29 % autour du prix de courbe pour KC1, de −18 % à +22 % pour DF1 : un ordre de grandeur, pas un prix exact.
A58: C. Application à 2026/27 (prévision USDA juin 2026)
C59: KC1 (c/lb) | D59: DF1 (US$/t)
A60: STU monde 2026/27 (USDA) | B60: ='1_Monde'!E21 -> 0.14623114
A61: Prix « de courbe » pour ce STU | C61: =EXP($C$40+$C$41/B60) -> 235.80008 | D61: =EXP($D$40+$D$41/B60) -> 3101.9362
A62: Dernier prix mensuel connu (août 2026) | C62: ='Prix_ICE'!C195 -> 313.2 | D62: ='Prix_ICE'!E195 -> 3695.6089
A63: Prime du marché vs la courbe | C63: =C62/C61-1 -> 0.3282438 | D63: =D62/D61-1 -> 0.19138777
A64: La prime reflète ce que le STU USDA ne voit pas : stocks certifiés ICE arabica au plus bas depuis 1999 (224 000 sacs fin août 2026), stocks des pays consommateurs encore bas, risque El Niño pour la floraison brésilienne 2027/28.
A66: D. Régimes de prix selon le STU monde (valeurs figées, campagnes 2010/11-2025/26)
A67: Zone de STU monde | B67: Campagnes | C67: KC1 moyen (c/lb) | D67: DF1 moyen (US$/t) | E67: Comportement typique
A68: < 15 % | B68: 2023/24, 2024/25, 2025/26 | C68: 283.09056 | D68: 3998.1545 | E68: Pénurie : prix ~2× la moyenne, forte volatilité, backwardation ; c'est le prix qui rationne la demande.
A69: 15 – 20 % | B69: 2011/12, 2017/18, 2021/22, 2022/23 | C69: 178.43 | D69: 2026.95 | E69: Transition : un choc météo fait +50 % (gel 2021) ; sans choc, le prix retombe vite (2022/23).
A70: 20 – 24 % | B70: 2010/11, 2015/16, 2016/17, 2018/19, 2019/20, 2020/21 | C70: 147.8725 | D70: 1714.0847 | E70: Confortable : prix plafonnés, fixés par le coût de production en dollars (donc par le BRL). 2010/11 = exception (voir analyse).
A71: > 24 % | B71: 2012/13, 2013/14, 2014/15 | C71: 152.06222 | D71: 1897.9278 | E71: Excédent : prix bas ; les rallyes (sécheresse 2014) s'essoufflent vite.
A73: E. Qui fait bouger l'offre ? Part de la variance des variations annuelles de production (2011-2026)
A74: Production | B74: 1er | C74: 2e | D74: 3e | E74: 4e
A75: Production totale | B75: Brésil 83 % | C75: Colombie 7 % | D75: Honduras 5 % | E75: Indonésie 4 %
A76: Arabica | B76: Brésil 82 % | C76: Colombie 8 % | D76: Honduras 5 % | E76: Éthiopie 2 %
A77: Robusta | B77: Vietnam 40 % | C77: Brésil 39 % | D77: Indonésie 17 % | E77: Côte d'Ivoire 5 %
A79: F. Conclusions (détail dans la page d'analyse)
A80: 1. Le STU mondial explique ~50 % des variations du niveau de KC1 et ~70 % de DF1 (courbe convexe en 1/STU, 16 campagnes).
A81: 2. Seuil clé ≈ 15-16 % (monde, stocks ÷ conso) : en dessous, changement de régime (2023/24-2025/26 : KC1 204-333 c/lb, DF1 3504-4702 $/t).
A82: 3. Le Brésil pèse 83 % de la volatilité de la production mondiale ; pour le robusta : Vietnam 40 %, Brésil (conilon) 39 %, Indonésie 17 %.
A83: 4. Meilleur thermomètre : les stocks des pays consommateurs (corr. -0,68 avec ln KC1, -0,83 avec ln DF1) ; UE : 14,0 → 7,5 M sacs entre 2021/22 et 2025/26.
A84: 5. Le surplus annuel (flux) n'explique pas le niveau du prix et ne prédit pas l'année suivante ; il accompagne la variation de l'année (arabica 6 pays : corr. -0,36). C'est son cumul sur 2-3 ans — donc le STU — qui fixe le niveau.
A85: 6. 2026/27 : STU USDA 14,6 % → KC1 ≈ 236 c/lb et DF1 ≈ 3102 $/t « de courbe », contre 313 c/lb et 3696 $/t en août 2026 (prime de marché +33 % / +19 %).
A91: Lignes de calcul (ne pas effacer)
A92: Campagne | C92: 2010/11 | D92: 2011/12 | E92: 2012/13 | F92: 2013/14 | G92: 2014/15 | H92: 2015/16 | I92: 2016/17 | J92: 2017/18 | K92: 2018/19 | L92: 2019/20 | M92: 2020/21 | N92: 2021/22 | O92: 2022/23 | P92: 2023/24 | Q92: 2024/25 | R92: 2025/26
A93: ln(KC1) | C93: =LN('Tableau_STU'!C38) -> 5.5201 | D93: =LN('Tableau_STU'!D38) -> 5.287467 | E93: =LN('Tableau_STU'!E38) -> 4.9466181 | F93: =LN('Tableau_STU'!F38) -> 5.0843039 | G93: =LN('Tableau_STU'!G38) -> 5.0370879 | H93: =LN('Tableau_STU'!H38) -> 4.8815322 | I93: =LN('Tableau_STU'!I38) -> 4.9682264 | J93: =LN('Tableau_STU'!J38) -> 4.7924862 | ... R93: =LN('Tableau_STU'!R38) -> 5.743676
A94: ln(DF1 US$/t) | C94: =LN('Tableau_STU'!C40) -> 7.7048485 | D94: =LN('Tableau_STU'!D40) -> 7.6082137 | E94: =LN('Tableau_STU'!E40) -> 7.5759274 | F94: =LN('Tableau_STU'!F40) -> 7.5460245 | G94: =LN('Tableau_STU'!G40) -> 7.5228962 | H94: =LN('Tableau_STU'!H40) -> 7.3981295 | I94: =LN('Tableau_STU'!I40) -> 7.6483157 | J94: =LN('Tableau_STU'!J40) -> 7.4534975 | ... R94: =LN('Tableau_STU'!R40) -> 8.2397158
A95: 1 / STU monde | C95: =1/'Tableau_STU'!C7 -> 4.7314246 | D95: =1/'Tableau_STU'!D7 -> 5.5472658 | E95: =1/'Tableau_STU'!E7 -> 4.0548565 | F95: =1/'Tableau_STU'!F7 -> 3.4935169 | G95: =1/'Tableau_STU'!G7 -> 3.4119215 | H95: =1/'Tableau_STU'!H7 -> 4.3828789 | I95: =1/'Tableau_STU'!I7 -> 4.2549036 | J95: =1/'Tableau_STU'!J7 -> 5.0272918 | ... R95: =1/'Tableau_STU'!R7 -> 7.1177267
A96: KC1 « courbe » (c/lb) | C96: =EXP($C$40+$C$41*C95) -> 159.65054 | D96: =EXP($C$40+$C$41*D95) -> 185.67383 | E96: =EXP($C$40+$C$41*E95) -> 140.85924 | F96: =EXP($C$40+$C$41*F95) -> 126.9588 | G96: =EXP($C$40+$C$41*G95) -> 125.05581 | H96: =EXP($C$40+$C$41*H95) -> 149.67629 | I96: =EXP($C$40+$C$41*I95) -> 146.17257 | J96: =EXP($C$40+$C$41*J95) -> 168.63716 | ... R96: =EXP($C$40+$C$41*R95) -> 248.30767
A97: DF1 « courbe » (US$/t) | C97: =EXP($D$40+$D$41*C95) -> 1944.4421 | D97: =EXP($D$40+$D$41*D95) -> 2329.8743 | E97: =EXP($D$40+$D$41*E95) -> 1673.6505 | F97: =EXP($D$40+$D$41*F95) -> 1477.8388 | G97: =EXP($D$40+$D$41*G95) -> 1451.3502 | H97: =EXP($D$40+$D$41*H95) -> 1799.8738 | I97: =EXP($D$40+$D$41*I95) -> 1749.5342 | J97: =EXP($D$40+$D$41*J95) -> 2076.2367 | ... R97: =EXP($D$40+$D$41*R95) -> 3299.9996

Sheet Prix_ICE
A1: Prix ICE — moyennes mensuelles New York (arabica, KC) et Londres (robusta, RC/DF)
A2: Source : ICO, Coffee Market Report, tableau 1 « ICO indicator prices and futures prices » (moyenne des 2e et 3e positions), 62 rapports mensuels ICO (oct. 2010 → août 2026) exploités sur ico.org. Proxy de KC1 / DF1 (1re position) : écart de quelques %.
A3: Londres converti par l'ICO en US cents/lb ; US$/t = cents/lb × 22,0462. Campagne = octobre → septembre (année caféière ICO). 2025/26 = oct. 2025 → août 2026 (11 mois ; le rapport de septembre 2026 n'est pas encore publié).
A4: Mois | B4: Campagne | C4: KC — ICE New York (US c/lb) | D4: Robusta — ICE Londres (US c/lb) | E4: DF — ICE Londres (US$/t) | F4: Indicateur composite ICO (US c/lb) | G4: Rapport ICO source | I4: Campagne | J4: KC moyen (US c/lb) | K4: Robusta Londres moyen (US c/lb) | L4: DF moyen (US$/t) | M4: Composite ICO moyen (US c/lb) | N4: Nb de mois
A5: 40452 | B5: 2010/11 | C5: 190.43 | D5: 80.08 | E5: =D5*22.0462262 -> 1765.4618 | F5: 161.56 | G5: cmr-1011-e.pdf | I5: 2010/11 | J5: =AVERAGE(C5:C16) -> 249.66 | K5: =AVERAGE(D5:D16) -> 100.65583 | L5: =AVERAGE(E5:E16) -> 2219.0813 | M5: =AVERAGE(F5:F16) -> 205.65083 | N5: =COUNT(C5:C16) -> 12
A6: 40483 | B6: 2010/11 | C6: 206.92 | D6: 86.4 | E6: =D6*22.0462262 -> 1904.7939 | F6: 173.9 | G6: cmr-1111-e.pdf | I6: 2011/12 | J6: =AVERAGE(C17:C28) -> 197.84167 | K6: =AVERAGE(D17:D28) -> 91.384167 | L6: =AVERAGE(E17:E28) -> 2014.676 | M6: =AVERAGE(F17:F28) -> 169.82 | N6: =COUNT(C17:C28) -> 12
A7: 40513 | B7: 2010/11 | C7: 221.51 | D7: 88.7 | E7: =D7*22.0462262 -> 1955.5003 | F7: 184.26 | G7: cmr-1211-e.pdf | I7: 2012/13 | J7: =AVERAGE(C29:C40) -> 140.69833 | K7: =AVERAGE(D29:D40) -> 88.480833 | L7: =AVERAGE(E29:E40) -> 1950.6685 | M7: =AVERAGE(F29:F40) -> 127.86167 | N7: =COUNT(C29:C40) -> 12
A8: 40544 | B8: 2010/11 | C8: 238.05 | D8: 96.02 | E8: =D8*22.0462262 -> 2116.8786 | F8: 197.35 | G8: cmr-1211-e.pdf | I8: 2013/14 | J8: =AVERAGE(C41:C52) -> 161.4675 | K8: =AVERAGE(D41:D52) -> 85.874167 | L8: =AVERAGE(E41:E52) -> 1893.2013 | M8: =AVERAGE(F41:F52) -> 140.99833 | N8: =COUNT(C41:C52) -> 12
A9: 40575 | B9: 2010/11 | C9: 261.41 | D9: 104.53 | E9: =D9*22.0462262 -> 2304.492 | F9: 216.03 | G9: cmr-1211-e.pdf | I9: 2014/15 | J9: =AVERAGE(C53:C64) -> 154.02083 | K9: =AVERAGE(D53:D64) -> 83.910833 | L9: =AVERAGE(E53:E64) -> 1849.9172 | M9: =AVERAGE(F53:F64) -> 136.14083 | N9: =COUNT(C53:C64) -> 12
A10: 40603 | B10: 2010/11 | C10: 274.1 | D10: 111.36 | E10: =D10*22.0462262 -> 2455.0677 | F10: 224.33 | G10: cmr-1211-e.pdf | I10: 2015/16 | J10: =AVERAGE(C65:C76) -> 131.8325 | K10: =AVERAGE(D65:D76) -> 74.068333 | L10: =AVERAGE(E65:E76) -> 1632.9272 | M10: =AVERAGE(F65:F76) -> 121.30417 | N10: =COUNT(C65:C76) -> 12
A11: 40634 | B11: 2010/11 | C11: 285.58 | D11: 111.34 | E11: =D11*22.0462262 -> 2454.6268 | F11: 231.24 | G11: cmr-1211-e.pdf | I11: 2016/17 | J11: =AVERAGE(C77:C88) -> 143.77167 | K11: =AVERAGE(D77:D88) -> 95.123333 | L11: =AVERAGE(E77:E88) -> 2097.1105 | M11: =AVERAGE(F77:F88) -> 132.43 | N11: =COUNT(C77:C88) -> 12
A12: 40664 | B12: 2010/11 | C12: 277.72 | D12: 116.76 | E12: =D12*22.0462262 -> 2574.1174 | F12: 227.97 | G12: cmr-1211-e.pdf | I12: 2017/18 | J12: =AVERAGE(C89:C100) -> 120.60083 | K12: =AVERAGE(D89:D100) -> 78.285 | L12: =AVERAGE(E89:E100) -> 1725.8888 | M12: =AVERAGE(F89:F100) -> 111.51417 | N12: =COUNT(C89:C100) -> 12
A13: 40695 | B13: 2010/11 | C13: 262.52 | D13: 110.51 | E13: =D13*22.0462262 -> 2436.3285 | F13: 215.58 | G13: cmr-1211-e.pdf | I13: 2018/19 | J13: =AVERAGE(C101:C112) -> 104.98083 | K13: =AVERAGE(D101:D112) -> 67.5325 | L13: =AVERAGE(E101:E112) -> 1488.8368 | M13: =AVERAGE(F101:F112) -> 100.47333 | N13: =COUNT(C101:C112) -> 12
A14: 40725 | B14: 2010/11 | C14: 255.9 | D14: 103.36 | E14: =D14*22.0462262 -> 2278.6979 | F14: 210.36 | G14: cmr-1211-e.pdf | I14: 2019/20 | J14: =AVERAGE(C113:C124) -> 113.23667 | K14: =AVERAGE(D113:D124) -> 59.220833 | L14: =AVERAGE(E113:E124) -> 1305.5959 | M14: =AVERAGE(F113:F124) -> 107.24917 | N14: =COUNT(C113:C124) -> 12
A15: 40756 | B15: 2010/11 | C15: 260.39 | D15: 102.71 | E15: =D15*22.0462262 -> 2264.3679 | F15: 212.19 | G15: cmr-1211-e.pdf | I15: 2020/21 | J15: =AVERAGE(C125:C136) -> 143.75333 | K15: =AVERAGE(D125:D136) -> 69.895833 | L15: =AVERAGE(E125:E136) -> 1540.9394 | M15: =AVERAGE(F125:F136) -> 130.4975 | N15: =COUNT(C125:C136) -> 12
A16: 40787 | B16: 2010/11 | C16: 261.39 | D16: 96.1 | E16: =D16*22.0462262 -> 2118.6423 | F16: 213.04 | G16: cmr-1211-e.pdf | I16: 2021/22 | J16: =AVERAGE(C137:C148) -> 224.0875 | K16: =AVERAGE(D137:D148) -> 97.529167 | L16: =AVERAGE(E137:E148) -> 2150.1501 | M16: =AVERAGE(F137:F148) -> 197.905 | N16: =COUNT(C137:C148) -> 12
A17: 40817 | B17: 2011/12 | C17: 236.74 | D17: 88.64 | E17: =D17*22.0462262 -> 1954.1775 | F17: 193.9 | G17: cmr-1012-e.pdf | I17: 2022/23 | J17: =AVERAGE(C149:C160) -> 171.19 | K17: =AVERAGE(D149:D160) -> 100.565 | L17: =AVERAGE(E149:E160) -> 2217.0787 | M17: =AVERAGE(F149:F160) -> 165.49833 | N17: =COUNT(C149:C160) -> 12
A18: 40848 | B18: 2011/12 | C18: 235.25 | D18: 85.78 | E18: =D18*22.0462262 -> 1891.1253 | F18: 193.66 | G18: cmr-1112-e.pdf | I18: 2023/24 | J18: =AVERAGE(C161:C172) -> 204.00167 | K18: =AVERAGE(D161:D172) -> 158.95 | L18: =AVERAGE(E161:E172) -> 3504.2477 | M18: =AVERAGE(F161:F172) -> 201.7 | N18: =COUNT(C161:C172) -> 12
A19: 40878 | B19: 2011/12 | C19: 227.23 | D19: 87.65 | E19: =D19*22.0462262 -> 1932.3517 | F19: 189.02 | G19: cmr-1212-e.pdf | I19: 2024/25 | J19: =AVERAGE(C173:C184) -> 333.06 | K19: =AVERAGE(D173:D184) -> 213.2675 | L19: =AVERAGE(E173:E184) -> 4701.7435 | M19: =AVERAGE(F173:F184) -> 306.61583 | N19: =COUNT(C173:C184) -> 12
A20: 40909 | B20: 2011/12 | C20: 227.5 | D20: 84.19 | E20: =D20*22.0462262 -> 1856.0718 | F20: 188.9 | G20: cmr-0113-e.pdf | I20: 2025/26 | J20: =AVERAGE(C185:C195) -> 312.21 | K20: =AVERAGE(D185:D195) -> 171.84182 | L20: =AVERAGE(E185:E195) -> 3788.4636 | M20: =AVERAGE(F185:F195) -> 285.94545 | N20: =COUNT(C185:C195) -> 11
A21: 40940 | B21: 2011/12 | C21: 212.09 | D21: 88.69 | E21: =D21*22.0462262 -> 1955.2798 | F21: 182.29 | G21: cmr-0213-e.pdf | I21: 2026/27 | J21: n.d. (campagne à venir)
A22: 40969 | B22: 2011/12 | C22: 188.78 | D22: 91.37 | E22: =D22*22.0462262 -> 2014.3637 | F22: 167.77 | G22: cmr-0313-e.pdf
A23: 41000 | B23: 2011/12 | C23: 181.75 | D23: 91.81 | E23: =D23*22.0462262 -> 2024.064 | F23: 160.46 | G23: cmr-0413-e.pdf
A24: 41030 | B24: 2011/12 | C24: 176.5 | D24: 96.82 | E24: =D24*22.0462262 -> 2134.5156 | F24: 157.68 | G24: cmr-0513-e.pdf
A25: 41061 | B25: 2011/12 | C25: 159.93 | D25: 94.75 | E25: =D25*22.0462262 -> 2088.8799 | F25: 145.31 | G25: cmr-0613-e.pdf
A26: 41091 | B26: 2011/12 | C26: 183.2 | D26: 96.14 | E26: =D26*22.0462262 -> 2119.5242 | F26: 159.07 | G26: cmr-0713-e.pdf
A27: 41122 | B27: 2011/12 | C27: 169.77 | D27: 96.12 | E27: =D27*22.0462262 -> 2119.0833 | F27: 148.5 | G27: cmr-0813-e.pdf
A28: 41153 | B28: 2011/12 | C28: 175.36 | D28: 94.65 | E28: =D28*22.0462262 -> 2086.6753 | F28: 151.28 | G28: cmr-0913-e.pdf
A29: 41183 | B29: 2012/13 | C29: 170.43 | D29: 94.66 | E29: =D29*22.0462262 -> 2086.8958 | F29: 147.12 | G29: cmr-1013-e.pdf
A30: 41214 | B30: 2012/13 | C30: 155.72 | D30: 87.32 | E30: =D30*22.0462262 -> 1925.0765 | F30: 136.35 | G30: cmr-1113-e.pdf
A31: 41244 | B31: 2012/13 | C31: 149.58 | D31: 85.94 | E31: =D31*22.0462262 -> 1894.6527 | F31: 131.31 | G31: cmr-1213-e.pdf
A32: 41275 | B32: 2012/13 | C32: 154.28 | D32: 88.85 | E32: =D32*22.0462262 -> 1958.8072 | F32: 135.38 | G32: cmr-0114-e.pdf
A33: 41306 | B33: 2012/13 | C33: 144.89 | D33: 94.41 | E33: =D33*22.0462262 -> 2081.3842 | F33: 131.51 | G33: cmr-0114-e.pdf
... A195: 46235 | B195: 2025/26 | C195: 313.2 | D195: 167.63 | E195: =D195*22.0462262 -> 3695.6089 | F195: 287.29 | G195: cmr-0826-e.pdf

Sheet Donnees_USDA
A1: Données USDA PSD Online — café (fichier juillet 2026 ; 2026/27 = prévision USDA juin 2026) — milliers de sacs de 60 kg
A2: Une ligne par pays, une colonne par campagne (année commerciale locale). Pays producteurs = production > 0 sur 2010-2026 ; importateurs = aucun café produit. Les parts arabica/robusta servent à répartir stocks et utilisation par espèce.
A3: Source : https://apps.fas.usda.gov/psdonline (téléchargement « Coffee » CSV). Totaux = sommes des pays (identiques aux totaux mondiaux USDA).
A5: Production totale | B5: Groupe | C5: 2010/11 | D5: 2011/12 | E5: 2012/13 | F5: 2013/14 | G5: 2014/15 | H5: 2015/16 | I5: 2016/17 | J5: 2017/18 | K5: 2018/19 | L5: 2019/20 | M5: 2020/21 | N5: 2021/22 | O5: 2022/23 | P5: 2023/24 | Q5: 2024/25 | R5: 2025/26 | S5: 2026/27
A6: Brazil | B6: Producteur | C6: 54500 | D6: 49200 | E6: 57600 | F6: 57200 | G6: 54300 | H6: 49400 | I6: 56100 | J6: 52100 | K6: 66500 | L6: 60500 | M6: 69900 | N6: 58100 | O6: 62600 | P6: 66300 | Q6: 65500 | R6: 63000 | S6: 71900
A7: Vietnam | B7: Producteur | C7: 19415 | D7: 26000 | E7: 26500 | F7: 29833 | G7: 27400 | H7: 28930 | I7: 26700 | J7: 29300 | K7: 30400 | L7: 31300 | M7: 29000 | N7: 31580 | O7: 28300 | P7: 27550 | Q7: 29000 | R7: 31700 | S7: 32500
A8: Colombia | B8: Producteur | C8: 8525 | D8: 7655 | E8: 9927 | F8: 12075 | G8: 13300 | H8: 14000 | I8: 14600 | J8: 13825 | K8: 13870 | L8: 14100 | M8: 13400 | N8: 11800 | O8: 10700 | P8: 12760 | Q8: 14800 | R8: 12500 | S8: 13400
A9: Ethiopia | B9: Producteur | C9: 6125 | D9: 6320 | E9: 6500 | F9: 6345 | G9: 6475 | H9: 6510 | I9: 6943 | J9: 7055 | K9: 7350 | L9: 7475 | M9: 7600 | N9: 8150 | O9: 7300 | P9: 9130 | Q9: 11460 | R9: 11560 | S9: 12100
A10: Indonesia | B10: Producteur | C10: 9325 | D10: 7970 | E10: 11900 | F10: 11900 | G10: 10470 | H10: 12100 | I10: 10600 | J10: 10400 | K10: 10600 | L10: 10700 | M10: 10700 | N10: 10580 | O10: 10700 | P10: 8150 | Q10: 10700 | R10: 12370 | S10: 11380
A11: Uganda | B11: Producteur | C11: 3212 | D11: 3075 | E11: 3600 | F11: 3850 | G11: 3500 | H11: 3550 | I11: 4875 | J11: 4600 | K11: 4650 | L11: 5475 | M11: 6630 | N11: 6050 | O11: 6565 | P11: 6400 | Q11: 6700 | R11: 7095 | S11: 7160
A12: India | B12: Producteur | C12: 5035 | D12: 5230 | E12: 5303 | F12: 5075 | G12: 5440 | H12: 5800 | I12: 5200 | J12: 5266 | K12: 5325 | L12: 4967 | M12: 5567 | N12: 5700 | O12: 5867 | P12: 6560 | Q12: 6059 | R12: 6430 | S12: 6140
A13: Honduras | B13: Producteur | C13: 3975 | D13: 5600 | E13: 4725 | F13: 4400 | G13: 5100 | H13: 5300 | I13: 7510 | J13: 7600 | K13: 7100 | L13: 5200 | M13: 6500 | N13: 4800 | O13: 5700 | P13: 5050 | Q13: 5200 | R13: 5530 | S13: 6030
A14: Peru | B14: Producteur | C14: 4100 | D14: 5200 | E14: 4300 | F14: 4250 | G14: 2900 | H14: 3500 | I14: 4225 | J14: 4375 | K14: 4390 | L14: 3925 | M14: 3369 | N14: 4200 | O14: 3475 | P14: 3912 | Q14: 4120 | R14: 4764 | S14: 4780
A15: Mexico | B15: Producteur | C15: 4000 | D15: 4300 | E15: 4650 | F15: 3950 | G15: 3180 | H15: 2300 | I15: 3300 | J15: 4000 | K15: 3550 | L15: 3700 | M15: 3530 | N15: 3740 | O15: 3545 | P15: 3856 | Q15: 3928 | R15: 4080 | S15: 4135
A16: Guatemala | B16: Producteur | C16: 3960 | D16: 4410 | E16: 4010 | F16: 3515 | G16: 3185 | H16: 3295 | I16: 3570 | J16: 3780 | K16: 3770 | L16: 3645 | M16: 3930 | N16: 3540 | O16: 3270 | P16: 3469 | Q16: 3270 | R16: 3155 | S16: 3260
A17: Nicaragua | B17: Producteur | C17: 1740 | D17: 2100 | E17: 1925 | F17: 2000 | G17: 2125 | H17: 2125 | I17: 2625 | J17: 2730 | K17: 2950 | L17: 2755 | M17: 2650 | N17: 2838 | O17: 2590 | P17: 2347 | Q17: 2660 | R17: 2560 | S17: 2440
... A98: Zimbabwe | B98: Importateur | C98: 0 | D98: 0 | E98: 0 | F98: 0 | G98: 0 | H98: 0 | I98: 0 | J98: 0 | K98: 0 | L98: 0 | M98: 0 | N98: 0 | O98: 0 | P98: 0 | Q98: 0 | R98: 0 | S98: 0
A99: Total pays producteurs | C99: =SUM(C6:C52) -> 141409 | D99: =SUM(D6:D52) -> 144837 | E99: =SUM(E6:E52) -> 158018 | F99: =SUM(F6:F52) -> 160054 | G99: =SUM(G6:G52) -> 153796 | H99: =SUM(H6:H52) -> 152429 | I99: =SUM(I6:I52) -> 161079 | J99: =SUM(J6:J52) -> 159814 | ... S99: =SUM(S6:S52) -> 189667
A100: Total pays importateurs | C100: =SUM(C53:C98) -> 0 | D100: =SUM(D53:D98) -> 0 | E100: =SUM(E53:E98) -> 0 | F100: =SUM(F53:F98) -> 0 | G100: =SUM(G53:G98) -> 0 | H100: =SUM(H53:H98) -> 0 | I100: =SUM(I53:I98) -> 0 | J100: =SUM(J53:J98) -> 0 | ... S100: =SUM(S53:S98) -> 0
A101: MONDE | C101: =C99+C100 -> 141409 | D101: =D99+D100 -> 144837 | E101: =E99+E100 -> 158018 | F101: =F99+F100 -> 160054 | G101: =G99+G100 -> 153796 | H101: =H99+H100 -> 152429 | I101: =I99+I100 -> 161079 | J101: =J99+J100 -> 159814 | ... S101: =S99+S100 -> 189667
A105: Production arabica | B105: Groupe | C105: 2010/11 | D105: 2011/12 | E105: 2012/13 | F105: 2013/14 | G105: 2014/15 | H105: 2015/16 | I105: 2016/17 | J105: 2017/18 | K105: 2018/19 | L105: 2019/20 | M105: 2020/21 | N105: 2021/22 | O105: 2022/23 | P105: 2023/24 | Q105: 2024/25 | R105: 2025/26 | S105: 2026/27
A106: Brazil | B106: Producteur | C106: 41800 | D106: 34700 | E106: 42100 | F106: 41800 | G106: 37300 | H106: 36100 | I106: 45600 | J106: 39500 | K106: 49700 | L106: 42000 | M106: 49700 | N106: 36400 | O106: 39800 | P106: 44900 | Q106: 44500 | R106: 38000 | S106: 47500
A107: Vietnam | B107: Producteur | C107: 650 | D107: 800 | E107: 900 | F107: 1175 | G107: 1050 | H107: 1100 | I107: 1100 | J107: 1026 | K107: 1064 | L107: 1100 | M107: 950 | N107: 1100 | O107: 1000 | P107: 1000 | Q107: 1000 | R107: 1200 | S107: 1100
A108: Colombia | B108: Producteur | C108: 8525 | D108: 7655 | E108: 9927 | F108: 12075 | G108: 13300 | H108: 14000 | I108: 14600 | J108: 13825 | K108: 13870 | L108: 14100 | M108: 13400 | N108: 11800 | O108: 10700 | P108: 12760 | Q108: 14800 | R108: 12500 | S108: 13400
A109: Ethiopia | B109: Producteur | C109: 6125 | D109: 6320 | E109: 6500 | F109: 6345 | G109: 6475 | H109: 6510 | I109: 6943 | J109: 7055 | K109: 7350 | L109: 7475 | M109: 7600 | N109: 8150 | O109: 7300 | P109: 9130 | Q109: 11460 | R109: 11560 | S109: 12100
A110: Indonesia | B110: Producteur | C110: 1375 | D110: 1300 | E110: 2000 | F110: 1900 | G110: 1270 | H110: 1500 | I110: 1300 | J110: 1000 | K110: 1200 | L110: 1250 | M110: 1300 | N110: 1280 | O110: 1200 | P110: 1350 | Q110: 1400 | R110: 1370 | S110: 1380
A111: Uganda | B111: Producteur | C111: 644 | D111: 875 | E111: 800 | F111: 850 | G111: 800 | H111: 950 | I111: 1100 | J111: 1200 | K111: 1050 | L111: 1025 | M111: 730 | N111: 990 | O111: 990 | P111: 1000 | Q111: 1030 | R111: 1120 | S111: 1135
A112: India | B112: Producteur | C112: 1570 | D112: 1690 | E112: 1643 | F112: 1703 | G112: 1630 | H112: 1725 | I112: 1583 | J112: 1583 | K112: 1583 | L112: 1450 | M112: 1650 | N112: 1583 | O112: 1667 | P112: 1480 | Q112: 1762 | R112: 1730 | S112: 1560
A113: Honduras | B113: Producteur | C113: 3975 | D113: 5600 | E113: 4725 | F113: 4400 | G113: 5100 | H113: 5300 | I113: 7510 | J113: 7600 | K113: 7100 | L113: 5200 | M113: 6500 | N113: 4800 | O113: 5700 | P113: 5050 | Q113: 5200 | R113: 5530 | S113: 6030
A114: Peru | B114: Producteur | C114: 4100 | D114: 5200 | E114: 4300 | F114: 4250 | G114: 2900 | H114: 3500 | I114: 4225 | J114: 4375 | K114: 4390 | L114: 3925 | M114: 3369 | N114: 4200 | O114: 3475 | P114: 3912 | Q114: 4120 | R114: 4764 | S114: 4780
A115: Mexico | B115: Producteur | C115: 3800 | D115: 4100 | E115: 4450 | F115: 3750 | G115: 2980 | H115: 2125 | I115: 3100 | J115: 3800 | K115: 3100 | L115: 3150 | M115: 3000 | N115: 3200 | O115: 3000 | P115: 3356 | Q115: 3588 | R115: 3580 | S115: 3575
A116: Guatemala | B116: Producteur | C116: 3950 | D116: 4400 | E116: 4000 | F116: 3500 | G116: 3125 | H116: 3125 | I116: 3400 | J116: 3600 | K116: 3520 | L116: 3515 | M116: 3810 | N116: 3410 | O116: 3150 | P116: 3339 | Q116: 3140 | R116: 3025 | S116: 3130
A117: Nicaragua | B117: Producteur | C117: 1740 | D117: 2100 | E117: 1925 | F117: 2000 | G117: 2100 | H117: 2100 | I117: 2600 | J117: 2700 | K117: 2900 | L117: 2675 | M117: 2550 | N117: 2718 | O117: 2430 | P117: 2187 | Q117: 2500 | R117: 2400 | S117: 2300
... A198: Zimbabwe | B198: Importateur | C198: 0 | D198: 0 | E198: 0 | F198: 0 | G198: 0 | H198: 0 | I198: 0 | J198: 0 | K198: 0 | L198: 0 | M198: 0 | N198: 0 | O198: 0 | P198: 0 | Q198: 0 | R198: 0 | S198: 0
A199: Total pays producteurs | C199: =SUM(C106:C152) -> 87943 | D199: =SUM(D106:D152) -> 84542 | E199: =SUM(E106:E152) -> 92872 | F199: =SUM(F106:F152) -> 92465 | G199: =SUM(G106:G152) -> 86688 | H199: =SUM(H106:H152) -> 86135 | I199: =SUM(I106:I152) -> 101136 | J199: =SUM(J106:J152) -> 95224 | ... S199: =SUM(S106:S152) -> 105867
A200: Total pays importateurs | C200: =SUM(C153:C198) -> 0 | D200: =SUM(D153:D198) -> 0 | E200: =SUM(E153:E198) -> 0 | F200: =SUM(F153:F198) -> 0 | G200: =SUM(G153:G198) -> 0 | H200: =SUM(H153:H198) -> 0 | I200: =SUM(I153:I198) -> 0 | J200: =SUM(J153:J198) -> 0 | ... S200: =SUM(S153:S198) -> 0
A201: MONDE | C201: =C199+C200 -> 87943 | D201: =D199+D200 -> 84542 | E201: =E199+E200 -> 92872 | F201: =F199+F200 -> 92465 | G201: =G199+G200 -> 86688 | H201: =H199+H200 -> 86135 | I201: =I199+I200 -> 101136 | J201: =J199+J200 -> 95224 | ... S201: =S199+S200 -> 105867
A205: Production robusta | B205: Groupe | C205: 2010/11 | D205: 2011/12 | E205: 2012/13 | F205: 2013/14 | G205: 2014/15 | H205: 2015/16 | I205: 2016/17 | J205: 2017/18 | K205: 2018/19 | L205: 2019/20 | M205: 2020/21 | N205: 2021/22 | O205: 2022/23 | P205: 2023/24 | Q205: 2024/25 | R205: 2025/26 | S205: 2026/27
A206: Brazil | B206: Producteur | C206: 12700 | D206: 14500 | E206: 15500 | F206: 15400 | G206: 17000 | H206: 13300 | I206: 10500 | J206: 12600 | K206: 16800 | L206: 18500 | M206: 20200 | N206: 21700 | O206: 22800 | P206: 21400 | Q206: 21000 | R206: 25000 | S206: 24400
A207: Vietnam | B207: Producteur | C207: 18765 | D207: 25200 | E207: 25600 | F207: 28658 | G207: 26350 | H207: 27830 | I207: 25600 | J207: 28274 | K207: 29336 | L207: 30200 | M207: 28050 | N207: 30480 | O207: 27300 | P207: 26550 | Q207: 28000 | R207: 30500 | S207: 31400
A208: Colombia | B208: Producteur | C208: 0 | D208: 0 | E208: 0 | F208: 0 | G208: 0 | H208: 0 | I208: 0 | J208: 0 | K208: 0 | L208: 0 | M208: 0 | N208: 0 | O208: 0 | P208: 0 | Q208: 0 | R208: 0 | S208: 0
A209: Ethiopia | B209: Producteur | C209: 0 | D209: 0 | E209: 0 | F209: 0 | G209: 0 | H209: 0 | I209: 0 | J209: 0 | K209: 0 | L209: 0 | M209: 0 | N209: 0 | O209: 0 | P209: 0 | Q209: 0 | R209: 0 | S209: 0
A210: Indonesia | B210: Producteur | C210: 7950 | D210: 6670 | E210: 9900 | F210: 10000 | G210: 9200 | H210: 10600 | I210: 9300 | J210: 9400 | K210: 9400 | L210: 9450 | M210: 9400 | N210: 9300 | O210: 9500 | P210: 6800 | Q210: 9300 | R210: 11000 | S210: 10000
A211: Uganda | B211: Producteur | C211: 2568 | D211: 2200 | E211: 2800 | F211: 3000 | G211: 2700 | H211: 2600 | I211: 3775 | J211: 3400 | K211: 3600 | L211: 4450 | M211: 5900 | N211: 5060 | O211: 5575 | P211: 5400 | Q211: 5670 | R211: 5975 | S211: 6025
A212: India | B212: Producteur | C212: 3465 | D212: 3540 | E212: 3660 | F212: 3372 | G212: 3810 | H212: 4075 | I212: 3617 | J212: 3683 | K212: 3742 | L212: 3517 | M212: 3917 | N212: 4117 | O212: 4200 | P212: 5080 | Q212: 4297 | R212: 4700 | S212: 4580
A213: Honduras | B213: Producteur | C213: 0 | D213: 0 | E213: 0 | F213: 0 | G213: 0 | H213: 0 | I213: 0 | J213: 0 | K213: 0 | L213: 0 | M213: 0 | N213: 0 | O213: 0 | P213: 0 | Q213: 0 | R213: 0 | S213: 0
A214: Peru | B214: Producteur | C214: 0 | D214: 0 | E214: 0 | F214: 0 | G214: 0 | H214: 0 | I214: 0 | J214: 0 | K214: 0 | L214: 0 | M214: 0 | N214: 0 | O214: 0 | P214: 0 | Q214: 0 | R214: 0 | S214: 0
A215: Mexico | B215: Producteur | C215: 200 | D215: 200 | E215: 200 | F215: 200 | G215: 200 | H215: 175 | I215: 200 | J215: 200 | K215: 450 | L215: 550 | M215: 530 | N215: 540 | O215: 545 | P215: 500 | Q215: 340 | R215: 500 | S215: 560
A216: Guatemala | B216: Producteur | C216: 10 | D216: 10 | E216: 10 | F216: 15 | G216: 60 | H216: 170 | I216: 170 | J216: 180 | K216: 250 | L216: 130 | M216: 120 | N216: 130 | O216: 120 | P216: 130 | Q216: 130 | R216: 130 | S216: 130
A217: Nicaragua | B217: Producteur | C217: 0 | D217: 0 | E217: 0 | F217: 0 | G217: 25 | H217: 25 | I217: 25 | J217: 30 | K217: 50 | L217: 80 | M217: 100 | N217: 120 | O217: 160 | P217: 160 | Q217: 160 | R217: 160 | S217: 140
... A298: Zimbabwe | B298: Importateur | C298: 0 | D298: 0 | E298: 0 | F298: 0 | G298: 0 | H298: 0 | I298: 0 | J298: 0 | K298: 0 | L298: 0 | M298: 0 | N298: 0 | O298: 0 | P298: 0 | Q298: 0 | R298: 0 | S298: 0
A299: Total pays producteurs | C299: =SUM(C206:C252) -> 53466 | D299: =SUM(D206:D252) -> 60295 | E299: =SUM(E206:E252) -> 65146 | F299: =SUM(F206:F252) -> 67589 | G299: =SUM(G206:G252) -> 67108 | H299: =SUM(H206:H252) -> 66294 | I299: =SUM(I206:I252) -> 59943 | J299: =SUM(J206:J252) -> 64590 | ... S299: =SUM(S206:S252) -> 83800
A300: Total pays importateurs | C300: =SUM(C253:C298) -> 0 | D300: =SUM(D253:D298) -> 0 | E300: =SUM(E253:E298) -> 0 | F300: =SUM(F253:F298) -> 0 | G300: =SUM(G253:G298) -> 0 | H300: =SUM(H253:H298) -> 0 | I300: =SUM(I253:I298) -> 0 | J300: =SUM(J253:J298) -> 0 | ... S300: =SUM(S253:S298) -> 0
A301: MONDE | C301: =C299+C300 -> 53466 | D301: =D299+D300 -> 60295 | E301: =E299+E300 -> 65146 | F301: =F299+F300 -> 67589 | G301: =G299+G300 -> 67108 | H301: =H299+H300 -> 66294 | I301: =I299+I300 -> 59943 | J301: =J299+J300 -> 64590 | ... S301: =S299+S300 -> 83800
A305: Stocks de début | B305: Groupe | C305: 2010/11 | D305: 2011/12 | E305: 2012/13 | F305: 2013/14 | G305: 2014/15 | H305: 2015/16 | I305: 2016/17 | J305: 2017/18 | K305: 2018/19 | L305: 2019/20 | M305: 2020/21 | N305: 2021/22 | O305: 2022/23 | P305: 2023/24 | Q305: 2024/25 | R305: 2025/26 | S305: 2026/27
A306: Brazil | B306: Producteur | C306: 2836 | D306: 2906 | E306: 2238 | F306: 9068 | G306: 11946 | H306: 9305 | I306: 2372 | J306: 3828 | K306: 3115 | L306: 5056 | M306: 2373 | N306: 4390 | O306: 540 | P306: 4620 | Q306: 2085 | R306: 955 | S306: 3895
A307: Vietnam | B307: Producteur | C307: 1012 | D307: 800 | E307: 1090 | F307: 1946 | G307: 2130 | H307: 6336 | I307: 4201 | J307: 2681 | K307: 254 | L307: 556 | M307: 2130 | N307: 3660 | O307: 3580 | P307: 839 | Q307: 889 | R307: 1089 | S307: 689
A308: Colombia | B308: Producteur | C308: 284 | D308: 99 | E308: 249 | F308: 771 | G308: 961 | H308: 671 | I308: 1131 | J308: 886 | K308: 1111 | L308: 552 | M308: 852 | N308: 1235 | O308: 760 | P308: 885 | Q308: 668 | R308: 922 | S308: 866
A309: Ethiopia | B309: Producteur | C309: 70 | D309: 100 | E309: 230 | F309: 100 | G309: 40 | H309: 30 | I309: 25 | J309: 15 | K309: 27 | L309: 10 | M309: 210 | N309: 135 | O309: 90 | P309: 50 | Q309: 50 | R309: 80 | S309: 175
A310: Indonesia | B310: Producteur | C310: 1603 | D310: 83 | E310: 88 | F310: 98 | G310: 48 | H310: 53 | I310: 46 | J310: 12 | K310: 593 | L310: 2419 | M310: 2298 | N310: 1669 | O310: 1056 | P310: 500 | Q310: 480 | R310: 622 | S310: 751
A311: Uganda | B311: Producteur | C311: 701 | D311: 613 | E311: 538 | F311: 363 | G311: 393 | H311: 313 | I311: 313 | J311: 338 | K311: 388 | L311: 338 | M311: 363 | N311: 379 | O311: 454 | P311: 469 | Q311: 244 | R311: 269 | S311: 334
A312: India | B312: Producteur | C312: 2633 | D312: 1742 | E312: 1473 | F312: 1982 | G312: 2026 | H312: 2586 | I312: 2645 | J312: 1873 | K312: 1248 | L312: 931 | M312: 973 | N312: 911 | O312: 168 | P312: 475 | Q312: 242 | R312: 323 | S312: 485
A313: Honduras | B313: Producteur | C313: 218 | D313: 30 | E313: 90 | F313: 140 | G313: 300 | H313: 340 | I313: 315 | J313: 300 | K313: 325 | L313: 162 | M313: 124 | N313: 269 | O313: 67 | P313: 112 | Q313: 143 | R313: 178 | S313: 435
A314: Peru | B314: Producteur | C314: 74 | D314: 124 | E314: 14 | F314: 44 | G314: 24 | H314: 4 | I314: 44 | J314: 75 | K314: 85 | L314: 12 | M314: 126 | N314: 85 | O314: 95 | P314: 95 | Q314: 28 | R314: 23 | S314: 21
A315: Mexico | B315: Producteur | C315: 124 | D315: 89 | E315: 62 | F315: 61 | G315: 169 | H315: 125 | I315: 210 | J315: 153 | K315: 183 | L315: 25 | M315: 99 | N315: 17 | O315: 99 | P315: 79 | Q315: 17 | R315: 20 | S315: 20
A316: Guatemala | B316: Producteur | C316: 227 | D316: 237 | E316: 387 | F316: 212 | G316: 215 | H316: 15 | I316: 26 | J316: 36 | K316: 106 | L316: 26 | M316: 120 | N316: 111 | O316: 21 | P316: 22 | Q316: 15 | R316: 6 | S316: 11
A317: Nicaragua | B317: Producteur | C317: 37 | D317: 22 | E317: 252 | F317: 17 | G317: 22 | H317: 102 | I317: 37 | J317: 72 | K317: 142 | L317: 147 | M317: 37 | N317: 37 | O317: 25 | P317: 25 | Q317: 140 | R317: 75 | S317: 55
... A398: Zimbabwe | B398: Importateur | C398: 0 | D398: 0 | E398: 0 | F398: 0 | G398: 0 | H398: 0 | I398: 0 | J398: 0 | K398: 0 | L398: 0 | M398: 0 | N398: 0 | O398: 0 | P398: 0 | Q398: 0 | R398: 0 | S398: 0
A399: Total pays producteurs | C399: =SUM(C306:C352) -> 16045 | D399: =SUM(D306:D352) -> 13230 | E399: =SUM(E306:E352) -> 13208 | F399: =SUM(F306:F352) -> 21540 | G399: =SUM(G306:G352) -> 25684 | H399: =SUM(H306:H352) -> 27557 | I399: =SUM(I306:I352) -> 19366 | J399: =SUM(J306:J352) -> 19248 | ... S399: =SUM(S306:S352) -> 14670
A400: Total pays importateurs | C400: =SUM(C353:C398) -> 12800 | D400: =SUM(D353:D398) -> 15410 | E400: =SUM(E353:E398) -> 12540 | F400: =SUM(F353:F398) -> 13825 | G400: =SUM(G353:G398) -> 15500 | H400: =SUM(H353:H398) -> 15575 | I400: =SUM(I353:I398) -> 15585 | J400: =SUM(J353:J398) -> 17205 | ... S400: =SUM(S353:S398) -> 9700
A401: MONDE | C401: =C399+C400 -> 28845 | D401: =D399+D400 -> 28640 | E401: =E399+E400 -> 25748 | F401: =F399+F400 -> 35365 | G401: =G399+G400 -> 41184 | H401: =H399+H400 -> 43132 | I401: =I399+I400 -> 34951 | J401: =J399+J400 -> 36453 | ... S401: =S399+S400 -> 24370
A405: Importations | B405: Groupe | C405: 2010/11 | D405: 2011/12 | E405: 2012/13 | F405: 2013/14 | G405: 2014/15 | H405: 2015/16 | I405: 2016/17 | J405: 2017/18 | K405: 2018/19 | L405: 2019/20 | M405: 2020/21 | N405: 2021/22 | O405: 2022/23 | P405: 2023/24 | Q405: 2024/25 | R405: 2025/26 | S405: 2026/27
A406: Brazil | B406: Producteur | C406: 0 | D406: 0 | E406: 0 | F406: 34 | G406: 52 | H406: 65 | I406: 62 | J406: 61 | K406: 67 | L406: 67 | M406: 72 | N406: 75 | O406: 75 | P406: 75 | Q406: 90 | R406: 90 | S406: 90
A407: Vietnam | B407: Producteur | C407: 350 | D407: 450 | E407: 824 | F407: 648 | G407: 590 | H407: 630 | I407: 1000 | J407: 1060 | K407: 1160 | L407: 700 | M407: 550 | N407: 550 | O407: 499 | P407: 800 | Q407: 1200 | R407: 1300 | S407: 1250
A408: Colombia | B408: Producteur | C408: 795 | D408: 1115 | E408: 650 | F408: 455 | G408: 230 | H408: 265 | I408: 360 | J408: 775 | K408: 1111 | L408: 980 | M408: 1818 | N408: 2235 | O408: 2185 | P408: 1018 | Q408: 980 | R408: 2454 | S408: 2004
A409: Ethiopia | B409: Producteur | C409: 0 | D409: 0 | E409: 0 | F409: 0 | G409: 0 | H409: 0 | I409: 0 | J409: 0 | K409: 0 | L409: 0 | M409: 0 | N409: 0 | O409: 0 | P409: 0 | Q409: 0 | R409: 0 | S409: 0
A410: Indonesia | B410: Producteur | C410: 535 | D410: 1305 | E410: 1250 | F410: 970 | G410: 1155 | H410: 964 | I410: 743 | J410: 1751 | K410: 1676 | L410: 1231 | M410: 993 | N410: 985 | O410: 1347 | P410: 1960 | Q410: 1600 | R410: 1411 | S410: 1420
A411: Uganda | B411: Producteur | C411: 0 | D411: 0 | E411: 0 | F411: 0 | G411: 0 | H411: 0 | I411: 0 | J411: 0 | K411: 0 | L411: 0 | M411: 0 | N411: 0 | O411: 0 | P411: 0 | Q411: 0 | R411: 0 | S411: 0
A412: India | B412: Producteur | C412: 820 | D412: 892 | E412: 1164 | F412: 1152 | G412: 1205 | H412: 1202 | I412: 1386 | J412: 1472 | K412: 1386 | L412: 1430 | M412: 1345 | N412: 1690 | O412: 1760 | P412: 1363 | Q412: 1337 | R412: 1333 | S412: 1390
A413: Honduras | B413: Producteur | C413: 23 | D413: 15 | E413: 15 | F413: 15 | G413: 20 | H413: 20 | I413: 25 | J413: 25 | K413: 12 | L413: 28 | M413: 24 | N413: 21 | O413: 22 | P413: 39 | Q413: 130 | R413: 137 | S413: 160
A414: Peru | B414: Producteur | C414: 0 | D414: 0 | E414: 0 | F414: 0 | G414: 0 | H414: 0 | I414: 0 | J414: 0 | K414: 0 | L414: 119 | M414: 138 | N414: 120 | O414: 90 | P414: 306 | Q414: 75 | R414: 80 | S414: 84
A415: Mexico | B415: Producteur | C415: 1145 | D415: 1325 | E415: 1135 | F415: 1614 | G415: 1675 | H415: 2450 | I415: 1565 | J415: 1545 | K415: 1768 | L415: 1980 | M415: 1984 | N415: 2125 | O415: 2035 | P415: 1880 | Q415: 2640 | R415: 2530 | S415: 2500
A416: Guatemala | B416: Producteur | C416: 200 | D416: 180 | E416: 185 | F416: 215 | G416: 185 | H416: 190 | I416: 225 | J416: 240 | K416: 249 | L416: 304 | M416: 361 | N416: 349 | O416: 350 | P416: 445 | Q416: 571 | R416: 705 | S416: 845
A417: Nicaragua | B417: Producteur | C417: 50 | D417: 35 | E417: 30 | F417: 25 | G417: 30 | H417: 30 | I417: 40 | J417: 25 | K417: 25 | L417: 25 | M417: 25 | N417: 25 | O417: 25 | P417: 0 | Q417: 0 | R417: 0 | S417: 0
... A498: Zimbabwe | B498: Importateur | C498: 0 | D498: 0 | E498: 0 | F498: 0 | G498: 0 | H498: 0 | I498: 0 | J498: 0 | K498: 0 | L498: 0 | M498: 0 | N498: 0 | O498: 0 | P498: 0 | Q498: 0 | R498: 0 | S498: 0
A499: Total pays producteurs | C499: =SUM(C406:C452) -> 33971 | D499: =SUM(D406:D452) -> 37478 | E499: =SUM(E406:E452) -> 39338 | F499: =SUM(F406:F452) -> 39977 | G499: =SUM(G406:G452) -> 39617 | H499: =SUM(H406:H452) -> 44197 | I499: =SUM(I406:I452) -> 44559 | J499: =SUM(J406:J452) -> 44345 | ... S499: =SUM(S406:S452) -> 52391
A500: Total pays importateurs | C500: =SUM(C453:C498) -> 76895 | D500: =SUM(D453:D498) -> 75655 | E500: =SUM(E453:E498) -> 78900 | F500: =SUM(F453:F498) -> 78925 | G500: =SUM(G453:G498) -> 79725 | H500: =SUM(H453:H498) -> 82224 | I500: =SUM(I453:I498) -> 84574 | J500: =SUM(J453:J498) -> 86140 | ... S500: =SUM(S453:S498) -> 98465
A501: MONDE | C501: =C499+C500 -> 110866 | D501: =D499+D500 -> 113133 | E501: =E499+E500 -> 118238 | F501: =F499+F500 -> 118902 | G501: =G499+G500 -> 119342 | H501: =H499+H500 -> 126421 | I501: =I499+I500 -> 129133 | J501: =J499+J500 -> 130485 | ... S501: =S499+S500 -> 150856
A505: Consommation domestique | B505: Groupe | C505: 2010/11 | D505: 2011/12 | E505: 2012/13 | F505: 2013/14 | G505: 2014/15 | H505: 2015/16 | I505: 2016/17 | J505: 2017/18 | K505: 2018/19 | L505: 2019/20 | M505: 2020/21 | N505: 2021/22 | O505: 2022/23 | P505: 2023/24 | Q505: 2024/25 | R505: 2025/26 | S505: 2026/27
A506: Brazil | B506: Producteur | C506: 19420 | D506: 20025 | E506: 20110 | F506: 20210 | G506: 20420 | H506: 20855 | I506: 21625 | J506: 22420 | K506: 23200 | L506: 22994 | M506: 22280 | N506: 22340 | O506: 22450 | P506: 22160 | Q506: 21970 | R506: 22280 | S506: 22390
A507: Vietnam | B507: Producteur | C507: 1337 | D507: 1665 | E507: 1825 | F507: 2008 | G507: 2217 | H507: 2630 | I507: 2770 | J507: 2880 | K507: 2940 | L507: 3100 | M507: 2720 | N507: 3200 | O507: 3200 | P507: 3900 | Q507: 4800 | R507: 4900 | S507: 5000
A508: Colombia | B508: Producteur | C508: 1120 | D508: 1260 | E508: 1200 | F508: 1300 | G508: 1400 | H508: 1415 | I508: 1450 | J508: 1650 | K508: 1925 | L508: 1775 | M508: 2080 | N508: 2145 | O508: 2150 | P508: 2225 | Q508: 2149 | R508: 2200 | S508: 2200
A509: Ethiopia | B509: Producteur | C509: 2860 | D509: 3050 | E509: 3130 | F509: 3120 | G509: 2985 | H509: 3110 | I509: 3100 | J509: 3150 | K509: 3193 | L509: 3140 | M509: 3000 | N509: 3364 | O509: 3430 | P509: 3500 | Q509: 4000 | R509: 4500 | S509: 5000
A510: Indonesia | B510: Producteur | C510: 1650 | D510: 2125 | E510: 2815 | F510: 2540 | G510: 2900 | H510: 3175 | I510: 3203 | J510: 3560 | K510: 4300 | L510: 4900 | M510: 4450 | N510: 4750 | O510: 4771 | P510: 4775 | Q510: 4873 | R510: 4810 | S510: 4830
A511: Uganda | B511: Producteur | C511: 150 | D511: 150 | E511: 200 | F511: 220 | G511: 230 | H511: 250 | I511: 250 | J511: 250 | K511: 250 | L511: 100 | M511: 100 | N511: 125 | O511: 300 | P511: 325 | Q511: 325 | R511: 330 | S511: 335
A512: India | B512: Producteur | C512: 1231 | D512: 1168 | E512: 1100 | F512: 1170 | G512: 1191 | H512: 1250 | I512: 1200 | J512: 1215 | K512: 1250 | L512: 1170 | M512: 1180 | N512: 875 | O512: 900 | P512: 1250 | Q512: 1150 | R512: 1575 | S512: 1580
A513: Honduras | B513: Producteur | C513: 286 | D513: 265 | E513: 210 | F513: 315 | G513: 320 | H513: 345 | I513: 375 | J513: 375 | K513: 365 | L513: 366 | M513: 369 | N513: 373 | O513: 367 | P513: 340 | Q513: 335 | R513: 380 | S513: 415
A514: Peru | B514: Producteur | C514: 170 | D514: 170 | E514: 170 | F514: 170 | G514: 170 | H514: 160 | I514: 169 | J514: 180 | K514: 170 | L514: 210 | M514: 222 | N514: 245 | O514: 240 | P514: 282 | Q514: 292 | R514: 300 | S514: 305
A515: Mexico | B515: Producteur | C515: 2620 | D515: 2287 | E515: 2170 | F515: 2731 | G515: 2339 | H515: 2325 | I515: 2057 | J515: 2295 | K515: 2580 | L515: 2620 | M515: 2589 | N515: 2850 | O515: 3035 | P515: 3100 | Q515: 3100 | R515: 3160 | S515: 3240
A516: Guatemala | B516: Producteur | C516: 425 | D516: 600 | E516: 600 | F516: 552 | G516: 500 | H516: 430 | I516: 455 | J516: 485 | K516: 495 | L516: 635 | M516: 609 | N516: 625 | O516: 600 | P516: 718 | Q516: 861 | R516: 875 | S516: 900
...
