Workbook

Sheet README
A1: Honduras coffee, year by year 2005 - 2026, with the change on the year before
A2: Built 25 Sep 2026 by research/honduras/excel/build_yoy_xlsx.py (data: research/honduras/yoy/data_yoy.py).
A4: Question: area and trees go up - so is productivity really falling? Did growers use less fertiliser? How much disease? Which varieties? Which financing? What did the lempira do?
A6: Sheets
A7: YoY: every yearly series side by side, each followed by its change on the year before (formulas).
A8: Productivity: output per bearing hectare and per bearing tree, trees per hectare, the IHCAFE registry, and the 2016-18 vs 2022-24 comparison.
A9: Fertiliser: FAOSTAT nitrogen / phosphate / potash use, urea imports, urea price in US$ and in lempiras, kg of urea bought by 1 kg of coffee, Bono Cafetalero.
A10: Disease: every rust (roya) figure found, by year, and the USDA remarks on rust, berry borer, drought and fertiliser.
A11: Varieties: resistant varieties released, and every figure on the share planted.
A12: Finance: state and bank programmes by year, debt, Bono Cafetalero, BCH bank credit to agriculture 2017-2026.
A13: FX: lempiras per US$ (BCH daily reference rate, annual mean), coffee and urea prices in lempiras.
A15: Crop year t = October t to September t+1 (label t/t+1). Calendar-year series (FAOSTAT, World Bank, BCH) are put on the crop year that starts in that year.
... A17: Units: bag = 60 kg of green coffee; quintal (qq) = 46 kg; lempira = L; kha = thousand hectares.

Sheet YoY
A1: Year by year and change on the year before
A2: Each series is followed by its change on the year before (black formula). Blank = no data. 2026/27: USDA forecast (area, trees, production); prices = Jan-Aug 2026; lempira = Jan - 25 Sep 2026.
A4: Crop year | B4: Bearing area (kha) [USDA attache] | C4: change | D4: Bearing trees (million) [USDA attache] | E4: change | F4: Non-bearing area (kha) [USDA attache] | G4: change | H4: Production (1 000 bags) [USDA PSD] | I4: change | J4: Yield (bags / bearing ha) [formula] | K4: change | L4: Green coffee per bearing tree (kg) [formula] | M4: change | N4: Bearing trees per ha [formula] | O4: change | P4: IHCAFE exports (1 000 qq of 46 kg) [IHCAFE] | Q4: change | R4: Nitrogen use, all crops (t N) [FAOSTAT] | S4: change | T4: Urea imports (t) [FAOSTAT] | U4: change | V4: Urea world price (US$/t) [World Bank] | W4: change | X4: Urea price (L per t) [formula] | Y4: change | Z4: Arabica world price (US$/kg) [World Bank] | AA4: change | AB4: Arabica in lempiras (L per qq) [formula] | AC4: change | AD4: kg urea bought by 1 kg coffee [formula] | AE4: change | AF4: Lempiras per US$ (BCH) [BCH] | AG4: change
A6: 2005/06 | B6: 184 | D6: 753 | F6: 64 | H6: 3204 | J6: =H6/B6 -> 17.413043 | L6: =H6*60/D6/1000 -> 0.2552988 | N6: =D6*1000/B6 -> 4092.3913 | P6: 3817.948 | R6: 41865 | T6: 35952.04 | V6: 217.35833 | X6: =V6*AF6 -> 4093.5362 | Z6: 2.5325 | AB6: =Z6*46*AF6 -> 2193.9647 | AD6: =Z6*1000/V6 -> 11.651267 | AF6: 18.833123
A7: 2006/07 | B7: 230 | C7: =B7/B6-1 -> 0.25 | D7: 1049 | E7: =D7/D6-1 -> 0.39309429 | F7: 13 | G7: =F7/F6-1 -> -0.796875 | H7: 3460 | I7: =H7/H6-1 -> 0.079900125 | J7: =H7/B7 -> 15.043478 | K7: =J7/J6-1 -> -0.1360799 | L7: =H7*60/D7/1000 -> 0.19790276 | M7: =L7/L6-1 -> -0.22481907 | N7: =D7*1000/B7 -> 4560.8696 | O7: =N7/N6-1 -> 0.11447543 | P7: 4194.523 | Q7: =P7/P6-1 -> 0.098632826 | R7: 66688 | S7: =R7/R6-1 -> 0.59292965 | T7: 85809.62 | U7: =T7/T6-1 -> 1.3867803 | V7: 222.14167 | W7: =V7/V6-1 -> 0.022006671 | X7: =V7*AF7 -> 4197.4125 | Y7: =X7/X6-1 -> 0.025375669 | Z7: 2.5216667 | AA7: =Z7/Z6-1 -> -0.0042777229 | AB7: =Z7*46*AF7 -> 2191.7809 | AC7: =AB7/AB6-1 -> -0.00099536988 | AD7: =Z7*1000/V7 -> 11.351615 | AE7: =AD7/AD6-1 -> -0.025718417 | AF7: 18.895206 | AG7: =AF7/AF6-1 -> 0.0032964544
A8: 2007/08 | B8: 230 | C8: =B8/B7-1 -> 0 | D8: 1049 | E8: =D8/D7-1 -> 0 | F8: 13 | G8: =F8/F7-1 -> 0 | H8: 3642 | I8: =H8/H7-1 -> 0.052601156 | J8: =H8/B8 -> 15.834783 | K8: =J8/J7-1 -> 0.052601156 | L8: =H8*60/D8/1000 -> 0.20831268 | M8: =L8/L7-1 -> 0.052601156 | N8: =D8*1000/B8 -> 4560.8696 | O8: =N8/N7-1 -> 0 | P8: 4427.991 | Q8: =P8/P7-1 -> 0.055660203 | R8: 63491 | S8: =R8/R7-1 -> -0.047939659 | T8: 79076.84 | U8: =T8/T7-1 -> -0.078461832 | V8: 307.11667 | W8: =V8/V7-1 -> 0.38252617 | X8: =V8*AF8 -> 5803.0006 | Y8: =X8/X7-1 -> 0.38251856 | Z8: 2.7241667 | AA8: =Z8/Z7-1 -> 0.080304032 | AB8: =Z8*46*AF8 -> 2367.7767 | AC8: =AB8/AB7-1 -> 0.080298087 | AD8: =Z8*1000/V8 -> 8.8701362 | AE8: =AD8/AD7-1 -> -0.21860138 | AF8: 18.895102 | AG8: =AF8/AF7-1 -> -5.502861e-06
A9: 2008/09 | B9: 224 | C9: =B9/B8-1 -> -0.026086957 | D9: 1049 | E9: =D9/D8-1 -> 0 | F9: 20 | G9: =F9/F8-1 -> 0.53846154 | H9: 3225 | I9: =H9/H8-1 -> -0.11449753 | J9: =H9/B9 -> 14.397321 | K9: =J9/J8-1 -> -0.090778713 | L9: =H9*60/D9/1000 -> 0.18446139 | M9: =L9/L8-1 -> -0.11449753 | N9: =D9*1000/B9 -> 4683.0357 | O9: =N9/N8-1 -> 0.026785714 | P9: 3940.279 | Q9: =P9/P8-1 -> -0.11014295 | R9: 55554 | S9: =R9/R8-1 -> -0.12500984 | V9: 514.98333 | W9: =V9/V8-1 -> 0.67683291 | X9: =V9*AF9 -> 9732.1326 | Y9: =X9/X8-1 -> 0.67708626 | Z9: 3.0808333 | AA9: =Z9/Z8-1 -> 0.13092689 | AB9: =Z9*46*AF9 -> 2678.1869 | AC9: =AB9/AB8-1 -> 0.13109776 | AD9: =Z9*1000/V9 -> 5.9823943 | AE9: =AD9/AD8-1 -> -0.32555779 | AF9: 18.897956 | AG9: =AF9/AF8-1 -> 0.00015109051
A10: 2009/10 | B10: 224 | C10: =B10/B9-1 -> 0 | D10: 1049 | E10: =D10/D9-1 -> 0 | F10: 20 | G10: =F10/F9-1 -> 0 | H10: 3550 | I10: =H10/H9-1 -> 0.10077519 | J10: =H10/B10 -> 15.848214 | K10: =J10/J9-1 -> 0.10077519 | L10: =H10*60/D10/1000 -> 0.20305052 | M10: =L10/L9-1 -> 0.10077519 | N10: =D10*1000/B10 -> 4683.0357 | O10: =N10/N9-1 -> 0 | P10: 4122.888 | Q10: =P10/P9-1 -> 0.04634418 | R10: 47616 | S10: =R10/R9-1 -> -0.142888 | T10: 60810.87 | V10: 251.1 | W10: =V10/V9-1 -> -0.5124114 | X10: =V10*AF10 -> 4744.5596 | Y10: =X10/X9-1 -> -0.51248511 | Z10: 3.1708333 | AA10: =Z10/Z9-1 -> 0.029212875 | AB10: =Z10*46*AF10 -> 2756.0078 | AC10: =AB10/AB9-1 -> 0.029057307 | AD10: =Z10*1000/V10 -> 12.627771 | AE10: =AD10/AD9-1 -> 1.1108223 | AF10: 18.8951 | AG10: =AF10/AF9-1 -> -0.00015115235
A11: 2010/11 | B11: 238 | C11: =B11/B10-1 -> 0.0625 | D11: 1049 | E11: =D11/D10-1 -> 0 | F11: 28 | G11: =F11/F10-1 -> 0.4 | H11: 3975 | I11: =H11/H10-1 -> 0.11971831 | J11: =H11/B11 -> 16.701681 | K11: =J11/J10-1 -> 0.053852527 | L11: =H11*60/D11/1000 -> 0.22735939 | M11: =L11/L10-1 -> 0.11971831 | N11: =D11*1000/B11 -> 4407.563 | O11: =N11/N10-1 -> -0.058823529 | P11: 5042.612 | Q11: =P11/P10-1 -> 0.22307761 | R11: 56041 | S11: =R11/R10-1 -> 0.17693632 | T11: 82828.86 | U11: =T11/T10-1 -> 0.36207326 | V11: 288.91667 | W11: =V11/V10-1 -> 0.15060401 | X11: =V11*AF11 -> 5459.0767 | Y11: =X11/X10-1 -> 0.15059713 | Z11: 4.32 | AA11: =Z11/Z10-1 -> 0.36241787 | AB11: =Z11*46*AF11 -> 3754.8118 | AC11: =AB11/AB10-1 -> 0.36240973 | AD11: =Z11*1000/V11 -> 14.952408 | AE11: =AD11/AD10-1 -> 0.18408928 | AF11: 18.894987 | AG11: =AF11/AF10-1 -> -5.9772733e-06
A12: 2011/12 | B12: 245 | C12: =B12/B11-1 -> 0.029411765 | D12: 1042 | E12: =D12/D11-1 -> -0.0066730219 | F12: 40 | G12: =F12/F11-1 -> 0.42857143 | H12: 5600 | I12: =H12/H11-1 -> 0.40880503 | J12: =H12/B12 -> 22.857143 | K12: =J12/J11-1 -> 0.36855346 | L12: =H12*60/D12/1000 -> 0.32245681 | M12: =L12/L11-1 -> 0.41826917 | N12: =D12*1000/B12 -> 4253.0612 | O12: =N12/N11-1 -> -0.035053793 | P12: 7139.81 | Q12: =P12/P11-1 -> 0.41589517 | R12: 85542 | S12: =R12/R11-1 -> 0.52641816 | T12: 128026.7 | U12: =T12/T11-1 -> 0.54567744 | V12: 398.94167 | W12: =V12/V11-1 -> 0.38081915 | X12: =V12*AF12 -> 7546.3322 | Y12: =X12/X11-1 -> 0.38234589 | Z12: 5.9766667 | AA12: =Z12/Z11-1 -> 0.38348765 | AB12: =Z12*46*AF12 -> 5200.4795 | AC12: =AB12/AB11-1 -> 0.38501734 | AD12: =Z12*1000/V12 -> 14.981305 | AE12: =AD12/AD11-1 -> 0.0019325502 | AF12: 18.915879 | AG12: =AF12/AF11-1 -> 0.0011056764
A13: 2012/13 | B13: 267 | C13: =B13/B12-1 -> 0.089795918 | D13: 1068 | E13: =D13/D12-1 -> 0.024952015 | F13: 48 | G13: =F13/F12-1 -> 0.2 | H13: 4725 | I13: =H13/H12-1 -> -0.15625 | J13: =H13/B13 -> 17.696629 | K13: =J13/J12-1 -> -0.22577247 | L13: =H13*60/D13/1000 -> 0.26544944 | M13: =L13/L12-1 -> -0.17679073 | N13: =D13*1000/B13 -> 4000 | O13: =N13/N12-1 -> -0.05950096 | P13: 5660.894 | Q13: =P13/P12-1 -> -0.2071366 | R13: 75417 | S13: =R13/R12-1 -> -0.11836291 | T13: 126987.33 | U13: =T13/T12-1 -> -0.0081183847 | V13: 398.6 | W13: =V13/V12-1 -> -0.00085643264 | X13: =V13*AF13 -> 7774.3162 | Y13: =X13/X12-1 -> 0.030211231 | Z13: 4.1116667 | AA13: =Z13/Z12-1 -> -0.31204685 | AB13: =Z13*46*AF13 -> 3688.9319 | AC13: =AB13/AB12-1 -> -0.29065543 | AD13: =Z13*1000/V13 -> 10.31527 | AE13: =AD13/AD12-1 -> -0.31145716 | AF13: 19.504055 | AG13: =AF13/AF12-1 -> 0.031094294
A14: 2013/14 | B14: 213 | C14: =B14/B13-1 -> -0.20224719 | D14: 900 | E14: =D14/D13-1 -> -0.15730337 | F14: 50 | G14: =F14/F13-1 -> 0.041666667 | H14: 4400 | I14: =H14/H13-1 -> -0.068783069 | J14: =H14/B14 -> 20.657277 | K14: =J14/J13-1 -> 0.1673001 | L14: =H14*60/D14/1000 -> 0.29333333 | M14: =L14/L13-1 -> 0.10504409 | N14: =D14*1000/B14 -> 4225.3521 | O14: =N14/N13-1 -> 0.056338028 | P14: 5446.757 | Q14: =P14/P13-1 -> -0.037827417 | R14: 74712 | S14: =R14/R13-1 -> -0.009348025 | V14: 339.60833 | W14: =V14/V13-1 -> -0.14799716 | X14: =V14*AF14 -> 6913.249 | Y14: =X14/X13-1 -> -0.11075794 | Z14: 3.0766667 | AA14: =Z14/Z13-1 -> -0.25172274 | AB14: =Z14*46*AF14 -> 2880.9926 | AC14: =AB14/AB13-1 -> -0.21901714 | AD14: =Z14*1000/V14 -> 9.0594557 | AE14: =AD14/AD13-1 -> -0.12174324 | AF14: 20.356535 | AG14: =AF14/AF13-1 -> 0.04370786
A15: 2014/15 | B15: 227 | C15: =B15/B14-1 -> 0.0657277 | D15: 966 | E15: =D15/D14-1 -> 0.073333333 | F15: 66 | G15: =F15/F14-1 -> 0.32 | H15: 5100 | I15: =H15/H14-1 -> 0.15909091 | J15: =H15/B15 -> 22.46696 | K15: =J15/J14-1 -> 0.087605126 | L15: =H15*60/D15/1000 -> 0.31677019 | M15: =L15/L14-1 -> 0.079898363 | N15: =D15*1000/B15 -> 4255.5066 | O15: =N15/N14-1 -> 0.0071365639 | P15: 6547.92 | Q15: =P15/P14-1 -> 0.20216856 | R15: 74007 | S15: =R15/R14-1 -> -0.0094362351 | T15: 103967.9 | V15: 308.44167 | W15: =V15/V14-1 -> -0.091772385 | X15: =V15*AF15 -> 6473.7649 | Y15: =X15/X14-1 -> -0.063571275 | Z15: 4.425 | AA15: =Z15/Z14-1 -> 0.43824485 | AB15: =Z15*46*AF15 -> 4272.2336 | AC15: =AB15/AB14-1 -> 0.48290337 | AD15: =Z15*1000/V15 -> 14.346311 | AE15: =AD15/AD14-1 -> 0.58357314 | AF15: 20.98862 | AG15: =AF15/AF14-1 -> 0.031050708
A16: 2015/16 | B16: 240 | C16: =B16/B15-1 -> 0.057268722 | D16: 1020 | E16: =D16/D15-1 -> 0.055900621 | F16: 63 | G16: =F16/F15-1 -> -0.045454545 | H16: 5300 | I16: =H16/H15-1 -> 0.039215686 | J16: =H16/B16 -> 22.083333 | K16: =J16/J15-1 -> -0.017075163 | L16: =H16*60/D16/1000 -> 0.31176471 | M16: =L16/L15-1 -> -0.015801615 | N16: =D16*1000/B16 -> 4250 | O16: =N16/N15-1 -> -0.0012939959 | P16: 6704.36 | Q16: =P16/P15-1 -> 0.023891556 | R16: 75343 | S16: =R16/R15-1 -> 0.018052346 | T16: 111558.82 | U16: =T16/T15-1 -> 0.073012151 | V16: 277.94167 | W16: =V16/V15-1 -> -0.098884176 | X16: =V16*AF16 -> 6099.9141 | Y16: =X16/X15-1 -> -0.057748589 | Z16: 3.5258333 | AA16: =Z16/Z15-1 -> -0.20320151 | AB16: =Z16*46*AF16 -> 3559.5056 | AC16: =AB16/AB15-1 -> -0.16682797 | AD16: =Z16*1000/V16 -> 12.685516 | AE16: =AD16/AD15-1 -> -0.11576462 | AF16: 21.946742 | AG16: =AF16/AF15-1 -> 0.045649611
A17: 2016/17 | B17: 280 | C17: =B17/B16-1 -> 0.16666667 | D17: 1191 | E17: =D17/D16-1 -> 0.16764706 | F17: 54 | G17: =F17/F16-1 -> -0.14285714 | H17: 7510 | I17: =H17/H16-1 -> 0.41698113 | J17: =H17/B17 -> 26.821429 | K17: =J17/J16-1 -> 0.21455526 | L17: =H17*60/D17/1000 -> 0.37833753 | M17: =L17/L16-1 -> 0.21353548 | N17: =D17*1000/B17 -> 4253.5714 | O17: =N17/N16-1 -> 0.00084033613 | P17: 9509.895 | Q17: =P17/P16-1 -> 0.41846425 | R17: 95944 | S17: =R17/R16-1 -> 0.27342952 | T17: 143032.93 | U17: =T17/T16-1 -> 0.28213018 | V17: 194.15 | W17: =V17/V16-1 -> -0.30147213 | X17: =V17*AF17 -> 4434.1043 | Y17: =X17/X16-1 -> -0.27308742 | Z17: 3.6125 | AA17: =Z17/Z16-1 -> 0.024580477 | AB17: =Z17*46*AF17 -> 3795.1959 | AC17: =AB17/AB16-1 -> 0.066214351 | AD17: =Z17*1000/V17 -> 18.606747 | AE17: =AD17/AD16-1 -> 0.46677108 | AF17: 22.838549 | AG17: =AF17/AF16-1 -> 0.040635045
A18: 2017/18 | B18: 298 | C18: =B18/B17-1 -> 0.064285714 | D18: 1269 | E18: =D18/D17-1 -> 0.065491184 | F18: 44 | G18: =F18/F17-1 -> -0.18518519 | H18: 7600 | I18: =H18/H17-1 -> 0.011984021 | J18: =H18/B18 -> 25.503356 | K18: =J18/J17-1 -> -0.04914253 | L18: =H18*60/D18/1000 -> 0.35933806 | M18: =L18/L17-1 -> -0.050218306 | N18: =D18*1000/B18 -> 4258.3893 | O18: =N18/N17-1 -> 0.001132656 | P18: 9410.583 | Q18: =P18/P17-1 -> -0.010443018 | R18: 110175 | S18: =R18/R17-1 -> 0.14832611 | T18: 157715.35 | U18: =T18/T17-1 -> 0.10265063 | V18: 213.88333 | W18: =V18/V17-1 -> 0.10163963 | X18: =V18*AF18 -> 5023.4204 | Y18: =X18/X17-1 -> 0.13290533 | Z18: 3.3241667 | AA18: =Z18/Z17-1 -> -0.079815456 | AB18: =Z18*46*AF18 -> 3591.3953 | AC18: =AB18/AB17-1 -> -0.053699638 | AD18: =Z18*1000/V18 -> 15.541962 | AE18: =AD18/AD17-1 -> -0.16471365 | AF18: 23.486732 | AG18: =AF18/AF17-1 -> 0.028381066
A19: 2018/19 | B19: 286 | C19: =B19/B18-1 -> -0.040268456 | D19: 1362 | E19: =D19/D18-1 -> 0.073286052 | F19: 36 | G19: =F19/F18-1 -> -0.18181818 | H19: 7100 | I19: =H19/H18-1 -> -0.065789474 | J19: =H19/B19 -> 24.825175 | K19: =J19/J18-1 -> -0.026591829 | L19: =H19*60/D19/1000 -> 0.31277533 | M19: =L19/L18-1 -> -0.12957918 | N19: =D19*1000/B19 -> 4762.2378 | O19: =N19/N18-1 -> 0.11831903 | P19: 8887.536 | Q19: =P19/P18-1 -> -0.055580722 | R19: 122752 | S19: =R19/R18-1 -> 0.11415475 | T19: 178390.81 | U19: =T19/T18-1 -> 0.13109352 | V19: 249.45 | W19: =V19/V18-1 -> 0.16629003 | X19: =V19*AF19 -> 5962.1335 | Y19: =X19/X18-1 -> 0.18686731 | Z19: 2.925 | AA19: =Z19/Z18-1 -> -0.12008022 | AB19: =Z19*46*AF19 -> 3215.8952 | AC19: =AB19/AB18-1 -> -0.10455548 | AD19: =Z19*1000/V19 -> 11.725797 | AE19: =AD19/AD18-1 -> -0.24553948 | AF19: 23.901116 | AG19: =AF19/AF18-1 -> 0.017643362
A20: 2019/20 | B20: 270 | C20: =B20/B19-1 -> -0.055944056 | D20: 1290 | E20: =D20/D19-1 -> -0.052863436 | F20: 35 | G20: =F20/F19-1 -> -0.027777778 | H20: 5200 | I20: =H20/H19-1 -> -0.26760563 | J20: =H20/B20 -> 19.259259 | K20: =J20/J19-1 -> -0.22420449 | L20: =H20*60/D20/1000 -> 0.24186047 | M20: =L20/L19-1 -> -0.22672781 | N20: =D20*1000/B20 -> 4777.7778 | O20: =N20/N19-1 -> 0.0032631751 | P20: 7182.026 | Q20: =P20/P19-1 -> -0.19189908 | R20: 86136 | S20: =R20/R19-1 -> -0.29829249 | T20: 134078.54 | U20: =T20/T19-1 -> -0.24839996 | V20: 245.28333 | W20: =V20/V19-1 -> -0.016703414 | X20: =V20*AF20 -> 6011.3133 | Y20: =X20/X19-1 -> 0.0082486857 | Z20: 2.88 | AA20: =Z20/Z19-1 -> -0.015384615 | AB20: =Z20*46*AF20 -> 3246.7709 | AC20: =AB20/AB19-1 -> 0.0096009503 | AD20: =Z20*1000/V20 -> 11.741523 | AE20: =AD20/AD19-1 -> 0.0013412014 | AF20: 24.50763 | AG20: =AF20/AF19-1 -> 0.025375965
A21: 2020/21 | B21: 273 | C21: =B21/B20-1 -> 0.011111111 | D21: 1295 | E21: =D21/D20-1 -> 0.003875969 | F21: 34 | G21: =F21/F20-1 -> -0.028571429 | H21: 6500 | I21: =H21/H20-1 -> 0.25 | J21: =H21/B21 -> 23.809524 | K21: =J21/J20-1 -> 0.23626374 | L21: =H21*60/D21/1000 -> 0.3011583 | M21: =L21/L20-1 -> 0.24517375 | N21: =D21*1000/B21 -> 4743.5897 | O21: =N21/N20-1 -> -0.0071556351 | P21: 7660.696 | Q21: =P21/P20-1 -> 0.066648325 | R21: 128016 | S21: =R21/R20-1 -> 0.48620786 | T21: 190619.62 | U21: =T21/T20-1 -> 0.42170119 | V21: 229.1 | W21: =V21/V20-1 -> -0.065978121 | X21: =V21*AF21 -> 5631.8037 | Y21: =X21/X20-1 -> -0.063132557 | Z21: 3.3233333 | AA21: =Z21/Z20-1 -> 0.15393519 | AB21: =Z21*46*AF21 -> 3757.9773 | AC21: =AB21/AB20-1 -> 0.15745073 | AD21: =Z21*1000/V21 -> 14.506038 | AE21: =AD21/AD20-1 -> 0.2354477 | AF21: 24.582295 | AG21: =AF21/AF20-1 -> 0.0030465708
A22: 2021/22 | B22: 275 | C22: =B22/B21-1 -> 0.0073260073 | D22: 1375 | E22: =D22/D21-1 -> 0.061776062 | F22: 32 | G22: =F22/F21-1 -> -0.058823529 | H22: 4800 | I22: =H22/H21-1 -> -0.26153846 | J22: =H22/B22 -> 17.454545 | K22: =J22/J21-1 -> -0.26690909 | L22: =H22*60/D22/1000 -> 0.20945455 | M22: =L22/L21-1 -> -0.3045035 | N22: =D22*1000/B22 -> 5000 | O22: =N22/N21-1 -> 0.054054054 | P22: 6131.226 | Q22: =P22/P21-1 -> -0.19965158 | R22: 104868 | S22: =R22/R21-1 -> -0.18082115 | T22: 173224.31 | U22: =T22/T21-1 -> -0.091256661 | V22: 483.21667 | W22: =V22/V21-1 -> 1.1091954 | X22: =V22*AF22 -> 11604.575 | Y22: =X22/X21-1 -> 1.0605432 | Z22: 4.5108333 | AA22: =Z22/Z21-1 -> 0.35732197 | AB22: =Z22*46*AF22 -> 4983.1267 | AC22: =AB22/AB21-1 -> 0.32601299 | AD22: =Z22*1000/V22 -> 9.3350119 | AE22: =AD22/AD21-1 -> -0.35647405 | AF22: 24.015262 | AG22: =AF22/AF21-1 -> -0.023066727
A23: 2022/23 | B23: 285 | C23: =B23/B22-1 -> 0.036363636 | D23: 1600 | E23: =D23/D22-1 -> 0.16363636 | F23: 35 | G23: =F23/F22-1 -> 0.09375 | H23: 5700 | I23: =H23/H22-1 -> 0.1875 | J23: =H23/B23 -> 20 | K23: =J23/J22-1 -> 0.14583333 | L23: =H23*60/D23/1000 -> 0.21375 | M23: =L23/L22-1 -> 0.020507812 | N23: =D23*1000/B23 -> 5614.0351 | O23: =N23/N22-1 -> 0.12280702 | P23: 6900 | Q23: =P23/P22-1 -> 0.12538667 | R23: 104865 | S23: =R23/R22-1 -> -2.8607392e-05 | V23: 700.03333 | W23: =V23/V22-1 -> 0.44869451 | X23: =V23*AF23 -> 17141.62 | Y23: =X23/X22-1 -> 0.47714331 | Z23: 5.6308333 | AA23: =Z23/Z22-1 -> 0.24829115 | AB23: =Z23*46*AF23 -> 6342.5462 | AC23: =AB23/AB22-1 -> 0.27280452 | AD23: =Z23*1000/V23 -> 8.0436646 | AE23: =AD23/AD22-1 -> -0.13833376 | AF23: 24.486862 | AG23: =AF23/AF22-1 -> 0.019637542
A24: 2023/24 | B24: 292 | C24: =B24/B23-1 -> 0.024561404 | D24: 1800 | E24: =D24/D23-1 -> 0.125 | F24: 38 | G24: =F24/F23-1 -> 0.085714286 | H24: 5050 | I24: =H24/H23-1 -> -0.11403509 | J24: =H24/B24 -> 17.294521 | K24: =J24/J23-1 -> -0.13527397 | L24: =H24*60/D24/1000 -> 0.16833333 | M24: =L24/L23-1 -> -0.21247563 | N24: =D24*1000/B24 -> 6164.3836 | O24: =N24/N23-1 -> 0.098030822 | R24: 104427 | S24: =R24/R23-1 -> -0.0041767987 | T24: 166700.89 | V24: 358.00833 | W24: =V24/V23-1 -> -0.48858388 | X24: =V24*AF24 -> 8807.5711 | Y24: =X24/X23-1 -> -0.48618793 | Z24: 4.5408333 | AA24: =Z24/Z23-1 -> -0.19357703 | AB24: =Z24*46*AF24 -> 5138.7373 | AC24: =AB24/AB23-1 -> -0.18979901 | AD24: =Z24*1000/V24 -> 12.683597 | AE24: =AD24/AD23-1 -> 0.57684307 | AF24: 24.601581 | AG24: =AF24/AF23-1 -> 0.0046849171
A25: 2024/25 | B25: 300 | C25: =B25/B24-1 -> 0.02739726 | D25: 1900 | E25: =D25/D24-1 -> 0.055555556 | F25: 40 | G25: =F25/F24-1 -> 0.052631579 | H25: 5200 | I25: =H25/H24-1 -> 0.02970297 | J25: =H25/B25 -> 17.333333 | K25: =J25/J24-1 -> 0.0022442244 | L25: =H25*60/D25/1000 -> 0.16421053 | M25: =L25/L24-1 -> -0.024491923 | N25: =D25*1000/B25 -> 6333.3333 | O25: =N25/N24-1 -> 0.027407407 | P25: 6117.3131 | R25: 106830 | S25: =R25/R24-1 -> 0.02301129 | T25: 179565.06 | U25: =T25/T24-1 -> 0.077169174 | V25: 338.28333 | W25: =V25/V24-1 -> -0.055096483 | X25: =V25*AF25 -> 8387.7329 | Y25: =X25/X24-1 -> -0.047667868 | Z25: 5.6208333 | AA25: =Z25/Z24-1 -> 0.23784181 | AB25: =Z25*46*AF25 -> 6410.9521 | AC25: =AB25/AB24-1 -> 0.24757343 | AD25: =Z25*1000/V25 -> 16.615756 | AE25: =AD25/AD24-1 -> 0.31001926 | AF25: 24.794993 | AG25: =AF25/AF24-1 -> 0.0078617708
A26: 2025/26 | B26: 310 | C26: =B26/B25-1 -> 0.033333333 | D26: 2000 | E26: =D26/D25-1 -> 0.052631579 | F26: 40 | G26: =F26/F25-1 -> 0 | H26: 5530 | I26: =H26/H25-1 -> 0.063461538 | J26: =H26/B26 -> 17.83871 | K26: =J26/J25-1 -> 0.029156328 | L26: =H26*60/D26/1000 -> 0.1659 | M26: =L26/L25-1 -> 0.010288462 | N26: =D26*1000/B26 -> 6451.6129 | O26: =N26/N25-1 -> 0.018675722 | V26: 422.65833 | W26: =V26/V25-1 -> 0.2494211 | X26: =V26*AF26 -> 10969.977 | Y26: =X26/X25-1 -> 0.30785956 | Z26: 8.47 | AA26: =Z26/Z25-1 -> 0.506894 | AB26: =Z26*46*AF26 -> 10112.476 | AC26: =AB26/AB25-1 -> 0.57737509 | AD26: =Z26*1000/V26 -> 20.039827 | AE26: =AD26/AD25-1 -> 0.20607376 | AF26: 25.954715 | AG26: =AF26/AF25-1 -> 0.046772429
A27: 2026/27 | B27: 330 | C27: =B27/B26-1 -> 0.064516129 | D27: 2100 | E27: =D27/D26-1 -> 0.05 | F27: 30 | G27: =F27/F26-1 -> -0.25 | H27: 6030 | I27: =H27/H26-1 -> 0.090415913 | J27: =H27/B27 -> 18.272727 | K27: =J27/J26-1 -> 0.0243301 | L27: =H27*60/D27/1000 -> 0.17228571 | M27: =L27/L26-1 -> 0.038491346 | N27: =D27*1000/B27 -> 6363.6364 | O27: =N27/N26-1 -> -0.013636364 | V27: 560.4375 | W27: =V27/V26-1 -> 0.32598237 | X27: =V27*AF27 -> 14930.065 | Y27: =X27/X26-1 -> 0.36099329 | Z27: 7.42375 | AA27: =Z27/Z26-1 -> -0.1235242 | AB27: =Z27*46*AF27 -> 9097.366 | AC27: =AB27/AB26-1 -> -0.10038195 | AD27: =Z27*1000/V27 -> 13.246348 | AE27: =AD27/AD26-1 -> -0.33899891 | AF27: 26.640017 | AG27: =AF27/AF26-1 -> 0.026403755
A29: Notes: bearing trees and area are the USDA attache estimates (IHCAFE data); the tree count jumps from 1 375 M (2021) to 2 100 M (2026) while the bearing area rises 20 %: check before quoting per-tree numbers.
A30: IHCAFE exports: 2005/06 - 2020/21 IHCAFE report 2020-2021; 2021/22 bulletin 07-02-2023; 2024/25 La Prensa 15 Jul 2026. 2025/26 estimate: 7 244 000 qq (Exports_nowcast of the forecast workbook) - not in this column.
A31: FAOSTAT nitrogen = imports - exports of nitrogen in all fertilisers (all crops, coffee not separated); 2022 is imputed by FAO (flag I).
A32: Lempira column: BCH daily reference rate (buying), mean of the days of the year; 2026 = 1 Jan - 25 Sep.

Sheet Productivity
A1: Is productivity really falling while area and trees go up?
A2: Averages of 2016/17-2018/19 (peak) against 2022/23-2024/25 (last three crops with an outcome). Formulas on the YoY sheet.
A4: Series | B4: 2016/17-2018/19 | C4: 2022/23-2024/25 | D4: Change
A5: Bearing area (kha) | B5: =AVERAGE(YoY!B17:B19) -> 288 | C5: =AVERAGE(YoY!B23:B25) -> 292.33333 | D5: =C5/B5-1 -> 0.015046296
A6: Bearing trees (million) | B6: =AVERAGE(YoY!D17:D19) -> 1274 | C6: =AVERAGE(YoY!D23:D25) -> 1766.6667 | D6: =C6/B6-1 -> 0.38670853
A7: Production (1 000 bags) | B7: =AVERAGE(YoY!H17:H19) -> 7403.3333 | C7: =AVERAGE(YoY!H23:H25) -> 5316.6667 | D7: =C7/B7-1 -> -0.28185502
A8: Yield (bags / bearing ha) | B8: =AVERAGE(YoY!J17:J19) -> 25.716653 | C8: =AVERAGE(YoY!J23:J25) -> 18.209285 | D8: =C8/B8-1 -> -0.29192634
A9: Green coffee per bearing tree (kg) | B9: =AVERAGE(YoY!L17:L19) -> 0.35015031 | C9: =AVERAGE(YoY!L23:L25) -> 0.18209795 | D9: =C9/B9-1 -> -0.47994347
A10: Bearing trees per ha | B10: =AVERAGE(YoY!N17:N19) -> 4424.7328 | C10: =AVERAGE(YoY!N23:N25) -> 6037.2507 | D10: =C10/B10-1 -> 0.36443282
A11: Nitrogen use, all crops (t N) | B11: =AVERAGE(YoY!R17:R19) -> 109623.67 | C11: =AVERAGE(YoY!R23:R25) -> 105374 | D11: =C11/B11-1 -> -0.03876596
A12: Urea imports (t) | B12: =AVERAGE(YoY!T17:T19) -> 159713.03 | C12: =AVERAGE(YoY!T23:T25) -> 173132.98 | D12: =C12/B12-1 -> 0.084025361
A13: Urea price (L per t) | B13: =AVERAGE(YoY!X17:X19) -> 5139.8861 | C13: =AVERAGE(YoY!X23:X25) -> 11445.641 | D13: =C13/B13-1 -> 1.2268278
A14: kg urea bought by 1 kg coffee | B14: =AVERAGE(YoY!AD17:AD19) -> 15.291502 | C14: =AVERAGE(YoY!AD23:AD25) -> 12.447672 | D14: =C14/B14-1 -> -0.18597451
A15: Lempiras per US$ | B15: =AVERAGE(YoY!AF17:AF19) -> 23.408799 | C15: =AVERAGE(YoY!AF23:AF25) -> 24.627812 | D15: =C15/B15-1 -> 0.052074994
A17: IHCAFE registry (farms registered with IHCAFE) | B17: Harvested ha | C17: 60-kg bags | D17: Bags per ha | E17: Producers | F17: Source
A18: 2022/23 | B18: 315731.11 | C18: 5576639 | D18: =C18/B18 -> 17.662621 | E18: 97277 | F18: GAIN 2024, table 1 (IHCAFE Coffee Statistics Report)
A19: 2023/24 | B19: 280097 | C19: 4650354 | D19: =C19/B19 -> 16.602656 | E19: 92421 | F19: GAIN 2025, table 1 (IHCAFE Coffee Statistics Report)
A20: 2024/25 | B20: 285557 | C20: 4804430 | D20: =C20/B20 -> 16.824767 | E20: 93628 | F20: GAIN 2026, table 1 (IHCAFE Coffee Statistics Report)
A21: Coffee producers 2018: about 130,000, 110,000 registered with IHCAFE (El Heraldo 5 Sep 2018 (read))
A22: Coffee producers 2022: about 100,000 (La Prensa / EFE 1 Nov 2022 (read): "mas de 100,000 productores")
A24: 2025/26: production implied by IHCAFE exports 6,045 thousand bags on 310 kha = 19.5 bags per ha (USDA estimate: 17.8).
A26: Reading: yes, output per hectare fell by about 30 % from the 2016-18 peak (25.7 to 18.2 bags per ha), and the IHCAFE registry (16.6-17.7 bags per ha in 2022-24) says the same as USDA. Output per tree fell by about half (0.35 to 0.18 kg) because USDA counts about 40 % more trees on about the same area (6 000 instead of 4 400 trees per ha: denser, younger plantings).
A27: Fertiliser does not explain it on its own: national nitrogen use in 2022-24 was only 4 % below 2016-18 (5 % per bearing coffee hectare), small next to the 30 % fall in yield. What changed: the 2012-15 renewal wave aged ("cyclical decline in productivity after a widespread re-planting effort ten years ago", USDA 2022), rust came back (Lempira lost its resistance in 2016/17; 15-25 % incidence after Eta/Iota in 2020; 5-8 % since 2022), fertiliser became dearer in lempiras (2021-22), the 2019-20 price slump cut care, labour ran short (USDA 2024) and Sep-Oct heat was higher (see the forecast workbook).

Sheet Fertiliser
A1: Fertiliser: how much, how dear, and the state gift (Bono Cafetalero)
A2: FAOSTAT: agricultural use = imports - exports of the nutrient in all fertilisers (all crops). Flag I = imputed by FAO. Urea imports: FAOSTAT fertilisers by product.
A4: Year | B4: N (t) | C4: change | D4: P2O5 (t) | E4: change | F4: K2O (t) | G4: change | H4: FAO flag (N imports) | I4: Urea imports (t) | J4: change | K4: Urea import unit value (US$/t) | L4: Urea world (US$/t) | M4: change | N4: Urea (L/t) | O4: change | P4: N per bearing coffee ha (kg, all-crop N) | Q4: Coffee bags per t of N
A5: 2005 | B5: 41865 | D5: 14829 | F5: 6958 | H5: E | I5: 35952.04 | K5: 278.11857 | L5: 217.35833 | N5: =L5*YoY!AF6 -> 4093.5362 | P5: =B5/YoY!B6 -> 227.52717 | Q5: =YoY!H6*1000/B5 -> 76.531709
A6: 2006 | B6: 66688 | C6: =B6/B5-1 -> 0.59292965 | D6: 20783 | E6: =D6/D5-1 -> 0.40151055 | F6: 15891 | G6: =F6/F5-1 -> 1.2838459 | H6: E | I6: 85809.62 | J6: =I6/I5-1 -> 1.3867803 | K6: 280.35097 | L6: 222.14167 | M6: =L6/L5-1 -> 0.022006671 | N6: =L6*YoY!AF7 -> 4197.4125 | O6: =N6/N5-1 -> 0.025375669 | P6: =B6/YoY!B7 -> 289.94783 | Q6: =YoY!H7*1000/B6 -> 51.883397
A7: 2007 | B7: 63491 | C7: =B7/B6-1 -> -0.047939659 | D7: 21414 | E7: =D7/D6-1 -> 0.030361353 | F7: 9776 | G7: =F7/F6-1 -> -0.38480901 | H7: E | I7: 79076.84 | J7: =I7/I6-1 -> -0.078461832 | K7: 350.12173 | L7: 307.11667 | M7: =L7/L6-1 -> 0.38252617 | N7: =L7*YoY!AF8 -> 5803.0006 | O7: =N7/N6-1 -> 0.38251856 | P7: =B7/YoY!B8 -> 276.04783 | Q7: =YoY!H8*1000/B7 -> 57.362461
A8: 2008 | B8: 55554 | C8: =B8/B7-1 -> -0.12500984 | D8: 16565 | E8: =D8/D7-1 -> -0.22644065 | F8: 6892 | G8: =F8/F7-1 -> -0.29500818 | H8: I | L8: 514.98333 | M8: =L8/L7-1 -> 0.67683291 | N8: =L8*YoY!AF9 -> 9732.1326 | O8: =N8/N7-1 -> 0.67708626 | P8: =B8/YoY!B9 -> 248.00893 | Q8: =YoY!H9*1000/B8 -> 58.051625
A9: 2009 | B9: 47616 | C9: =B9/B8-1 -> -0.142888 | D9: 11716 | E9: =D9/D8-1 -> -0.29272563 | F9: 4008 | G9: =F9/F8-1 -> -0.41845618 | H9: E | I9: 60810.87 | K9: 306.96272 | L9: 251.1 | M9: =L9/L8-1 -> -0.5124114 | N9: =L9*YoY!AF10 -> 4744.5596 | O9: =N9/N8-1 -> -0.51248511 | P9: =B9/YoY!B10 -> 212.57143 | Q9: =YoY!H10*1000/B9 -> 74.554772
A10: 2010 | B10: 56041 | C10: =B10/B9-1 -> 0.17693632 | D10: 15327 | E10: =D10/D9-1 -> 0.30821099 | F10: 15828 | G10: =F10/F9-1 -> 2.9491018 | H10: E | I10: 82828.86 | J10: =I10/I9-1 -> 0.36207326 | K10: 327.73879 | L10: 288.91667 | M10: =L10/L9-1 -> 0.15060401 | N10: =L10*YoY!AF11 -> 5459.0767 | O10: =N10/N9-1 -> 0.15059713 | P10: =B10/YoY!B11 -> 235.46639 | Q10: =YoY!H11*1000/B10 -> 70.930212
A11: 2011 | B11: 85542 | C11: =B11/B10-1 -> 0.52641816 | D11: 23195 | E11: =D11/D10-1 -> 0.51334247 | F11: 25119 | G11: =F11/F10-1 -> 0.58699773 | H11: E | I11: 128026.7 | J11: =I11/I10-1 -> 0.54567744 | K11: 418.44303 | L11: 398.94167 | M11: =L11/L10-1 -> 0.38081915 | N11: =L11*YoY!AF12 -> 7546.3322 | O11: =N11/N10-1 -> 0.38234589 | P11: =B11/YoY!B12 -> 349.15102 | Q11: =YoY!H12*1000/B11 -> 65.464918
A12: 2012 | B12: 75417 | C12: =B12/B11-1 -> -0.11836291 | D12: 18301 | E12: =D12/D11-1 -> -0.21099375 | F12: 16134 | G12: =F12/F11-1 -> -0.35769736 | H12: E | I12: 126987.33 | J12: =I12/I11-1 -> -0.0081183847 | K12: 462.85594 | L12: 398.6 | M12: =L12/L11-1 -> -0.00085643264 | N12: =L12*YoY!AF13 -> 7774.3162 | O12: =N12/N11-1 -> 0.030211231 | P12: =B12/YoY!B13 -> 282.46067 | Q12: =YoY!H13*1000/B12 -> 62.651657
A13: 2013 | B13: 74712 | C13: =B13/B12-1 -> -0.009348025 | D13: 21794 | E13: =D13/D12-1 -> 0.19086389 | F13: 29688 | G13: =F13/F12-1 -> 0.84008925 | H13: I | L13: 339.60833 | M13: =L13/L12-1 -> -0.14799716 | N13: =L13*YoY!AF14 -> 6913.249 | O13: =N13/N12-1 -> -0.11075794 | P13: =B13/YoY!B14 -> 350.76056 | Q13: =YoY!H14*1000/B13 -> 58.892815
A14: 2014 | B14: 74007 | C14: =B14/B13-1 -> -0.0094362351 | D14: 25287 | E14: =D14/D13-1 -> 0.16027347 | F14: 43243 | G14: =F14/F13-1 -> 0.45658178 | H14: E | I14: 103967.9 | K14: 366.54333 | L14: 308.44167 | M14: =L14/L13-1 -> -0.091772385 | N14: =L14*YoY!AF15 -> 6473.7649 | O14: =N14/N13-1 -> -0.063571275 | P14: =B14/YoY!B15 -> 326.02203 | Q14: =YoY!H15*1000/B14 -> 68.9124
A15: 2015 | B15: 75343 | C15: =B15/B14-1 -> 0.018052346 | D15: 33145 | E15: =D15/D14-1 -> 0.31075256 | F15: 25793 | G15: =F15/F14-1 -> -0.40353352 | H15: E | I15: 111558.82 | J15: =I15/I14-1 -> 0.073012151 | K15: 324.5954 | L15: 277.94167 | M15: =L15/L14-1 -> -0.098884176 | N15: =L15*YoY!AF16 -> 6099.9141 | O15: =N15/N14-1 -> -0.057748589 | P15: =B15/YoY!B16 -> 313.92917 | Q15: =YoY!H16*1000/B15 -> 70.344956
A16: 2016 | B16: 95944 | C16: =B16/B15-1 -> 0.27342952 | D16: 34653 | E16: =D16/D15-1 -> 0.045497058 | F16: 36674 | G16: =F16/F15-1 -> 0.42185864 | H16: E | I16: 143032.93 | J16: =I16/I15-1 -> 0.28213018 | K16: 238.62071 | L16: 194.15 | M16: =L16/L15-1 -> -0.30147213 | N16: =L16*YoY!AF17 -> 4434.1043 | O16: =N16/N15-1 -> -0.27308742 | P16: =B16/YoY!B17 -> 342.65714 | Q16: =YoY!H17*1000/B16 -> 78.274827
A17: 2017 | B17: 110175 | C17: =B17/B16-1 -> 0.14832611 | D17: 34591 | E17: =D17/D16-1 -> -0.0017891669 | F17: 43065 | G17: =F17/F16-1 -> 0.17426515 | H17: E | I17: 157715.35 | J17: =I17/I16-1 -> 0.10265063 | K17: 258.66296 | L17: 213.88333 | M17: =L17/L16-1 -> 0.10163963 | N17: =L17*YoY!AF18 -> 5023.4204 | O17: =N17/N16-1 -> 0.13290533 | P17: =B17/YoY!B18 -> 369.71477 | Q17: =YoY!H18*1000/B17 -> 68.981166
A18: 2018 | B18: 122752 | C18: =B18/B17-1 -> 0.11415475 | D18: 39277 | E18: =D18/D17-1 -> 0.13546876 | F18: 47080 | G18: =F18/F17-1 -> 0.093231162 | H18: E | I18: 178390.81 | J18: =I18/I17-1 -> 0.13109352 | K18: 293.32604 | L18: 249.45 | M18: =L18/L17-1 -> 0.16629003 | N18: =L18*YoY!AF19 -> 5962.1335 | O18: =N18/N17-1 -> 0.18686731 | P18: =B18/YoY!B19 -> 429.2028 | Q18: =YoY!H19*1000/B18 -> 57.840198
A19: 2019 | B19: 86136 | C19: =B19/B18-1 -> -0.29829249 | D19: 31343 | E19: =D19/D18-1 -> -0.20200117 | F19: 42804 | G19: =F19/F18-1 -> -0.090824129 | H19: E | I19: 134078.54 | J19: =I19/I18-1 -> -0.24839996 | K19: 288.57511 | L19: 245.28333 | M19: =L19/L18-1 -> -0.016703414 | N19: =L19*YoY!AF20 -> 6011.3133 | O19: =N19/N18-1 -> 0.0082486857 | P19: =B19/YoY!B20 -> 319.02222 | Q19: =YoY!H20*1000/B19 -> 60.369648
A20: 2020 | B20: 128016 | C20: =B20/B19-1 -> 0.48620786 | D20: 44680 | E20: =D20/D19-1 -> 0.42551766 | F20: 69967 | G20: =F20/F19-1 -> 0.63459023 | H20: E | I20: 190619.62 | J20: =I20/I19-1 -> 0.42170119 | K20: 265.9348 | L20: 229.1 | M20: =L20/L19-1 -> -0.065978121 | N20: =L20*YoY!AF21 -> 5631.8037 | O20: =N20/N19-1 -> -0.063132557 | P20: =B20/YoY!B21 -> 468.92308 | Q20: =YoY!H21*1000/B20 -> 50.774903
A21: 2021 | B21: 104868 | C21: =B21/B20-1 -> -0.18082115 | D21: 33278 | E21: =D21/D20-1 -> -0.25519248 | F21: 56411 | G21: =F21/F20-1 -> -0.19374848 | H21: E | I21: 173224.31 | J21: =I21/I20-1 -> -0.091256661 | K21: 406.13757 | L21: 483.21667 | M21: =L21/L20-1 -> 1.1091954 | N21: =L21*YoY!AF22 -> 11604.575 | O21: =N21/N20-1 -> 1.0605432 | P21: =B21/YoY!B22 -> 381.33818 | Q21: =YoY!H22*1000/B21 -> 45.771827
A22: 2022 | B22: 104865 | C22: =B22/B21-1 -> -2.8607392e-05 | D22: 33274 | E22: =D22/D21-1 -> -0.00012019953 | F22: 56407 | G22: =F22/F21-1 -> -7.0908156e-05 | H22: I | L22: 700.03333 | M22: =L22/L21-1 -> 0.44869451 | N22: =L22*YoY!AF23 -> 17141.62 | O22: =N22/N21-1 -> 0.47714331 | P22: =B22/YoY!B23 -> 367.94737 | Q22: =YoY!H23*1000/B22 -> 54.3556
A23: 2023 | B23: 104427 | C23: =B23/B22-1 -> -0.0041767987 | D23: 35527 | E23: =D23/D22-1 -> 0.067710525 | F23: 51399 | G23: =F23/F22-1 -> -0.088783307 | H23: E | I23: 166700.89 | K23: 395.67575 | L23: 358.00833 | M23: =L23/L22-1 -> -0.48858388 | N23: =L23*YoY!AF24 -> 8807.5711 | O23: =N23/N22-1 -> -0.48618793 | P23: =B23/YoY!B24 -> 357.62671 | Q23: =YoY!H24*1000/B23 -> 48.359141
A24: 2024 | B24: 106830 | C24: =B24/B23-1 -> 0.02301129 | D24: 38420 | E24: =D24/D23-1 -> 0.081431024 | F24: 56337 | G24: =F24/F23-1 -> 0.096071908 | H24: E | I24: 179565.06 | J24: =I24/I23-1 -> 0.077169174 | K24: 365.22378 | L24: 338.28333 | M24: =L24/L23-1 -> -0.055096483 | N24: =L24*YoY!AF25 -> 8387.7329 | O24: =N24/N23-1 -> -0.047667868 | P24: =B24/YoY!B25 -> 356.1 | Q24: =YoY!H25*1000/B24 -> 48.675466
A25: 2025 | L25: 422.65833 | M25: =L25/L24-1 -> 0.2494211 | N25: =L25*YoY!AF26 -> 10969.977 | O25: =N25/N24-1 -> 0.30785956
A26: 2026 | L26: 560.4375 | M26: =L26/L25-1 -> 0.32598237 | N26: =L26*YoY!AF27 -> 14930.065 | O26: =N26/N25-1 -> 0.36099329
A29: Bono Cafetalero (fertiliser given by the state) | B29: Fertiliser (qq of 46 kg) | C29: Fertiliser (t) | D29: Producers | E29: Lempiras (M) | F29: US$ (M) | G29: Status | H29: Source
A30: 2020 | B30: =C30*1000/46 -> 547565.22 | C30: 25188 | D30: 91778 | F30: 12 | G30: ✔ USDA report (read) | H30: GAIN 2021
A31: 2021 | D31: 91500 | F31: 12.5 | G31: ✔ USDA report (read) | H31: GAIN 2021 (extension to Dec 2021)
A32: 2022 | B32: 216223 | C32: =B32*46/1000 -> 9946.258 | D32: 83273 | E32: 250 | G32: ✔ document read | H32: La Prensa 27 Jul 2022 (read): 2-5 qq per grower, formula 17-3-17
A33: 2023 | B33: 253032 | C33: =B33*46/1000 -> 11639.472 | D33: 95000 | G33: ⚠ web extract, not read | H33: Gobierno Solidario (search summary)
A34: 2024 | B34: 186000 | C34: =B34*46/1000 -> 8556 | G34: ⚠ web extract, not read | H34: TNH (search summary: "mas de 186 mil sacos")
A35: 2025 | B35: 300000 | C35: =B35*46/1000 -> 13800 | G35: ✔ document read | H35: El Heraldo 14 Feb 2026 (read): "pasando de 300 mil quintales a cerca de 400 mil"
A36: 2026 | B36: 400000 | C36: =B36*46/1000 -> 18400 | D36: 85600 | G36: ✔ document read | H36: El Heraldo 14 Feb 2026 (read): plan "cerca de 400 mil quintales", > 85 600 producers
A39: Reading: national nitrogen use in 2021-24 (about 105 000 t) is below the 2018 and 2020 peaks (123 000 and 128 000 t) but above 2016 (96 000 t), the year before the record crop. Per bearing coffee hectare it is 5 % below 2016-18. The fall in yield since 2019 is therefore not a fall in national fertiliser use; the big one-year cuts (2019: -30 %) do line up with output.
A40: What did change is the price in lempiras: urea cost L 4 400/t in 2016 and L 17 100/t in 2022 (4 times more), L 8 400/t in 2024 and about L 14 900/t in Jan-Aug 2026. Coffee bought 18.6 kg of urea per kg in 2016, 8.0 in 2022, 13.2 in 2026.
A41: The Bono Cafetalero gives 2-5 qq per small or medium grower: 25 188 t in 2020, 216 223 qq in 2022, 300 000 qq in 2025, about 400 000 qq planned for 2026. 300 000 qq = 13 800 t of product, about 8 % of national urea imports by weight (it is not all urea).

Sheet Disease
A1: Rust (roya) and other problems, every figure found
A2: There is no published yearly series in the files we could reach: IHCAFE early-warning bulletins (monthly, about 1 200 farms) are behind the blocked ihcafe.hn host. Figures below are those printed by USDA or the press.
A4: Year | B4: When | C4: Value (%) | D4: What it measures | E4: Status | F4: Source
A5: 2012 | B5: 2012/13 crop | C5: 25 | D5: % of coffee AREA affected (71 000 ha) | E5: ✔ USDA report (read) | F5: GAIN 2013, 2014
A6: 2014 | B6: Apr 2014 | C6: 12 | D6: national average incidence (first national survey) | E6: ✔ USDA report (read) | F6: GAIN 2014
A7: 2017 | B7: Apr 2017 | C7: 3 | D7: % of LEMPIRA plants with rust (Lempira lost its resistance in 2016/17) | E7: ✔ USDA report (read) | F7: GAIN 2017, 2018
A8: 2020 | B8: end 2020 | C8: 20 | D8: incidence in 5 departments after hurricanes Eta and Iota | E8: ✔ USDA report (read) | F8: GAIN 2021
A9: 2020 | B9: Nov 2020 | D9: Eta and Iota: > 4 200 ha of coffee farms hit, > 150 000 qq lost | E9: ✔ document read | F9: La Prensa / EFE 1 Nov 2022 (read)
A10: 2022 | B10: 2022/23 crop | C10: 20 | D10: % of PRODUCTION affected by rust (IHCAFE director) | E10: ✔ document read | F10: La Prensa / EFE 1 Nov 2022 (read)
A11: 2022 | B11: Apr 2022 | C11: 5.42 | D11: national average incidence (66 % of farms low, 29 % medium, 5 % high) | E11: ✔ USDA report (read) | F11: GAIN 2022
A12: 2023 | B12: May 2023 | C12: 5.8 | D12: national average incidence (La Paz 9.7 %, Fco. Morazan 8.2 %) | E12: ✔ USDA report (read) | F12: GAIN 2023 (repeated in GAIN 2024)
A13: 2024 | B13: Mar 2024 | C13: 7.38 | D13: national average incidence | E13: ⚠ web extract, not read | F13: web search summary (La Prensa / El Heraldo)
A14: 2024 | B14: Apr 2024 | D14: 76 % of sampled farms low, 19 % medium, 5 % high | E14: ✔ USDA report (read) | F14: GAIN 2025
A15: 2024 | B15: 2024 | D15: BCH: exports about 500 000 qq lower than 2023 "due to high rust incidence and labour shortage" | E15: ✔ document read | F15: El Heraldo 23 Jun 2024 (read)
A16: 2025 | B16: Jan-Mar 2025 | C16: 5.71 | D16: national average (13 of 15 departments hit; Santa Barbara 9.29 %, El Paraiso 7.91 %, Comayagua 7.20 %; worst varieties Obata and Catuai) | E16: ✔ document read | F16: El Heraldo 13 May 2025 (read)
A17: 2025 | B17: Apr 2025 | D17: sampled farms: 16.7 % medium (5-10 %), 7.8 % high (10-15 %), 21.6 % very high (> 15 %) | E17: ✔ USDA report (read) | F17: GAIN 2026
A18: 2026 | B18: end Jan 2026 | C18: 8.44 | D18: national average incidence (from 7.57 %); departments 2.06-14.08 %; ~30 % of farms > 10 % | E18: ✔ document read | F18: El Heraldo 15 Feb 2026 (read); GAIN 2026
A20: IHCAFE rule of thumb
A21: IHCAFE rule of thumb: rust damage of 15 % means about 20 % less production (GAIN 2017: "if the damage from rust reaches 15 percent, there could be a 20 percent reduction in production").
A22: IHCAFE thresholds: 0-5 % low, 5-20 % medium (USDA 2022-2025).
A24: Crop year | B24: What USDA wrote that year (drought, disease, fertiliser, labour)
A25: 2015/16 | B25: El Nino drought: "Producers did not apply fertilizer due to the drought" (GAIN 2016).
A26: 2016/17 | B26: First crop from plantings renewed after the 2012-14 rust (GAIN 2016).
A27: 2017/18 | B27: Drought forecast; "Small farmers lack the resources to apply fertilizers" (GAIN 2017). Lempira hit by rust in 2016/17 (GAIN 2018).
A28: 2019/20 | B28: Price 2.88 $/kg, lowest since 2007.
A29: 2020/21 | B29: Bono Cafetalero: 25 188 t of fertiliser to 91 778 producers (GAIN 2021); hurricanes Eta and Iota in November.
A30: 2021/22 | B30: "cyclical decline in productivity after a widespread re-planting effort ten years ago" and rust (GAIN 2022); fertiliser prices up (Russia) (GAIN 2022).
A31: 2022/23 | B31: Less rust and "coffee drill bit" (berry borer) expected; high fertiliser costs (GAIN 2023).
A32: 2023/24 | B32: "high incidence of coffee rust and ongoing labor shortage" (GAIN 2024).
A33: 2024/25 | B33: Less rust, better labour availability, prices +81 % (GAIN 2025).
A34: 2025/26 | B34: Parainema plantings harvested; rust up to 8.44 % by Jan 2026; fertiliser supply risk (Persian Gulf) (GAIN 2026).

Sheet Varieties
A1: Rust-resistant varieties: releases and share planted
A3: Variety | B3: Released | C3: Type | D3: Status now | E3: Source
A4: IHCAFE 90 | B4: 1990 | D4: Resistant 1990–2015; from 2016 about 20 % of plants susceptible to the new rust races (IHCAFE, 2019); 80 % resistance to the new strain (IHCAFE via La Prensa, 24 Aug 2017). USDA 2018: still resistant. World Coffee Research: "recently confirmed susceptible in Honduras" | E4: Morales & Grajeda (IHCAFE), PROMECAFE 24th symposium 2019, table "Durabilidad de resistencia"; GAIN 2018; WCR variety page
A5: Lempira | B5: 1998 | D5: Resistant 1998–2001; tolerant 2002–2015 (rust already on 100 % of plants, low severity, in seed plots in July 2007); susceptible in 2016 (Olancho, full defoliation), spread over the whole country 2017–2019. USDA: IHCAFE confirmed the loss in April 2017 | E5: Morales & Grajeda (IHCAFE), PROMECAFE 2019; GAIN 2017; WCR variety page
A6: Parainema | B6: 2004 | D6: Resistant 2004–2019 in IHCAFE tests (fully resistant to the new races); USDA 2018, 2020, 2021: still resistant. Nothing later found | E6: Morales & Grajeda (IHCAFE), PROMECAFE 2019; WCR ("released in 2004"); GAIN 2018, 2020, 2021, 2025
A7: Ihcatú 75, Anacafé 14 SHN, Obatá SHN | B7: 2024 | D7: Presented as more rust resistant and productive; seed for at least 1 500 manzanas in 2024. Caution: IHCAFE's 2019 study listed the Icatu 75 line as susceptible since 2016 and Obatá as 20 % susceptible | E7: El Heraldo, 29 Feb 2024 (read); La Prensa, 29 Sep 2023 (read: "at least 4" to be released in 2024; last release Parainema 2004); PROMECAFE 2019
A9: When | B9: Scope | C9: Resistant share (%) | D9: Status | E9: Source | F9: Quote
A10: Jun 2013 | B10: national, % of coffee AREA | C10: 50 | D10: ✔ USDA report (read) | E10: GAIN 2013 | F10: IHCAFE reports that 50 percent of the total area of coffee production is planted with rust susceptible varieties.
A11: since 2012 | B11: cultivated area, dominated by Lempira | C11: 65 | D11: ✔ document read | E11: Morales & Grajeda (IHCAFE), PROMECAFE 2019 (read) | F11: Estos materiales resistentes reemplazaron los susceptibles y constituyen el 65% del área cultivada desde 2012 dominada por Lempira.
A12: Apr 2014 | B12: national, % of PRODUCERS | C12: 60 | D12: ✔ USDA report (read) | E12: GAIN 2014 | F12: the number of coffee producers, growing coffee rust resistant varieties, is moving up to 60 percent and 40 percent of them are still using non-resistant types.
A13: 2014 | B13: 5 departments (60 % of area), % of FARMS | C13: 62 | D13: ✔ USDA report (read) | E13: GAIN 2014 (USDA/TechnoServe baseline) | F13: 62 percent of the coffee farms had resistant varieties to coffee leaf rust and 38 percent had varieties susceptible
A14: 24 Aug 2017 | B14: national coffee park (plants) | C14: 60 | D14: ✔ document read | E14: La Prensa, 24 Aug 2017 (read, ihcafe_docs3) | F14: En la actualidad, el 60% del parque cafetalero nacional está conformado por plantas mejoradas y resistentes a la roya y otras enfermedades.
A15: Oct 2017 | B15: farms sampled by the rust early-warning system | C15: 17.2 | D15: ⚠ web extract, not read | E15: IHCAFE SAT bulletin No 8 (search snippet) | F15: Lempira = 56.08 % of sampled farms, 67.74 % of farms classed as susceptible
A16: ~2020 | B16: national, % of cultivation | C16: 60 | D16: ⚠ web extract, not read | E16: Perfect Daily Grind, Mar 2020 (search extract) | F16: about 60 % of Honduran coffee is planted with resistant varieties (Lempira, IHCAFE 90, Parainema)
A18: Reading: about half the area was resistant in 2013 and about 60-65 % from 2014-2017 on; no later national figure was found. Lempira, the main resistant variety, lost its resistance in 2016/17, so part of that 60 % became susceptible again. Parainema (2004) plantings are now being harvested (USDA 2025, 2026). Three more (Ihcatu 75, Anacafe 14, Obata) were released in 2024.
A19: Not found: yield by variety, and any share after 2020.

Sheet Finance
A1: Financing: state, IHCAFE and banks, by year
A2: No yearly series of bank credit to coffee could be reached (BCH credit by activity is not in the files). The programmes and amounts below are those read in USDA reports, decrees and the press.
A4: Year | B4: Programme | C4: US$ M | D4: Lempiras M | E4: Who | F4: Terms | G4: Status | H4: Source
A5: 2002 | B5: Government loan to all growers (coffee crisis) | C5: 20 | E5: all producers | F5: 20 years | G5: ✔ USDA report (read) | H5: GAIN 2011
A6: 2004 | B6: Coffee trust fund (Law of Financial Reactivation, 2003) | E6: 87,000 producers take part (2011) | F6: US$13.25/qq deducted at sale: US$9 trust fund (returned if no debt), US$1 for 1999–2001 loans, US$3.25 (US$0.50 to the 2002 loan; rest 36 % IHCAFE, 64 % National Coffee Fund) | G6: ✔ USDA report (read) | H6: GAIN 2011, GAIN 2015
A7: 2013 | B7: Rust credit made available (banks, BCH, BANHPROVI, BANADESA, IHCAFE) | C7: =D7/YoY!AF14 -> 84.248129 | D7: 1715 | E7: L335 M actually used by April 2014; BANADESA loans up to L25,000, banks up to L150,000 | F7: 10 % interest, 7 years; to be repaid by 2019 (USDA) | G7: ✔ document read | H7: El Heraldo, 7 Apr 2014 (read); GAIN 2017 for the 2019 repayment date
A8: 2015 | B8: IHCAFE fertiliser credit line | C8: 17 | D8: 370 | E8: coffee producers | F8: fertiliser at cost, 1 year, interest-free | G8: ✔ USDA report (read) | H8: GAIN 2015
A9: 2015 | B9: PAPP (IHCAFE + National Coffee Fund) and PEPP (BANADESA) | E9: about 23,000 small producers | F9: replant 1 manzana (0.7 ha), no interest; aim 5 → 45 qq per manzana | G9: ✔ USDA report (read) | H9: GAIN 2015–2017
A10: 2018 | B10: Decreto 93-2018: IHCAFE loan to growers (low prices, rust) | C10: 77 | D10: 1900 | E10: all growers who ask | F10: L200 per quintal oro produced in 2016/17 (≈ 8,4 $, not the "25 $" in USDA 2020); up to L1 900 M; repaid by 1,50 $ per qq retained at export | G10: ✔ document read | H10: El Heraldo, 29 Aug 2018 (read); GAIN 2020 (about 77 M$, 5 Sep 2018)
A11: 2018 | B11: Fondo para el Sector Cafetero (BANHPROVI) | C11: =D11/YoY!AF19 -> 12.551715 | D11: 300 | E11: backs refinancing and debt readjustment of growers | F11: L300 M in three instalments | G11: ✔ document read | H11: El Heraldo, 29 Aug 2018 (read)
A12: 2020 | B12: Bono Cafetalero (PCM 030-2020): free fertiliser | C12: 12 | E12: 91,778 small and medium producers (87 %) | F12: 25,188 t of fertiliser, producers up to 6.8 t | G12: ✔ USDA report (read) | H12: GAIN 2021
A13: 2021 | B13: Bono Cafetalero extension (PCM 031-2021) | C13: 12.5 | E13: over 91,500 producers | F13: fertiliser; plus state credit at 5 % and guarantees | G13: ✔ USDA report (read) | H13: GAIN 2021
A14: 2023 | B14: IHCAFE renovation programme 2023–2027 | E14: 33,000 producers, 250,000 manzanas (63 % of the coffee park) | F14: target 7.0–7.5 million 46-kg bags | G14: ✔ USDA report (read) | H14: GAIN 2024
A15: 2025 | B15: Bono Cafetalero 2025 | C15: =D15/YoY!AF26 -> 13.485026 | D15: 350 | E15: 119,803 producers | F15: 300,000 qq of fertiliser | G15: ⚠ web extract, not read | H15: TNH (search snippet)
A17: 2021 | B17: Debt of growers to banks, cooperatives and IHCAFE | C17: =D17/YoY!AF22 -> 231.72765 | D17: 5565 | G17: ⚠ web extract, not read | H17: La Tribuna, 25 Jun 2021 (search snippet)
A20: Bank credit to agriculture (BCH, all farming: coffee is not separated), millions of lempiras
A21: Year | B21: Loans outstanding, December | C21: change | D21: New loans in the year | E21: change | F21: Share of all new loans | G21: Loans outstanding in US$ M | H21: Source
A22: 2017 | B22: 20610.3 | D22: 10924.8 | F22: 0.0467803 | G22: =B22/YoY!AF18 -> 877.52951 | H22: BCH, Prestamos de las Otras Sociedades de Depositos por Actividad (xlsx read, raw/ihcafe_docs5)
A23: 2018 | B23: 24314.8 | C23: =B23/B22-1 -> 0.17974023 | D23: 16237 | E23: =D23/D22-1 -> 0.48625146 | F23: 0.061453298 | G23: =B23/YoY!AF19 -> 1017.3081 | H23: BCH, Prestamos de las Otras Sociedades de Depositos por Actividad (xlsx read, raw/ihcafe_docs5)
A24: 2019 | B24: 25923.5 | C24: =B24/B23-1 -> 0.06616135 | D24: 15389.3 | E24: =D24/D23-1 -> -0.05220792 | F24: 0.057438278 | G24: =B24/YoY!AF20 -> 1057.7726 | H24: BCH, Prestamos de las Otras Sociedades de Depositos por Actividad (xlsx read, raw/ihcafe_docs5)
A25: 2020 | B25: 23787.4 | C25: =B25/B24-1 -> -0.082400139 | D25: 14129.4 | E25: =D25/D24-1 -> -0.081868571 | F25: 0.05046344 | G25: =B25/YoY!AF21 -> 967.66394 | H25: BCH, Prestamos de las Otras Sociedades de Depositos por Actividad (xlsx read, raw/ihcafe_docs5)
A26: 2021 | B26: 25569.7 | C26: =B26/B25-1 -> 0.074926221 | D26: 14373.7 | E26: =D26/D25-1 -> 0.017290189 | F26: 0.04722364 | G26: =B26/YoY!AF22 -> 1064.7271 | H26: BCH, Prestamos de las Otras Sociedades de Depositos por Actividad (xlsx read, raw/ihcafe_docs5)
A27: 2022 | B27: 27310.5 | C27: =B27/B26-1 -> 0.06808058 | D27: 15012.9 | E27: =D27/D26-1 -> 0.044470109 | F27: 0.039778776 | G27: =B27/YoY!AF23 -> 1115.3124 | H27: BCH, Prestamos de las Otras Sociedades de Depositos por Actividad (xlsx read, raw/ihcafe_docs5)
A28: 2023 | B28: 27976.066 | C28: =B28/B27-1 -> 0.024370325 | D28: 15346.5 | E28: =D28/D27-1 -> 0.02222089 | F28: 0.035556751 | G28: =B28/YoY!AF24 -> 1137.1654 | H28: BCH, Prestamos de las Otras Sociedades de Depositos por Actividad (xlsx read, raw/ihcafe_docs5)
A29: 2024 | B29: 30700.613 | C29: =B29/B28-1 -> 0.097388518 | D29: 17038.596 | E29: =D29/D28-1 -> 0.11025939 | F29: 0.034048481 | G29: =B29/YoY!AF25 -> 1238.1779 | H29: BCH, Prestamos de las Otras Sociedades de Depositos por Actividad (xlsx read, raw/ihcafe_docs5)
A30: 2025 | B30: 31109.75 | C30: =B30/B29-1 -> 0.013326658 | D30: 19080.135 | E30: =D30/D29-1 -> 0.1198185 | F30: 0.035541606 | G30: =B30/YoY!AF26 -> 1198.6165 | H30: BCH, Prestamos de las Otras Sociedades de Depositos por Actividad (xlsx read, raw/ihcafe_docs5)
A31: 2026 Jan-Jul | B31: 32548.22 | C31: =B31/B32-1 -> 0.10396745 | D31: 19250.338 | E31: =D31/D32-1 -> 0.83616856
A32: 2025 Jan-Jul | B32: 29482.952 | D32: 10483.971
A34: Reading: credit to agriculture grew slower than total credit (its share of new loans fell from 6.1 % in 2018 to 3.4 % in 2024) and fell in 2020 (-8 %). It picked up in 2024-2025 (+11 %, +12 % new loans) and jumped in 2026: new loans Jan-Jul +84 % on Jan-Jul 2025, with average lending rates down 3.8 points (BCH communique, June 2026). Coffee is not separated in BCH data.

Sheet FX
A1: Lempira against the dollar, and what it did to coffee and urea prices in lempiras
A2: BCH reference rate (buying), mean of the daily values; 2026 = 1 Jan - 25 Sep. Coffee = World Bank arabica (other milds, ex-dock) x 46 kg x rate: a world price in lempiras, not the farm-gate price.
A4: Year | B4: L per US$ | C4: change | D4: Arabica (US$/kg) | E4: change | F4: Arabica (L per qq) | G4: change | H4: Urea (US$/t) | I4: Urea (L per t) | J4: change | K4: FAOSTAT farm-gate (L per t, official only) | L4: change
A5: 2005 | B5: =YoY!AF6 -> 18.833123 | D5: =YoY!Z6 -> 2.5325 | F5: =D5*46*B5 -> 2193.9647 | H5: =YoY!V6 -> 217.35833 | I5: =H5*B5 -> 4093.5362 | K5: 33000
A6: 2006 | B6: =YoY!AF7 -> 18.895206 | C6: =B6/B5-1 -> 0.0032964544 | D6: =YoY!Z7 -> 2.5216667 | E6: =D6/D5-1 -> -0.0042777229 | F6: =D6*46*B6 -> 2191.7809 | G6: =F6/F5-1 -> -0.00099536988 | H6: =YoY!V7 -> 222.14167 | I6: =H6*B6 -> 4197.4125 | J6: =I6/I5-1 -> 0.025375669 | K6: 39600 | L6: =K6/K5-1 -> 0.2
A7: 2007 | B7: =YoY!AF8 -> 18.895102 | C7: =B7/B6-1 -> -5.502861e-06 | D7: =YoY!Z8 -> 2.7241667 | E7: =D7/D6-1 -> 0.080304032 | F7: =D7*46*B7 -> 2367.7767 | G7: =F7/F6-1 -> 0.080298087 | H7: =YoY!V8 -> 307.11667 | I7: =H7*B7 -> 5803.0006 | J7: =I7/I6-1 -> 0.38251856 | K7: 44000 | L7: =K7/K6-1 -> 0.11111111
A8: 2008 | B8: =YoY!AF9 -> 18.897956 | C8: =B8/B7-1 -> 0.00015109051 | D8: =YoY!Z9 -> 3.0808333 | E8: =D8/D7-1 -> 0.13092689 | F8: =D8*46*B8 -> 2678.1869 | G8: =F8/F7-1 -> 0.13109776 | H8: =YoY!V9 -> 514.98333 | I8: =H8*B8 -> 9732.1326 | J8: =I8/I7-1 -> 0.67708626 | K8: 44950 | L8: =K8/K7-1 -> 0.021590909
A9: 2009 | B9: =YoY!AF10 -> 18.8951 | C9: =B9/B8-1 -> -0.00015115235 | D9: =YoY!Z10 -> 3.1708333 | E9: =D9/D8-1 -> 0.029212875 | F9: =D9*46*B9 -> 2756.0078 | G9: =F9/F8-1 -> 0.029057307 | H9: =YoY!V10 -> 251.1 | I9: =H9*B9 -> 4744.5596 | J9: =I9/I8-1 -> -0.51248511
A10: 2010 | B10: =YoY!AF11 -> 18.894987 | C10: =B10/B9-1 -> -5.9772733e-06 | D10: =YoY!Z11 -> 4.32 | E10: =D10/D9-1 -> 0.36241787 | F10: =D10*46*B10 -> 3754.8118 | G10: =F10/F9-1 -> 0.36240973 | H10: =YoY!V11 -> 288.91667 | I10: =H10*B10 -> 5459.0767 | J10: =I10/I9-1 -> 0.15059713
A11: 2011 | B11: =YoY!AF12 -> 18.915879 | C11: =B11/B10-1 -> 0.0011056764 | D11: =YoY!Z12 -> 5.9766667 | E11: =D11/D10-1 -> 0.38348765 | F11: =D11*46*B11 -> 5200.4795 | G11: =F11/F10-1 -> 0.38501734 | H11: =YoY!V12 -> 398.94167 | I11: =H11*B11 -> 7546.3322 | J11: =I11/I10-1 -> 0.38234589
A12: 2012 | B12: =YoY!AF13 -> 19.504055 | C12: =B12/B11-1 -> 0.031094294 | D12: =YoY!Z13 -> 4.1116667 | E12: =D12/D11-1 -> -0.31204685 | F12: =D12*46*B12 -> 3688.9319 | G12: =F12/F11-1 -> -0.29065543 | H12: =YoY!V13 -> 398.6 | I12: =H12*B12 -> 7774.3162 | J12: =I12/I11-1 -> 0.030211231
A13: 2013 | B13: =YoY!AF14 -> 20.356535 | C13: =B13/B12-1 -> 0.04370786 | D13: =YoY!Z14 -> 3.0766667 | E13: =D13/D12-1 -> -0.25172274 | F13: =D13*46*B13 -> 2880.9926 | G13: =F13/F12-1 -> -0.21901714 | H13: =YoY!V14 -> 339.60833 | I13: =H13*B13 -> 6913.249 | J13: =I13/I12-1 -> -0.11075794
A14: 2014 | B14: =YoY!AF15 -> 20.98862 | C14: =B14/B13-1 -> 0.031050708 | D14: =YoY!Z15 -> 4.425 | E14: =D14/D13-1 -> 0.43824485 | F14: =D14*46*B14 -> 4272.2336 | G14: =F14/F13-1 -> 0.48290337 | H14: =YoY!V15 -> 308.44167 | I14: =H14*B14 -> 6473.7649 | J14: =I14/I13-1 -> -0.063571275
A15: 2015 | B15: =YoY!AF16 -> 21.946742 | C15: =B15/B14-1 -> 0.045649611 | D15: =YoY!Z16 -> 3.5258333 | E15: =D15/D14-1 -> -0.20320151 | F15: =D15*46*B15 -> 3559.5056 | G15: =F15/F14-1 -> -0.16682797 | H15: =YoY!V16 -> 277.94167 | I15: =H15*B15 -> 6099.9141 | J15: =I15/I14-1 -> -0.057748589
A16: 2016 | B16: =YoY!AF17 -> 22.838549 | C16: =B16/B15-1 -> 0.040635045 | D16: =YoY!Z17 -> 3.6125 | E16: =D16/D15-1 -> 0.024580477 | F16: =D16*46*B16 -> 3795.1959 | G16: =F16/F15-1 -> 0.066214351 | H16: =YoY!V17 -> 194.15 | I16: =H16*B16 -> 4434.1043 | J16: =I16/I15-1 -> -0.27308742
A17: 2017 | B17: =YoY!AF18 -> 23.486732 | C17: =B17/B16-1 -> 0.028381066 | D17: =YoY!Z18 -> 3.3241667 | E17: =D17/D16-1 -> -0.079815456 | F17: =D17*46*B17 -> 3591.3953 | G17: =F17/F16-1 -> -0.053699638 | H17: =YoY!V18 -> 213.88333 | I17: =H17*B17 -> 5023.4204 | J17: =I17/I16-1 -> 0.13290533
A18: 2018 | B18: =YoY!AF19 -> 23.901116 | C18: =B18/B17-1 -> 0.017643362 | D18: =YoY!Z19 -> 2.925 | E18: =D18/D17-1 -> -0.12008022 | F18: =D18*46*B18 -> 3215.8952 | G18: =F18/F17-1 -> -0.10455548 | H18: =YoY!V19 -> 249.45 | I18: =H18*B18 -> 5962.1335 | J18: =I18/I17-1 -> 0.18686731
A19: 2019 | B19: =YoY!AF20 -> 24.50763 | C19: =B19/B18-1 -> 0.025375965 | D19: =YoY!Z20 -> 2.88 | E19: =D19/D18-1 -> -0.015384615 | F19: =D19*46*B19 -> 3246.7709 | G19: =F19/F18-1 -> 0.0096009503 | H19: =YoY!V20 -> 245.28333 | I19: =H19*B19 -> 6011.3133 | J19: =I19/I18-1 -> 0.0082486857
A20: 2020 | B20: =YoY!AF21 -> 24.582295 | C20: =B20/B19-1 -> 0.0030465708 | D20: =YoY!Z21 -> 3.3233333 | E20: =D20/D19-1 -> 0.15393519 | F20: =D20*46*B20 -> 3757.9773 | G20: =F20/F19-1 -> 0.15745073 | H20: =YoY!V21 -> 229.1 | I20: =H20*B20 -> 5631.8037 | J20: =I20/I19-1 -> -0.063132557
A21: 2021 | B21: =YoY!AF22 -> 24.015262 | C21: =B21/B20-1 -> -0.023066727 | D21: =YoY!Z22 -> 4.5108333 | E21: =D21/D20-1 -> 0.35732197 | F21: =D21*46*B21 -> 4983.1267 | G21: =F21/F20-1 -> 0.32601299 | H21: =YoY!V22 -> 483.21667 | I21: =H21*B21 -> 11604.575 | J21: =I21/I20-1 -> 1.0605432
A22: 2022 | B22: =YoY!AF23 -> 24.486862 | C22: =B22/B21-1 -> 0.019637542 | D22: =YoY!Z23 -> 5.6308333 | E22: =D22/D21-1 -> 0.24829115 | F22: =D22*46*B22 -> 6342.5462 | G22: =F22/F21-1 -> 0.27280452 | H22: =YoY!V23 -> 700.03333 | I22: =H22*B22 -> 17141.62 | J22: =I22/I21-1 -> 0.47714331 | K22: 98273.9
A23: 2023 | B23: =YoY!AF24 -> 24.601581 | C23: =B23/B22-1 -> 0.0046849171 | D23: =YoY!Z24 -> 4.5408333 | E23: =D23/D22-1 -> -0.19357703 | F23: =D23*46*B23 -> 5138.7373 | G23: =F23/F22-1 -> -0.18979901 | H23: =YoY!V24 -> 358.00833 | I23: =H23*B23 -> 8807.5711 | J23: =I23/I22-1 -> -0.48618793 | K23: 76161.7 | L23: =K23/K22-1 -> -0.22500583
A24: 2024 | B24: =YoY!AF25 -> 24.794993 | C24: =B24/B23-1 -> 0.0078617708 | D24: =YoY!Z25 -> 5.6208333 | E24: =D24/D23-1 -> 0.23784181 | F24: =D24*46*B24 -> 6410.9521 | G24: =F24/F23-1 -> 0.24757343 | H24: =YoY!V25 -> 338.28333 | I24: =H24*B24 -> 8387.7329 | J24: =I24/I23-1 -> -0.047667868 | K24: 128803.6 | L24: =K24/K23-1 -> 0.69118599
A25: 2025 | B25: =YoY!AF26 -> 25.954715 | C25: =B25/B24-1 -> 0.046772429 | D25: =YoY!Z26 -> 8.47 | E25: =D25/D24-1 -> 0.506894 | F25: =D25*46*B25 -> 10112.476 | G25: =F25/F24-1 -> 0.57737509 | H25: =YoY!V26 -> 422.65833 | I25: =H25*B25 -> 10969.977 | J25: =I25/I24-1 -> 0.30785956
A26: 2026 | B26: =YoY!AF27 -> 26.640017 | C26: =B26/B25-1 -> 0.026403755 | D26: =YoY!Z27 -> 7.42375 | E26: =D26/D25-1 -> -0.1235242 | F26: =D26*46*B26 -> 9097.366 | G26: =F26/F25-1 -> -0.10038195 | H26: =YoY!V27 -> 560.4375 | I26: =H26*B26 -> 14930.065 | J26: =I26/I25-1 -> 0.36099329
A29: Reading: the lempira lost value slowly: 18.9 per US$ in 2005-2011 (fixed band), then 2-5 % more lempiras per dollar each year to 24.5 in 2019, flat 2019-2024 (24.0-24.8), then +4.7 % in 2025 (25.95) and +2.6 % so far in 2026 (26.64; 26.89 on 25 Sep).
A30: For growers paid in lempiras the depreciation adds a few % a year to the dollar price; it is small next to the swings of the coffee price itself (-31 % in 2012, +81 % in 2024-25 in US$).
A31: The same depreciation makes imported urea dearer in lempiras: +33 % in US$ and +36 % in lempiras in 2026.
