Workbook

Sheet README
A1: Honduras arabica : ce qui fait bouger la surface et les arbres (2005–2026)
A2: Une ligne par campagne (octobre N – septembre N+1). Chiffres en bleu = copiés des sources ; en noir = formules. Les feuilles se recalculent dans Excel.
A4: Annual : surfaces en production / pas encore en production, total, variations, arbres, densité, production, rendement, prix de l'arabica et des engrais, usage d'engrais au Honduras, forêts, cultures permanentes, pâturages, emploi agricole, registre IHCAFE.
A5: Regimes : variation moyenne de la surface par phase de prix (boom 2010–2012, rouille 2013, rénovation 2014–2017, crise 2018–2019, prix hauts 2022–2026).
A6: Margin : marge indicative par quintal et par hectare. C'est une estimation : le coût vient de quelques chiffres datés (IHCAFE, presse, non vérifiés). Modifie les cellules bleues.
A7: Rust_2012 : la météo de 2011–2013 dans les 3 zones (pluie des pluviomètres GPCC, températures des stations), pour voir ce qui a favorisé la rouille.
A8: USDA_quotes : ce que disent les rapports de l'attaché USDA, année par année (rouille, rénovation, terres, main-d'œuvre, variétés, engrais).
A9: Production_1960_2026 : la production USDA du Honduras depuis 1960/61, avec la variation d'une année sur l'autre.
A11: À SAVOIR AVANT D'INTERPRÉTER
A12: Les nombres d'arbres de l'USDA sont des estimations : 1 049 millions chaque année de 2006 à 2010, puis une densité fixe d'environ 4 250 arbres/ha jusqu'en 2017, et 6 400/ha depuis 2023. Depuis 2020, les deux tiers de la hausse des arbres viennent de cette densité, pas de nouvelles surfaces.
A13: La FAO marque la surface de café du Honduras comme imputée depuis 2013 et le prix producteur comme estimé : non utilisés.
A14: Le registre de l'IHCAFE (surface récoltée des fermes inscrites) baisse de 315 700 ha (2022/23) à 280 100 (2023/24) puis 285 600 ha (2024/25), alors que l'USDA l'augmente : la hausse récente de la surface est incertaine.

Sheet Annual
A1: Year (MY start) | B1: Marketing year | C1: Bearing area (1000 ha) | D1: Non-bearing area (1000 ha) | E1: Total planted area (1000 ha) | F1: Total area, change (1000 ha) | G1: Bearing area, change (1000 ha) | H1: Non-bearing area, change (1000 ha) | I1: Bearing trees (million) | J1: Non-bearing trees (million) | K1: Trees per ha, bearing | L1: Trees per ha, non-bearing | M1: Production, USDA PSD (1000 bags 60 kg) | N1: Yield (bags 60 kg per bearing ha) | O1: Production, change % | P1: Arabica, World Bank "Other Milds" ($/kg, calendar year N) | Q1: Arabica ($/lb) | R1: Urea, World Bank ($/t) | S1: DAP ($/t) | T1: Potassium chloride ($/t) | U1: kg urea bought by 1 kg arabica | V1: Fertiliser use Honduras: N (t, FAO) | W1: P2O5 (t, FAO) | X1: K2O (t, FAO) | Y1: N+P2O5+K2O (t) | Z1: Urea import price Honduras ($/t, FAO trade) | AA1: Forest land (1000 ha, FAO) | AB1: Permanent crops (1000 ha, FAO) | AC1: Pastures (1000 ha, FAO) | AD1: Employment in agriculture (1000, ILO model via FAO) | AE1: IHCAFE registered harvested area (ha) | AF1: IHCAFE registered small producers | AG1: Price regime
A2: 2005 | B2: 2005/06 | C2: 184 | D2: 64 | E2: =C2+D2 -> 248 | I2: 753 | J2: 131 | K2: =I2/C2*1000 -> 4092.3913 | L2: =J2/D2*1000 -> 2046.875 | M2: 3204 | N2: =M2/C2 -> 17.413043 | P2: 2.532 | Q2: =P2/2.20462 -> 1.1484972 | R2: 217.358 | S2: 226.8 | T2: 155 | U2: =P2*1000/R2 -> 11.648985 | V2: 41865 | W2: 14829 | X2: 6958 | Y2: =V2+W2+X2 -> 63652 | Z2: 278.11857 | AA2: 6937.08 | AB2: 400 | AC2: 1663 | AD2: 658.35 | AG2: 1 · 2005–2009 flat prices
A3: 2006 | B3: 2006/07 | C3: 230 | D3: 13 | E3: =C3+D3 -> 243 | F3: =E3-E2 -> -5 | G3: =C3-C2 -> 46 | H3: =D3-D2 -> -51 | I3: 1049 | J3: 141 | K3: =I3/C3*1000 -> 4560.8696 | L3: =J3/D3*1000 -> 10846.154 | M3: 3460 | N3: =M3/C3 -> 15.043478 | O3: =M3/M2-1 -> 0.079900125 | P3: 2.522 | Q3: =P3/2.20462 -> 1.1439613 | R3: 222.142 | S3: 229.875 | T3: 178.333 | U3: =P3*1000/R3 -> 11.353098 | V3: 66688 | W3: 20783 | X3: 15891 | Y3: =V3+W3+X3 -> 103362 | Z3: 280.35097 | AA3: 6898.6 | AB3: 410 | AC3: 1694 | AD3: 730.8 | AG3: 1 · 2005–2009 flat prices
A4: 2007 | B4: 2007/08 | C4: 230 | D4: 13 | E4: =C4+D4 -> 243 | F4: =E4-E3 -> 0 | G4: =C4-C3 -> 0 | H4: =D4-D3 -> 0 | I4: 1049 | J4: 141 | K4: =I4/C4*1000 -> 4560.8696 | L4: =J4/D4*1000 -> 10846.154 | M4: 3642 | N4: =M4/C4 -> 15.834783 | O4: =M4/M3-1 -> 0.052601156 | P4: 2.724 | Q4: =P4/2.20462 -> 1.2355871 | R4: 307.117 | S4: 391.958 | T4: 195.417 | U4: =P4*1000/R4 -> 8.8695839 | V4: 63491 | W4: 21414 | X4: 9776 | Y4: =V4+W4+X4 -> 94681 | Z4: 350.12173 | AA4: 6860.12 | AB4: 410 | AC4: 1725 | AD4: 706.37 | AG4: 1 · 2005–2009 flat prices
A5: 2008 | B5: 2008/09 | C5: 224 | D5: 20 | E5: =C5+D5 -> 244 | F5: =E5-E4 -> 1 | G5: =C5-C4 -> -6 | H5: =D5-D4 -> 7 | I5: 1049 | J5: 141 | K5: =I5/C5*1000 -> 4683.0357 | L5: =J5/D5*1000 -> 7050 | M5: 3225 | N5: =M5/C5 -> 14.397321 | O5: =M5/M4-1 -> -0.11449753 | P5: 3.081 | Q5: =P5/2.20462 -> 1.3975198 | R5: 514.983 | S5: 861.625 | T5: 455.967 | U5: =P5*1000/R5 -> 5.9827218 | V5: 55554 | W5: 16565 | X5: 6892 | Y5: =V5+W5+X5 -> 79011 | AA5: 6821.65 | AB5: 410 | AC5: 1756 | AD5: 729.37 | AG5: 1 · 2005–2009 flat prices
A6: 2009 | B6: 2009/10 | C6: 224 | D6: 20 | E6: =C6+D6 -> 244 | F6: =E6-E5 -> 0 | G6: =C6-C5 -> 0 | H6: =D6-D5 -> 0 | I6: 1049 | J6: 141 | K6: =I6/C6*1000 -> 4683.0357 | L6: =J6/D6*1000 -> 7050 | M6: 3550 | N6: =M6/C6 -> 15.848214 | O6: =M6/M5-1 -> 0.10077519 | P6: 3.171 | Q6: =P6/2.20462 -> 1.4383431 | R6: 251.1 | S6: 288.475 | T6: 558.475 | U6: =P6*1000/R6 -> 12.628435 | V6: 47616 | W6: 11716 | X6: 4008 | Y6: =V6+W6+X6 -> 63340 | Z6: 306.96272 | AA6: 6783.17 | AB6: 418 | AC6: 1737.69 | AD6: 801.84 | AG6: 1 · 2005–2009 flat prices
A7: 2010 | B7: 2010/11 | C7: 238 | D7: 28 | E7: =C7+D7 -> 266 | F7: =E7-E6 -> 22 | G7: =C7-C6 -> 14 | H7: =D7-D6 -> 8 | I7: 1049 | J7: 141 | K7: =I7/C7*1000 -> 4407.563 | L7: =J7/D7*1000 -> 5035.7143 | M7: 3975 | N7: =M7/C7 -> 16.701681 | O7: =M7/M6-1 -> 0.11971831 | P7: 4.32 | Q7: =P7/2.20462 -> 1.9595214 | R7: 288.917 | S7: 456.425 | T7: 332.15 | U7: =P7*1000/R7 -> 14.952391 | V7: 56041 | W7: 15327 | X7: 15828 | Y7: =V7+W7+X7 -> 87196 | Z7: 327.73879 | AA7: 6744.69 | AB7: 480 | AC7: 1719.38 | AD7: 862.14 | AG7: 2 · 2010–2012 price boom
A8: 2011 | B8: 2011/12 | C8: 245 | D8: 40 | E8: =C8+D8 -> 285 | F8: =E8-E7 -> 19 | G8: =C8-C7 -> 7 | H8: =D8-D7 -> 12 | I8: 1042 | J8: 170 | K8: =I8/C8*1000 -> 4253.0612 | L8: =J8/D8*1000 -> 4250 | M8: 5600 | N8: =M8/C8 -> 22.857143 | O8: =M8/M7-1 -> 0.40880503 | P8: 5.977 | Q8: =P8/2.20462 -> 2.7111248 | R8: 398.942 | S8: 516.292 | T8: 392.825 | U8: =P8*1000/R8 -> 14.982128 | V8: 85542 | W8: 23195 | X8: 25119 | Y8: =V8+W8+X8 -> 133856 | Z8: 418.44303 | AA8: 6701.15 | AB8: 510 | AC8: 1701.07 | AD8: 820.02 | AG8: 2 · 2010–2012 price boom
A9: 2012 | B9: 2012/13 | C9: 267 | D9: 48 | E9: =C9+D9 -> 315 | F9: =E9-E8 -> 30 | G9: =C9-C8 -> 22 | H9: =D9-D8 -> 8 | I9: 1068 | J9: 188 | K9: =I9/C9*1000 -> 4000 | L9: =J9/D9*1000 -> 3916.6667 | M9: 4725 | N9: =M9/C9 -> 17.696629 | O9: =M9/M8-1 -> -0.15625 | P9: 4.112 | Q9: =P9/2.20462 -> 1.865174 | R9: 398.6 | S9: 480.242 | T9: 465.375 | U9: =P9*1000/R9 -> 10.316106 | V9: 75417 | W9: 18301 | X9: 16134 | Y9: =V9+W9+X9 -> 109852 | Z9: 462.85594 | AA9: 6657.61 | AB9: 540 | AC9: 1682.76 | AD9: 882.57 | AG9: 2 · 2010–2012 price boom
A10: 2013 | B10: 2013/14 | C10: 213 | D10: 50 | E10: =C10+D10 -> 263 | F10: =E10-E9 -> -52 | G10: =C10-C9 -> -54 | H10: =D10-D9 -> 2 | I10: 900 | J10: 210 | K10: =I10/C10*1000 -> 4225.3521 | L10: =J10/D10*1000 -> 4200 | M10: 4400 | N10: =M10/C10 -> 20.657277 | O10: =M10/M9-1 -> -0.068783069 | P10: 3.077 | Q10: =P10/2.20462 -> 1.3957054 | R10: 339.608 | S10: 410.975 | T10: 395 | U10: =P10*1000/R10 -> 9.0604462 | V10: 74712 | W10: 21794 | X10: 29688 | Y10: =V10+W10+X10 -> 126194 | AA10: 6614.08 | AB10: 540 | AC10: 1664.45 | AD10: 879.75 | AG10: 3 · 2013 rust + price crash
A11: 2014 | B11: 2014/15 | C11: 227 | D11: 66 | E11: =C11+D11 -> 293 | F11: =E11-E10 -> 30 | G11: =C11-C10 -> 14 | H11: =D11-D10 -> 16 | I11: 966 | J11: 279 | K11: =I11/C11*1000 -> 4255.5066 | L11: =J11/D11*1000 -> 4227.2727 | M11: 5100 | N11: =M11/C11 -> 22.46696 | O11: =M11/M10-1 -> 0.15909091 | P11: 4.425 | Q11: =P11/2.20462 -> 2.0071486 | R11: 308.442 | S11: 429.6 | T11: 296.625 | U11: =P11*1000/R11 -> 14.346295 | V11: 74007 | W11: 25287 | X11: 43243 | Y11: =V11+W11+X11 -> 142537 | Z11: 366.54333 | AA11: 6570.54 | AB11: 540 | AC11: 1646.13 | AD11: 735.24 | AG11: 4 · 2014–2017 renovation
A12: 2015 | B12: 2015/16 | C12: 240 | D12: 63 | E12: =C12+D12 -> 303 | F12: =E12-E11 -> 10 | G12: =C12-C11 -> 13 | H12: =D12-D11 -> -3 | I12: 1020 | J12: 270 | K12: =I12/C12*1000 -> 4250 | L12: =J12/D12*1000 -> 4285.7143 | M12: 5300 | N12: =M12/C12 -> 22.083333 | O12: =M12/M11-1 -> 0.039215686 | P12: 3.526 | Q12: =P12/2.20462 -> 1.5993686 | R12: 277.942 | S12: 416.633 | T12: 296.067 | U12: =P12*1000/R12 -> 12.6861 | V12: 75343 | W12: 33145 | X12: 25793 | Y12: =V12+W12+X12 -> 134281 | Z12: 324.5954 | AA12: 6527 | AB12: 540 | AC12: 1627.82 | AD12: 761.26 | AG12: 4 · 2014–2017 renovation
A13: 2016 | B13: 2016/17 | C13: 280 | D13: 54 | E13: =C13+D13 -> 334 | F13: =E13-E12 -> 31 | G13: =C13-C12 -> 40 | H13: =D13-D12 -> -9 | I13: 1191 | J13: 234 | K13: =I13/C13*1000 -> 4253.5714 | L13: =J13/D13*1000 -> 4333.3333 | M13: 7510 | N13: =M13/C13 -> 26.821429 | O13: =M13/M12-1 -> 0.41698113 | P13: 3.612 | Q13: =P13/2.20462 -> 1.6383776 | R13: 194.15 | S13: 315.808 | T13: 260.333 | U13: =P13*1000/R13 -> 18.604172 | V13: 95944 | W13: 34653 | X13: 36674 | Y13: =V13+W13+X13 -> 167271 | Z13: 238.62071 | AA13: 6444.09 | AB13: 540 | AC13: 1609.51 | AD13: 726.4 | AG13: 4 · 2014–2017 renovation
A14: 2017 | B14: 2017/18 | C14: 298 | D14: 44 | E14: =C14+D14 -> 342 | F14: =E14-E13 -> 8 | G14: =C14-C13 -> 18 | H14: =D14-D13 -> -10 | I14: 1269 | J14: 186 | K14: =I14/C14*1000 -> 4258.3893 | L14: =J14/D14*1000 -> 4227.2727 | M14: 7600 | N14: =M14/C14 -> 25.503356 | O14: =M14/M13-1 -> 0.011984021 | P14: 3.324 | Q14: =P14/2.20462 -> 1.5077428 | R14: 213.883 | S14: 323.042 | T14: 218.233 | U14: =P14*1000/R14 -> 15.541207 | V14: 110175 | W14: 34591 | X14: 43065 | Y14: =V14+W14+X14 -> 187831 | Z14: 258.66296 | AA14: 6361.17 | AB14: 652.83 | AC14: 1591.2 | AD14: 925.6 | AG14: 4 · 2014–2017 renovation
A15: 2018 | B15: 2018/19 | C15: 286 | D15: 36 | E15: =C15+D15 -> 322 | F15: =E15-E14 -> -20 | G15: =C15-C14 -> -12 | H15: =D15-D14 -> -8 | I15: 1362 | J15: 153 | K15: =I15/C15*1000 -> 4762.2378 | L15: =J15/D15*1000 -> 4250 | M15: 7100 | N15: =M15/C15 -> 24.825175 | O15: =M15/M14-1 -> -0.065789474 | P15: 2.925 | Q15: =P15/2.20462 -> 1.3267593 | R15: 249.45 | S15: 393.442 | T15: 215.5 | U15: =P15*1000/R15 -> 11.725797 | V15: 122752 | W15: 39277 | X15: 47080 | Y15: =V15+W15+X15 -> 209109 | Z15: 293.32604 | AA15: 6278.26 | AB15: 652.83 | AC15: 1572.89 | AD15: 964.19 | AG15: 5 · 2018–2019 price below cost
A16: 2019 | B16: 2019/20 | C16: 270 | D16: 35 | E16: =C16+D16 -> 305 | F16: =E16-E15 -> -17 | G16: =C16-C15 -> -16 | H16: =D16-D15 -> -1 | I16: 1290 | J16: 150 | K16: =I16/C16*1000 -> 4777.7778 | L16: =J16/D16*1000 -> 4285.7143 | M16: 5200 | N16: =M16/C16 -> 19.259259 | O16: =M16/M15-1 -> -0.26760563 | P16: 2.88 | Q16: =P16/2.20462 -> 1.3063476 | R16: 245.283 | S16: 306.367 | T16: 255.5 | U16: =P16*1000/R16 -> 11.741539 | V16: 86136 | W16: 31343 | X16: 42804 | Y16: =V16+W16+X16 -> 160283 | Z16: 288.57511 | AA16: 6195.34 | AB16: 652.83 | AC16: 1554.58 | AD16: 898.75 | AG16: 5 · 2018–2019 price below cost
A17: 2020 | B17: 2020/21 | C17: 273 | D17: 34 | E17: =C17+D17 -> 307 | F17: =E17-E16 -> 2 | G17: =C17-C16 -> 3 | H17: =D17-D16 -> -1 | I17: 1295 | J17: 163 | K17: =I17/C17*1000 -> 4743.5897 | L17: =J17/D17*1000 -> 4794.1176 | M17: 6500 | N17: =M17/C17 -> 23.809524 | O17: =M17/M16-1 -> 0.25 | P17: 3.323 | Q17: =P17/2.20462 -> 1.5072892 | R17: 229.1 | S17: 312.425 | T17: 241.083 | U17: =P17*1000/R17 -> 14.504583 | V17: 128016 | W17: 44680 | X17: 69967 | Y17: =V17+W17+X17 -> 242663 | Z17: 265.9348 | AA17: 6112.43 | AB17: 652.83 | AC17: 1536.27 | AD17: 856.79 | AG17: 6 · 2020–2021 recovery
A18: 2021 | B18: 2021/22 | C18: 275 | D18: 32 | E18: =C18+D18 -> 307 | F18: =E18-E17 -> 0 | G18: =C18-C17 -> 2 | H18: =D18-D17 -> -2 | I18: 1375 | J18: 172 | K18: =I18/C18*1000 -> 5000 | L18: =J18/D18*1000 -> 5375 | M18: 4800 | N18: =M18/C18 -> 17.454545 | O18: =M18/M17-1 -> -0.26153846 | P18: 4.511 | Q18: =P18/2.20462 -> 2.0461576 | R18: 483.217 | S18: 600.967 | T18: 542.817 | U18: =P18*1000/R18 -> 9.3353504 | V18: 104868 | W18: 33278 | X18: 56411 | Y18: =V18+W18+X18 -> 194557 | Z18: 406.13757 | AA18: 6062.21 | AB18: 652.83 | AC18: 1517.96 | AD18: 888.76 | AG18: 6 · 2020–2021 recovery
A19: 2022 | B19: 2022/23 | C19: 285 | D19: 35 | E19: =C19+D19 -> 320 | F19: =E19-E18 -> 13 | G19: =C19-C18 -> 10 | H19: =D19-D18 -> 3 | I19: 1600 | J19: 200 | K19: =I19/C19*1000 -> 5614.0351 | L19: =J19/D19*1000 -> 5714.2857 | M19: 5700 | N19: =M19/C19 -> 20 | O19: =M19/M18-1 -> 0.1875 | P19: 5.631 | Q19: =P19/2.20462 -> 2.5541817 | R19: 700.033 | S19: 772.158 | T19: 863.425 | U19: =P19*1000/R19 -> 8.0439065 | V19: 104865 | W19: 33274 | X19: 56407 | Y19: =V19+W19+X19 -> 194546 | AA19: 6011.99 | AB19: 652.83 | AC19: 1499.65 | AD19: 824.33 | AE19: 315731.11 | AF19: 90522 | AG19: 7 · 2022–2026 high prices
A20: 2023 | B20: 2023/24 | C20: 292 | D20: 38 | E20: =C20+D20 -> 330 | F20: =E20-E19 -> 10 | G20: =C20-C19 -> 7 | H20: =D20-D19 -> 3 | I20: 1800 | J20: 232 | K20: =I20/C20*1000 -> 6164.3836 | L20: =J20/D20*1000 -> 6105.2632 | M20: 5050 | N20: =M20/C20 -> 17.294521 | O20: =M20/M19-1 -> -0.11403509 | P20: 4.541 | Q20: =P20/2.20462 -> 2.0597654 | R20: 358.008 | S20: 550.067 | T20: 383.233 | U20: =P20*1000/R20 -> 12.684074 | V20: 104427 | W20: 35527 | X20: 51399 | Y20: =V20+W20+X20 -> 191353 | Z20: 395.67575 | AA20: 5961.77 | AB20: 652.83 | AC20: 1481.34 | AD20: 895.66 | AE20: 280097 | AF20: 87136 | AG20: 7 · 2022–2026 high prices
A21: 2024 | B21: 2024/25 | C21: 300 | D21: 40 | E21: =C21+D21 -> 340 | F21: =E21-E20 -> 10 | G21: =C21-C20 -> 8 | H21: =D21-D20 -> 2 | I21: 1900 | J21: 245 | K21: =I21/C21*1000 -> 6333.3333 | L21: =J21/D21*1000 -> 6125 | M21: 5200 | N21: =M21/C21 -> 17.333333 | O21: =M21/M20-1 -> 0.02970297 | P21: 5.621 | Q21: =P21/2.20462 -> 2.5496457 | R21: 338.283 | S21: 563.667 | T21: 295.108 | U21: =P21*1000/R21 -> 16.616265 | V21: 106830 | W21: 38420 | X21: 56337 | Y21: =V21+W21+X21 -> 201587 | Z21: 365.22378 | AA21: 5911.55 | AB21: 706.8276 | AC21: 1463.0246 | AD21: 914.59 | AE21: 285557 | AF21: 86895 | AG21: 7 · 2022–2026 high prices
A22: 2025 | B22: 2025/26 | C22: 310 | D22: 40 | E22: =C22+D22 -> 350 | F22: =E22-E21 -> 10 | G22: =C22-C21 -> 10 | H22: =D22-D21 -> 0 | I22: 2000 | J22: 260 | K22: =I22/C22*1000 -> 6451.6129 | L22: =J22/D22*1000 -> 6500 | M22: 5530 | N22: =M22/C22 -> 17.83871 | O22: =M22/M21-1 -> 0.063461538 | P22: 8.47 | Q22: =P22/2.20462 -> 3.8419319 | R22: 422.658 | S22: 685.225 | T22: 347.517 | U22: =P22*1000/R22 -> 20.039843 | AA22: 5861.33 | AD22: 925.47 | AG22: 7 · 2022–2026 high prices
A23: 2026 | B23: 2026/27 | C23: 330 | D23: 30 | E23: =C23+D23 -> 360 | F23: =E23-E22 -> 10 | G23: =C23-C22 -> 20 | H23: =D23-D22 -> -10 | I23: 2100 | J23: 270 | K23: =I23/C23*1000 -> 6363.6364 | L23: =J23/D23*1000 -> 9000 | M23: 6030 | N23: =M23/C23 -> 18.272727 | O23: =M23/M22-1 -> 0.090415913 | P23: 7.424 | Q23: =P23/2.20462 -> 3.3674738 | R23: 560.438 | S23: 719.675 | T23: 388.913 | U23: =P23*1000/R23 -> 13.246782 | AG23: 7 · 2022–2026 high prices
A25: Sources. Areas and trees: USDA attaché, Coffee Annual reports from Tegucigalpa (latest revision of each year; non-bearing area = area planted − area harvested). Production: USDA PSD online, Honduras arabica, marketing year Oct–Sep. Prices: World Bank Pink Sheet, update 2 Sep 2026 (2026 = Jan–Aug). Fertiliser use, urea import value ÷ quantity, land use, employment: FAOSTAT bulk files (Sep 2026). IHCAFE registry: tables reproduced in the USDA reports.
A26: Read with care: the USDA tree numbers are estimates (1,049 million every year 2006–2010; a fixed ~4,250 trees/ha until 2017, then ~6,400/ha). FAO flags Honduras coffee area as imputed after 2012 and producer prices as estimated, so neither is used here. FAO 2022 fertiliser use repeats 2021.
A27: Blue = input copied from the source; black = formula.

Sheet Regimes
A1: Area change by price regime (averages per year, from the Annual sheet)
A3: Price regime | B3: Years | C3: Arabica ($/kg) | D3: kg urea per kg arabica | E3: Total area change (1000 ha/yr) | F3: Bearing area change (1000 ha/yr) | G3: Non-bearing area change (1000 ha/yr) | H3: Production change (%/yr)
A4: 1 · 2005–2009 flat prices | B4: =COUNTIF(Annual!$AG$2:$AG$23,$A4) -> 5 | C4: =AVERAGEIFS(Annual!$P$2:$P$23,Annual!$AG$2:$AG$23,$A4) -> 2.806 | D4: =AVERAGEIFS(Annual!$U$2:$U$23,Annual!$AG$2:$AG$23,$A4) -> 10.096565 | E4: =AVERAGEIFS(Annual!$F$2:$F$23,Annual!$AG$2:$AG$23,$A4) -> -1 | F4: =AVERAGEIFS(Annual!$G$2:$G$23,Annual!$AG$2:$AG$23,$A4) -> 10 | G4: =AVERAGEIFS(Annual!$H$2:$H$23,Annual!$AG$2:$AG$23,$A4) -> -11 | H4: =AVERAGEIFS(Annual!$O$2:$O$23,Annual!$AG$2:$AG$23,$A4) -> 0.029694736
A5: 2 · 2010–2012 price boom | B5: =COUNTIF(Annual!$AG$2:$AG$23,$A5) -> 3 | C5: =AVERAGEIFS(Annual!$P$2:$P$23,Annual!$AG$2:$AG$23,$A5) -> 4.803 | D5: =AVERAGEIFS(Annual!$U$2:$U$23,Annual!$AG$2:$AG$23,$A5) -> 13.416875 | E5: =AVERAGEIFS(Annual!$F$2:$F$23,Annual!$AG$2:$AG$23,$A5) -> 23.666667 | F5: =AVERAGEIFS(Annual!$G$2:$G$23,Annual!$AG$2:$AG$23,$A5) -> 14.333333 | G5: =AVERAGEIFS(Annual!$H$2:$H$23,Annual!$AG$2:$AG$23,$A5) -> 9.3333333 | H5: =AVERAGEIFS(Annual!$O$2:$O$23,Annual!$AG$2:$AG$23,$A5) -> 0.12409111
A6: 3 · 2013 rust + price crash | B6: =COUNTIF(Annual!$AG$2:$AG$23,$A6) -> 1 | C6: =AVERAGEIFS(Annual!$P$2:$P$23,Annual!$AG$2:$AG$23,$A6) -> 3.077 | D6: =AVERAGEIFS(Annual!$U$2:$U$23,Annual!$AG$2:$AG$23,$A6) -> 9.0604462 | E6: =AVERAGEIFS(Annual!$F$2:$F$23,Annual!$AG$2:$AG$23,$A6) -> -52 | F6: =AVERAGEIFS(Annual!$G$2:$G$23,Annual!$AG$2:$AG$23,$A6) -> -54 | G6: =AVERAGEIFS(Annual!$H$2:$H$23,Annual!$AG$2:$AG$23,$A6) -> 2 | H6: =AVERAGEIFS(Annual!$O$2:$O$23,Annual!$AG$2:$AG$23,$A6) -> -0.068783069
A7: 4 · 2014–2017 renovation | B7: =COUNTIF(Annual!$AG$2:$AG$23,$A7) -> 4 | C7: =AVERAGEIFS(Annual!$P$2:$P$23,Annual!$AG$2:$AG$23,$A7) -> 3.72175 | D7: =AVERAGEIFS(Annual!$U$2:$U$23,Annual!$AG$2:$AG$23,$A7) -> 15.294444 | E7: =AVERAGEIFS(Annual!$F$2:$F$23,Annual!$AG$2:$AG$23,$A7) -> 19.75 | F7: =AVERAGEIFS(Annual!$G$2:$G$23,Annual!$AG$2:$AG$23,$A7) -> 21.25 | G7: =AVERAGEIFS(Annual!$H$2:$H$23,Annual!$AG$2:$AG$23,$A7) -> -1.5 | H7: =AVERAGEIFS(Annual!$O$2:$O$23,Annual!$AG$2:$AG$23,$A7) -> 0.15681794
A8: 5 · 2018–2019 price below cost | B8: =COUNTIF(Annual!$AG$2:$AG$23,$A8) -> 2 | C8: =AVERAGEIFS(Annual!$P$2:$P$23,Annual!$AG$2:$AG$23,$A8) -> 2.9025 | D8: =AVERAGEIFS(Annual!$U$2:$U$23,Annual!$AG$2:$AG$23,$A8) -> 11.733668 | E8: =AVERAGEIFS(Annual!$F$2:$F$23,Annual!$AG$2:$AG$23,$A8) -> -18.5 | F8: =AVERAGEIFS(Annual!$G$2:$G$23,Annual!$AG$2:$AG$23,$A8) -> -14 | G8: =AVERAGEIFS(Annual!$H$2:$H$23,Annual!$AG$2:$AG$23,$A8) -> -4.5 | H8: =AVERAGEIFS(Annual!$O$2:$O$23,Annual!$AG$2:$AG$23,$A8) -> -0.16669755
A9: 6 · 2020–2021 recovery | B9: =COUNTIF(Annual!$AG$2:$AG$23,$A9) -> 2 | C9: =AVERAGEIFS(Annual!$P$2:$P$23,Annual!$AG$2:$AG$23,$A9) -> 3.917 | D9: =AVERAGEIFS(Annual!$U$2:$U$23,Annual!$AG$2:$AG$23,$A9) -> 11.919967 | E9: =AVERAGEIFS(Annual!$F$2:$F$23,Annual!$AG$2:$AG$23,$A9) -> 1 | F9: =AVERAGEIFS(Annual!$G$2:$G$23,Annual!$AG$2:$AG$23,$A9) -> 2.5 | G9: =AVERAGEIFS(Annual!$H$2:$H$23,Annual!$AG$2:$AG$23,$A9) -> -1.5 | H9: =AVERAGEIFS(Annual!$O$2:$O$23,Annual!$AG$2:$AG$23,$A9) -> -0.0057692308
A10: 7 · 2022–2026 high prices | B10: =COUNTIF(Annual!$AG$2:$AG$23,$A10) -> 5 | C10: =AVERAGEIFS(Annual!$P$2:$P$23,Annual!$AG$2:$AG$23,$A10) -> 6.3374 | D10: =AVERAGEIFS(Annual!$U$2:$U$23,Annual!$AG$2:$AG$23,$A10) -> 14.126174 | E10: =AVERAGEIFS(Annual!$F$2:$F$23,Annual!$AG$2:$AG$23,$A10) -> 10.6 | F10: =AVERAGEIFS(Annual!$G$2:$G$23,Annual!$AG$2:$AG$23,$A10) -> 11 | G10: =AVERAGEIFS(Annual!$H$2:$H$23,Annual!$AG$2:$AG$23,$A10) -> -0.4 | H10: =AVERAGEIFS(Annual!$O$2:$O$23,Annual!$AG$2:$AG$23,$A10) -> 0.051409067
A12: Averages skip 2005 for the changes (no 2004 row). The regimes are defined by the arabica price path and the 2012–2013 rust.

Sheet Margin
A1: Indicative producer margin per quintal (100 lb = 45.36 kg) and per hectare
A2: An estimate, not a measured margin: edit the blue cells. Farm-gate factor and costs come from the few dated figures below (IHCAFE, press).
A4: Farm-gate price ÷ international "Other Milds" price | D4: 0.78 | E4: Calibration: 2021/22 IHCAFE producer average L4,584.61 = $187.85/qq vs World Bank 2022 $255/qq → 0.74; 2024 producers paid L5,270/qq ≈ $212/qq vs $255/qq → 0.83 (press, unverified).
A6: Year | B6: Arabica Other Milds ($/lb) | C6: Farm-gate estimate ($/lb) | D6: Cost of production ($/lb) | E6: Cost basis | F6: Margin ($ per quintal) | G6: Yield (quintals per bearing ha) | H6: Margin ($ per bearing ha) | I6: kg urea per kg arabica
A7: 2005 | B7: =Annual!Q2 -> 1.1484972 | C7: =B7*$D$4 -> 0.89582785 | E7: no cost data | G7: =Annual!N2*60/45.3592 -> 23.033533 | I7: =Annual!U2 -> 11.648985
A8: 2006 | B8: =Annual!Q3 -> 1.1439613 | C8: =B8*$D$4 -> 0.89228983 | E8: no cost data | G8: =Annual!N3*60/45.3592 -> 19.899132 | I8: =Annual!U3 -> 11.353098
A9: 2007 | B9: =Annual!Q4 -> 1.2355871 | C9: =B9*$D$4 -> 0.96375793 | E9: no cost data | G9: =Annual!N4*60/45.3592 -> 20.945849 | I9: =Annual!U4 -> 8.8695839
A10: 2008 | B10: =Annual!Q5 -> 1.3975198 | C10: =B10*$D$4 -> 1.0900654 | E10: no cost data | G10: =Annual!N5*60/45.3592 -> 19.044412 | I10: =Annual!U5 -> 5.9827218
A11: 2009 | B11: =Annual!Q6 -> 1.4383431 | C11: =B11*$D$4 -> 1.1219076 | E11: no cost data | G11: =Annual!N6*60/45.3592 -> 20.963616 | I11: =Annual!U6 -> 12.628435
A12: 2010 | B12: =Annual!Q7 -> 1.9595214 | C12: =B12*$D$4 -> 1.5284267 | E12: no cost data | G12: =Annual!N7*60/45.3592 -> 22.09256 | I12: =Annual!U7 -> 14.952391
A13: 2011 | B13: =Annual!Q8 -> 2.7111248 | C13: =B13*$D$4 -> 2.1146774 | E13: no cost data | G13: =Annual!N8*60/45.3592 -> 30.234849 | I13: =Annual!U8 -> 14.982128
A14: 2012 | B14: =Annual!Q9 -> 1.865174 | C14: =B14*$D$4 -> 1.4548358 | D14: 1.5 | E14: benchmark | F14: =(C14-D14)*100 -> -4.5164246 | G14: =Annual!N9*60/45.3592 -> 23.408653 | H14: =F14*G14 -> -105.72341 | I14: =Annual!U9 -> 10.316106
A15: 2013 | B15: =Annual!Q10 -> 1.3957054 | C15: =B15*$D$4 -> 1.0886502 | D15: 1.4571429 | E15: interpolated 2012–2019 | F15: =(C15-D15)*100 -> -36.849266 | G15: =Annual!N10*60/45.3592 -> 27.324922 | H15: =F15*G15 -> -1006.9033 | I15: =Annual!U10 -> 9.0604462
A16: 2014 | B16: =Annual!Q11 -> 2.0071486 | C16: =B16*$D$4 -> 1.5655759 | D16: 1.4142857 | E16: interpolated 2012–2019 | F16: =(C16-D16)*100 -> 15.129021 | G16: =Annual!N11*60/45.3592 -> 29.718726 | H16: =F16*G16 -> 449.61523 | I16: =Annual!U11 -> 14.346295
A17: 2015 | B17: =Annual!Q12 -> 1.5993686 | C17: =B17*$D$4 -> 1.2475075 | D17: 1.3714286 | E17: interpolated 2012–2019 | F17: =(C17-D17)*100 -> -12.392106 | G17: =Annual!N12*60/45.3592 -> 29.211274 | H17: =F17*G17 -> -361.98921 | I17: =Annual!U12 -> 12.6861
A18: 2016 | B18: =Annual!Q13 -> 1.6383776 | C18: =B18*$D$4 -> 1.2779345 | D18: 1.3285714 | E18: interpolated 2012–2019 | F18: =(C18-D18)*100 -> -5.0636909 | G18: =Annual!N13*60/45.3592 -> 35.478706 | H18: =F18*G18 -> -179.6532 | I18: =Annual!U13 -> 18.604172
A19: 2017 | B19: =Annual!Q14 -> 1.5077428 | C19: =B19*$D$4 -> 1.1760394 | D19: 1.2857143 | E19: interpolated 2012–2019 | F19: =(C19-D19)*100 -> -10.967488 | G19: =Annual!N14*60/45.3592 -> 33.735192 | H19: =F19*G19 -> -369.99031 | I19: =Annual!U14 -> 15.541207
A20: 2018 | B20: =Annual!Q15 -> 1.3267593 | C20: =B20*$D$4 -> 1.0348722 | D20: 1.2428571 | E20: interpolated 2012–2019 | F20: =(C20-D20)*100 -> -20.798492 | G20: =Annual!N15*60/45.3592 -> 32.838112 | H20: =F20*G20 -> -682.98321 | I20: =Annual!U15 -> 11.725797
A21: 2019 | B21: =Annual!Q16 -> 1.3063476 | C21: =B21*$D$4 -> 1.0189511 | D21: 1.2 | E21: benchmark | F21: =(C21-D21)*100 -> -18.104889 | G21: =Annual!N16*60/45.3592 -> 25.47566 | H21: =F21*G21 -> -461.23399 | I21: =Annual!U16 -> 11.741539
A22: 2020 | B22: =Annual!Q17 -> 1.5072892 | C22: =B22*$D$4 -> 1.1756856 | D22: 1.2333333 | E22: interpolated 2019–2022 | F22: =(C22-D22)*100 -> -5.7647728 | G22: =Annual!N17*60/45.3592 -> 31.494635 | H22: =F22*G22 -> -181.55941 | I22: =Annual!U17 -> 14.504583
A23: 2021 | B23: =Annual!Q18 -> 2.0461576 | C23: =B23*$D$4 -> 1.5960029 | D23: 1.2666667 | E23: interpolated 2019–2022 | F23: =(C23-D23)*100 -> 32.933627 | G23: =Annual!N18*60/45.3592 -> 23.08843 | H23: =F23*G23 -> 760.38576 | I23: =Annual!U18 -> 9.3353504
A24: 2022 | B24: =Annual!Q19 -> 2.5541817 | C24: =B24*$D$4 -> 1.9922617 | D24: 1.3 | E24: benchmark | F24: =(C24-D24)*100 -> 69.22617 | G24: =Annual!N19*60/45.3592 -> 26.455493 | H24: =F24*G24 -> 1831.4125 | I24: =Annual!U19 -> 8.0439065
A25: 2023 | B25: =Annual!Q20 -> 2.0597654 | C25: =B25*$D$4 -> 1.606617 | D25: 1.3 | E25: benchmark | F25: =(C25-D25)*100 -> 30.661701 | G25: =Annual!N20*60/45.3592 -> 22.876753 | H25: =F25*G25 -> 701.44018 | I25: =Annual!U20 -> 12.684074
... A28: 2026 | B28: =Annual!Q23 -> 3.3674738 | C28: =B28*$D$4 -> 2.6266295 | D28: 1.3 | E28: held at 2023 level (2026 picking wages +67%, urea +32%: cost understated) | F28: =(C28-D28)*100 -> 132.66295 | G28: =Annual!N23*60/45.3592 -> 24.1707 | H28: =F28*G28 -> 3206.5565 | I28: =Annual!U23 -> 13.246782
A30: Cost benchmarks and sources
A31: 2012 | B31: 1.5 | C31: IHCAFE: a price over $150/qq is favourable (USDA May 2012) — upper bound
A32: 2019 | B32: 1.2 | C32: Press, Jul 2019: producers about $20 below a cost near $120/qq; exporters said the market needed ≥ $135 (unverified)
A33: 2022 | B33: 1.3 | C33: Press on 2022–23: cost about $130/qq; fertiliser bags doubled to L1,200–1,500 (unverified)
A34: 2023 | B34: 1.3 | C34: Same as 2022 (unverified)
A35: Other dated figures (press, unverified): picking paid L60 per lata in 2025, L100 in Feb 2026; pickers earn L200–400 a day; exporters pay producers L5,270/qq (2024).
A36: Yield in quintals uses USDA production ÷ USDA bearing area (60-kg bags converted to 100-lb quintals).

Sheet Rust_2012
A1: Weather before and during the 2012–2013 rust epidemic: mean of Comayagua, Ocotepeque and Copán
A2: Mean of the 3 grid cells. Normal = 2005–2019 average of the same month. Rain from two independent gauge analyses (GPCC 1°, CPC 0.5°); temperatures and humidity from NASA POWER (the most consistent temperature source here; station temperature grids have breaks). The 2012 pattern matches Avelino et al. (2015, Food Security 7:303–321): a wet first half, a drier second half and a reduced day–night range, which favour rust infection.
A4: Month | B4: Rain, % of 2005–2019 normal (GPCC gauges) | C4: Rain, % of normal (CPC gauges) | D4: Min temperature anomaly (°C, NASA) | E4: Max temperature anomaly (°C, NASA) | F4: Day–night range anomaly (°C, NASA) | G4: Relative humidity anomaly (points, NASA)
A5: 2011-01 | B5: 135 | C5: 80 | D5: 0.07 | E5: 0.79 | F5: 0.72 | G5: -1.1
A6: 2011-02 | B6: 236 | C6: 171 | D6: 0.12 | E6: 0.09 | F6: -0.03 | G6: 0.2
A7: 2011-03 | B7: 109 | C7: 84 | D7: -0.98 | E7: -0.31 | F7: 0.68 | G7: -2.8
A8: 2011-04 | B8: 156 | C8: 165 | D8: -0.36 | E8: 0.06 | F8: 0.42 | G8: -3.2
A9: 2011-05 | B9: 94 | C9: 92 | D9: -0.3 | E9: -0.17 | F9: 0.14 | G9: 1.2
A10: 2011-06 | B10: 118 | C10: 127 | D10: -0.15 | E10: -0.28 | F10: -0.12 | G10: -0.7
A11: 2011-07 | B11: 166 | C11: 185 | D11: -0.07 | E11: -1.17 | F11: -1.1 | G11: 4.1
A12: 2011-08 | B12: 95 | C12: 101 | D12: 0.02 | E12: -0.65 | F12: -0.67 | G12: 2.4
A13: 2011-09 | B13: 115 | C13: 109 | D13: -0.12 | E13: -0.69 | F13: -0.57 | G13: 1.8
A14: 2011-10 | B14: 148 | C14: 155 | D14: -0.76 | E14: -1.7 | F14: -0.94 | G14: 2.3
A15: 2011-11 | B15: 91 | C15: 91 | D15: -0.64 | E15: -0.58 | F15: 0.07 | G15: 1.4
A16: 2011-12 | B16: 129 | C16: 124 | D16: -0.53 | E16: -1.67 | F16: -1.14 | G16: 4.2
... A40: 2013-12 | B40: 90 | C40: 76 | D40: 0.42 | E40: -0.29 | F40: -0.71 | G40: 2.4
A42: Year | B42: Rain % (GPCC) | C42: Rain May–Oct % (GPCC) | D42: Min temp anomaly | E42: Max temp anomaly | F42: Day–night range anomaly | G42: Humidity anomaly
A43: 2005 | B43: 95 | C43: 98 | D43: 0.31 | E43: 0.66 | F43: 0.35 | G43: -2.4
A44: 2006 | B44: 86 | C44: 85 | D44: 0.06 | E44: 0.02 | F44: -0.04 | G44: -0.8
A45: 2007 | B45: 102 | C45: 104 | D45: -0.1 | E45: -0.18 | F45: -0.08 | G45: 0.2
A46: 2008 | B46: 121 | C46: 127 | D46: -0.33 | E46: -0.79 | F46: -0.46 | G46: 1.6
A47: 2009 | B47: 103 | C47: 98 | D47: -0.32 | E47: -0.62 | F47: -0.31 | G47: 1.6
A48: 2010 | B48: 115 | C48: 114 | D48: -0.43 | E48: -0.43 | F48: 0 | G48: 1.1
A49: 2011 | B49: 124 | C49: 123 | D49: -0.31 | E49: -0.52 | F49: -0.21 | G49: 0.8
A50: 2012 | B50: 107 | C50: 107 | D50: -0.28 | E50: -0.78 | F50: -0.5 | G50: 1.9
A51: 2013 | B51: 101 | C51: 101 | D51: 0.1 | E51: -0.03 | F51: -0.13 | G51: 0.5
A52: 2014 | B52: 99 | C52: 98 | D52: -0.02 | E52: -0.17 | F52: -0.16 | G52: 0.5
A53: 2015 | B53: 89 | C53: 83 | D53: 0.4 | E53: 0.38 | F53: -0.02 | G53: -0.3
A54: 2016 | B54: 78 | C54: 75 | D54: 0.41 | E54: 0.61 | F54: 0.2 | G54: -0.6
... A57: 2019 | B57: 85 | C57: 90 | D57: 0.56 | E57: 1.65 | F57: 1.09 | G57: -3.9

Sheet USDA_quotes
A1: Report date | B1: Topic | C1: What the USDA attaché report says (close to the original English) | D1: Report
A2: May 2011 | B2: Land | C2: Higher prices are motivating landholders with other crops or in other professions to convert larger portions of their lands to coffee growing. | D2: Coffee Annual 4-18-2011
A3: May 2012 | B3: Inputs | C3: Producers used more inputs such as fertilizer, new seeds, the improvement of planting density, and soil conservation techniques to increase yields. | D3: Coffee Annual 5-9-2012
A4: May 2012 | B4: Cost | C4: IHCAFE estimates that even though coffee prices are going down, there is still an incentive to the producer since a price over US$150 per quintal is favorable. | D4: Coffee Annual 5-9-2012
A5: Jun 2013 | B5: Rust | C5: On January 24, 2013, Honduras became the fourth Central American country to declare a state of emergency due to coffee rust. 25 percent (~71,000 ha) affected: more than 14,000 ha completely devastated, ~57,000 ha heavily affected. | D5: Coffee Annual 6-20-2013
A6: Jun 2013 | B6: Rust | C6: About 50 percent of the total area of coffee production is still planted with rust-susceptible varieties. The decrease is attributed to coffee leaf rust and low coffee prices. | D6: Coffee Annual 6-20-2013
A7: Jun 2013 | B7: Area | C7: Areas planted and harvested in 2013/14 and 2012/13 will remain below 2011/12 due to the rust and the renovation and rehabilitation of plantations; bearing trees have decreased. | D7: Coffee Annual 6-20-2013
A8: May 2014 | B8: Renovation | C8: The renovation and re-planting of new trees started five years ago and continues to rehabilitate the farms damaged by the rust. April 2014 national survey: rust incidence 12 percent; 62 percent of farms with resistant varieties. | D8: Coffee Annual HO1402 5-30-2014
A9: Apr 2015 | B9: Rust | C9: About 22,000 hectares (10,000 families) had a total loss of their farms; 58,000 ha (20,000 families) saw production fall by 50 percent. Restoration depended on the producer's access to credit. | D9: Coffee Annual 4-20-2015
A10: Apr 2016 | B10: Renovation | C10: New planted area with bean-bearing trees will be harvested for the first time since the rust; PAPP funds small producers to replant one manzana (0.71 ha), about 23,000 producers, interest-free. | D10: Coffee Annual 4-26-2016
A11: May 2017 | B11: Genetics | C11: In April 2017 IHCAFE confirmed the loss of resistance of the Lempira variety to coffee leaf rust. | D11: Coffee Annual 5-24-2017
A12: May 2018 | B12: Cost | C12: Producers face increased production costs to prevent rust and a decline in international coffee prices; many still repay the 2012 rust loans, due by 2019. | D12: Coffee Annual 5-22-2018
... A18: Apr 2026 | B18: Area | C18: IHCAFE: growth driven by improved plant nutrition, favorable biennial cycles, expansion of productive area, enhanced pruning and crop management, and maturation of newly established plantations. IHCAFE helps growers meet the EU Deforestation Regulation. | D18: Coffee Annual HO2026-0002

Sheet Production_1960_2026
A1: Marketing year (Oct N – Sep N+1) | B1: Year N | C1: Production (1000 bags 60 kg) | D1: Change on the year before | E1: Bean exports (1000 bags)
A2: 1960/61 | B2: 1960 | C2: 291 | E2: 225
A3: 1961/62 | B3: 1961 | C3: 315 | D3: =IF(C2=0,"",C3/C2-1) -> 0.082474227 | E3: 247
A4: 1962/63 | B4: 1962 | C4: 405 | D4: =IF(C3=0,"",C4/C3-1) -> 0.28571429 | E4: 334
A5: 1963/64 | B5: 1963 | C5: 390 | D5: =IF(C4=0,"",C5/C4-1) -> -0.037037037 | E5: 317
A6: 1964/65 | B6: 1964 | C6: 479 | D6: =IF(C5=0,"",C6/C5-1) -> 0.22820513 | E6: 404
A7: 1965/66 | B7: 1965 | C7: 461 | D7: =IF(C6=0,"",C7/C6-1) -> -0.037578288 | E7: 383
A8: 1966/67 | B8: 1966 | C8: 431 | D8: =IF(C7=0,"",C8/C7-1) -> -0.065075922 | E8: 351
A9: 1967/68 | B9: 1967 | C9: 495 | D9: =IF(C8=0,"",C9/C8-1) -> 0.14849188 | E9: 413
A10: 1968/69 | B10: 1968 | C10: 514 | D10: =IF(C9=0,"",C10/C9-1) -> 0.038383838 | E10: 364
A11: 1969/70 | B11: 1969 | C11: 443 | D11: =IF(C10=0,"",C11/C10-1) -> -0.1381323 | E11: 470
A12: 1970/71 | B12: 1970 | C12: 545 | D12: =IF(C11=0,"",C12/C11-1) -> 0.23024831 | E12: 379
A13: 1971/72 | B13: 1971 | C13: 586 | D13: =IF(C12=0,"",C13/C12-1) -> 0.075229358 | E13: 560
A14: 1972/73 | B14: 1972 | C14: 759 | D14: =IF(C13=0,"",C14/C13-1) -> 0.29522184 | E14: 686
... A68: 2026/27 | B68: 2026 | C68: 6030 | D68: =IF(C67=0,"",C68/C67-1) -> 0.090415913 | E68: 5500
A70: USDA PSD online, Coffee, Green, Honduras, 1000 60-kg bags, marketing year Oct-Sep, download of July 2026. 2025/26 and 2026/27 are USDA estimates and forecasts.
