Workbook

Sheet README
A1: Honduras coffee: price, farm-gate, cost, varieties, rust, financing, yield (2005 → 2026)
A2: Built 25 Sep 2026 by research/honduras/excel/build_finance_varieties_xlsx.py from files saved in research/honduras/.
A4: Status column
A5: ✔ USDA report (read) = quoted from a USDA FAS Coffee Annual Honduras report saved in research/honduras/raw/usda_gain/ (2011-2018, 2020-2026; the 2019 report was not found).
A6: ✔ FAOSTAT (read) = FAOSTAT bulk file saved in research/honduras/raw/faostat/ (official "A" values only; exchange rates flag X = IMF).
A7: ⚠ web extract, NOT verified = seen only in a web-search summary. The page itself (IHCAFE, World Coffee Research, PROMECAFE, ICO, BCH, Honduran press) could not be opened: the network policy of this environment blocks those hosts. Check these before quoting them.
A9: Units
A10: qq = quintal oro = 46 kg = 100 lb of green coffee. Bag = 60 kg. 1 manzana = 0.7 ha. L = lempira. Lempira amounts are converted with the FAOSTAT annual average rate of the same year.
A11: World price = World Bank Pink Sheet "Coffee, Arabica" (ICO other milds, ex-dock), annual mean of monthly prices; 2026 = Jan-Aug.
A13: Sheets
A14: Price_annual: world price, YoY, farm-gate price (FAOSTAT), share of the world price, exchange rate.
A15: Price_vs_cost: every cost figure found, against the world price and the Honduran export price of the same year.
... A22: Not found anywhere we could reach: yield by variety, a yearly series of bank credit to coffee (BCH), a yearly farm-gate series 2009-2021, official IHCAFE cost-of-production studies.

Sheet Price_annual
A1: World arabica price and Honduran farm-gate price, annual
A2: Blue = input. Farm-gate: FAOSTAT "Coffee, green" producer price, official values only (2009-2021 and 2025 not published). 2024: the FAOSTAT USD cell repeats 2023, so US$/t = lempiras / rate.
A4: Year | B4: World price $/kg | C4: YoY | D4: World price $/qq | E4: Farm-gate L/t (FAOSTAT) | F4: L per US$ (FAOSTAT) | G4: Farm-gate $/t | H4: Farm-gate $/qq | I4: Farm-gate / world price | J4: Note
A5: 2005 | B5: 2.5325 | D5: =B5*46 -> 116.495 | E5: 33000 | F5: 18.832342 | G5: 1752.3 | H5: =G5*0.046 -> 80.6058 | I5: =H5/D5 -> 0.69192498
A6: 2006 | B6: 2.5216667 | C6: =B6/B5-1 -> -0.0042777229 | D6: =B6*46 -> 115.99667 | E6: 39600 | F6: 18.895208 | G6: 2095.8 | H6: =G6*0.046 -> 96.4068 | I6: =H6/D6 -> 0.83111699
A7: 2007 | B7: 2.7241667 | C7: =B7/B6-1 -> 0.080304032 | D7: =B7*46 -> 125.31167 | E7: 44000 | F7: 18.8951 | G7: 2328.6 | H7: =G7*0.046 -> 107.1156 | I7: =H7/D7 -> 0.85479351
A8: 2008 | B8: 3.0808333 | C8: =B8/B7-1 -> 0.13092689 | D8: =B8*46 -> 141.71833 | E8: 44950 | F8: 18.903758 | G8: 2377.8 | H8: =G8*0.046 -> 109.3788 | I8: =H8/D8 -> 0.77180417
A9: 2009 | B9: 3.1708333 | C9: =B9/B8-1 -> 0.029212875 | D9: =B9*46 -> 145.85833 | F9: 18.8951
A10: 2010 | B10: 4.32 | C10: =B10/B9-1 -> 0.36241787 | D10: =B10*46 -> 198.72 | F10: 18.8951
A11: 2011 | B11: 5.9766667 | C11: =B11/B10-1 -> 0.38348765 | D11: =B11*46 -> 274.92667 | F11: 18.917142
A12: 2012 | B12: 4.1116667 | C12: =B12/B11-1 -> -0.31204685 | D12: =B12*46 -> 189.13667 | F12: 19.50225 | J12: rust epidemic
A13: 2013 | B13: 3.0766667 | C13: =B13/B12-1 -> -0.25172274 | D13: =B13*46 -> 141.52667 | F13: 20.353779 | J13: rust epidemic
A14: 2014 | B14: 4.425 | C14: =B14/B13-1 -> 0.43824485 | D14: =B14*46 -> 203.55 | F14: 20.987158 | J14: mean 4.425 $/kg (Brazil drought)
A15: 2015 | B15: 3.5258333 | C15: =B15/B14-1 -> -0.20320151 | D15: =B15*46 -> 162.18833 | F15: 21.945175
A16: 2016 | B16: 3.6125 | C16: =B16/B15-1 -> 0.024580477 | D16: =B16*46 -> 166.175 | F16: 22.835018
A17: 2017 | B17: 3.3241667 | C17: =B17/B16-1 -> -0.079815456 | D17: =B17*46 -> 152.91167 | F17: 23.487084
A18: 2018 | B18: 2.925 | C18: =B18/B17-1 -> -0.12008022 | D18: =B18*46 -> 134.55 | F18: 23.902728
A19: 2019 | B19: 2.88 | C19: =B19/B18-1 -> -0.015384615 | D19: =B19*46 -> 132.48 | F19: 24.508539
A20: 2020 | B20: 3.3233333 | C20: =B20/B19-1 -> 0.15393519 | D20: =B20*46 -> 152.87333 | F20: 24.581881
A21: 2021 | B21: 4.5108333 | C21: =B21/B20-1 -> 0.35732197 | D21: =B21*46 -> 207.49833 | F21: 24.016655
A22: 2022 | B22: 5.6308333 | C22: =B22/B21-1 -> 0.24829115 | D22: =B22*46 -> 259.01833 | E22: 98273.9 | F22: 24.485874 | G22: 4013.5 | H22: =G22*0.046 -> 184.621 | I22: =H22/D22 -> 0.71277194
A23: 2023 | B23: 4.5408333 | C23: =B23/B22-1 -> -0.19357703 | D23: =B23*46 -> 208.87833 | E23: 76161.7 | F23: 24.601646 | G23: 3095.8 | H23: =G23*0.046 -> 142.4068 | I23: =H23/D23 -> 0.68176913
A24: 2024 | B24: 5.6208333 | C24: =B24/B23-1 -> 0.23784181 | D24: =B24*46 -> 258.55833 | E24: 128803.6 | F24: 24.799282 | G24: =E24/F24 -> 5193.8438 | H24: =G24*0.046 -> 238.91682 | I24: =H24/D24 -> 0.92403448 | J24: FAOSTAT 2024 row inconsistent (USD = 2023 value): farm-gate from lempiras
A25: 2025 | B25: 8.47 | C25: =B25/B24-1 -> 0.506894 | D25: =B25*46 -> 389.62 | F25: 25.952675 | J25: record year
A26: 2026 | B26: 7.42375 | C26: =B26/B25-1 -> -0.1235242 | D26: =B26*46 -> 341.4925 | J26: Jan-Aug only

Sheet Price_vs_cost
A1: Cost of production against the price, US$ per quintal oro (46 kg)
A2: World price looked up in Price_annual. Export price = Honduran average export price printed by USDA for the crop year ending that year.
A4: Year | B4: What the figure is | C4: Cost or threshold $/qq | D4: Same in $/kg | E4: World price $/qq | F4: Honduran export price $/qq | G4: Export price − cost | H4: Status | I4: Source | J4: Quote / extract
A5: 2012 | B5: price IHCAFE calls "favourable" (a threshold, not a cost) | C5: 150 | D5: =C5/46 -> 3.2608696 | E5: =INDEX(Price_annual!D5:D26,MATCH(A5,Price_annual!A5:A26,0)) -> 189.13667 | F5: 197 | G5: =F5-C5 -> 47 | H5: ✔ USDA report (read) | I5: GAIN 2012 | J5: there is still an incentive to the producer since a price over US$150 per quintal (hundred pounds) is favorable
A6: 2018 | B6: total cost, conventional coffee (PROMECAFE 2018 study: 3.49 $/kg) | C6: 160.5 | D6: =C6/46 -> 3.4891304 | E6: =INDEX(Price_annual!D5:D26,MATCH(A6,Price_annual!A5:A26,0)) -> 134.55 | H6: ⚠ web extract, NOT verified | I6: PROMECAFE 2018 as cited in Carpio et al., HortTechnology 33(1), 2023 (search snippet) | J6: A 2018 study by PROMECAFE estimated that the total cost of producing 1 kg of conventional coffee in Honduras is $3.49
A7: 2019 | B7: cost implied: producers "20 dollars below" cost at a 100–107 $/qq price (range 120-127; upper bound used) | C7: 127 | D7: =C7/46 -> 2.7608696 | E7: =INDEX(Price_annual!D5:D26,MATCH(A7,Price_annual!A5:A26,0)) -> 132.48 | F7: 106.89 | G7: =F7-C7 -> -20.11 | H7: ⚠ web extract, NOT verified | I7: La Prensa 2019, "Precios de café no cubren costo de producción"; hondurasensusmanos.info, 2 Oct 2019 (search snippets) | J7: the 2018-2019 season closed at 107 dollars average per quintal oro ... producers were 20 dollars below the production cost of a quintal
A8: 2019 | B8: minimum price growers said they needed | C8: 135 | D8: =C8/46 -> 2.9347826 | E8: =INDEX(Price_annual!D5:D26,MATCH(A8,Price_annual!A5:A26,0)) -> 132.48 | F8: 106.89 | G8: =F8-C8 -> -28.11 | H8: ⚠ web extract, NOT verified | I8: La Prensa 2019 (search snippet) | J8: growers needed an international price of at least US$135/qq
A9: n.d. | B9: average cost; margin only at 130–140 $/qq (year not given) | C9: 117 | D9: =C9/46 -> 2.5434783 | H9: ⚠ web extract, NOT verified | I9: El Heraldo (search snippet, undated) | J9: a coffee producer invests the equivalent of 117 dollars to produce a single quintal of coffee, and to obtain a profit margin requires market prices between 130 and 140 dollars per quintal
A10: 2023 | B10: production cost | C10: 130 | D10: =C10/46 -> 2.826087 | E10: =INDEX(Price_annual!D5:D26,MATCH(A10,Price_annual!A5:A26,0)) -> 208.87833 | H10: ⚠ web extract, NOT verified | I10: La Prensa, Jan 2023 (search snippet) | J10: production cost about US$130 per quintal
A12: Honduran average export price (USDA)
A13: Crop year | B13: US$ per 46-kg bag | C13: $/kg | D13: Source | E13: Quote | F13: Note
A14: 2010/11 | B14: 248 | C14: =B14/46 -> 5.3913043 | D14: GAIN 2012 (Coffee Annual_Tegucigalpa_Honduras_5-9-2012) | E14: The average export price in the 2010/2011 harvest was US$248 per 46 kg bag
A15: 2011/12 | B15: 197 | C15: =B15/46 -> 4.2826087 | D15: GAIN 2013 (Coffee Annual_Tegucigalpa_Honduras_6-20-2013) | E15: The average export price in the 2011/2012 harvest was US $197 per 46-kg bag
A16: 2012/13 | B16: 140 | C16: =B16/46 -> 3.0434783 | D16: GAIN 2014 (Coffee Annual_Tegucigalpa_Honduras_5-28-2014) | E16: The average export price for MY 2012/2013 harvest was US $140 per 46-kg bag compared to the average price of US $201 in MY 2011/2012
A17: 2018/19 | B17: 106.89 | C17: =B17/46 -> 2.3236957 | D17: GAIN 2020 (Coffee Annual_Tegucigalpa_Honduras_05-15-2020) | E17: During MY 2018/19, Honduras exported to 60 countries at an average price of $106.89 per bag | F17: bag size not stated; 106.89 $/46 kg = 2.32 $/kg matches the ~107 $/qq press figure, so read as per quintal

Sheet Varieties
A1: Rust-resistant varieties released by IHCAFE
A2: Resistance status is read in USDA reports; release years are web extracts (the IHCAFE and World Coffee Research pages could not be opened).
A4: Variety | B4: Family | C4: Released | D4: Release year status | E4: Resistance status | F4: Year resistance lost | G4: Source | H4: Note
A5: IHCAFE 90 | B5: Catimor (Caturra × Timor Hybrid) | C5: 1990s | D5: ⚠ web extract, NOT verified | E5: Still resistant in April 2018 (IHCAFE, 4 new rust strains found); not listed as resistant in USDA 2020 (16 new strains, April 2019) | G5: GAIN 2013 ("The varieties developed were the IHCAFE 90 and Lempira"); GAIN 2018; GAIN 2020 | H5: Release year not in a document we could open; the name points to 1990.
A6: Lempira | B6: Catimor (Timor Hybrid 832/1 × Caturra) | C6: 1997–98 | D6: ⚠ web extract, NOT verified | E6: Resistance loss confirmed by IHCAFE in April 2017; rust on 3 % of Lempira plants | F6: 2017 | G6: GAIN 2017 ("In April 2017, IHCAFE confirmed the loss of resistance of the Lempira variety"; "rust was present on three percent of Lempira variety plants") | H6: Release 1997/98 and the 56 % share of sampled farms (IHCAFE bulletin No 8, Oct 2017) are search snippets only.
A7: Parainema | B7: Sarchimor T-5296 (Villa Sarchí × Timor Hybrid) | C7: 2004 | D7: ⚠ web extract, NOT verified | E7: Still resistant per IHCAFE (USDA 2018, 2020, 2021); USDA 2025–26: area growth "driven by the introduction of the Parainema variety" | G7: GAIN 2014 (third IHCAFE variety listed); GAIN 2018; GAIN 2020; GAIN 2025 | H7: Release year 2004 is a search snippet.
A8: Ihcatú 75, Anacafé 14 SHN, Obatá SHN | B8: 3 varieties presented by IHCAFE | C8: Feb 2024 | D8: ⚠ web extract, NOT verified | E8: Presented as rust resistant, productive; seed for at least 1 500 manzanas in 2024 | G8: El Heraldo, "Honduras dispone de tres nuevas variedades de café" (2024) | H8: Search snippet only; first releases about 20 years after Parainema.
A9: 4 more in the pipeline | B9: IHCAFE research centres | C9: announced | D9: ⚠ web extract, NOT verified | E9: "at least 4 more rust-resistant varieties" being prepared | G9: La Prensa, "Ihcafé se prepara para liberar 4 variedades más resistentes a roya" | H9: Search snippet only.
A11: Count
A12: 1990-2004: 3 releases (IHCAFE 90, Lempira, Parainema). 2005-2023: none. Feb 2024: 3 (Ihcatú 75, Anacafé 14 SHN, Obatá SHN, ⚠). Announced: 4 more (⚠).
A13: Yield by variety: no official figure found. Web extract: Obatá about 20 % more productive than Caturra (⚠). PAPP target 5 → 45 qq per manzana (USDA 2017).

Sheet Adoption
A1: Share planted with rust-resistant varieties
A3: When | B3: Scope | C3: Resistant share % | D3: Lempira share % | E3: Status | F3: Source | G3: Quote / extract
A4: Jun 2013 | B4: national, % of coffee AREA | C4: 50 | E4: ✔ USDA report (read) | F4: GAIN 2013 | G4: IHCAFE reports that 50 percent of the total area of coffee production is planted with rust susceptible varieties.
A5: 2013 | B5: national, manzanas | C5: 50 | E5: ⚠ web extract, NOT verified | F5: El Heraldo 2013 (search snippet) | G5: of 400,000 manzanas cultivated, 200,000 resistant; the rest Catuaí, Caturra, Bourbon, Pacas
A6: Apr 2014 | B6: national, % of PRODUCERS | C6: 60 | E6: ✔ USDA report (read) | F6: GAIN 2014 | G6: the number of coffee producers, growing coffee rust resistant varieties, is moving up to 60 percent and 40 percent of them are still using non-resistant types.
A7: 2014 | B7: 5 departments (60 % of area), % of FARMS | C7: 62 | E7: ✔ USDA report (read) | F7: GAIN 2014 (USDA/TechnoServe baseline) | G7: 62 percent of the coffee farms had resistant varieties to coffee leaf rust and 38 percent had varieties susceptible
A8: Oct 2017 | B8: farms sampled by the rust early-warning system | D8: 56.08 | E8: ⚠ web extract, NOT verified | F8: IHCAFE SAT bulletin No 8 (search snippet) | G8: Lempira = 56.08 % of sampled farms, 67.74 % of farms classed as susceptible

Sheet Rust
A1: Coffee leaf rust in Honduras: surveys and events (IHCAFE, as printed by USDA)
A2: IHCAFE rule of thumb: rust damage of 15 % means about 20 % less production (GAIN 2017: "if the damage from rust reaches 15 percent, there could be a 20 percent reduction in production").
A4: When | B4: Value | C4: Unit / what | D4: Status | E4: Source | F4: Quote
A5: 2012/13 | B5: 25 | C5: % of coffee area affected | D5: ✔ USDA report (read) | E5: GAIN 2014 (Coffee Annual_Tegucigalpa_Honduras_5-28-2014) | F5: affected by the coffee leaf rust in about 25 percent of the cultivated coffee acreage (71,000 hectares) in MY 2012/2013
A6: 2012/13 | C6: damage | D6: ✔ USDA report (read) | E6: GAIN 2015 (Coffee Annual_Tegucigalpa_Honduras_4-20-2015) | F6: About 22,000 hectares (10,000 families) had a total loss of their farms; 58,000 ha. (20,000 families) saw a decrease of their coffee production by 50 percent.
A7: Apr 2014 | B7: 12 | C7: national average incidence, % | D7: ✔ USDA report (read) | E7: GAIN 2014 (Coffee Annual_Tegucigalpa_Honduras_5-28-2014) | F7: a low national average incidence of coffee rust with 12 percent and an average of severely affected coffee farms of one percent
A8: Apr 2017 | B8: 3 | C8: % of Lempira plants with rust | D8: ✔ USDA report (read) | E8: GAIN 2017 (Coffee Annual_Tegucigalpa_Honduras_5-24-2017) | F8: As of April 2017, rust was present on three percent of Lempira variety plants.
A9: Apr 2018 | B9: 4 | C9: new strains | D9: ✔ USDA report (read) | E9: GAIN 2018 (Coffee Annual_Tegucigalpa_Honduras_5-22-2018) | F9: in April 2018, studies done by IHCAFE identified four new coffee rust strains
A10: Apr 2019 | B10: 16 | C10: new strains | D10: ✔ USDA report (read) | E10: GAIN 2020 (Coffee Annual_Tegucigalpa_Honduras_05-15-2020) | F10: In April 2019, studies done by IHCAFE identified 16 new coffee rust strains.
A11: end 2020 | B11: 20 | C11: incidence in 5 departments after hurricanes Eta and Iota, % (range 15-25 %) | D11: ✔ USDA report (read) | E11: GAIN 2021 (Coffee Annual_Tegucigalpa_Honduras_05-15-2021) | F11: favored a 15 - 25% incidence of leaf rust in five departments of Honduras by the end of 2020
A12: Apr 2022 | B12: 5.42 | C12: national average incidence, % | D12: ✔ USDA report (read) | E12: GAIN 2022 (Coffee Annual_Tegucigalpa_Honduras_HO2022-0005) | F12: an average coffee rust incidence of 5.42% ... 66% of them showed a low-level presence of coffee rust, 29% a medium presence and 5% with a high presence
A13: May 2023 | B13: 5.8 | C13: national average incidence, % | D13: ✔ USDA report (read) | E13: GAIN 2023 (Coffee Annual_Tegucigalpa_Honduras_HO2023-0003) | F13: an average coffee rust incidence of 5.8%
A14: 2024/25 | B14: 2.9 | C14: national average incidence (forecast Jul 2024–Aug 2025), % | D14: ✔ USDA report (read) | E14: GAIN 2025 (Coffee Annual_Tegucigalpa_Honduras_HO2025-0002) | F14: national incidence levels forecast to remain low through August 2025, averaging 2.9 percent
A15: Mar 2026 | B15: 8.44 | C15: national average incidence, % | D15: ✔ USDA report (read) | E15: GAIN 2026 (Coffee Annual_Tegucigalpa_Honduras_HO2026-0002) | F15: As of March 2026, national average incidence increased from 7.57 percent to 8.44 percent

Sheet Finance
A1: Financing programmes for Honduran coffee growers
A2: US$ used = amount stated in US$, otherwise lempiras / FAOSTAT rate of that year (looked up in Price_annual).
A4: Year | B4: Programme | C4: US$ M stated | D4: Lempiras M | E4: L per US$ | F4: US$ M used | G4: Who | H4: Terms | I4: Status | J4: Source | K4: Quote / extract
A5: 2002 | B5: Government loan to all growers (coffee crisis) | C5: 20 | F5: =C5 -> 20 | G5: all producers | H5: 20 years | I5: ✔ USDA report (read) | J5: GAIN 2011 | K5: the GOH obtained a loan for US$20 million to be paid over 20 years. Through the loan, funds supported all coffee producers in 2002.
A6: 2004 | B6: Coffee trust fund (Law of Financial Reactivation, 2003) | G6: 87,000 producers take part (2011) | H6: US$13.25/qq deducted at sale: US$9 trust fund (returned if no debt), US$1 for 1999–2001 loans, US$3.25 (US$0.50 to the 2002 loan; rest 36 % IHCAFE, 64 % National Coffee Fund) | I6: ✔ USDA report (read) | J6: GAIN 2011, GAIN 2015 | K6: deduction of US$ 13.25 per quintal ... distributed in blocks of US$ 9.00, US $ 1.00 and US$ 3.25
A7: 2013 | B7: Rust emergency credit (banks, BANHPROVI, BANADESA) | D7: 1715 | E7: =INDEX(Price_annual!F5:F26,MATCH(A7,Price_annual!A5:A26,0)) -> 20.353779 | F7: =D7/E7 -> 84.259537 | G7: growers hit by rust; BANADESA loans up to L25,000 | H7: to be repaid by 2019 (USDA) | I7: ⚠ web extract, NOT verified | J7: El Heraldo 2013 (search snippet); GAIN 2017 for the 2019 repayment date | K7: approximately 1,715 million lempiras were made available to coffee growers to confront the advance of coffee rust
A8: 2015 | B8: IHCAFE fertiliser credit line | C8: 17 | D8: 370 | E8: =INDEX(Price_annual!F5:F26,MATCH(A8,Price_annual!A5:A26,0)) -> 21.945175 | F8: =C8 -> 17 | G8: coffee producers | H8: fertiliser at cost, 1 year, interest-free | I8: ✔ USDA report (read) | J8: GAIN 2015 | K8: IHCAFE maintains a credit line for 370 million Lempiras (about US$ 17 million) to buy fertilizer
A9: 2015 | B9: PAPP (IHCAFE + National Coffee Fund) and PEPP (BANADESA) | E9: =INDEX(Price_annual!F5:F26,MATCH(A9,Price_annual!A5:A26,0)) -> 21.945175 | G9: about 23,000 small producers | H9: replant 1 manzana (0.7 ha), no interest; aim 5 → 45 qq per manzana | I9: ✔ USDA report (read) | J9: GAIN 2015–2017 | K9: This program supports about 23,000 small producers ... The program aims to increase production from 5 to 45 quintals per manzana ... No interest is charged.
A10: 2018 | B10: Decreto 93-2018: IHCAFE loan to growers (low prices, rust) | C10: 77 | D10: 1900 | E10: =INDEX(Price_annual!F5:F26,MATCH(A10,Price_annual!A5:A26,0)) -> 23.902728 | F10: =C10 -> 77 | G10: all registered growers who ask | H10: L200 per qq produced in 2016/17 (decree, snippet) — USDA wrote "about $25 per 100 pounds"; repaid by US$1.50/qq deducted on exports | I10: ✔ USDA report (read) | J10: GAIN 2020 (US$77 million, 5 Sep 2018); decree text via search snippet (L1,900 M, L200/qq) | K10: On September 5, 2018, the Honduran Congress authorized IHCAFE to contract ... financing for about $77 million.
A11: 2019 | B11: Decreto 47-2018 debt readjustment + BANHPROVI coffee fund | D11: 300 | E11: =INDEX(Price_annual!F5:F26,MATCH(A11,Price_annual!A5:A26,0)) -> 24.508539 | F11: =D11/E11 -> 12.240632 | G11: > 55,000 growers | H11: up to 20 years at 2 % | I11: ⚠ web extract, NOT verified | J11: El Heraldo; MiAmbiente (search snippets) | K11: BANHPROVI Coffee Sector Fund L300 million
A12: 2020 | B12: Bono Cafetalero (PCM 030-2020): free fertiliser | C12: 12 | E12: =INDEX(Price_annual!F5:F26,MATCH(A12,Price_annual!A5:A26,0)) -> 24.581881 | F12: =C12 -> 12 | G12: 91,778 small and medium producers (87 %) | H12: 25,188 t of fertiliser, producers up to 6.8 t | I12: ✔ USDA report (read) | J12: GAIN 2021 | K12: In 2020, The GOH (via this program) distributed about $12million in fertilizer (25,188 MT) to 91,778 small and medium sized coffee producers
A13: 2021 | B13: Bono Cafetalero extension (PCM 031-2021) | C13: 12.5 | E13: =INDEX(Price_annual!F5:F26,MATCH(A13,Price_annual!A5:A26,0)) -> 24.016655 | F13: =C13 -> 12.5 | G13: over 91,500 producers | H13: fertiliser; plus state credit at 5 % and guarantees | I13: ✔ USDA report (read) | J13: GAIN 2021 | K13: On April 13, 2021, the GOH extended the Coffee Bonus Program via Presidential decree PCM 031-2021 with an additional $12.5 million investment
A14: 2023 | B14: IHCAFE renovation programme 2023–2027 | E14: =INDEX(Price_annual!F5:F26,MATCH(A14,Price_annual!A5:A26,0)) -> 24.601646 | G14: 33,000 producers, 250,000 manzanas (63 % of the coffee park) | H14: target 7.0–7.5 million 46-kg bags | I14: ✔ USDA report (read) | J14: GAIN 2024 | K14: support to 33 thousand producers, covering an area of 250 thousand blocks (63 percent of the total coffee park)
A15: 2025 | B15: Bono Cafetalero 2025 | D15: 350 | E15: =INDEX(Price_annual!F5:F26,MATCH(A15,Price_annual!A5:A26,0)) -> 25.952675 | F15: =D15/E15 -> 13.486086 | G15: 119,803 producers | H15: 300,000 qq of fertiliser | I15: ⚠ web extract, NOT verified | J15: TNH (search snippet) | K15: L350 million, 119,803 producers, 300,000 qq fertiliser
A17: Debt
A18: Jun 2021 | B18: Growers owed banks, co-ops and IHCAFE | D18: 5565 | E18: =INDEX(Price_annual!F5:F26,MATCH(2021,Price_annual!A5:A26,0)) -> 24.016655 | F18: =D18/E18 -> 231.7142 | I18: ⚠ web extract, NOT verified | J18: La Tribuna, 25 Jun 2021 (search snippet)
A20: Ratios
B21: Bono 2020: US$ per producer | F21: =12000000/91778 -> 130.75029
B22: Decree 93-2018: L200 per qq in US$ (2018 rate) | F22: =200/INDEX(Price_annual!F5:F26,MATCH(2018,Price_annual!A5:A26,0)) -> 8.3672457
B23: … as a share of the 2018/19 export price (106.89 $/qq) | F23: =F22/106.89 -> 0.078279032

Sheet Yield
A1: Yield: USDA production per bearing hectare, and the IHCAFE registry by farm size
A2: Marketing year Oct-Sep (e.g. 2012 = 2012/13). Production: USDA PSD, 1 000 60-kg bags. Bearing area: USDA attaché tables, 1 000 ha. Last year = USDA forecast.
A4: Marketing year | B4: Production (1 000 bags) | C4: Bearing area (1 000 ha) | D4: Bags per bearing ha | E4: qq oro per manzana
A5: 2005/06 | B5: 3204 | C5: 184 | D5: =B5/C5 -> 17.413043 | E5: =D5*60*0.7/46 -> 15.898866
A6: 2006/07 | B6: 3460 | C6: 230 | D6: =B6/C6 -> 15.043478 | E6: =D6*60*0.7/46 -> 13.73535
A7: 2007/08 | B7: 3642 | C7: 230 | D7: =B7/C7 -> 15.834783 | E7: =D7*60*0.7/46 -> 14.457845
A8: 2008/09 | B8: 3225 | C8: 224 | D8: =B8/C8 -> 14.397321 | E8: =D8*60*0.7/46 -> 13.14538
A9: 2009/10 | B9: 3550 | C9: 224 | D9: =B9/C9 -> 15.848214 | E9: =D9*60*0.7/46 -> 14.470109
A10: 2010/11 | B10: 3975 | C10: 238 | D10: =B10/C10 -> 16.701681 | E10: =D10*60*0.7/46 -> 15.249361
A11: 2011/12 | B11: 5600 | C11: 245 | D11: =B11/C11 -> 22.857143 | E11: =D11*60*0.7/46 -> 20.869565
A12: 2012/13 | B12: 4725 | C12: 267 | D12: =B12/C12 -> 17.696629 | E12: =D12*60*0.7/46 -> 16.157792
A13: 2013/14 | B13: 4400 | C13: 213 | D13: =B13/C13 -> 20.657277 | E13: =D13*60*0.7/46 -> 18.860992
A14: 2014/15 | B14: 5100 | C14: 227 | D14: =B14/C14 -> 22.46696 | E14: =D14*60*0.7/46 -> 20.513312
A15: 2015/16 | B15: 5300 | C15: 240 | D15: =B15/C15 -> 22.083333 | E15: =D15*60*0.7/46 -> 20.163043
A16: 2016/17 | B16: 7510 | C16: 280 | D16: =B16/C16 -> 26.821429 | E16: =D16*60*0.7/46 -> 24.48913
... A26: 2026/27 | B26: 6030 | C26: 330 | D26: =B26/C26 -> 18.272727 | E26: =D26*60*0.7/46 -> 16.683794
A28: IHCAFE registry (Coffee Statistics Reports, table 1 of USDA reports 2024-2026)
A29: Crop year / size | B29: Farmers | C29: Hectares harvested | D29: 60-kg bags | E29: Bags per ha | F29: Source
A30: 2022/23 small | B30: 90522 | C30: 209202 | D30: 2907394 | E30: =D30/C30 -> 13.897544 | F30: GAIN 2024, table 1
A31: 2022/23 medium | B31: 6126 | C31: 79764.38 | D31: 1820667 | E31: =D31/C31 -> 22.825564 | F31: GAIN 2024, table 1
A32: 2022/23 large | B32: 629 | C32: 26764.73 | D32: 848578 | E32: =D32/C32 -> 31.705084 | F32: GAIN 2024, table 1
A33: 2023/24 small | B33: 87136 | C33: 193092 | D33: 2502386 | E33: =D33/C33 -> 12.959553 | F33: GAIN 2025, table 1
A34: 2023/24 medium | B34: 4746 | C34: 62494 | D34: 1400613 | E34: =D34/C34 -> 22.41196 | F34: GAIN 2025, table 1
A35: 2023/24 large | B35: 539 | C35: 24511 | D35: 747355 | E35: =D35/C35 -> 30.490596 | F35: GAIN 2025, table 1
A36: 2024/25 small | B36: 86895 | C36: 179271 | D36: 2627164 | E36: =D36/C36 -> 14.654707 | F36: GAIN 2026, table 1
A37: 2024/25 medium | B37: 6359 | C37: 85040 | D37: 1661733 | E37: =D37/C37 -> 19.540604 | F37: GAIN 2026, table 1
A38: 2024/25 large | B38: 374 | C38: 21246 | D38: 515533 | E38: =D38/C38 -> 24.264944 | F38: GAIN 2026, table 1

Sheet Web_extracts
A1: Web-search extracts collected on 25 Sep 2026: NOT verified (pages blocked by the network policy)
A3: section | B3: topic | C3: claim_as_in_search_summary | D3: value | E3: unit | F3: year | G3: verification_status | H3: search_query | I3: candidate_source_urls
A4: 1 | B4: Lempira | C4: IHCAFE recognized in 2017 that Lempira 98 had lost rust resistance; new races broke resistance in 2017 | D4: 2017 | E4: year | F4: 2017 | G4: UNVERIFIED - search-engine summary only; document NOT downloaded | H4: variedad Lempira IHCAFE pérdida de resistencia roya 2017 | I4: https://www.ihcafe.hn/?mdocs-file=5360 ; https://mvcafe.es/variedad-popular-hondurena-lempira-encontrada-susceptible-a-la-roya-de-la-hoja/
A5: 1 | B5: Lempira | C5: IHCAFE breeding programme monitored progressive loss of Lempira resistance since 2007; susceptible by 2015; appears as susceptible in national monitoring 2016-17 | D5: 2007/2015 | E5: year | F5: 2016-17 | G5: UNVERIFIED - search-engine summary only; document NOT downloaded | H5: variedad Lempira IHCAFE pérdida de resistencia roya 2017 | I5: https://wikicafe.promecafe.net/index.php/DURABILIDAD_DE_LA_RESISTENCIA_GEN%C3%89TICA_A_LA_ROYA_DEL_CAF%C3%89_(HEMILEIA_VASTATRIX)_EN_VARIEDADES_MEJORADAS_EN_HONDURAS_AL_2019
A6: 2 | B6: Lempira share of sampled farms | C6: Lempira = 56.08% of total sampled farms and 67.74% of farms classed as rust-susceptible varieties (IHCAFE Boletín No 8, Oct 2017) | D6: 56.08 ; 67.74 | E6: % of sampled farms (SAT monitoring) | F6: 2017 | G6: UNVERIFIED - search-engine summary only; document NOT downloaded | H6: variedad Lempira IHCAFE pérdida de resistencia roya 2017 | I6: https://www.ihcafe.hn/?mdocs-file=5360
A7: 1 | B7: Lempira | C7: Lempira national average rust incidence 3.21% (range 0-33.99%) (IHCAFE Boletín No 8, Oct 2017) | D7: 3.21 | E7: % incidence | F7: 2017 | G7: UNVERIFIED - search-engine summary only; document NOT downloaded | H7: variedad Lempira IHCAFE pérdida de resistencia roya 2017 | I7: https://www.ihcafe.hn/?mdocs-file=5360
A8: 1 | B8: Lempira | C8: Catimor; cross Hybrid Timor 832/1 x Caturra; released 1997 (also called Lempira-98) | D8: 1997/1998 | E8: release year | G8: UNVERIFIED - search-engine summary only; document NOT downloaded | H8: variedad Lempira liberada 1998 IHCAFE Catimor | I8: https://varieties.worldcoffeeresearch.org/varieties/lempira ; https://cafesmyway.com/variedad/lempira/
A9: 1 | B9: IHCAFE 90 | C9: Catimor (Caturra x Timor Hybrid, CIFC Portugal 1959); Catimor lines introduced in Honduras from 1979; IHCAFE 90 selected after ~10 years of evaluation | D9: 1979 | E9: year lines introduced | G9: UNVERIFIED - search-engine summary only; document NOT downloaded | H9: IHCAFE 90 variedad Catimor liberada año | I9: https://www.yumpu.com/es/document/view/58384474/guia-de-variedades-de-cafe/15 ; https://inheritancecoffee.com/pages/cultivar/ihcafe-90
A10: 1 | B10: Parainema | C10: Sarchimor selection by IHCAFE (crossed 1980s), officially released 2004; rust + nematode resistance; target 1000-1400 m | D10: 2004 | E10: release year | G10: UNVERIFIED - search-engine summary only; document NOT downloaded | H10: Parainema variety World Coffee Research Honduras IHCAFE | I10: https://varieties.worldcoffeeresearch.org/varieties/parainema ; https://library.sweetmarias.com/glossary/parainema/
A11: 1 | B11: New releases 2024 | C11: Feb 2024 IHCAFE presented three varieties: Ihcatú 75, Anacafé 14 SHN, Ihcatú 75 Obatá SHN (first releases ~20 years after Parainema); seed for >=1,500 manzanas in 2024 | D11: 2024 ; 1500 | E11: year ; manzanas of seed | F11: 2024 | G11: UNVERIFIED - search-engine summary only; document NOT downloaded | H11: IHCAFE nuevas variedades liberadas 2022 2023 2024 | I11: https://www.elheraldo.hn/economia/honduras-dispone-de-tres-nuevas-variedades-de-cafe-IK17849302
A12: 1 | B12: New releases pipeline | C12: IHCAFE preparing to release at least 4 more rust-resistant varieties, evaluated in 7 research centres | D12: 4 | E12: varieties | F12: 2023 | G12: UNVERIFIED - search-engine summary only; document NOT downloaded | H12: IHCAFE nuevas variedades liberadas 2022 2023 2024 | I12: https://www.laprensa.hn/honduras/honduras-ihcafe-prepara-liberar-4-variedades-resistentes-roya-KC15606396
A13: 1 | B13: Obatá | C13: Obatá SHN (from Brazil) official in Honduras; productivity ~20% above Caturra; moderate rust resistance; in Proyecto de Renovación de Fincas official list | D13: 20 | E13: % above Caturra | G13: UNVERIFIED - search-engine summary only; document NOT downloaded | H13: Obatá Rojo IHCAFE Honduras | I13: https://www.anacafe.org/uploads/file/b5280eca11c54a24a2adf4c5647c9205/07-obata-variedad-brasilena.pdf ; https://tripartito.coffee/estas-son-las-nuevas-variedades-de-cafe-en-honduras/
A14: 2 | B14: Resistant share | C14: ~60% of Honduran coffee in resistant varieties (Lempira, IHCAFE 90, Parainema) [date unclear, secondary blog] | D14: 60 | E14: % cultivation | F14: ~2020 | G14: UNVERIFIED - search-engine summary only; document NOT downloaded | H14: Honduras porcentaje área café variedades resistentes | I14: https://perfectdailygrind.com/es/2020/03/18/explorando-las-variedades-comunes-de-cafe-de-honduras/
A15: 2 | B15: Resistant share 2012-13 | C15: Of 400,000 manzanas cultivated, 200,000 resistant to rust; rest Catuaí, Caturra, Bourbon, Pacas (press, rust era) | D15: 200000 of 400000 | E15: manzanas | F15: 2012-13 | G15: UNVERIFIED - search-engine summary only; document NOT downloaded | H15: roya Honduras 2012-2013 manzanas afectadas | I15: https://www.elheraldo.hn/honduras/precios-bajos-y-ataque-de-la-roya-dejaran-perdidas-por-700-millones-GOEH566347 ; https://bdigital.zamorano.edu/items/e6eb0227-c664-4e78-a24e-15fb71ce3f71
A16: 2 | B16: Rust impact 2012-13 | C16: Rust affected 25% of area (~100,000 mz): ~30,000 mz severe (renovation), ~70,000 mz moderate (rehabilitation); IHCAFE prelim loss ~1.5 million qq, ~US$250 million | D16: 100000 ; 1.5 million qq ; 250 million USD | E16: mz ; qq ; USD | F16: 2012-13 | G16: UNVERIFIED - search-engine summary only; document NOT downloaded | H16: roya Honduras 2012-2013 manzanas afectadas | I16: https://www.elheraldo.hn/economia/caficultura-tardara-tres-anos-para-recuperarse-de-estragos-de-la-roya-FKEH610243 ; https://www.elheraldo.hn/honduras/precios-bajos-y-ataque-de-la-roya-dejaran-perdidas-por-700-millones-GOEH566347
A17: 2 | B17: Avelino 2015 | C17: Central America production -16% in 2013 vs 2011-12 and -10% in 2013-14 vs 2012-13 (Colombia -31% avg vs 2007) | D17: -16 ; -10 | E17: % | F17: 2013 | G17: UNVERIFIED - search-engine summary only; document NOT downloaded | H17: Avelino 2015 coffee rust crises | I17: https://agritrop.cirad.fr/575723/ ; https://d-nb.info/1198124938/34
A18: 3 | B18: National yield | C18: Average yield ~18 qq/mz (could reach 30 with investment); 2022-23 production 7,159,804 qq oro | D18: 18 ; 7159804 | E18: qq oro/mz ; qq oro | F18: 2022-23 | G18: UNVERIFIED - search-engine summary only; document NOT downloaded | H18: Honduras rendimiento promedio quintales oro por manzana | I18: https://www.elheraldo.hn/economia/siete-departamentos-mas-cafe-producen-honduras-PA19802085 ; https://www.laprensa.hn/economia/departamentos-cafe-producen-honduras-EA19803315
A19: 3 | B19: Dept yields | C19: Copán 21.25 qq/mz on 51,131 mz; Comayagua 17.34 on 66,121 mz; Lempira 18.82; Ocotepeque 19.20; Yoro 18.92; Intibucá 18.39 | D19: see claim | E19: qq oro/mz | F19: ~2023 | G19: UNVERIFIED - search-engine summary only; document NOT downloaded | H19: Honduras rendimiento promedio quintales oro por manzana | I19: https://www.elheraldo.hn/economia/siete-departamentos-mas-cafe-producen-honduras-PA19802085
A20: 4 | B20: Fideicomiso 2003 | C20: Decreto 152-2003 (17 Sep 2003) Ley de Reactivación Financiera del Sector Productor de Café created the trust; reformed by Decreto 56-2007 (8 May 2007); snippet mentions US$4/qq retention (NOT US$9 - conflicts with brief) | D20: 4 | E20: USD/qq retention | F20: 2003 | G20: UNVERIFIED - search-engine summary only; document NOT downloaded | H20: Ley de Reactivación Financiera ... 2003 | I20: https://faolex.fao.org/docs/pdf/hon94834.pdf ; https://www.ecolex.org/es/details/legislation/decreto-no-5607-modifica-el-decreto-no-15203-ley-de-reactivacion-financiera-del-sector-productor-de-cafe-lex-faoc094836/
A21: 4 | B21: Decreto 93-2018 | C21: Authorised IHCAFE to contract financing up to L1,900 million to lend L200 per quintal clean coffee, based on 2016/17 registered production (snippet did NOT confirm US$25/qq or US$1.50/qq) | D21: 1900 million ; 200 | E21: Lempiras ; L/qq | F21: 2018 | G21: UNVERIFIED - search-engine summary only; document NOT downloaded | H21: Decreto 93-2018 fideicomiso café | I21: https://www.ihcafe.hn/wp-content/uploads/2021/06/Decreto-93-2018_Prestamo-L200_Leyes-IHCAFE-1.pdf ; https://hn.vlex.com/vid/decreto-no-93-2018-742043561
A22: 4 | B22: 2018 debt relief | C22: Decreto 47-2018 agricultural debt readjustment up to 20 years at 2%; BANHPROVI Coffee Sector Fund L300 million (guarantee supporting >L5 billion refinancing); >55,000 growers | D22: 300 million ; 20 yrs ; 2% | E22: L ; years ; interest | F22: 2018-19 | G22: UNVERIFIED - search-engine summary only; document NOT downloaded | H22: readecuación deudas caficultores Honduras 2019 | I22: https://www.elheraldo.hn/honduras/aprueban-dos-formas-de-financiamiento-para-los-caficultores-FWEH1211602 ; http://www.miambiente.gob.hn/blog/view/mas-de-55000-caficultores-se-beneficiaran-con-readecuacion-y-refinanciamiento-de-deuda
A23: 4 | B23: Rust credit 2013 | C23: ~L1,715 million made available to growers through different sources to face rust (2013); banks to lend L900 million | D23: 1715 million ; 900 million | E23: Lempiras | F23: 2013 | G23: UNVERIFIED - search-engine summary only; document NOT downloaded | H23: línea de crédito 370 millones lempiras fertilizante | I23: https://www.elheraldo.hn/economia/caficultura-tardara-tres-anos-para-recuperarse-de-estragos-de-la-roya-FKEH610243 ; https://www.elheraldo.hn/economia/bancos-prestaran-l-900-millones-a-los-caficultores-BKEH610212
A24: 4 | B24: Rust emergency 2013 | C24: Gaceta No. 33,050 of 13 Feb 2013 references phytosanitary emergency for coffee rust (decree number not in snippet) | D24: 13 Feb 2013 | E24: date | F24: 2013 | G24: UNVERIFIED - search-engine summary only; document NOT downloaded | H24: emergencia roya Honduras febrero 2013 decreto | I24: https://faolex.fao.org/docs/pdf/hon123550.pdf
A25: 4 | B25: BANADESA rust | C25: BANADESA attended 360 rust-affected producers, lending >L28 million (regional, year unclear) | D25: 28 million ; 360 | E25: L ; producers | F25: ~2013 | G25: UNVERIFIED - search-engine summary only; document NOT downloaded | H25: emergencia roya Honduras ... BANADESA | I25: https://www.elheraldo.hn/honduras/caficultura-movio-prestamos-por-59-millones-de-lempiras-DCEH781103
... A40: 7 | B40: ICO I-CIP | C40: I-CIP averaged 310.12 USc/lb Jan 2025; 297.05 Aug 2025; Other Milds 354.47 Jan 2025 | D40: 310.12 ; 297.05 ; 354.47 | E40: US cents/lb | F40: 2025 | G40: UNVERIFIED - search-engine summary only; document NOT downloaded | H40: ICO prices paid to growers Honduras | I40: https://www.ico.org/documents/cy2024-25/cmr-0125-e.pdf ; https://www.ico.org/documents/cy2024-25/cmr-0825-e.pdf
